Workbook

Sheet Медиаплан
A1: МЕДИАПЛАН — ВБ РЕКЛАМА
A2: Синее — от руководителя. Жёлтое — твои цифры. Серое — считается само.
A4: ▼ ИЮЛЬ 2026
A5: Бюджет на месяц, ₽ | B5: 30000 | C5: Целевой DRR | D5: 0.1 | F5: Средний чек, ₽ | G5: 856 | I5: % выкупа | J5: 0.95
A6: Рекламная кампания | B6: Бюджет, ₽ | C6: Прогноз охвата | D6: CTR % | E6: Клики | F6: CR в заказ % | G6: Заказы | H6: CPO, ₽ | I6: Выкупы | J6: Стоимость выкупа, ₽ | K6: Выручка, ₽ | L6: DRR
A7: тестовые | B7: 15000 | C7: 10000 | D7: 0.05 | E7: =IF(OR(C7="",D7=""),"",ROUND(C7*D7,0)) -> 500 | F7: 0.5 | G7: =IF(OR(E7="",F7=""),"",ROUND(E7*F7,0)) -> 250 | H7: =IF(N(G7)=0,"",B7/G7) -> 60 | I7: =IF(OR(N(G7)=0,$J$5=""),"",ROUND(G7*$J$5,0)) -> 238 | J7: =IF(N(I7)=0,"",B7/I7) -> 63.02521 | K7: =IF(N(I7)=0,"",I7*$G$5) -> 203728 | L7: =IF(N(K7)=0,"",B7/K7) -> 0.073627582
E8: =IF(OR(C8="",D8=""),"",ROUND(C8*D8,0)) | G8: =IF(OR(E8="",F8=""),"",ROUND(E8*F8,0)) | H8: =IF(N(G8)=0,"",B8/G8) | I8: =IF(OR(N(G8)=0,$J$5=""),"",ROUND(G8*$J$5,0)) | J8: =IF(N(I8)=0,"",B8/I8) | K8: =IF(N(I8)=0,"",I8*$G$5) | L8: =IF(N(K8)=0,"",B8/K8)
E9: =IF(OR(C9="",D9=""),"",ROUND(C9*D9,0)) | G9: =IF(OR(E9="",F9=""),"",ROUND(E9*F9,0)) | H9: =IF(N(G9)=0,"",B9/G9) | I9: =IF(OR(N(G9)=0,$J$5=""),"",ROUND(G9*$J$5,0)) | J9: =IF(N(I9)=0,"",B9/I9) | K9: =IF(N(I9)=0,"",I9*$G$5) | L9: =IF(N(K9)=0,"",B9/K9)
E10: =IF(OR(C10="",D10=""),"",ROUND(C10*D10,0)) | G10: =IF(OR(E10="",F10=""),"",ROUND(E10*F10,0)) | H10: =IF(N(G10)=0,"",B10/G10) | I10: =IF(OR(N(G10)=0,$J$5=""),"",ROUND(G10*$J$5,0)) | J10: =IF(N(I10)=0,"",B10/I10) | K10: =IF(N(I10)=0,"",I10*$G$5) | L10: =IF(N(K10)=0,"",B10/K10)
E11: =IF(OR(C11="",D11=""),"",ROUND(C11*D11,0)) | G11: =IF(OR(E11="",F11=""),"",ROUND(E11*F11,0)) | H11: =IF(N(G11)=0,"",B11/G11) | I11: =IF(OR(N(G11)=0,$J$5=""),"",ROUND(G11*$J$5,0)) | J11: =IF(N(I11)=0,"",B11/I11) | K11: =IF(N(I11)=0,"",I11*$G$5) | L11: =IF(N(K11)=0,"",B11/K11)
E12: =IF(OR(C12="",D12=""),"",ROUND(C12*D12,0)) | G12: =IF(OR(E12="",F12=""),"",ROUND(E12*F12,0)) | H12: =IF(N(G12)=0,"",B12/G12) | I12: =IF(OR(N(G12)=0,$J$5=""),"",ROUND(G12*$J$5,0)) | J12: =IF(N(I12)=0,"",B12/I12) | K12: =IF(N(I12)=0,"",I12*$G$5) | L12: =IF(N(K12)=0,"",B12/K12)
E13: =IF(OR(C13="",D13=""),"",ROUND(C13*D13,0)) | G13: =IF(OR(E13="",F13=""),"",ROUND(E13*F13,0)) | H13: =IF(N(G13)=0,"",B13/G13) | I13: =IF(OR(N(G13)=0,$J$5=""),"",ROUND(G13*$J$5,0)) | J13: =IF(N(I13)=0,"",B13/I13) | K13: =IF(N(I13)=0,"",I13*$G$5) | L13: =IF(N(K13)=0,"",B13/K13)
A14: ИТОГО | B14: =SUM(B7:B13) -> 15000 | C14: =SUM(C7:C13) -> 10000 | E14: =SUM(E7:E13) -> 500 | G14: =SUM(G7:G13) -> 250 | H14: =IF(N(G14)=0,"",B14/G14) -> 60 | I14: =SUM(I7:I13) -> 238 | J14: =IF(N(I14)=0,"",B14/I14) -> 63.02521 | K14: =SUM(K7:K13) -> 203728 | L14: =IF(N(K14)=0,"",B14/K14) -> 0.073627582
A15: Вердикт | B15: =IF(OR(N(K14)=0,N($D$5)=0),"— заполни цели",IF(AND(B14<=$B$5,B14/K14<=$D$5),"OK: в лимите и по DRR",IF(B14>$B$5,"БЮДЖЕТ ПРЕВЫШЕН","DRR ВЫШЕ ЦЕЛЕВОГО"))) -> OK: в лимите и по DRR
A17: ▼ АВГУСТ 2026
A18: Бюджет на месяц, ₽ | B18: 70500 | C18: Целевой DRR | D18: 0.1 | F18: Средний чек, ₽ | G18: 856 | I18: % выкупа | J18: 0.95
A19: Рекламная кампания | B19: Бюджет, ₽ | C19: Прогноз охвата | D19: CTR % | E19: Клики | F19: CR в заказ % | G19: Заказы | H19: CPO, ₽ | I19: Выкупы | J19: Стоимость выкупа, ₽ | K19: Выручка, ₽ | L19: DRR
A20: ВБ Продвижение СPM (просмотры) | B20: 35000 | C20: 190000 | D20: 0.064 | E20: =IF(OR(C20="",D20=""),"",ROUND(C20*D20,0)) -> 12160 | F20: 0.051 | G20: =IF(OR(E20="",F20=""),"",ROUND(E20*F20,0)) -> 620 | H20: =IF(N(G20)=0,"",B20/G20) -> 56.451613 | I20: =IF(OR(N(G20)=0,$J$18=""),"",ROUND(G20*$J$18,0)) -> 589 | J20: =IF(N(I20)=0,"",B20/I20) -> 59.42275 | K20: =IF(N(I20)=0,"",I20*$G$18) -> 504184 | L20: =IF(N(K20)=0,"",B20/K20) -> 0.069419101
A21: ВБ Продвижение СPC (Клик) | B21: 35000 | C21: 70000 | D21: 0.034 | E21: =IF(OR(C21="",D21=""),"",ROUND(C21*D21,0)) -> 2380 | F21: 0.13 | G21: =IF(OR(E21="",F21=""),"",ROUND(E21*F21,0)) -> 309 | H21: =IF(N(G21)=0,"",B21/G21) -> 113.26861 | I21: =IF(OR(N(G21)=0,$J$18=""),"",ROUND(G21*$J$18,0)) -> 294 | J21: =IF(N(I21)=0,"",B21/I21) -> 119.04762 | K21: =IF(N(I21)=0,"",I21*$G$18) -> 251664 | L21: =IF(N(K21)=0,"",B21/K21) -> 0.13907432
E22: =IF(OR(C22="",D22=""),"",ROUND(C22*D22,0)) | G22: =IF(OR(E22="",F22=""),"",ROUND(E22*F22,0)) | H22: =IF(N(G22)=0,"",B22/G22) | I22: =IF(OR(N(G22)=0,$J$18=""),"",ROUND(G22*$J$18,0)) | J22: =IF(N(I22)=0,"",B22/I22) | K22: =IF(N(I22)=0,"",I22*$G$18) | L22: =IF(N(K22)=0,"",B22/K22)
E23: =IF(OR(C23="",D23=""),"",ROUND(C23*D23,0)) | G23: =IF(OR(E23="",F23=""),"",ROUND(E23*F23,0)) | H23: =IF(N(G23)=0,"",B23/G23) | I23: =IF(OR(N(G23)=0,$J$18=""),"",ROUND(G23*$J$18,0)) | J23: =IF(N(I23)=0,"",B23/I23) | K23: =IF(N(I23)=0,"",I23*$G$18) | L23: =IF(N(K23)=0,"",B23/K23)
E24: =IF(OR(C24="",D24=""),"",ROUND(C24*D24,0)) | G24: =IF(OR(E24="",F24=""),"",ROUND(E24*F24,0)) | H24: =IF(N(G24)=0,"",B24/G24) | I24: =IF(OR(N(G24)=0,$J$18=""),"",ROUND(G24*$J$18,0)) | J24: =IF(N(I24)=0,"",B24/I24) | K24: =IF(N(I24)=0,"",I24*$G$18) | L24: =IF(N(K24)=0,"",B24/K24)
E25: =IF(OR(C25="",D25=""),"",ROUND(C25*D25,0)) | G25: =IF(OR(E25="",F25=""),"",ROUND(E25*F25,0)) | H25: =IF(N(G25)=0,"",B25/G25) | I25: =IF(OR(N(G25)=0,$J$18=""),"",ROUND(G25*$J$18,0)) | J25: =IF(N(I25)=0,"",B25/I25) | K25: =IF(N(I25)=0,"",I25*$G$18) | L25: =IF(N(K25)=0,"",B25/K25)
E26: =IF(OR(C26="",D26=""),"",ROUND(C26*D26,0)) | G26: =IF(OR(E26="",F26=""),"",ROUND(E26*F26,0)) | H26: =IF(N(G26)=0,"",B26/G26) | I26: =IF(OR(N(G26)=0,$J$18=""),"",ROUND(G26*$J$18,0)) | J26: =IF(N(I26)=0,"",B26/I26) | K26: =IF(N(I26)=0,"",I26*$G$18) | L26: =IF(N(K26)=0,"",B26/K26)
A27: ИТОГО | B27: =SUM(B20:B26) -> 70000 | C27: =SUM(C20:C26) -> 260000 | E27: =SUM(E20:E26) -> 14540 | G27: =SUM(G20:G26) -> 929 | H27: =IF(N(G27)=0,"",B27/G27) -> 75.349839 | I27: =SUM(I20:I26) -> 883 | J27: =IF(N(I27)=0,"",B27/I27) -> 79.275198 | K27: =SUM(K20:K26) -> 755848 | L27: =IF(N(K27)=0,"",B27/K27) -> 0.092611213
A28: Вердикт | B28: =IF(OR(N(K27)=0,N($D$18)=0),"— заполни цели",IF(AND(B27<=$B$18,B27/K27<=$D$18),"OK: в лимите и по DRR",IF(B27>$B$18,"БЮДЖЕТ ПРЕВЫШЕН","DRR ВЫШЕ ЦЕЛЕВОГО"))) -> OK: в лимите и по DRR
A30: ▼ СЕНТЯБРЬ 2026
A31: Бюджет на месяц, ₽ | B31: 140000 | C31: Целевой DRR | D31: 0.1 | F31: Средний чек, ₽ | G31: 900 | I31: % выкупа | J31: 0.95
A32: Рекламная кампания | B32: Бюджет, ₽ | C32: Прогноз охвата | D32: CTR % | E32: Клики | F32: CR в заказ % | G32: Заказы | H32: CPO, ₽ | I32: Выкупы | J32: Стоимость выкупа, ₽ | K32: Выручка, ₽ | L32: DRR
A33: ВБ Продвижение СPM (просмотры) | B33: 35000 | C33: 153900 | D33: 0.0284 | E33: =IF(OR(C33="",D33=""),"",ROUND(C33*D33,0)) -> 4371 | F33: 0.0364 | G33: =IF(OR(E33="",F33=""),"",ROUND(E33*F33,0)) -> 159 | H33: =IF(N(G33)=0,"",B33/G33) -> 220.12579 | I33: =IF(OR(N(G33)=0,$J$31=""),"",ROUND(G33*$J$31,0)) -> 151 | J33: =IF(N(I33)=0,"",B33/I33) -> 231.78808 | K33: =IF(N(I33)=0,"",I33*$G$31) -> 135900 | L33: =IF(N(K33)=0,"",B33/K33) -> 0.25754231
A34: ВБ Продвижение СPC (Клик) | B34: 35000 | C34: 59372 | D34: 0.0577 | E34: =IF(OR(C34="",D34=""),"",ROUND(C34*D34,0)) -> 3426 | F34: 0.0938 | G34: =IF(OR(E34="",F34=""),"",ROUND(E34*F34,0)) -> 321 | H34: =IF(N(G34)=0,"",B34/G34) -> 109.03427 | I34: =IF(OR(N(G34)=0,$J$31=""),"",ROUND(G34*$J$31,0)) -> 305 | J34: =IF(N(I34)=0,"",B34/I34) -> 114.7541 | K34: =IF(N(I34)=0,"",I34*$G$31) -> 274500 | L34: =IF(N(K34)=0,"",B34/K34) -> 0.12750455
A35: ОЗОН | B35: 70000 | C35: 13100 | D35: 0.068 | E35: =IF(OR(C35="",D35=""),"",ROUND(C35*D35,0)) -> 891 | F35: 0.46 | G35: =IF(OR(E35="",F35=""),"",ROUND(E35*F35,0)) -> 410 | H35: =IF(N(G35)=0,"",B35/G35) -> 170.73171 | I35: =IF(OR(N(G35)=0,$J$31=""),"",ROUND(G35*$J$31,0)) -> 390 | J35: =IF(N(I35)=0,"",B35/I35) -> 179.48718 | K35: =IF(N(I35)=0,"",I35*$G$31) -> 351000 | L35: =IF(N(K35)=0,"",B35/K35) -> 0.1994302
E36: =IF(OR(C36="",D36=""),"",ROUND(C36*D36,0)) | G36: =IF(OR(E36="",F36=""),"",ROUND(E36*F36,0)) | H36: =IF(N(G36)=0,"",B36/G36) | I36: =IF(OR(N(G36)=0,$J$31=""),"",ROUND(G36*$J$31,0)) | J36: =IF(N(I36)=0,"",B36/I36) | K36: =IF(N(I36)=0,"",I36*$G$31) | L36: =IF(N(K36)=0,"",B36/K36)
E37: =IF(OR(C37="",D37=""),"",ROUND(C37*D37,0)) | G37: =IF(OR(E37="",F37=""),"",ROUND(E37*F37,0)) | H37: =IF(N(G37)=0,"",B37/G37) | I37: =IF(OR(N(G37)=0,$J$31=""),"",ROUND(G37*$J$31,0)) | J37: =IF(N(I37)=0,"",B37/I37) | K37: =IF(N(I37)=0,"",I37*$G$31) | L37: =IF(N(K37)=0,"",B37/K37)
E38: =IF(OR(C38="",D38=""),"",ROUND(C38*D38,0)) | G38: =IF(OR(E38="",F38=""),"",ROUND(E38*F38,0)) | H38: =IF(N(G38)=0,"",B38/G38) | I38: =IF(OR(N(G38)=0,$J$31=""),"",ROUND(G38*$J$31,0)) | J38: =IF(N(I38)=0,"",B38/I38) | K38: =IF(N(I38)=0,"",I38*$G$31) | L38: =IF(N(K38)=0,"",B38/K38)
E39: =IF(OR(C39="",D39=""),"",ROUND(C39*D39,0)) | G39: =IF(OR(E39="",F39=""),"",ROUND(E39*F39,0)) | H39: =IF(N(G39)=0,"",B39/G39) | I39: =IF(OR(N(G39)=0,$J$31=""),"",ROUND(G39*$J$31,0)) | J39: =IF(N(I39)=0,"",B39/I39) | K39: =IF(N(I39)=0,"",I39*$G$31) | L39: =IF(N(K39)=0,"",B39/K39)
A40: ИТОГО | B40: =SUM(B33:B39) -> 140000 | C40: =SUM(C33:C39) -> 226372 | E40: =SUM(E33:E39) -> 8688 | G40: =SUM(G33:G39) -> 890 | H40: =IF(N(G40)=0,"",B40/G40) -> 157.30337 | I40: =SUM(I33:I39) -> 846 | J40: =IF(N(I40)=0,"",B40/I40) -> 165.48463 | K40: =SUM(K33:K39) -> 761400 | L40: =IF(N(K40)=0,"",B40/K40) -> 0.18387182
A41: Вердикт | B41: =IF(OR(N(K40)=0,N($D$31)=0),"— заполни цели",IF(AND(B40<=$B$31,B40/K40<=$D$31),"OK: в лимите и по DRR",IF(B40>$B$31,"БЮДЖЕТ ПРЕВЫШЕН","DRR ВЫШЕ ЦЕЛЕВОГО"))) -> DRR ВЫШЕ ЦЕЛЕВОГО
A43: ▼ ОКТЯБРЬ 2026
A44: Бюджет на месяц, ₽ | C44: Целевой DRR | F44: Средний чек, ₽ | I44: % выкупа
A45: Рекламная кампания | B45: Бюджет, ₽ | C45: Прогноз охвата | D45: CTR % | E45: Клики | F45: CR в заказ % | G45: Заказы | H45: CPO, ₽ | I45: Выкупы | J45: Стоимость выкупа, ₽ | K45: Выручка, ₽ | L45: DRR
E46: =IF(OR(C46="",D46=""),"",ROUND(C46*D46,0)) | G46: =IF(OR(E46="",F46=""),"",ROUND(E46*F46,0)) | H46: =IF(N(G46)=0,"",B46/G46) | I46: =IF(OR(N(G46)=0,$J$44=""),"",ROUND(G46*$J$44,0)) | J46: =IF(N(I46)=0,"",B46/I46) | K46: =IF(N(I46)=0,"",I46*$G$44) | L46: =IF(N(K46)=0,"",B46/K46)
E47: =IF(OR(C47="",D47=""),"",ROUND(C47*D47,0)) | G47: =IF(OR(E47="",F47=""),"",ROUND(E47*F47,0)) | H47: =IF(N(G47)=0,"",B47/G47) | I47: =IF(OR(N(G47)=0,$J$44=""),"",ROUND(G47*$J$44,0)) | J47: =IF(N(I47)=0,"",B47/I47) | K47: =IF(N(I47)=0,"",I47*$G$44) | L47: =IF(N(K47)=0,"",B47/K47)
E48: =IF(OR(C48="",D48=""),"",ROUND(C48*D48,0)) | G48: =IF(OR(E48="",F48=""),"",ROUND(E48*F48,0)) | H48: =IF(N(G48)=0,"",B48/G48) | I48: =IF(OR(N(G48)=0,$J$44=""),"",ROUND(G48*$J$44,0)) | J48: =IF(N(I48)=0,"",B48/I48) | K48: =IF(N(I48)=0,"",I48*$G$44) | L48: =IF(N(K48)=0,"",B48/K48)
E49: =IF(OR(C49="",D49=""),"",ROUND(C49*D49,0)) | G49: =IF(OR(E49="",F49=""),"",ROUND(E49*F49,0)) | H49: =IF(N(G49)=0,"",B49/G49) | I49: =IF(OR(N(G49)=0,$J$44=""),"",ROUND(G49*$J$44,0)) | J49: =IF(N(I49)=0,"",B49/I49) | K49: =IF(N(I49)=0,"",I49*$G$44) | L49: =IF(N(K49)=0,"",B49/K49)
E50: =IF(OR(C50="",D50=""),"",ROUND(C50*D50,0)) | G50: =IF(OR(E50="",F50=""),"",ROUND(E50*F50,0)) | H50: =IF(N(G50)=0,"",B50/G50) | I50: =IF(OR(N(G50)=0,$J$44=""),"",ROUND(G50*$J$44,0)) | J50: =IF(N(I50)=0,"",B50/I50) | K50: =IF(N(I50)=0,"",I50*$G$44) | L50: =IF(N(K50)=0,"",B50/K50)
E51: =IF(OR(C51="",D51=""),"",ROUND(C51*D51,0)) | G51: =IF(OR(E51="",F51=""),"",ROUND(E51*F51,0)) | H51: =IF(N(G51)=0,"",B51/G51) | I51: =IF(OR(N(G51)=0,$J$44=""),"",ROUND(G51*$J$44,0)) | J51: =IF(N(I51)=0,"",B51/I51) | K51: =IF(N(I51)=0,"",I51*$G$44) | L51: =IF(N(K51)=0,"",B51/K51)
E52: =IF(OR(C52="",D52=""),"",ROUND(C52*D52,0)) | G52: =IF(OR(E52="",F52=""),"",ROUND(E52*F52,0)) | H52: =IF(N(G52)=0,"",B52/G52) | I52: =IF(OR(N(G52)=0,$J$44=""),"",ROUND(G52*$J$44,0)) | J52: =IF(N(I52)=0,"",B52/I52) | K52: =IF(N(I52)=0,"",I52*$G$44) | L52: =IF(N(K52)=0,"",B52/K52)
A53: ИТОГО | B53: =SUM(B46:B52) -> 0 | C53: =SUM(C46:C52) -> 0 | E53: =SUM(E46:E52) -> 0 | G53: =SUM(G46:G52) -> 0 | H53: =IF(N(G53)=0,"",B53/G53) | I53: =SUM(I46:I52) -> 0 | J53: =IF(N(I53)=0,"",B53/I53) | K53: =SUM(K46:K52) -> 0 | L53: =IF(N(K53)=0,"",B53/K53)
A54: Вердикт | B54: =IF(OR(N(K53)=0,N($D$44)=0),"— заполни цели",IF(AND(B53<=$B$44,B53/K53<=$D$44),"OK: в лимите и по DRR",IF(B53>$B$44,"БЮДЖЕТ ПРЕВЫШЕН","DRR ВЫШЕ ЦЕЛЕВОГО"))) -> — заполни цели
A56: ▼ НОЯБРЬ 2026
A57: Бюджет на месяц, ₽ | C57: Целевой DRR | F57: Средний чек, ₽ | I57: % выкупа
A58: Рекламная кампания | B58: Бюджет, ₽ | C58: Прогноз охвата | D58: CTR % | E58: Клики | F58: CR в заказ % | G58: Заказы | H58: CPO, ₽ | I58: Выкупы | J58: Стоимость выкупа, ₽ | K58: Выручка, ₽ | L58: DRR
E59: =IF(OR(C59="",D59=""),"",ROUND(C59*D59,0)) | G59: =IF(OR(E59="",F59=""),"",ROUND(E59*F59,0)) | H59: =IF(N(G59)=0,"",B59/G59) | I59: =IF(OR(N(G59)=0,$J$57=""),"",ROUND(G59*$J$57,0)) | J59: =IF(N(I59)=0,"",B59/I59) | K59: =IF(N(I59)=0,"",I59*$G$57) | L59: =IF(N(K59)=0,"",B59/K59)
E60: =IF(OR(C60="",D60=""),"",ROUND(C60*D60,0)) | G60: =IF(OR(E60="",F60=""),"",ROUND(E60*F60,0)) | H60: =IF(N(G60)=0,"",B60/G60) | I60: =IF(OR(N(G60)=0,$J$57=""),"",ROUND(G60*$J$57,0)) | J60: =IF(N(I60)=0,"",B60/I60) | K60: =IF(N(I60)=0,"",I60*$G$57) | L60: =IF(N(K60)=0,"",B60/K60)
E61: =IF(OR(C61="",D61=""),"",ROUND(C61*D61,0)) | G61: =IF(OR(E61="",F61=""),"",ROUND(E61*F61,0)) | H61: =IF(N(G61)=0,"",B61/G61) | I61: =IF(OR(N(G61)=0,$J$57=""),"",ROUND(G61*$J$57,0)) | J61: =IF(N(I61)=0,"",B61/I61) | K61: =IF(N(I61)=0,"",I61*$G$57) | L61: =IF(N(K61)=0,"",B61/K61)
E62: =IF(OR(C62="",D62=""),"",ROUND(C62*D62,0)) | G62: =IF(OR(E62="",F62=""),"",ROUND(E62*F62,0)) | H62: =IF(N(G62)=0,"",B62/G62) | I62: =IF(OR(N(G62)=0,$J$57=""),"",ROUND(G62*$J$57,0)) | J62: =IF(N(I62)=0,"",B62/I62) | K62: =IF(N(I62)=0,"",I62*$G$57) | L62: =IF(N(K62)=0,"",B62/K62)
E63: =IF(OR(C63="",D63=""),"",ROUND(C63*D63,0)) | G63: =IF(OR(E63="",F63=""),"",ROUND(E63*F63,0)) | H63: =IF(N(G63)=0,"",B63/G63) | I63: =IF(OR(N(G63)=0,$J$57=""),"",ROUND(G63*$J$57,0)) | J63: =IF(N(I63)=0,"",B63/I63) | K63: =IF(N(I63)=0,"",I63*$G$57) | L63: =IF(N(K63)=0,"",B63/K63)
E64: =IF(OR(C64="",D64=""),"",ROUND(C64*D64,0)) | G64: =IF(OR(E64="",F64=""),"",ROUND(E64*F64,0)) | H64: =IF(N(G64)=0,"",B64/G64) | I64: =IF(OR(N(G64)=0,$J$57=""),"",ROUND(G64*$J$57,0)) | J64: =IF(N(I64)=0,"",B64/I64) | K64: =IF(N(I64)=0,"",I64*$G$57) | L64: =IF(N(K64)=0,"",B64/K64)
E65: =IF(OR(C65="",D65=""),"",ROUND(C65*D65,0)) | G65: =IF(OR(E65="",F65=""),"",ROUND(E65*F65,0)) | H65: =IF(N(G65)=0,"",B65/G65) | I65: =IF(OR(N(G65)=0,$J$57=""),"",ROUND(G65*$J$57,0)) | J65: =IF(N(I65)=0,"",B65/I65) | K65: =IF(N(I65)=0,"",I65*$G$57) | L65: =IF(N(K65)=0,"",B65/K65)
A66: ИТОГО | B66: =SUM(B59:B65) -> 0 | C66: =SUM(C59:C65) -> 0 | E66: =SUM(E59:E65) -> 0 | G66: =SUM(G59:G65) -> 0 | H66: =IF(N(G66)=0,"",B66/G66) | I66: =SUM(I59:I65) -> 0 | J66: =IF(N(I66)=0,"",B66/I66) | K66: =SUM(K59:K65) -> 0 | L66: =IF(N(K66)=0,"",B66/K66)
A67: Вердикт | B67: =IF(OR(N(K66)=0,N($D$57)=0),"— заполни цели",IF(AND(B66<=$B$57,B66/K66<=$D$57),"OK: в лимите и по DRR",IF(B66>$B$57,"БЮДЖЕТ ПРЕВЫШЕН","DRR ВЫШЕ ЦЕЛЕВОГО"))) -> — заполни цели
A69: ▼ ДЕКАБРЬ 2026
A70: Бюджет на месяц, ₽ | C70: Целевой DRR | F70: Средний чек, ₽ | I70: % выкупа
A71: Рекламная кампания | B71: Бюджет, ₽ | C71: Прогноз охвата | D71: CTR % | E71: Клики | F71: CR в заказ % | G71: Заказы | H71: CPO, ₽ | I71: Выкупы | J71: Стоимость выкупа, ₽ | K71: Выручка, ₽ | L71: DRR
E72: =IF(OR(C72="",D72=""),"",ROUND(C72*D72,0)) | G72: =IF(OR(E72="",F72=""),"",ROUND(E72*F72,0)) | H72: =IF(N(G72)=0,"",B72/G72) | I72: =IF(OR(N(G72)=0,$J$70=""),"",ROUND(G72*$J$70,0)) | J72: =IF(N(I72)=0,"",B72/I72) | K72: =IF(N(I72)=0,"",I72*$G$70) | L72: =IF(N(K72)=0,"",B72/K72)
E73: =IF(OR(C73="",D73=""),"",ROUND(C73*D73,0)) | G73: =IF(OR(E73="",F73=""),"",ROUND(E73*F73,0)) | H73: =IF(N(G73)=0,"",B73/G73) | I73: =IF(OR(N(G73)=0,$J$70=""),"",ROUND(G73*$J$70,0)) | J73: =IF(N(I73)=0,"",B73/I73) | K73: =IF(N(I73)=0,"",I73*$G$70) | L73: =IF(N(K73)=0,"",B73/K73)
E74: =IF(OR(C74="",D74=""),"",ROUND(C74*D74,0)) | G74: =IF(OR(E74="",F74=""),"",ROUND(E74*F74,0)) | H74: =IF(N(G74)=0,"",B74/G74) | I74: =IF(OR(N(G74)=0,$J$70=""),"",ROUND(G74*$J$70,0)) | J74: =IF(N(I74)=0,"",B74/I74) | K74: =IF(N(I74)=0,"",I74*$G$70) | L74: =IF(N(K74)=0,"",B74/K74)
E75: =IF(OR(C75="",D75=""),"",ROUND(C75*D75,0)) | G75: =IF(OR(E75="",F75=""),"",ROUND(E75*F75,0)) | H75: =IF(N(G75)=0,"",B75/G75) | I75: =IF(OR(N(G75)=0,$J$70=""),"",ROUND(G75*$J$70,0)) | J75: =IF(N(I75)=0,"",B75/I75) | K75: =IF(N(I75)=0,"",I75*$G$70) | L75: =IF(N(K75)=0,"",B75/K75)
E76: =IF(OR(C76="",D76=""),"",ROUND(C76*D76,0)) | G76: =IF(OR(E76="",F76=""),"",ROUND(E76*F76,0)) | H76: =IF(N(G76)=0,"",B76/G76) | I76: =IF(OR(N(G76)=0,$J$70=""),"",ROUND(G76*$J$70,0)) | J76: =IF(N(I76)=0,"",B76/I76) | K76: =IF(N(I76)=0,"",I76*$G$70) | L76: =IF(N(K76)=0,"",B76/K76)
E77: =IF(OR(C77="",D77=""),"",ROUND(C77*D77,0)) | G77: =IF(OR(E77="",F77=""),"",ROUND(E77*F77,0)) | H77: =IF(N(G77)=0,"",B77/G77) | I77: =IF(OR(N(G77)=0,$J$70=""),"",ROUND(G77*$J$70,0)) | J77: =IF(N(I77)=0,"",B77/I77) | K77: =IF(N(I77)=0,"",I77*$G$70) | L77: =IF(N(K77)=0,"",B77/K77)
E78: =IF(OR(C78="",D78=""),"",ROUND(C78*D78,0)) | G78: =IF(OR(E78="",F78=""),"",ROUND(E78*F78,0)) | H78: =IF(N(G78)=0,"",B78/G78) | I78: =IF(OR(N(G78)=0,$J$70=""),"",ROUND(G78*$J$70,0)) | J78: =IF(N(I78)=0,"",B78/I78) | K78: =IF(N(I78)=0,"",I78*$G$70) | L78: =IF(N(K78)=0,"",B78/K78)
A79: ИТОГО | B79: =SUM(B72:B78) -> 0 | C79: =SUM(C72:C78) -> 0 | E79: =SUM(E72:E78) -> 0 | G79: =SUM(G72:G78) -> 0 | H79: =IF(N(G79)=0,"",B79/G79) | I79: =SUM(I72:I78) -> 0 | J79: =IF(N(I79)=0,"",B79/I79) | K79: =SUM(K72:K78) -> 0 | L79: =IF(N(K79)=0,"",B79/K79)
A80: Вердикт | B80: =IF(OR(N(K79)=0,N($D$70)=0),"— заполни цели",IF(AND(B79<=$B$70,B79/K79<=$D$70),"OK: в лимите и по DRR",IF(B79>$B$70,"БЮДЖЕТ ПРЕВЫШЕН","DRR ВЫШЕ ЦЕЛЕВОГО"))) -> — заполни цели

Sheet Отчёт по неделям
A1: ОТЧЁТ ПО НЕДЕЛЯМ — Триггер · факт vs план | Y1: =IF($B$15="Весь период","<>",$B$15) -> <>
A2: Синее — план (из «Медиаплан»). Жёлтое — вносишь вручную. Серое — считается само. Зелёное — итоги. Слева ▼ сворачивает недели и месяцы. | Y2: =IF($D$15="Все недели","<>",$D$15) -> <>
A4: СВОДКА · ВЫРУЧКА: ПЛАН vs ФАКТ ПО МЕСЯЦАМ
A5: Месяц | B5: Выручка план, ₽ | C5: Выручка факт, ₽ | D5: Выполнение % | F5: DRR факт | G5: Заказы | I5: Выкупы
A6: Июль | B6: =T25 -> 203728 | C6: =P25 -> 140469 | D6: =IF(N(B6)=0,"",C6/B6) -> 0.68949285 | F6: =S25 -> 0.19866305 | G6: =I25 -> 214 | I6: =L25 -> 208
A7: Август | B7: =T56 -> 755848 | C7: =P56 -> 299234 | D7: =IF(N(B7)=0,"",C7/B7) -> 0.39589177 | F7: =S56 -> 0.24629888 | G7: =I56 -> 498 | I7: =L56 -> 425
A8: Сентябрь | B8: =T87 -> 761400 | C8: =P87 -> 747664 | D8: =IF(N(B8)=0,"",C8/B8) -> 0.98195955 | F8: =S87 -> 0.24506329 | G8: =I87 -> 1150 | I8: =L87 -> 1072
A9: Октябрь | B9: =T129 -> 0 | C9: =P129 -> 0 | D9: =IF(N(B9)=0,"",C9/B9) | F9: =S129 | G9: =I129 -> 0 | I9: =L129 -> 0
A10: Ноябрь | B10: =T160 -> 0 | C10: =P160 -> 0 | D10: =IF(N(B10)=0,"",C10/B10) | F10: =S160 | G10: =I160 -> 0 | I10: =L160 -> 0
A11: Декабрь | B11: =T191 -> 0 | C11: =P191 -> 0 | D11: =IF(N(B11)=0,"",C11/B11) | F11: =S191 | G11: =I191 -> 0 | I11: =L191 -> 0
A12: ИТОГО | B12: =SUM(B6:B11) -> 1720976 | C12: =SUM(C6:C11) -> 1187367 | D12: =IF(N(B12)=0,"",C12/B12) -> 0.68993815 | F12: =IF(N(C12)=0,"",SUMIFS(C25:C221,V25:V221,"<>")/C12) -> 0.22729114 | G12: =SUM(G6:G11) -> 1862 | I12: =SUM(I6:I11) -> 1705
A14: СВОДКА · ФАКТ ПО ПРОДУКТАМ (срез по месяцу/неделе · новый продукт впиши в пустую строку «Продукт»)
A15: Месяц: | B15: Весь период | C15: Неделя: | D15: Все недели
A16: Продукт | B16: Бюджет, ₽ | C16: Заказы | D16: Выкупы | F16: Выручка факт, ₽ | G16: CPO, ₽ | I16: Ст.выкупа, ₽ | J16: DRR
A17: Триггер | B17: =IF($A$17="","",SUMIFS($C$25:$C$221,$V$25:$V$221,$Y$1,$W$25:$W$221,$Y$2,$B$25:$B$221,$A$17)) -> 258515 | C17: =IF($A$17="","",SUMIFS($I$25:$I$221,$V$25:$V$221,$Y$1,$W$25:$W$221,$Y$2,$B$25:$B$221,$A$17)) -> 1807 | D17: =IF($A$17="","",SUMIFS($L$25:$L$221,$V$25:$V$221,$Y$1,$W$25:$W$221,$Y$2,$B$25:$B$221,$A$17)) -> 1656 | F17: =IF($A$17="","",SUMIFS($P$25:$P$221,$V$25:$V$221,$Y$1,$W$25:$W$221,$Y$2,$B$25:$B$221,$A$17)) -> 1136556 | G17: =IF(N(C17)=0,"",B17/C17) -> 143.06309 | I17: =IF(N(D17)=0,"",B17/D17) -> 156.10809 | J17: =IF(N(F17)=0,"",B17/F17) -> 0.2274547
A18: Аппликатор | B18: =IF($A$18="","",SUMIFS($C$25:$C$221,$V$25:$V$221,$Y$1,$W$25:$W$221,$Y$2,$B$25:$B$221,$A$18)) -> 10411 | C18: =IF($A$18="","",SUMIFS($I$25:$I$221,$V$25:$V$221,$Y$1,$W$25:$W$221,$Y$2,$B$25:$B$221,$A$18)) -> 6 | D18: =IF($A$18="","",SUMIFS($L$25:$L$221,$V$25:$V$221,$Y$1,$W$25:$W$221,$Y$2,$B$25:$B$221,$A$18)) -> 6 | F18: =IF($A$18="","",SUMIFS($P$25:$P$221,$V$25:$V$221,$Y$1,$W$25:$W$221,$Y$2,$B$25:$B$221,$A$18)) -> 17385 | G18: =IF(N(C18)=0,"",B18/C18) -> 1735.1667 | I18: =IF(N(D18)=0,"",B18/D18) -> 1735.1667 | J18: =IF(N(F18)=0,"",B18/F18) -> 0.59884958
B19: =IF($A$19="","",SUMIFS($C$25:$C$221,$V$25:$V$221,$Y$1,$W$25:$W$221,$Y$2,$B$25:$B$221,$A$19)) | C19: =IF($A$19="","",SUMIFS($I$25:$I$221,$V$25:$V$221,$Y$1,$W$25:$W$221,$Y$2,$B$25:$B$221,$A$19)) | D19: =IF($A$19="","",SUMIFS($L$25:$L$221,$V$25:$V$221,$Y$1,$W$25:$W$221,$Y$2,$B$25:$B$221,$A$19)) | F19: =IF($A$19="","",SUMIFS($P$25:$P$221,$V$25:$V$221,$Y$1,$W$25:$W$221,$Y$2,$B$25:$B$221,$A$19)) | G19: =IF(N(C19)=0,"",B19/C19) | I19: =IF(N(D19)=0,"",B19/D19) | J19: =IF(N(F19)=0,"",B19/F19)
B20: =IF($A$20="","",SUMIFS($C$25:$C$221,$V$25:$V$221,$Y$1,$W$25:$W$221,$Y$2,$B$25:$B$221,$A$20)) | C20: =IF($A$20="","",SUMIFS($I$25:$I$221,$V$25:$V$221,$Y$1,$W$25:$W$221,$Y$2,$B$25:$B$221,$A$20)) | D20: =IF($A$20="","",SUMIFS($L$25:$L$221,$V$25:$V$221,$Y$1,$W$25:$W$221,$Y$2,$B$25:$B$221,$A$20)) | F20: =IF($A$20="","",SUMIFS($P$25:$P$221,$V$25:$V$221,$Y$1,$W$25:$W$221,$Y$2,$B$25:$B$221,$A$20)) | G20: =IF(N(C20)=0,"",B20/C20) | I20: =IF(N(D20)=0,"",B20/D20) | J20: =IF(N(F20)=0,"",B20/F20)
B21: =IF($A$21="","",SUMIFS($C$25:$C$221,$V$25:$V$221,$Y$1,$W$25:$W$221,$Y$2,$B$25:$B$221,$A$21)) | C21: =IF($A$21="","",SUMIFS($I$25:$I$221,$V$25:$V$221,$Y$1,$W$25:$W$221,$Y$2,$B$25:$B$221,$A$21)) | D21: =IF($A$21="","",SUMIFS($L$25:$L$221,$V$25:$V$221,$Y$1,$W$25:$W$221,$Y$2,$B$25:$B$221,$A$21)) | F21: =IF($A$21="","",SUMIFS($P$25:$P$221,$V$25:$V$221,$Y$1,$W$25:$W$221,$Y$2,$B$25:$B$221,$A$21)) | G21: =IF(N(C21)=0,"",B21/C21) | I21: =IF(N(D21)=0,"",B21/D21) | J21: =IF(N(F21)=0,"",B21/F21)
A22: ИТОГО | B22: =SUMIFS($C$25:$C$221,$V$25:$V$221,$Y$1,$W$25:$W$221,$Y$2) -> 269878 | C22: =SUMIFS($I$25:$I$221,$V$25:$V$221,$Y$1,$W$25:$W$221,$Y$2) -> 1813 | D22: =SUMIFS($L$25:$L$221,$V$25:$V$221,$Y$1,$W$25:$W$221,$Y$2) -> 1662 | F22: =SUMIFS($P$25:$P$221,$V$25:$V$221,$Y$1,$W$25:$W$221,$Y$2) -> 1153941 | G22: =IF(N(C22)=0,"",B22/C22) -> 148.85714 | I22: =IF(N(D22)=0,"",B22/D22) -> 162.38147 | J22: =IF(N(F22)=0,"",B22/F22) -> 0.23387504
A24: Период / Рекламная кампания | B24: Продукт | C24: Бюджет потрачен, ₽ | D24: Охват | E24: Клики | F24: Всего заказов | G24: Кол-во самовыкупов | H24: CR из клика в заказ % | I24: Заказы от рекламы | J24: CR в заказ % | K24: % выкупа | L24: Выкупы | M24: Цена продажи до СПП | N24: %Скидки СПП | O24: Средний чек, ₽ | P24: Выручка факт, ₽ | Q24: CPO факт, ₽ | R24: Стоимость выкупа факт, ₽ | S24: DRR факт | T24: Выручка план, ₽ | U24: Выполнение плана % | X24: Рейтинг
A25: ▼ ИЮЛЬ 2026 | C25: =C26+C32+C38+C44+C50 -> 27906 | D25: =D26+D32+D38+D44+D50 -> 97351 | F25: =F26+F32+F38+F44+F50 -> 707 | I25: =I26+I32+I38+I44+I50 -> 214 | J25: =IF(N(D25)=0,"",I25/D25) -> 0.0021982311 | K25: =IF(N(I25)=0,"",L25/I25) -> 0.97196262 | L25: =L26+L32+L38+L44+L50 -> 208 | O25: =IF(N(L25)=0,"",P25/L25) -> 675.33173 | P25: =P26+P32+P38+P44+P50 -> 140469 | Q25: =IF(N(I25)=0,"",C25/I25) -> 130.40187 | R25: =IF(N(L25)=0,"",C25/L25) -> 134.16346 | S25: =IF(N(P25)=0,"",C25/P25) -> 0.19866305 | T25: ='Медиаплан'!$K$14 -> 203728 | U25: =IF(N(T25)=0,"",P25/T25) -> 0.68949285
A26: Неделя 1 · 01–07.07 | C26: =SUM(C27:C31) -> 5096 | D26: =SUM(D27:D31) -> 11166 | F26: =SUM(F27:F31) -> 66 | I26: =SUM(I27:I31) -> 40 | J26: =IF(N(D26)=0,"",I26/D26) -> 0.0035823034 | K26: =IF(N(I26)=0,"",L26/I26) -> 0.725 | L26: =SUM(L27:L31) -> 29 | O26: =IF(N(L26)=0,"",P26/L26) -> 722.58621 | P26: =SUM(P27:P31) -> 20955 | Q26: =IF(N(I26)=0,"",C26/I26) -> 127.4 | R26: =IF(N(L26)=0,"",C26/L26) -> 175.72414 | S26: =IF(N(P26)=0,"",C26/P26) -> 0.24318778 | T26: =ROUND('Медиаплан'!$K$14*7/31,0) -> 46003 | U26: =IF(N(T26)=0,"",P26/T26) -> 0.45551377
A27: CPC | B27: Триггер | C27: 2979 | D27: 4364 | F27: 48 | I27: 39 | J27: =IF(N(D27)=0,"",I27/D27) -> 0.0089367553 | K27: 0.7166 | L27: =IF(OR(I27="",K27=""),"",ROUND(I27*K27,0)) -> 28 | O27: 595 | P27: =IF(N(L27)=0,"",L27*O27) -> 16660 | Q27: =IF(N(I27)=0,"",C27/I27) -> 76.384615 | R27: =IF(N(L27)=0,"",C27/L27) -> 106.39286 | S27: =IF(N(P27)=0,"",C27/P27) -> 0.17881152 | V27: Июль | W27: Нед.1
A28: CPM | B28: Триггер | J28: =IF(N(D28)=0,"",I28/D28) | L28: =IF(OR(I28="",K28=""),"",ROUND(I28*K28,0)) | P28: =IF(N(L28)=0,"",L28*O28) | Q28: =IF(N(I28)=0,"",C28/I28) | R28: =IF(N(L28)=0,"",C28/L28) | S28: =IF(N(P28)=0,"",C28/P28) | V28: Июль | W28: Нед.1
A29: CPC | B29: Аппликатор | C29: 120 | D29: 37 | F29: 18 | I29: 1 | J29: =IF(N(D29)=0,"",I29/D29) -> 0.027027027 | K29: 1 | L29: =IF(OR(I29="",K29=""),"",ROUND(I29*K29,0)) -> 1 | O29: 4295 | P29: =IF(N(L29)=0,"",L29*O29) -> 4295 | Q29: =IF(N(I29)=0,"",C29/I29) -> 120 | R29: =IF(N(L29)=0,"",C29/L29) -> 120 | S29: =IF(N(P29)=0,"",C29/P29) -> 0.027939464 | V29: Июль | W29: Нед.1
A30: CPM | B30: Аппликатор | C30: 1997 | D30: 6765 | I30: 0 | J30: =IF(N(D30)=0,"",I30/D30) -> 0 | L30: =IF(OR(I30="",K30=""),"",ROUND(I30*K30,0)) | O30: 4295 | P30: =IF(N(L30)=0,"",L30*O30) | Q30: =IF(N(I30)=0,"",C30/I30) | R30: =IF(N(L30)=0,"",C30/L30) | S30: =IF(N(P30)=0,"",C30/P30) | V30: Июль | W30: Нед.1
J31: =IF(N(D31)=0,"",I31/D31) | L31: =IF(OR(I31="",K31=""),"",ROUND(I31*K31,0)) | P31: =IF(N(L31)=0,"",L31*O31) | Q31: =IF(N(I31)=0,"",C31/I31) | R31: =IF(N(L31)=0,"",C31/L31) | S31: =IF(N(P31)=0,"",C31/P31) | V31: Июль | W31: Нед.1
A32: Неделя 2 · 08–14.07 | C32: =SUM(C33:C37) -> 631 | D32: =SUM(D33:D37) -> 1800 | F32: =SUM(F33:F37) -> 202 | I32: =SUM(I33:I37) -> 10 | J32: =IF(N(D32)=0,"",I32/D32) -> 0.0055555556 | K32: =IF(N(I32)=0,"",L32/I32) -> 0.6 | L32: =SUM(L33:L37) -> 6 | O32: =IF(N(L32)=0,"",P32/L32) -> 595 | P32: =SUM(P33:P37) -> 3570 | Q32: =IF(N(I32)=0,"",C32/I32) -> 63.1 | R32: =IF(N(L32)=0,"",C32/L32) -> 105.16667 | S32: =IF(N(P32)=0,"",C32/P32) -> 0.1767507 | T32: =ROUND('Медиаплан'!$K$14*7/31,0) -> 46003 | U32: =IF(N(T32)=0,"",P32/T32) -> 0.077603635
A33: CPC | B33: Триггер | C33: 462 | D33: 1235 | F33: 198 | I33: 10 | J33: =IF(N(D33)=0,"",I33/D33) -> 0.008097166 | K33: 0.5883 | L33: =IF(OR(I33="",K33=""),"",ROUND(I33*K33,0)) -> 6 | O33: 595 | P33: =IF(N(L33)=0,"",L33*O33) -> 3570 | Q33: =IF(N(I33)=0,"",C33/I33) -> 46.2 | R33: =IF(N(L33)=0,"",C33/L33) -> 77 | S33: =IF(N(P33)=0,"",C33/P33) -> 0.12941176 | V33: Июль | W33: Нед.2
A34: CPM | B34: Триггер | J34: =IF(N(D34)=0,"",I34/D34) | K34: 0.5883 | L34: =IF(OR(I34="",K34=""),"",ROUND(I34*K34,0)) | O34: 595 | P34: =IF(N(L34)=0,"",L34*O34) | Q34: =IF(N(I34)=0,"",C34/I34) | R34: =IF(N(L34)=0,"",C34/L34) | S34: =IF(N(P34)=0,"",C34/P34) | V34: Июль | W34: Нед.2
A35: CPC | B35: Аппликатор | F35: 4 | J35: =IF(N(D35)=0,"",I35/D35) | L35: =IF(OR(I35="",K35=""),"",ROUND(I35*K35,0)) | P35: =IF(N(L35)=0,"",L35*O35) | Q35: =IF(N(I35)=0,"",C35/I35) | R35: =IF(N(L35)=0,"",C35/L35) | S35: =IF(N(P35)=0,"",C35/P35) | V35: Июль | W35: Нед.2
A36: CPM | B36: Аппликатор | C36: 169 | D36: 565 | I36: 0 | J36: =IF(N(D36)=0,"",I36/D36) -> 0 | L36: =IF(OR(I36="",K36=""),"",ROUND(I36*K36,0)) | O36: 4295 | P36: =IF(N(L36)=0,"",L36*O36) | Q36: =IF(N(I36)=0,"",C36/I36) | R36: =IF(N(L36)=0,"",C36/L36) | S36: =IF(N(P36)=0,"",C36/P36) | V36: Июль | W36: Нед.2
J37: =IF(N(D37)=0,"",I37/D37) | L37: =IF(OR(I37="",K37=""),"",ROUND(I37*K37,0)) | P37: =IF(N(L37)=0,"",L37*O37) | Q37: =IF(N(I37)=0,"",C37/I37) | R37: =IF(N(L37)=0,"",C37/L37) | S37: =IF(N(P37)=0,"",C37/P37) | V37: Июль | W37: Нед.2
A38: Неделя 3 · 15–21.07 | C38: =SUM(C39:C43) -> 4084 | D38: =SUM(D39:D43) -> 13884 | F38: =SUM(F39:F43) -> 240 | I38: =SUM(I39:I43) -> 31 | J38: =IF(N(D38)=0,"",I38/D38) -> 0.0022327859 | K38: =IF(N(I38)=0,"",L38/I38) -> 1.6774194 | L38: =SUM(L39:L43) -> 52 | O38: =IF(N(L38)=0,"",P38/L38) -> 666 | P38: =SUM(P39:P43) -> 34632 | Q38: =IF(N(I38)=0,"",C38/I38) -> 131.74194 | R38: =IF(N(L38)=0,"",C38/L38) -> 78.538462 | S38: =IF(N(P38)=0,"",C38/P38) -> 0.11792562 | T38: =ROUND('Медиаплан'!$K$14*7/31,0) -> 46003 | U38: =IF(N(T38)=0,"",P38/T38) -> 0.75282047
A39: CPC | B39: Триггер | C39: 819 | D39: 1821 | F39: 239 | I39: 11 | J39: =IF(N(D39)=0,"",I39/D39) -> 0.006040637 | K39: 1.68 | L39: =IF(OR(I39="",K39=""),"",ROUND(I39*K39,0)) -> 18 | O39: 666 | P39: =IF(N(L39)=0,"",L39*O39) -> 11988 | Q39: =IF(N(I39)=0,"",C39/I39) -> 74.454545 | R39: =IF(N(L39)=0,"",C39/L39) -> 45.5 | S39: =IF(N(P39)=0,"",C39/P39) -> 0.068318318 | V39: Июль | W39: Нед.3
A40: CPM | B40: Триггер | C40: 3190 | D40: 12026 | I40: 20 | J40: =IF(N(D40)=0,"",I40/D40) -> 0.0016630634 | K40: 1.68 | L40: =IF(OR(I40="",K40=""),"",ROUND(I40*K40,0)) -> 34 | O40: 666 | P40: =IF(N(L40)=0,"",L40*O40) -> 22644 | Q40: =IF(N(I40)=0,"",C40/I40) -> 159.5 | R40: =IF(N(L40)=0,"",C40/L40) -> 93.823529 | S40: =IF(N(P40)=0,"",C40/P40) -> 0.14087617 | V40: Июль | W40: Нед.3
A41: CPC | B41: Аппликатор | C41: 75 | D41: 37 | F41: 1 | J41: =IF(N(D41)=0,"",I41/D41) -> 0 | K41: 1 | L41: =IF(OR(I41="",K41=""),"",ROUND(I41*K41,0)) | O41: 4295 | P41: =IF(N(L41)=0,"",L41*O41) | Q41: =IF(N(I41)=0,"",C41/I41) | R41: =IF(N(L41)=0,"",C41/L41) | S41: =IF(N(P41)=0,"",C41/P41) | V41: Июль | W41: Нед.3
A42: CPM | B42: Аппликатор | J42: =IF(N(D42)=0,"",I42/D42) | L42: =IF(OR(I42="",K42=""),"",ROUND(I42*K42,0)) | P42: =IF(N(L42)=0,"",L42*O42) | Q42: =IF(N(I42)=0,"",C42/I42) | R42: =IF(N(L42)=0,"",C42/L42) | S42: =IF(N(P42)=0,"",C42/P42) | V42: Июль | W42: Нед.3
J43: =IF(N(D43)=0,"",I43/D43) | L43: =IF(OR(I43="",K43=""),"",ROUND(I43*K43,0)) | P43: =IF(N(L43)=0,"",L43*O43) | Q43: =IF(N(I43)=0,"",C43/I43) | R43: =IF(N(L43)=0,"",C43/L43) | S43: =IF(N(P43)=0,"",C43/P43) | V43: Июль | W43: Нед.3
A44: Неделя 4 · 22–28.07 | C44: =SUM(C45:C49) -> 12108 | D44: =SUM(D45:D49) -> 38115 | F44: =SUM(F45:F49) -> 157 | I44: =SUM(I45:I49) -> 109 | J44: =IF(N(D44)=0,"",I44/D44) -> 0.0028597665 | K44: =IF(N(I44)=0,"",L44/I44) -> 0.80733945 | L44: =SUM(L45:L49) -> 88 | O44: =IF(N(L44)=0,"",P44/L44) -> 639 | P44: =SUM(P45:P49) -> 56232 | Q44: =IF(N(I44)=0,"",C44/I44) -> 111.08257 | R44: =IF(N(L44)=0,"",C44/L44) -> 137.59091 | S44: =IF(N(P44)=0,"",C44/P44) -> 0.21532224 | T44: =ROUND('Медиаплан'!$K$14*7/31,0) -> 46003 | U44: =IF(N(T44)=0,"",P44/T44) -> 1.2223551
A45: CPC | B45: Триггер | C45: 4544 | D45: 8466 | F45: 154 | I45: 62 | J45: =IF(N(D45)=0,"",I45/D45) -> 0.0073234113 | K45: 0.81 | L45: =IF(OR(I45="",K45=""),"",ROUND(I45*K45,0)) -> 50 | O45: 639 | P45: =IF(N(L45)=0,"",L45*O45) -> 31950 | Q45: =IF(N(I45)=0,"",C45/I45) -> 73.290323 | R45: =IF(N(L45)=0,"",C45/L45) -> 90.88 | S45: =IF(N(P45)=0,"",C45/P45) -> 0.14222222 | V45: Июль | W45: Нед.4
A46: CPM | B46: Триггер | C46: 7464 | D46: 29611 | I46: 47 | J46: =IF(N(D46)=0,"",I46/D46) -> 0.001587248 | K46: 0.81 | L46: =IF(OR(I46="",K46=""),"",ROUND(I46*K46,0)) -> 38 | O46: 639 | P46: =IF(N(L46)=0,"",L46*O46) -> 24282 | Q46: =IF(N(I46)=0,"",C46/I46) -> 158.80851 | R46: =IF(N(L46)=0,"",C46/L46) -> 196.42105 | S46: =IF(N(P46)=0,"",C46/P46) -> 0.30738819 | V46: Июль | W46: Нед.4
A47: CPC | B47: Аппликатор | C47: 100 | D47: 38 | F47: 3 | J47: =IF(N(D47)=0,"",I47/D47) -> 0 | L47: =IF(OR(I47="",K47=""),"",ROUND(I47*K47,0)) | O47: 4295 | P47: =IF(N(L47)=0,"",L47*O47) | Q47: =IF(N(I47)=0,"",C47/I47) | R47: =IF(N(L47)=0,"",C47/L47) | S47: =IF(N(P47)=0,"",C47/P47) | V47: Июль | W47: Нед.4
A48: CPM | B48: Аппликатор | J48: =IF(N(D48)=0,"",I48/D48) | L48: =IF(OR(I48="",K48=""),"",ROUND(I48*K48,0)) | P48: =IF(N(L48)=0,"",L48*O48) | Q48: =IF(N(I48)=0,"",C48/I48) | R48: =IF(N(L48)=0,"",C48/L48) | S48: =IF(N(P48)=0,"",C48/P48) | V48: Июль | W48: Нед.4
J49: =IF(N(D49)=0,"",I49/D49) | L49: =IF(OR(I49="",K49=""),"",ROUND(I49*K49,0)) | P49: =IF(N(L49)=0,"",L49*O49) | Q49: =IF(N(I49)=0,"",C49/I49) | R49: =IF(N(L49)=0,"",C49/L49) | S49: =IF(N(P49)=0,"",C49/P49) | V49: Июль | W49: Нед.4
A50: Неделя 5 · 29–31.07 | C50: =SUM(C51:C55) -> 5987 | D50: =SUM(D51:D55) -> 32386 | F50: =SUM(F51:F55) -> 42 | I50: =SUM(I51:I55) -> 24 | J50: =IF(N(D50)=0,"",I50/D50) -> 0.00074106095 | K50: =IF(N(I50)=0,"",L50/I50) -> 1.375 | L50: =SUM(L51:L55) -> 33 | O50: =IF(N(L50)=0,"",P50/L50) -> 760 | P50: =SUM(P51:P55) -> 25080 | Q50: =IF(N(I50)=0,"",C50/I50) -> 249.45833 | R50: =IF(N(L50)=0,"",C50/L50) -> 181.42424 | S50: =IF(N(P50)=0,"",C50/P50) -> 0.23871611 | T50: ='Медиаплан'!$K$14-(T26+T32+T38+T44) -> 19716 | U50: =IF(N(T50)=0,"",P50/T50) -> 1.2720633
A51: CPC | B51: Триггер | C51: 621 | D51: 1942 | F51: 41 | I51: 6 | J51: =IF(N(D51)=0,"",I51/D51) -> 0.0030895984 | K51: 1.41 | L51: =IF(OR(I51="",K51=""),"",ROUND(I51*K51,0)) -> 8 | O51: 760 | P51: =IF(N(L51)=0,"",L51*O51) -> 6080 | Q51: =IF(N(I51)=0,"",C51/I51) -> 103.5 | R51: =IF(N(L51)=0,"",C51/L51) -> 77.625 | S51: =IF(N(P51)=0,"",C51/P51) -> 0.10213816 | V51: Июль | W51: Нед.5 | X51: 4.5
A52: CPM | B52: Триггер | C52: 5366 | D52: 30444 | I52: 18 | J52: =IF(N(D52)=0,"",I52/D52) -> 0.00059124951 | K52: 1.41 | L52: =IF(OR(I52="",K52=""),"",ROUND(I52*K52,0)) -> 25 | O52: 760 | P52: =IF(N(L52)=0,"",L52*O52) -> 19000 | Q52: =IF(N(I52)=0,"",C52/I52) -> 298.11111 | R52: =IF(N(L52)=0,"",C52/L52) -> 214.64 | S52: =IF(N(P52)=0,"",C52/P52) -> 0.28242105 | V52: Июль | W52: Нед.5
A53: CPC | B53: Аппликатор | F53: 1 | J53: =IF(N(D53)=0,"",I53/D53) | L53: =IF(OR(I53="",K53=""),"",ROUND(I53*K53,0)) | P53: =IF(N(L53)=0,"",L53*O53) | Q53: =IF(N(I53)=0,"",C53/I53) | R53: =IF(N(L53)=0,"",C53/L53) | S53: =IF(N(P53)=0,"",C53/P53) | V53: Июль | W53: Нед.5
A54: CPM | B54: Аппликатор | J54: =IF(N(D54)=0,"",I54/D54) | L54: =IF(OR(I54="",K54=""),"",ROUND(I54*K54,0)) | P54: =IF(N(L54)=0,"",L54*O54) | Q54: =IF(N(I54)=0,"",C54/I54) | R54: =IF(N(L54)=0,"",C54/L54) | S54: =IF(N(P54)=0,"",C54/P54) | V54: Июль | W54: Нед.5
J55: =IF(N(D55)=0,"",I55/D55) | L55: =IF(OR(I55="",K55=""),"",ROUND(I55*K55,0)) | P55: =IF(N(L55)=0,"",L55*O55) | Q55: =IF(N(I55)=0,"",C55/I55) | R55: =IF(N(L55)=0,"",C55/L55) | S55: =IF(N(P55)=0,"",C55/P55) | V55: Июль | W55: Нед.5
A56: ▼ АВГУСТ 2026 | C56: =C57+C63+C69+C75+C81 -> 73701 | D56: =D57+D63+D69+D75+D81 -> 164759 | F56: =F57+F63+F69+F75+F81 -> 1544 | G56: =G57+G63+G69+G75+G81 -> 239 | I56: =I57+I63+I69+I75+I81 -> 498 | J56: =IF(N(D56)=0,"",I56/D56) -> 0.0030225966 | K56: =IF(N(I56)=0,"",L56/I56) -> 0.85341365 | L56: =L57+L63+L69+L75+L81 -> 425 | O56: =IF(N(L56)=0,"",P56/L56) -> 704.08 | P56: =P57+P63+P69+P75+P81 -> 299234 | Q56: =IF(N(I56)=0,"",C56/I56) -> 147.99398 | R56: =IF(N(L56)=0,"",C56/L56) -> 173.41412 | S56: =IF(N(P56)=0,"",C56/P56) -> 0.24629888 | T56: ='Медиаплан'!$K$27 -> 755848 | U56: =IF(N(T56)=0,"",P56/T56) -> 0.39589177
A57: Неделя 1 · 01–07.08 | C57: =SUM(C58:C62) -> 11275 | D57: =SUM(D58:D62) -> 41709 | F57: =SUM(F58:F62) -> 176 | G57: =SUM(G58:G62) -> 30 | I57: =SUM(I58:I62) -> 80 | J57: =IF(N(D57)=0,"",I57/D57) -> 0.0019180513 | K57: =IF(N(I57)=0,"",L57/I57) -> 0.7375 | L57: =SUM(L58:L62) -> 59 | O57: =IF(N(L57)=0,"",P57/L57) -> 814 | P57: =SUM(P58:P62) -> 48026 | Q57: =IF(N(I57)=0,"",C57/I57) -> 140.9375 | R57: =IF(N(L57)=0,"",C57/L57) -> 191.10169 | S57: =IF(N(P57)=0,"",C57/P57) -> 0.23476867 | T57: =ROUND('Медиаплан'!$K$27*7/31,0) -> 170675 | U57: =IF(N(T57)=0,"",P57/T57) -> 0.2813886
A58: CPC | B58: Триггер | C58: 4019 | D58: 6603 | F58: 151 | G58: 30 | I58: 34 | J58: =IF(N(D58)=0,"",I58/D58) -> 0.0051491746 | K58: 0.731 | L58: =IF(OR(I58="",K58=""),"",ROUND(I58*K58,0)) -> 25 | O58: 814 | P58: =IF(N(L58)=0,"",L58*O58) -> 20350 | Q58: =IF(N(I58)=0,"",C58/I58) -> 118.20588 | R58: =IF(N(L58)=0,"",C58/L58) -> 160.76 | S58: =IF(N(P58)=0,"",C58/P58) -> 0.19749386 | V58: Август | W58: Нед.1 | X58: 4.6
A59: CPM | B59: Триггер | C59: 7256 | D59: 35106 | I59: 46 | J59: =IF(N(D59)=0,"",I59/D59) -> 0.0013103173 | K59: 0.731 | L59: =IF(OR(I59="",K59=""),"",ROUND(I59*K59,0)) -> 34 | O59: 814 | P59: =IF(N(L59)=0,"",L59*O59) -> 27676 | Q59: =IF(N(I59)=0,"",C59/I59) -> 157.73913 | R59: =IF(N(L59)=0,"",C59/L59) -> 213.41176 | S59: =IF(N(P59)=0,"",C59/P59) -> 0.26217662 | V59: Август | W59: Нед.1
A60: CPC | B60: Аппликатор | F60: 0 | J60: =IF(N(D60)=0,"",I60/D60) | L60: =IF(OR(I60="",K60=""),"",ROUND(I60*K60,0)) | P60: =IF(N(L60)=0,"",L60*O60) | Q60: =IF(N(I60)=0,"",C60/I60) | R60: =IF(N(L60)=0,"",C60/L60) | S60: =IF(N(P60)=0,"",C60/P60) | V60: Август | W60: Нед.1
A61: CPM | B61: Аппликатор | J61: =IF(N(D61)=0,"",I61/D61) | L61: =IF(OR(I61="",K61=""),"",ROUND(I61*K61,0)) | P61: =IF(N(L61)=0,"",L61*O61) | Q61: =IF(N(I61)=0,"",C61/I61) | R61: =IF(N(L61)=0,"",C61/L61) | S61: =IF(N(P61)=0,"",C61/P61) | V61: Август | W61: Нед.1
A62: ОЗОН | B62: Триггер | F62: 25 | J62: =IF(N(D62)=0,"",I62/D62) | L62: =IF(OR(I62="",K62=""),"",ROUND(I62*K62,0)) | O62: 590 | P62: =IF(N(L62)=0,"",L62*O62) | Q62: =IF(N(I62)=0,"",C62/I62) | R62: =IF(N(L62)=0,"",C62/L62) | S62: =IF(N(P62)=0,"",C62/P62) | V62: Август | W62: Нед.1
A63: Неделя 2 · 08–14.08 | C63: =SUM(C64:C68) -> 16715 | D63: =SUM(D64:D68) -> 40531 | F63: =SUM(F64:F68) -> 260 | G63: =SUM(G64:G68) -> 62 | I63: =SUM(I64:I68) -> 94 | J63: =IF(N(D63)=0,"",I63/D63) -> 0.0023192125 | K63: =IF(N(I63)=0,"",L63/I63) -> 0.69148936 | L63: =SUM(L64:L68) -> 65 | O63: =IF(N(L63)=0,"",P63/L63) -> 738.61538 | P63: =SUM(P64:P68) -> 48010 | Q63: =IF(N(I63)=0,"",C63/I63) -> 177.81915 | R63: =IF(N(L63)=0,"",C63/L63) -> 257.15385 | S63: =IF(N(P63)=0,"",C63/P63) -> 0.34815663 | T63: =ROUND('Медиаплан'!$K$27*7/31,0) -> 170675 | U63: =IF(N(T63)=0,"",P63/T63) -> 0.28129486
A64: CPC | B64: Триггер | C64: 5784 | D64: 7717 | F64: 167 | G64: 52 | I64: 30 | J64: =IF(N(D64)=0,"",I64/D64) -> 0.0038875211 | K64: 0.6849 | L64: =IF(OR(I64="",K64=""),"",ROUND(I64*K64,0)) -> 21 | O64: 800 | P64: =IF(N(L64)=0,"",L64*O64) -> 16800 | Q64: =IF(N(I64)=0,"",C64/I64) -> 192.8 | R64: =IF(N(L64)=0,"",C64/L64) -> 275.42857 | S64: =IF(N(P64)=0,"",C64/P64) -> 0.34428571 | V64: Август | W64: Нед.2 | X64: 4.6
A65: CPM | B65: Триггер | C65: 6798 | D65: 30219 | I65: 36 | J65: =IF(N(D65)=0,"",I65/D65) -> 0.0011913035 | K65: 0.6849 | L65: =IF(OR(I65="",K65=""),"",ROUND(I65*K65,0)) -> 25 | O65: 800 | P65: =IF(N(L65)=0,"",L65*O65) -> 20000 | Q65: =IF(N(I65)=0,"",C65/I65) -> 188.83333 | R65: =IF(N(L65)=0,"",C65/L65) -> 271.92 | S65: =IF(N(P65)=0,"",C65/P65) -> 0.3399 | V65: Август | W65: Нед.2
A66: CPC | B66: Аппликатор | C66: 240 | D66: 138 | F66: 1 | J66: =IF(N(D66)=0,"",I66/D66) -> 0 | K66: % | L66: =IF(OR(I66="",K66=""),"",ROUND(I66*K66,0)) | O66: 3505 | P66: =IF(N(L66)=0,"",L66*O66) | Q66: =IF(N(I66)=0,"",C66/I66) | R66: =IF(N(L66)=0,"",C66/L66) | S66: =IF(N(P66)=0,"",C66/P66) | V66: Август | W66: Нед.2
A67: CPM | B67: Аппликатор | J67: =IF(N(D67)=0,"",I67/D67) | L67: =IF(OR(I67="",K67=""),"",ROUND(I67*K67,0)) | P67: =IF(N(L67)=0,"",L67*O67) | Q67: =IF(N(I67)=0,"",C67/I67) | R67: =IF(N(L67)=0,"",C67/L67) | S67: =IF(N(P67)=0,"",C67/P67) | V67: Август | W67: Нед.2
A68: ОЗОН | B68: Триггер | C68: 3893 | D68: 2457 | F68: 92 | G68: 10 | I68: 28 | J68: =IF(N(D68)=0,"",I68/D68) -> 0.011396011 | K68: 0.6849 | L68: =IF(OR(I68="",K68=""),"",ROUND(I68*K68,0)) -> 19 | O68: 590 | P68: =IF(N(L68)=0,"",L68*O68) -> 11210 | Q68: =IF(N(I68)=0,"",C68/I68) -> 139.03571 | R68: =IF(N(L68)=0,"",C68/L68) -> 204.89474 | S68: =IF(N(P68)=0,"",C68/P68) -> 0.34727921 | V68: Август | W68: Нед.2 | X68: 5
A69: Неделя 3 · 15–21.08 | C69: =SUM(C70:C74) -> 23408 | D69: =SUM(D70:D74) -> 29682 | F69: =SUM(F70:F74) -> 406 | G69: =SUM(G70:G74) -> 75 | I69: =SUM(I70:I74) -> 165 | J69: =IF(N(D69)=0,"",I69/D69) -> 0.0055589246 | K69: =IF(N(I69)=0,"",L69/I69) -> 0.96363636 | L69: =SUM(L70:L74) -> 159 | O69: =IF(N(L69)=0,"",P69/L69) -> 676.7044 | P69: =SUM(P70:P74) -> 107596 | Q69: =IF(N(I69)=0,"",C69/I69) -> 141.86667 | R69: =IF(N(L69)=0,"",C69/L69) -> 147.22013 | S69: =IF(N(P69)=0,"",C69/P69) -> 0.21755456 | T69: =ROUND('Медиаплан'!$K$27*7/31,0) -> 170675 | U69: =IF(N(T69)=0,"",P69/T69) -> 0.63041453
A70: CPC | B70: Триггер | C70: 2253 | D70: 4807 | F70: 146 | G70: 68 | I70: 19 | J70: =IF(N(D70)=0,"",I70/D70) -> 0.0039525692 | K70: 0.9507 | L70: =IF(OR(I70="",K70=""),"",ROUND(I70*K70,0)) -> 18 | O70: 743 | P70: =IF(N(L70)=0,"",L70*O70) -> 13374 | Q70: =IF(N(I70)=0,"",C70/I70) -> 118.57895 | R70: =IF(N(L70)=0,"",C70/L70) -> 125.16667 | S70: =IF(N(P70)=0,"",C70/P70) -> 0.16846119 | V70: Август | W70: Нед.3 | X70: 4.6
A71: CPM | B71: Триггер | C71: 5595 | D71: 22890 | I71: 15 | J71: =IF(N(D71)=0,"",I71/D71) -> 0.00065530799 | K71: 0.9507 | L71: =IF(OR(I71="",K71=""),"",ROUND(I71*K71,0)) -> 14 | O71: 743 | P71: =IF(N(L71)=0,"",L71*O71) -> 10402 | Q71: =IF(N(I71)=0,"",C71/I71) -> 373 | R71: =IF(N(L71)=0,"",C71/L71) -> 399.64286 | S71: =IF(N(P71)=0,"",C71/P71) -> 0.53787733 | V71: Август | W71: Нед.3
A72: CPC | B72: Аппликатор | C72: 720 | D72: 300 | J72: =IF(N(D72)=0,"",I72/D72) -> 0 | L72: =IF(OR(I72="",K72=""),"",ROUND(I72*K72,0)) | O72: 3505 | P72: =IF(N(L72)=0,"",L72*O72) | Q72: =IF(N(I72)=0,"",C72/I72) | R72: =IF(N(L72)=0,"",C72/L72) | S72: =IF(N(P72)=0,"",C72/P72) | V72: Август | W72: Нед.3
A73: CPM | B73: Аппликатор | J73: =IF(N(D73)=0,"",I73/D73) | L73: =IF(OR(I73="",K73=""),"",ROUND(I73*K73,0)) | P73: =IF(N(L73)=0,"",L73*O73) | Q73: =IF(N(I73)=0,"",C73/I73) | R73: =IF(N(L73)=0,"",C73/L73) | S73: =IF(N(P73)=0,"",C73/P73) | V73: Август | W73: Нед.3
A74: ОЗОН | B74: Триггер | C74: 14840 | D74: 1685 | F74: 260 | G74: 7 | I74: 131 | J74: =IF(N(D74)=0,"",I74/D74) -> 0.077744807 | K74: 0.97 | L74: =IF(OR(I74="",K74=""),"",ROUND(I74*K74,0)) -> 127 | O74: 660 | P74: =IF(N(L74)=0,"",L74*O74) -> 83820 | Q74: =IF(N(I74)=0,"",C74/I74) -> 113.28244 | R74: =IF(N(L74)=0,"",C74/L74) -> 116.85039 | S74: =IF(N(P74)=0,"",C74/P74) -> 0.17704605 | V74: Август | W74: Нед.3 | X74: 4.9
A75: Неделя 4 · 22–28.08 | C75: =SUM(C76:C80) -> 15623 | D75: =SUM(D76:D80) -> 30190 | F75: =SUM(F76:F80) -> 470 | G75: =SUM(G76:G80) -> 26 | I75: =SUM(I76:I80) -> 107 | J75: =IF(N(D75)=0,"",I75/D75) -> 0.0035442199 | K75: =IF(N(I75)=0,"",L75/I75) -> 0.89719626 | L75: =SUM(L76:L80) -> 96 | O75: =IF(N(L75)=0,"",P75/L75) -> 670.63542 | P75: =SUM(P76:P80) -> 64381 | Q75: =IF(N(I75)=0,"",C75/I75) -> 146.00935 | R75: =IF(N(L75)=0,"",C75/L75) -> 162.73958 | S75: =IF(N(P75)=0,"",C75/P75) -> 0.24266476 | T75: =ROUND('Медиаплан'!$K$27*7/31,0) -> 170675 | U75: =IF(N(T75)=0,"",P75/T75) -> 0.377214
A76: CPC | B76: Триггер | C76: 1104 | D76: 3197 | F76: 107 | G76: 25 | I76: 29 | J76: =IF(N(D76)=0,"",I76/D76) -> 0.0090710041 | K76: 0.859 | L76: =IF(OR(I76="",K76=""),"",ROUND(I76*K76,0)) -> 25 | O76: 713 | P76: =IF(N(L76)=0,"",L76*O76) -> 17825 | Q76: =IF(N(I76)=0,"",C76/I76) -> 38.068966 | R76: =IF(N(L76)=0,"",C76/L76) -> 44.16 | S76: =IF(N(P76)=0,"",C76/P76) -> 0.061935484 | V76: Август | W76: Нед.4 | X76: 4.7
A77: CPM | B77: Триггер | C77: 6392 | D77: 26296 | I77: 26 | J77: =IF(N(D77)=0,"",I77/D77) -> 0.00098874354 | K77: 0.859 | L77: =IF(OR(I77="",K77=""),"",ROUND(I77*K77,0)) -> 22 | O77: 713 | P77: =IF(N(L77)=0,"",L77*O77) -> 15686 | Q77: =IF(N(I77)=0,"",C77/I77) -> 245.84615 | R77: =IF(N(L77)=0,"",C77/L77) -> 290.54545 | S77: =IF(N(P77)=0,"",C77/P77) -> 0.40749713 | V77: Август | W77: Нед.4
A78: CPC | B78: Аппликатор | C78: 2280 | D78: 236 | F78: 3 | J78: =IF(N(D78)=0,"",I78/D78) -> 0 | K78: 0.95 | L78: =IF(OR(I78="",K78=""),"",ROUND(I78*K78,0)) | O78: 3505 | P78: =IF(N(L78)=0,"",L78*O78) | Q78: =IF(N(I78)=0,"",C78/I78) | R78: =IF(N(L78)=0,"",C78/L78) | S78: =IF(N(P78)=0,"",C78/P78) | V78: Август | W78: Нед.4 | X78: 4.9
A79: CPM | B79: Аппликатор | J79: =IF(N(D79)=0,"",I79/D79) | L79: =IF(OR(I79="",K79=""),"",ROUND(I79*K79,0)) | O79: 3505 | P79: =IF(N(L79)=0,"",L79*O79) | Q79: =IF(N(I79)=0,"",C79/I79) | R79: =IF(N(L79)=0,"",C79/L79) | S79: =IF(N(P79)=0,"",C79/P79) | V79: Август | W79: Нед.4
A80: ОЗОН | B80: Триггер | C80: 5847 | D80: 461 | F80: 360 | G80: 1 | I80: 52 | J80: =IF(N(D80)=0,"",I80/D80) -> 0.11279826 | K80: 0.95 | L80: =IF(OR(I80="",K80=""),"",ROUND(I80*K80,0)) -> 49 | O80: 630 | P80: =IF(N(L80)=0,"",L80*O80) -> 30870 | Q80: =IF(N(I80)=0,"",C80/I80) -> 112.44231 | R80: =IF(N(L80)=0,"",C80/L80) -> 119.32653 | S80: =IF(N(P80)=0,"",C80/P80) -> 0.18940719 | V80: Август | W80: Нед.4 | X80: 4.9
A81: Неделя 5 · 29–31.08 | C81: =SUM(C82:C86) -> 6680 | D81: =SUM(D82:D86) -> 22647 | F81: =SUM(F82:F86) -> 232 | G81: =SUM(G82:G86) -> 46 | I81: =SUM(I82:I86) -> 52 | J81: =IF(N(D81)=0,"",I81/D81) -> 0.0022961099 | K81: =IF(N(I81)=0,"",L81/I81) -> 0.88461538 | L81: =SUM(L82:L86) -> 46 | O81: =IF(N(L81)=0,"",P81/L81) -> 678.71739 | P81: =SUM(P82:P86) -> 31221 | Q81: =IF(N(I81)=0,"",C81/I81) -> 128.46154 | R81: =IF(N(L81)=0,"",C81/L81) -> 145.21739 | S81: =IF(N(P81)=0,"",C81/P81) -> 0.21395855 | T81: ='Медиаплан'!$K$27-(T57+T63+T69+T75) -> 73148 | U81: =IF(N(T81)=0,"",P81/T81) -> 0.4268196
A82: CPC | B82: Триггер | C82: 280 | D82: 405 | F82: 86 | G82: 45 | I82: 11 | J82: =IF(N(D82)=0,"",I82/D82) -> 0.027160494 | K82: 0.859 | L82: =IF(OR(I82="",K82=""),"",ROUND(I82*K82,0)) -> 9 | O82: 713 | P82: =IF(N(L82)=0,"",L82*O82) -> 6417 | Q82: =IF(N(I82)=0,"",C82/I82) -> 25.454545 | R82: =IF(N(L82)=0,"",C82/L82) -> 31.111111 | S82: =IF(N(P82)=0,"",C82/P82) -> 0.043634097 | V82: Август | W82: Нед.5
A83: CPM | B83: Триггер | C83: 4250 | D83: 20391 | I83: 21 | J83: =IF(N(D83)=0,"",I83/D83) -> 0.0010298661 | K83: 0.859 | L83: =IF(OR(I83="",K83=""),"",ROUND(I83*K83,0)) -> 18 | O83: 713 | P83: =IF(N(L83)=0,"",L83*O83) -> 12834 | Q83: =IF(N(I83)=0,"",C83/I83) -> 202.38095 | R83: =IF(N(L83)=0,"",C83/L83) -> 236.11111 | S83: =IF(N(P83)=0,"",C83/P83) -> 0.33115163 | V83: Август | W83: Нед.5
A84: CPC | B84: Аппликатор | F84: 5 | J84: =IF(N(D84)=0,"",I84/D84) | K84: 0.95 | L84: =IF(OR(I84="",K84=""),"",ROUND(I84*K84,0)) | O84: 3505 | P84: =IF(N(L84)=0,"",L84*O84) | Q84: =IF(N(I84)=0,"",C84/I84) | R84: =IF(N(L84)=0,"",C84/L84) | S84: =IF(N(P84)=0,"",C84/P84) | V84: Август | W84: Нед.5
A85: CPM | B85: Аппликатор | J85: =IF(N(D85)=0,"",I85/D85) | L85: =IF(OR(I85="",K85=""),"",ROUND(I85*K85,0)) | O85: 3505 | P85: =IF(N(L85)=0,"",L85*O85) | Q85: =IF(N(I85)=0,"",C85/I85) | R85: =IF(N(L85)=0,"",C85/L85) | S85: =IF(N(P85)=0,"",C85/P85) | V85: Август | W85: Нед.5
A86: ОЗОН | B86: Триггер | C86: 2150 | D86: 1851 | F86: 141 | G86: 1 | I86: 20 | J86: =IF(N(D86)=0,"",I86/D86) -> 0.01080497 | K86: 0.95 | L86: =IF(OR(I86="",K86=""),"",ROUND(I86*K86,0)) -> 19 | O86: 630 | P86: =IF(N(L86)=0,"",L86*O86) -> 11970 | Q86: =IF(N(I86)=0,"",C86/I86) -> 107.5 | R86: =IF(N(L86)=0,"",C86/L86) -> 113.15789 | S86: =IF(N(P86)=0,"",C86/P86) -> 0.17961571 | V86: Август | W86: Нед.5
A87: ▼ СЕНТЯБРЬ 2026 | C87: =C88+C96+C105+C114+C123 -> 183225 | D87: =D88+D96+D105+D114+D123 -> 504839 | F87: =F88+F96+F105+F114+F123 -> 3179 | G87: =G88+G96+G105+G114+G123 -> 88 | I87: =I88+I96+I105+I114+I123 -> 1150 | J87: =IF(N(D87)=0,"",I87/D87) -> 0.002277954 | K87: =IF(N(I87)=0,"",L87/I87) -> 0.93217391 | L87: =L88+L96+L105+L114+L123 -> 1072 | O87: =IF(N(L87)=0,"",P87/L87) -> 697.44776 | P87: =P88+P96+P105+P114+P123 -> 747664 | Q87: =IF(N(I87)=0,"",C87/I87) -> 159.32609 | R87: =IF(N(L87)=0,"",C87/L87) -> 170.91884 | S87: =IF(N(P87)=0,"",C87/P87) -> 0.24506329 | T87: ='Медиаплан'!$K$40 -> 761400 | U87: =IF(N(T87)=0,"",P87/T87) -> 0.98195955
A88: Неделя 1 · 01–07.09 | C88: =SUM(C89:C95) -> 20300 | D88: =SUM(D89:D95) -> 63634 | F88: =SUM(F89:F95) -> 395 | G88: =SUM(G89:G95) -> 16 | I88: =SUM(I89:I95) -> 115 | J88: =IF(N(D88)=0,"",I88/D88) -> 0.00180721 | K88: =IF(N(I88)=0,"",L88/I88) -> 0.91304348 | L88: =SUM(L89:L95) -> 105 | O88: =IF(N(L88)=0,"",P88/L88) -> 678.85714 | P88: =SUM(P89:P94) -> 71280 | Q88: =IF(N(I88)=0,"",C88/I88) -> 176.52174 | R88: =IF(N(L88)=0,"",C88/L88) -> 193.33333 | S88: =IF(N(P88)=0,"",C88/P88) -> 0.28479237 | T88: =ROUND('Медиаплан'!$K$40*7/30,0) -> 177660 | U88: =IF(N(T88)=0,"",P88/T88) -> 0.40121581
A89: CPC | B89: Триггер | C89: 738 | D89: 1121 | F89: 116 | G89: 12 | I89: 5 | J89: =IF(N(D89)=0,"",I89/D89) -> 0.0044603033 | K89: 0.85 | L89: =IF(OR(I89="",K89=""),"",ROUND(I89*K89,0)) -> 4 | O89: 731 | P89: =IF(N(L89)=0,"",L89*O89) -> 2924 | Q89: =IF(N(I89)=0,"",C89/I89) -> 147.6 | R89: =IF(N(L89)=0,"",C89/L89) -> 184.5 | S89: =IF(N(P89)=0,"",C89/P89) -> 0.25239398 | V89: Сентябрь | W89: Нед.1 | X89: 4.7
A90: CPM | B90: Триггер | C90: 8542 | D90: 47558 | I90: 31 | J90: =IF(N(D90)=0,"",I90/D90) -> 0.00065183565 | K90: 0.85 | L90: =IF(OR(I90="",K90=""),"",ROUND(I90*K90,0)) -> 26 | O90: 731 | P90: =IF(N(L90)=0,"",L90*O90) -> 19006 | Q90: =IF(N(I90)=0,"",C90/I90) -> 275.54839 | R90: =IF(N(L90)=0,"",C90/L90) -> 328.53846 | S90: =IF(N(P90)=0,"",C90/P90) -> 0.44943702 | V90: Сентябрь | W90: Нед.1
A91: ВБ | B91: Триггер2 | F91: 27 | K91: 0.85 | L91: =IF(OR(I91="",K91=""),"",ROUND(I91*K91,0)) | O91: 1154 | X91: 5
A92: CPC | B92: Аппликатор | F92: 3 | J92: =IF(N(D92)=0,"",I92/D92) | K92: 0.95 | L92: =IF(OR(I92="",K92=""),"",ROUND(I92*K92,0)) | O92: 3806 | P92: =IF(N(L92)=0,"",L92*O92) | Q92: =IF(N(I92)=0,"",C92/I92) | R92: =IF(N(L92)=0,"",C92/L92) | S92: =IF(N(P92)=0,"",C92/P92) | V92: Сентябрь | W92: Нед.1 | X92: 4.9
A93: CPM | B93: Аппликатор | J93: =IF(N(D93)=0,"",I93/D93) | K93: 0.95 | L93: =IF(OR(I93="",K93=""),"",ROUND(I93*K93,0)) | O93: 3806 | P93: =IF(N(L93)=0,"",L93*O93) | Q93: =IF(N(I93)=0,"",C93/I93) | R93: =IF(N(L93)=0,"",C93/L93) | S93: =IF(N(P93)=0,"",C93/P93) | V93: Сентябрь | W93: Нед.1
A94: ОЗОН | B94: Триггер | C94: 11020 | D94: 14955 | F94: 227 | G94: 4 | I94: 79 | J94: =IF(N(D94)=0,"",I94/D94) -> 0.0052825142 | K94: 0.95 | L94: =IF(OR(I94="",K94=""),"",ROUND(I94*K94,0)) -> 75 | O94: 658 | P94: =IF(N(L94)=0,"",L94*O94) -> 49350 | Q94: =IF(N(I94)=0,"",C94/I94) -> 139.49367 | R94: =IF(N(L94)=0,"",C94/L94) -> 146.93333 | S94: =IF(N(P94)=0,"",C94/P94) -> 0.22330294 | V94: Сентябрь | W94: Нед.1 | X94: 4.8
A95: ОЗОН | B95: Триггер2 | F95: 22 | K95: 0.95 | O95: 1069
A96: Неделя 2 · 08–14.09 | C96: =SUM(C97:C102) -> 34622 | D96: =SUM(D97:D102) -> 107515 | F96: =SUM(F97:F104) -> 908 | G96: =SUM(G97:G104) -> 5 | I96: =SUM(I97:I104) -> 273 | J96: =IF(N(D96)=0,"",I96/D96) -> 0.0025391806 | K96: =IF(N(I96)=0,"",L96/I96) -> 0.91575092 | L96: =SUM(L97:L104) -> 250 | N96: =AVERAGE(N97:N103) -> 0.33428571 | O96: =IF(N(L96)=0,"",P96/L96) -> 639.616 | P96: =SUM(P97:P102) -> 159904 | Q96: =IF(N(I96)=0,"",C96/I96) -> 126.82051 | R96: =IF(N(L96)=0,"",C96/L96) -> 138.488 | S96: =IF(N(P96)=0,"",C96/P96) -> 0.21651741 | T96: =ROUND('Медиаплан'!$K$40*7/30,0) -> 177660 | U96: =IF(N(T96)=0,"",P96/T96) -> 0.90005629
A97: CPC | B97: Триггер | C97: 6075 | D97: 7966 | F97: 296 | G97: 0 | I97: 79 | J97: =IF(N(D97)=0,"",I97/D97) -> 0.0099171479 | K97: 0.86 | L97: =IF(OR(I97="",K97=""),"",ROUND(I97*K97,0)) -> 68 | M97: 812 | N97: 0.2 | O97: 656 | P97: =IF(N(L97)=0,"",L97*O97) -> 44608 | Q97: =IF(N(I97)=0,"",C97/I97) -> 76.898734 | R97: =IF(N(L97)=0,"",C97/L97) -> 89.338235 | S97: =IF(N(P97)=0,"",C97/P97) -> 0.13618633 | V97: Сентябрь | W97: Нед.2 | X97: 4.7
A98: CPM | B98: Триггер | C98: 11911 | D98: 73781 | I98: 63 | J98: =IF(N(D98)=0,"",I98/D98) -> 0.00085387837 | K98: 0.86 | L98: =IF(OR(I98="",K98=""),"",ROUND(I98*K98,0)) -> 54 | M98: 812 | N98: 0.2 | O98: 656 | P98: =IF(N(L98)=0,"",L98*O98) -> 35424 | Q98: =IF(N(I98)=0,"",C98/I98) -> 189.06349 | R98: =IF(N(L98)=0,"",C98/L98) -> 220.57407 | S98: =IF(N(P98)=0,"",C98/P98) -> 0.33624097 | V98: Сентябрь | W98: Нед.2
A99: ВБ | B99: Триггер2 | F99: 26 | M99: 1508 | N99: 0.23 | O99: 1118 | X99: 5
A100: CPC | B100: Аппликатор | F100: 4 | G100: 0 | J100: =IF(N(D100)=0,"",I100/D100) | K100: 0.95 | L100: =IF(OR(I100="",K100=""),"",ROUND(I100*K100,0)) | M100: 6603 | N100: 0.38 | O100: 3862 | P100: =IF(N(L100)=0,"",L100*O100) | Q100: =IF(N(I100)=0,"",C100/I100) | R100: =IF(N(L100)=0,"",C100/L100) | S100: =IF(N(P100)=0,"",C100/P100) | V100: Сентябрь | W100: Нед.2 | X100: 4.9
A101: CPM | B101: Аппликатор | J101: =IF(N(D101)=0,"",I101/D101) | K101: 0.95 | L101: =IF(OR(I101="",K101=""),"",ROUND(I101*K101,0)) | M101: 6603 | N101: 0.38 | O101: 3862 | P101: =IF(N(L101)=0,"",L101*O101) | Q101: =IF(N(I101)=0,"",C101/I101) | R101: =IF(N(L101)=0,"",C101/L101) | S101: =IF(N(P101)=0,"",C101/P101) | V101: Сентябрь | W101: Нед.2
A102: ОЗОН | B102: Триггер | C102: 16636 | D102: 25768 | F102: 535 | G102: 5 | I102: 131 | J102: =IF(N(D102)=0,"",I102/D102) -> 0.0050838249 | K102: 0.9765 | L102: =IF(OR(I102="",K102=""),"",ROUND(I102*K102,0)) -> 128 | M102: 1184 | N102: 0.47 | O102: 624 | P102: =IF(N(L102)=0,"",L102*O102) -> 79872 | Q102: =IF(N(I102)=0,"",C102/I102) -> 126.99237 | R102: =IF(N(L102)=0,"",C102/L102) -> 129.96875 | S102: =IF(N(P102)=0,"",C102/P102) -> 0.20828325 | V102: Сентябрь | W102: Нед.2 | X102: 4.8
A103: ОЗОН | B103: Триггер2 | F103: 46 | K103: 0.9765 | M103: 1974 | N103: 0.48 | O103: 1029
...
