Workbook

Sheet Мои блогеры
A1: БАЗА БЛОГЕРОВ — Менеджер 2
A2: Имя блогера — кликабельная ссылка на канал. Ответственный пусто = свободен, можно брать. Стоит «Анна» = уже в работе.
A4: Блогер (ссылка на канал) | B4: Площадка | C4: Источник | D4: Тематика | E4: Подписчики | F4: Ср. охват/просмотры | G4: ER % | H4: Цена (посл.), ₽ | I4: Контакты | J4: Основа промокода | K4: Ответственный | L4: Заметка о работе | M4: Комментарий | N4: Ссылка на канал (URL) | O4: Расчётный CPV, ₽ | P4: Расчётный CPM, ₽
A5: Во саду ли в огороде | B5: YouTube | C5: YouTube-база | D5: Сад-огород | E5: 2110000 | F5: 284882 | G5: 0.0446 | I5: https://www.gosuslugi.ru/snet/67b0da6bb984972032651c5e; https://www.wildberries.ru/catalog/342956246/detail.aspx?targetUrl=EX&utm_source=VoSaduLi&utm_medium=YT&utm_campaign=795299-id-MKSVRassada14.04.26 | J5: VOSADULI | K5: Менеджер 2 | N5: https://www.youtube.com/channel/UCiWA1Ct_IdiUA8a-DTwBj9A
A6: Садовый Гид | B6: YouTube | C6: YouTube-база | D6: Сад-огород | E6: 1840000 | F6: 288127 | G6: 0.0331 | I6: larazara67@mail.ru; https://knd.gov.ru/license?; https://fitstars.ru/subscribe?tariffs%255B%255D=51&utm_source=YouTube&utm_medium=%D0%A1%D0%90%D0%94%D0%9E%D0%92%D0%AB%D0%99%D0%93%D0%98%D0%94%D0%AE%D0%A2%D0%A3%D0%91&utm_campaign=2022&promo=%D0%A1%D0%90%D0%94%D0%9E%D0%92%D0%AB%D0%99 | J6: SADOVYIG | K6: Менеджер 2 | N6: https://www.youtube.com/channel/UCTXMeEml1hhGYagq7QZFqcA
A7: Fishing-Life TVvk | B7: VK | C7: YouTube-база | D7: Рыбалка | E7: 7700 | F7: 30000 | H7: 27500 | K7: Менеджер 2 | L7: договор в работе | N7: https://vkvideo.ru/@fishinglifetv/all | O7: =H7/F7 -> 0.91666667 | P7: =(H7/F7)*1000 -> 916.66667
A8: Fishing-Life TV | B8: YouTube | C8: YouTube-база | D8: Рыбалка | E8: 182000 | F8: 50000 | G8: 0.0256 | H8: 27500 | I8: fishinglifetvsibir@gmail.com | J8: FISHINGL | K8: Менеджер 2 | L8: договор в работе | N8: https://www.youtube.com/channel/UCw4X4WsJHT7UA_XhPONv5VQ | O8: =H8/F8 -> 0.55 | P8: =(H8/F8)*1000 -> 550
A9: Наша Дача | B9: Telegram | C9: Telega.in | D9: Сад-огород | E9: 176000 | G9: 0.0003 | H9: 14266 | I9: https://telega.in/channels/+7oFpKSAGX-s0MTcy/card | J9: NASHADAC | K9: Менеджер 2 | N9: https://t.me/+7oFpKSAGX-s0MTcy
A10: Уютный хуторок | B10: YouTube | C10: YouTube-база | D10: Сад-огород | E10: 176000 | F10: 84181 | G10: 0.0598 | I10: SalniS58@yandex.ru; vk.com/hutorok2025 | J10: UYUTNYIH | K10: Менеджер 2 | N10: https://www.youtube.com/channel/UC8n00W78oxs3zSx33-dC6PQ
A11: Дача | Дом | Огород | B11: Telegram | C11: Telega.in | D11: Сад-огород | E11: 173000 | G11: 0.00029 | H11: 22587 | I11: https://telega.in/channels/+qxekrBe5oJU5ZmIy/card | J11: DACHADOM | K11: Менеджер 2 | N11: https://t.me/+qxekrBe5oJU5ZmIy
A12: Северная рыбалка /Nord fishing | B12: YouTube | C12: YouTube-база | D12: Рыбалка | E12: 119000 | F12: 100000 | G12: 0.064 | H12: 78335 | I12: severnayarybalka@adisom.net; vk.com/club122717706; https://www.ozon.ru/product/zhilet-canadian-camper-fokel-1698137246/?at=RltylDMrRI0nRWVpF0EnV3MTMYnv99i3w8YrqtvljWpG&from_sku=1698146084&oos_search=false; https://www.ozon.ru/product/kurtka-canadian-camper-forkan-1831554104/?at=BrtzmXwVMupolJYQuyAXR0Ys6ApOM2fWO10grSDvNDqp&from_sku=1698094916&oos_search=false | J12: SEVERNAY | K12: Менеджер 2 | L12: отправлено письмо | N12: https://www.youtube.com/channel/UC-wseWH5WqECF0lZhZKxJJA | O12: =H12/F12 -> 0.78335 | P12: =(H12/F12)*1000 -> 783.35
A13: @batya_ilin | B13: YouTube | C13: YouTube-база | D13: Рыбалка | E13: 29600 | F13: 100000 | H13: 38000 | K13: Менеджер 2 | L13: отправлено письмо | N13: https://youtube.com/@batya_ilin | O13: =H13/F13 -> 0.38 | P13: =(H13/F13)*1000 -> 380
A14: novo_fish | B14: TikTok | C14: Tiktok-база | D14: Рыбалка | E14: 7930 | F14: 20000 | H14: 5000 | K14: Менеджер 2 | L14: договор в работе | N14: https://www.tiktok.com/@novo_fish | O14: =H14/F14 -> 0.25 | P14: =(H14/F14)*1000 -> 250
A15: viktorlife24 | B15: TikTok | C15: Tiktok-база | D15: Рыбалка | E15: 33000 | F15: 100000 | H15: 50000 | K15: Менеджер 2 | L15: договор в работе | N15: https://www.tiktok.com/@viktorlife24 | O15: =H15/F15 -> 0.5 | P15: =(H15/F15)*1000 -> 500
A16: viktorlife24youtube | B16: YouTube | C16: YouTube-база | D16: Рыбалка | E16: 6000 | F16: 40000 | H16: 15000 | K16: Менеджер 2 | L16: договор в работе | N16: https://www.youtube.com/@%D0%92%D0%B8%D0%BA%D1%82%D0%BE%D1%80%D0%BF%D1%80%D0%BE%D1%81%D1%82%D0%B0%D0%BD%D0%B8%D1%87%D0%BD%D1%83%D1%8E%D0%B6%D0%B8%D0%B7%D0%BD%D1%8C | O16: =H16/F16 -> 0.375 | P16: =(H16/F16)*1000 -> 375
A17: Хороший день для Рыбалки | B17: YouTube | C17: YouTube-база | D17: Рыбалка | E17: 62700 | F17: 10000 | G17: 0.0244 | H17: 7000 | I17: morfion321@gmail.com; vk.com/id222841731; https://www.donationalerts.com/r/golovinv; https://minoga.ru/?erid=2VtzquxLtyV | J17: HOROSHII | K17: Менеджер 2 | L17: отправлено письмо | N17: https://www.youtube.com/channel/UCppHEwOGz7QvGcXab64tIxQ | O17: =H17/F17 -> 0.7 | P17: =(H17/F17)*1000 -> 700
A18: Сибирский Странник | B18: YouTube | C18: YouTube-база | D18: Рыбалка | E18: 1320000 | F18: 749311 | G18: 0.0488 | I18: RUS151083@mail.ru; vk.com/id52521280; vk.com/alekssibirskiy; https://www.wildberries.ru/seller/250090340 | J18: SIBIRSKI | K18: Менеджер 2 | L18: сказал что подумает | N18: https://www.youtube.com/channel/UCgkes8es2x4yoEmLTGpMjEA | O18: =H18/F18 -> 0 | P18: =(H18/F18)*1000 -> 0
A19: PETROVCHANKA LERA | B19: YouTube | C19: YouTube-база | D19: Сад-огород | E19: 1220000 | F19: 1184993 | G19: 0.0325 | I19: @petrovchanka_lera; https://knd.gov.ru/license? | J19: PETROVCH | K19: Менеджер 2 | N19: https://www.youtube.com/channel/UCqJUOdRU1eFDk02BYxbWRnw
A20: AssistanceTV | B20: YouTube | C20: YouTube-база | D20: Рыбалка | E20: 1060000 | F20: 151971 | G20: 0.0311 | I20: serggioq21@gmail.com | J20: ASSISTAN | K20: Менеджер 2 | L20: украина | N20: https://www.youtube.com/channel/UC53tGQacLCKgMoViyQJTA_g | O20: =H20/F20 -> 0 | P20: =(H20/F20)*1000 -> 0
A21: Снасти здрасьте! | B21: YouTube | C21: YouTube-база | D21: Рыбалка | E21: 945000 | F21: 408588 | G21: 0.0342 | I21: Snastizdraste@yandex.ru | J21: SNASTIZD | K21: Менеджер 2 | L21: отправлено письмо | N21: https://www.youtube.com/channel/UCfkn7KM1LBAxxAq7r034a1w | O21: =H21/F21 -> 0 | P21: =(H21/F21)*1000 -> 0
A22: Тепличный бизнес в деревне! | B22: YouTube | C22: YouTube-база | D22: Сад-огород | E22: 938000 | F22: 188314 | G22: 0.0606 | I22: @yakov_ogorodnik; vk.com/public175441970; vk.com/id521874877; https://yakovogorodnik.ru; https://yakovogorodnik.ru/education | J22: TEPLICHN | K22: Менеджер 2 | N22: https://www.youtube.com/channel/UCqL7Y7jcVarKAxI45yjdfnw
A23: Сад-огород! LIFE | B23: YouTube | C23: YouTube-база | D23: Сад-огород | E23: 884000 | F23: 66164 | G23: 0.0175 | I23: https://max.ru/ch_62af5280dda22178b423a5d8 | J23: SADOGORO | K23: Менеджер 2 | N23: https://www.youtube.com/channel/UCpDmoTV4_8FRuiLVqlpa1ww
A24: Вероника Поливкина | B24: YouTube | C24: YouTube-база | D24: Сад-огород | E24: 814000 | F24: 65479 | G24: 0.0453 | I24: @veronika_polivkina; vk.com/club211638113; https://gosuslugi.ru/snet/67af2e74a7b872052aa3f19c; https://wibes.ru/author/1079485 | J24: VERONIKA | K24: Менеджер 2 | N24: https://www.youtube.com/channel/UC_zKdhty-DNqhnySR9FcVWg
A25: Голова садовая | B25: YouTube | C25: YouTube-база | D25: Сад-огород | E25: 770000 | F25: 73265 | G25: 0.0282 | I25: afontovo-tv@mail.ru; @golovasadova | J25: GOLOVASA | K25: Менеджер 2 | N25: https://www.youtube.com/channel/UCZP-t7tMmA-_hXpL90L3WBw
A26: СУПЕР - ОТПУСК на ДАЧЕ | B26: YouTube | C26: YouTube-база | D26: Сад-огород | E26: 714000 | F26: 129402 | G26: 0.056 | H26: 300 | I26: @garden_ramenskoe; vk.com/superotpusknadache; vk.com/garden_ram; https://knd.gov.ru/license?; https://bit.ly/484Z1aJ | J26: SUPEROTP | K26: Менеджер 2 | N26: https://www.youtube.com/channel/UCDbkx0Ci91M09HjQxzU9yuw
A27: ГЕНЕРАЛЬСКИЙ САД | B27: YouTube | C27: YouTube-база | D27: Сад-огород | E27: 675000 | F27: 214572 | G27: 0.0108 | I27: yrojaysad@gmail.com | J27: GENERALS | K27: Менеджер 2 | N27: https://www.youtube.com/channel/UCHQQ4wAhue1Tx46_IvzNOMQ
A28: Огород - сад Медведевых | B28: YouTube | C28: YouTube-база | D28: Сад-огород | E28: 581000 | F28: 81343 | G28: 0.0706 | I28: tomatoved@mail.ru; @ogorodsadmedvedevykh; vk.com/svoitomaty; https://svoisemena.ru; https://svoisemena.ru/pelargonii | J28: OGORODSA | K28: Менеджер 2 | N28: https://www.youtube.com/channel/UC7oAhM5FWIUgOzHZ8oXDQqQ
A29: КРУГОВОРОТ_ДАЧА_ОГОРОД | B29: YouTube | C29: YouTube-база | D29: Сад-огород | E29: 513000 | F29: 171767 | G29: 0.0372 | I29: -buba22438@gmail.com; @krugovorottdo | J29: KRUGOVOR | K29: Менеджер 2 | N29: https://www.youtube.com/channel/UCVyq0UBgM60QB434-iaDTVg
A30: Моя дача | B30: Telegram | C30: Telega.in | D30: Сад-огород | E30: 471000 | G30: 0.00027 | H30: 34965 | I30: https://telega.in/channels/mydaca/card | J30: MOYADACH | K30: Менеджер 2 | N30: https://t.me/mydaca
A31: Просто Марина | B31: YouTube | C31: YouTube-база | D31: Сад-огород | E31: 431000 | F31: 83052 | G31: 0.0471 | I31: alt-marina@yandex.ru; https://knd.gov.ru/license?; https://ydolv.mobz.click/umrkl3 | J31: PROSTOMA | K31: Менеджер 2 | N31: https://www.youtube.com/channel/UCFkoPqrepBhhmfKzClA-r_w
A32: ОРЗ ТВ - Охотники и Рыболовы ЗАПОЛЯРЬЯ | B32: YouTube | C32: YouTube-база | D32: Рыбалка | E32: 171000 | F32: 25000 | G32: 0.0504 | H32: 35000 | I32: orztv@themakers.ru; https://clck.ru/F4QLL; https://clck.ru/F4QKx | J32: ORZTVOHO | K32: Менеджер 2 | L32: отправлено письмо | N32: https://www.youtube.com/channel/UC6_SwzIMfPfWotQyRqWIKiQ | O32: =H32/F32 -> 1.4 | P32: =(H32/F32)*1000 -> 1400
A33: https://vk.ru/ohotnikinao | B33: VK | C33: Vkontakte-база | D33: Рыбалка | E33: 7500 | F33: 7000 | H33: 0 | K33: Менеджер 2 | N33: https://vk.ru/ohotnikinao | O33: =H33/F33 -> 0 | P33: =(H33/F33)*1000 -> 0
A34: АГАТ | B34: YouTube | C34: YouTube-база | D34: Рыбалка | E34: 408000 | F34: 360256 | G34: 0.049 | H34: 10000 | I34: agat017@yandex.ru | J34: AGAT | K34: Менеджер 2 | L34: отправлено письмо | N34: https://www.youtube.com/channel/UC8X_Ri3NBTXCoSNpOfgX82g | O34: =H34/F34 -> 0.027758039 | P34: =(H34/F34)*1000 -> 27.758039
A35: Волшебная грядка Марины Шевляковой | B35: YouTube | C35: YouTube-база | D35: Сад-огород | E35: 379000 | F35: 62039 | G35: 0.0333 | I35: marasja@gmail.com; @volshebnayagryadka; vk.com/volshebnaya_gryadka; https://gosuslugi.ru/snet/67b4a2d08c08d3723f2f3832; https://clck.ru/3TDmmp | J35: VOLSHEBN | K35: Менеджер 2 | N35: https://www.youtube.com/channel/UCbODBVkNzh3Ny23-m7X5s4w
A36: Татьяна Башмакова - Ваша Дача (vashadacha) | B36: YouTube | C36: YouTube-база | D36: Сад-огород | E36: 363000 | F36: 41670 | G36: 0.0696 | I36: vk.com/best_dacha | J36: TATYANAB | K36: Менеджер 2 | N36: https://www.youtube.com/channel/UCK_1NtbyzOK3w_ARLqNiWbg
A37: Алёнин сад | B37: YouTube | C37: YouTube-база | D37: Сад-огород | E37: 335000 | F37: 41378 | G37: 0.0601 | I37: @aleninsad; vk.com/aleninsad; http://www.aleninsad.com; https://web.max.ru/-68671270868407 | J37: ALENINSA | K37: Менеджер 2 | N37: https://www.youtube.com/channel/UCnJXX-FozHVLpLTeumHCrWQ
A38: Дача мечты | B38: Telegram | C38: Telega.in | D38: Сад-огород | E38: 333000 | G38: 0.00026 | H38: 30769 | I38: https://telega.in/channels/+D03xUB3vKRYyNDk6/card | J38: DACHAMEC | K38: Менеджер 2 | N38: https://t.me/+D03xUB3vKRYyNDk6
A39: Земеля | B39: YouTube | C39: YouTube-база | D39: Рыбалка | E39: 246000 | F39: 347154 | G39: 0.0532 | J39: ZEMELYA | K39: Менеджер 2 | L39: отправлено письмо в вк | N39: https://www.youtube.com/channel/UC1XrVpIJKHZUD9OCm9mDh8A | O39: =H39/F39 -> 0 | P39: =(H39/F39)*1000 -> 0
A40: Павел Про TV | B40: YouTube | C40: YouTube-база | D40: Рыбалка | E40: 319000 | F40: 219926 | G40: 0.061 | I40: vk.com/id366371122; @pavelprotv; altfishing-club.ru/user/755-pavel-pro | J40: PAVELPRO | K40: Менеджер 2 | L40: не подходит | N40: https://www.youtube.com/channel/UCjD01pt7Oic6hJg-h0NVihQ | O40: =H40/F40 -> 0 | P40: =(H40/F40)*1000 -> 0
A41: Клёвая рыбалка / Hot fishing | B41: YouTube | C41: YouTube-база | D41: Рыбалка | E41: 613000 | F41: 242206 | G41: 0.0507 | I41: vk.com/coolhotfishing; https://клеваярыбалка.рф; https://hot-fishing.com | J41: KLEVAYAR | K41: Менеджер 2 | L41: не подходит | N41: https://www.youtube.com/channel/UCaRJiAXxS3j2dEz0FLIjEGg | O41: =H41/F41 -> 0 | P41: =(H41/F41)*1000 -> 0
A42: Roman Boldov | B42: YouTube | C42: YouTube-база | D42: Рыбалка | E42: 137000 | F42: 10000 | G42: 0.0429 | H42: 12000 | I42: Roman-b-87@mail.ru | J42: ROMANBOL | K42: Менеджер 2 | L42: отказ | N42: https://www.youtube.com/channel/UCV0m-qMKxE470KxHvlt0jjA | O42: =H42/F42 -> 1.2 | P42: =(H42/F42)*1000 -> 1200
A43: Жизнь Рыбака | B43: YouTube | C43: YouTube-база | D43: Рыбалка | E43: 538000 | F43: 2285529 | G43: 0.0046 | I43: respectmr745@gmail.com; https://ozon.ru/t/qu5sJ2W; https://www.wildberries.ru/brands/berkutiv?utm_source=vkentryprofit&click_id=v1_1423720072 | J43: ZHIZNRYB | K43: Менеджер 2 | L43: отказ | N43: https://www.youtube.com/channel/UCZN71cXa20jqDvUJqM_4Dsw | O43: =H43/F43 -> 0 | P43: =(H43/F43)*1000 -> 0
A44: ДАЧА БЕЗ ПРОБЛЕМ | B44: YouTube | C44: YouTube-база | D44: Сад-огород | E44: 317000 | F44: 39208 | G44: 0.0202 | I44: https://vk.cc/cn46oL; https://app-qr.expert-garden.com | J44: DACHABEZ | K44: Менеджер 2 | N44: https://www.youtube.com/channel/UCMUja_GhH1ms0OLsjzNnwFA
A45: Огород с Вероникой | B45: YouTube | C45: YouTube-база | D45: Сад-огород | E45: 314000 | F45: 99701 | G45: 0.0078 | I45: @tantorro | J45: OGORODSV | K45: Менеджер 2 | N45: https://www.youtube.com/channel/UCllLNbD58QyOfXRyRxoPKFA
A46: Sergei Sorokin | B46: YouTube | C46: YouTube-база | D46: Рыбалка | E46: 312000 | F46: 293907 | G46: 0.0319 | I46: ser-sor@rambler.ru; @sorokinofficial; vk.com/sorokinpodvodoi | J46: SERGEISO | K46: Менеджер 2 | L46: мертвый канал | N46: https://www.youtube.com/channel/UCqxZ1TG5xVXS2Ra9vO0voOw | O46: =H46/F46 -> 0 | P46: =(H46/F46)*1000 -> 0
A47: САДОВОД ТВ | B47: YouTube | C47: YouTube-база | D47: Сад-огород | E47: 302000 | F47: 4192 | G47: 0.0335 | J47: SADOVODT | K47: Менеджер 2 | N47: https://www.youtube.com/channel/UC8W3xi4E2e_HUmP8RukpUDg
A48: "Газета садовод" | B48: YouTube | C48: YouTube-база | D48: Сад-огород | E48: 289000 | F48: 59875 | G48: 0.0705 | J48: GAZETASA | K48: Менеджер 2 | N48: https://www.youtube.com/channel/UCvZYCYUdqcHlHMxF4SvrCvQ
A49: Team Mida. Современная рыбалка. | B49: YouTube | C49: YouTube-база | D49: Рыбалка | E49: 147000 | F49: 46004 | G49: 0.029 | I49: vk.com/teammida; https://max.ru/join/lvR6xd6lSl1epeCKSuKe59pguk-8BVv6P9c5qhxpxp0; https://v | J49: TEAMMIDA | K49: Менеджер 2 | L49: отказ | N49: https://www.youtube.com/channel/UCDpg1XIZgBzK3mAOOOIbY7w | O49: =H49/F49 -> 0 | P49: =(H49/F49)*1000 -> 0
A50: Зеленый подоконник | B50: YouTube | C50: YouTube-база | D50: Сад-огород | E50: 147000 | F50: 175885 | G50: 0.0198 | I50: @green_podokonnik; @selfsation | J50: ZELENYIP | K50: Менеджер 2 | N50: https://www.youtube.com/channel/UCsAuu01m7B7VL-4GgF3hL2g
A51: Дача для души | B51: Telegram | C51: Telega.in | D51: Сад-огород | E51: 135000 | G51: 0.00036 | H51: 20979 | I51: https://telega.in/channels/+lq7V6APtadU0NTVi/card | J51: DACHADLY | K51: Менеджер 2 | N51: https://t.me/+lq7V6APtadU0NTVi
A52: Юг Fishing | B52: YouTube | C52: YouTube-база | D52: Рыбалка | E52: 133000 | F52: 90479 | G52: 0.032 | I52: vk.com/id711496236; https://www.ozon.ru/product/pellets-zhirnyy-yug-fishing-dlya-flet-metod-3-mm-1000-g-3756839039/?at=gpt4WzPVyuoGn155h0G2w2ZuqmREDpi8KYmQPcZ2o7Bo; https://www.avito.ru/novotitarovskaya/ohota_i_rybalka/pellets_karpovyy_1_kg_zhirnyy_fl | J52: YUGFISHI | K52: Менеджер 2 | L52: отказ | N52: https://www.youtube.com/channel/UCRb6HzMKtsH-dKJz831_dXA | O52: =H52/F52 -> 0 | P52: =(H52/F52)*1000 -> 0
A53: Рыбалка с SIBIRYAK'ом'007 | B53: YouTube | C53: YouTube-база | D53: Рыбалка | E53: 235000 | F53: 111659 | G53: 0.0303 | I53: https://knd.gov.ru/license? | J53: RYBALKAS | K53: Менеджер 2 | L53: отказ | N53: https://www.youtube.com/channel/UCyuBTqJ7N1mtWa6o_nuQWCA | O53: =H53/F53 -> 0 | P53: =(H53/F53)*1000 -> 0
A54: Нина К Дача, Огород и не только | B54: YouTube | C54: YouTube-база | D54: Сад-огород | E54: 225000 | F54: 35137 | G54: 0.0207 | I54: @garden42; vk.com/club184536437; https://rutube.ru/channel/23844582; https://ok.ru | J54: NINAKDAC | K54: Менеджер 2 | N54: https://www.youtube.com/channel/UC5lF8cWA7q0pcNcWC0ZOfSQ
A55: Идеи для Дачи | Дома | B55: Telegram | C55: Telega.in | D55: Сад-огород | E55: 222000 | G55: 0.00022 | H55: 10490 | I55: https://telega.in/channels/+U9natNWIHh1hNmNi/card | J55: IDEIDLYA | K55: Менеджер 2 | N55: https://t.me/+U9natNWIHh1hNmNi
A56: Простая рыбалка | B56: YouTube | C56: YouTube-база | D56: Рыбалка | E56: 222000 | F56: 49920 | G56: 0.0514 | I56: alex.afoni2012@yandex.ru | J56: PROSTAYA | K56: Менеджер 2 | L56: отказ | N56: https://www.youtube.com/channel/UCVFMI_n1if4JN71Sx0BAYPA | O56: =H56/F56 -> 0 | P56: =(H56/F56)*1000 -> 0
A57: Aleksandr Chikachev | B57: YouTube | C57: YouTube-база | D57: Рыбалка | E57: 34800 | F57: 34646 | G57: 0.0363 | I57: @alex666 | J57: ALEKSAND | K57: Менеджер 2 | N57: https://www.youtube.com/channel/UC10svREzub45n5TXQ_LMT5w | O57: =H57/F57 -> 0 | P57: =(H57/F57)*1000 -> 0
A58: ОХОТА И РЫБАЛКА В ТАЙГЕ Коми | B58: YouTube | C58: YouTube-база | D58: Рыбалка | E58: 286000 | F58: 77594 | G58: 0.0524 | I58: https://clck.ru/3Sx2nS | J58: OHOTAIRY | K58: Менеджер 2 | L58: мертвый канал | N58: https://www.youtube.com/channel/UCnEv7KTEI9IUGMNybDZQaCg | O58: =H58/F58 -> 0 | P58: =(H58/F58)*1000 -> 0
A59: ViNsad | B59: YouTube | C59: YouTube-база | D59: Сад-огород | E59: 282000 | F59: 210495 | G59: 0.0434 | J59: VINSAD | K59: Менеджер 2 | N59: https://www.youtube.com/channel/UCzeq_faG6ZzS5YFTwrPFCSA
A60: Агрофирма Аэлита | B60: YouTube | C60: YouTube-база | D60: Сад-огород | E60: 254000 | F60: 23023 | G60: 0.0784 | I60: vopros@ailita.ru; ailitazen@yandex.ru; https://www.ailita.ru; https://ailita-shop.ru | J60: AGROFIRM | K60: Менеджер 2 | N60: https://www.youtube.com/channel/UCQheT4QWhOG56NLrJV4kzyg
A61: Вкусный Огород | B61: YouTube | C61: YouTube-база | D61: Сад-огород | E61: 243000 | F61: 10918 | G61: 0.051 | I61: @tastygarden; vk.com/club212881292 | J61: VKUSNYIO | K61: Менеджер 2 | N61: https://www.youtube.com/channel/UC7ZlNkIlRRcPt3-c5pC2VYg
A62: Дачные будни | B62: Telegram | C62: Telega.in | D62: Сад-огород | E62: 214000 | G62: 0.00026 | H62: 9790 | I62: https://telega.in/channels/dacha_ogorod/card | J62: DACHNYEB | K62: Менеджер 2 | N62: https://t.me/dacha_ogorod
A63: Реальный садовод | B63: YouTube | C63: YouTube-база | D63: Сад-огород | E63: 205000 | F63: 20198 | G63: 0.009 | I63: vk.com/realny_sadovod; https://clck.ru/3MYtDa; https://click.tgtrack.ru/f637b132c0c7 | J63: REALNYIS | K63: Менеджер 2 | N63: https://www.youtube.com/channel/UCbJyBJL4jOKXBTfWpevKDYQ
A64: ЗУЛЬФИЯ САДОВОД ТУРЕЦКАЯ ДУБАЙСКАЯ ОДЕЖДА | B64: YouTube | C64: YouTube-база | D64: Сад-огород | E64: 192000 | F64: 16950 | G64: 0.011 | I64: @ZulfiyaSadovod | J64: ZULFIYAS | K64: Менеджер 2 | N64: https://www.youtube.com/channel/UCPkFY__r3ZHzRl8cmdn6gWg
A65: Садовая видеошкола "Сияние" | B65: YouTube | C65: YouTube-база | D65: Сад-огород | E65: 185000 | F65: 44360 | G65: 0.035 | I65: https://экологическоесадоводство.рф/%20es | J65: SADOVAYA | K65: Менеджер 2 | N65: https://www.youtube.com/channel/UCh4MKSoSFtBN2RVhhfGm6PQ
A66: Хатунский питомник | B66: YouTube | C66: YouTube-база | D66: Сад-огород | E66: 170000 | F66: 186730 | G66: 0.01 | I66: https://t.me/+6RZbRI24FrJiMmQ6; +7-926-579-45-11 (WhatsApp/Telegram) | J66: HATUNSKI | K66: Менеджер 2 | N66: https://www.youtube.com/channel/UCcodNXOztPjbz0JeEi4L33g
A67: VOLGA BAITS | B67: YouTube | C67: YouTube-база | D67: Рыбалка | E67: 160000 | F67: 60996 | G67: 0.0307 | I67: @volgabaits_support; vk.com/id729264477 | J67: VOLGABAI | K67: Менеджер 2 | L67: отправлено письмо в вк | N67: https://www.youtube.com/channel/UCuecqsAJJpRuN9f-aMYkHQA | O67: =H67/F67 -> 0 | P67: =(H67/F67)*1000 -> 0
A68: Моя любимая дача | B68: Telegram | C68: Telega.in | D68: Сад-огород | E68: 157000 | G68: 0.00033 | H68: 13986 | I68: https://telega.in/channels/+Jcbpgq-uhLA3NGNi/card | J68: MOYALYUB | K68: Менеджер 2 | N68: https://t.me/+Jcbpgq-uhLA3NGNi
A69: Садовый участок | B69: Telegram | C69: Telega.in | D69: Сад-огород | E69: 155000 | G69: 0.00025 | H69: 13986 | I69: https://telega.in/channels/+CC9q_wKrlc9kYmNi/card | J69: SADOVYIU | K69: Менеджер 2 | N69: https://t.me/+CC9q_wKrlc9kYmNi
A70: Сад и огород | Дача | B70: Telegram | C70: Telega.in | D70: Сад-огород | E70: 153000 | G70: 0.00034 | H70: 20979 | I70: https://telega.in/channels/+rC-80Q6BOmZmOTVi/card | J70: SADIOGOR | K70: Менеджер 2 | N70: https://t.me/+rC-80Q6BOmZmOTVi
A71: ЗА ВЕРСТУ... | B71: YouTube | C71: YouTube-база | D71: Рыбалка | E71: 151000 | F71: 250189 | G71: 0.0486 | I71: mikhail_krapivin@inbox.ru; @public220850526; https://vkvideo.ru/@public220850526/all | J71: ZAVERSTU | K71: Менеджер 2 | L71: отправлено письмо | N71: https://www.youtube.com/channel/UCRh5y1xNocuLxXJXDi1ovbQ | O71: =H71/F71 -> 0 | P71: =(H71/F71)*1000 -> 0
A72: Павел Теплов - Рыболовный Канал | B72: YouTube | C72: YouTube-база | D72: Рыбалка | E72: 112000 | F72: 38603 | G72: 0.0184 | J72: PAVELTEP | K72: Менеджер 2 | L72: не активный | N72: https://www.youtube.com/channel/UCehAWDtHiubIXsmqtNSjM4g | O72: =H72/F72 -> 0 | P72: =(H72/F72)*1000 -> 0
A73: Рыбалка на басса Продакшн | B73: YouTube | C73: YouTube-база | D73: Рыбалка | E73: 106000 | F73: 265481 | G73: 0.0175 | I73: advertising@linguana.com; @BassFishingProductions; https://lnk.to/BFPRussian; https://directs.me/matsato-ru | J73: RYBALKAN | K73: Менеджер 2 | L73: не наша ца | N73: https://www.youtube.com/channel/UCn6qEUsCGx37M_zOP9TiYGQ | O73: =H73/F73 -> 0 | P73: =(H73/F73)*1000 -> 0
A74: Рыбалка крупным планом | AnglersZoom | B74: YouTube | C74: YouTube-база | D74: Рыбалка | E74: 102000 | F74: 37003 | G74: 0.0345 | I74: https://gosuslugi.ru/snet/685e4f1ef794ae5554881e8d | J74: RYBALKAK | K74: Менеджер 2 | L74: не активный | N74: https://www.youtube.com/channel/UCmkkLCACwkNesX4dHMo4s9g | O74: =H74/F74 -> 0 | P74: =(H74/F74)*1000 -> 0
A75: DUNAEV MEDIA | B75: YouTube | C75: YouTube-база | D75: Рыбалка | E75: 95900 | F75: 30301 | G75: 0.039 | I75: @dunaevmedia; vk.com/dunaevmedia; https://frsrus.ru/wp-content/uploads/2026/03/reglament_provedenija_kubka_rossii_2026_goda_po_lovle_poplavochnoj.pdf; https://www.mirrods.ru | J75: DUNAEVME | K75: Менеджер 2 | L75: отказ | N75: https://www.youtube.com/channel/UCpC0_0lnarWbM2_iGR12f1w | O75: =H75/F75 -> 0 | P75: =(H75/F75)*1000 -> 0
A76: в ожидании поклевки | B76: YouTube | C76: YouTube-база | D76: Рыбалка | E76: 93000 | F76: 199356 | G76: 0.003 | I76: ivan_bgrff@mail.ru | J76: VOZHIDAN | K76: Менеджер 2 | L76: накрученый | N76: https://www.youtube.com/channel/UChEXU5Uil5PBXX6qoovJ7AA | O76: =H76/F76 -> 0 | P76: =(H76/F76)*1000 -> 0
A77: DMITRY KANEV Охота и Рыбалка | B77: YouTube | C77: YouTube-база | D77: Рыбалка | E77: 70300 | F77: 50465 | G77: 0.0325 | I77: vk.com/id299096755 | J77: DMITRYKA | K77: Менеджер 2 | L77: не активный | N77: https://www.youtube.com/channel/UCPmC7_3zFWhckq5cmnE5uwg | O77: =H77/F77 -> 0 | P77: =(H77/F77)*1000 -> 0
A78: Рыбалка С Олегом | B78: YouTube | C78: YouTube-база | D78: Рыбалка | E78: 78300 | F78: 54137 | G78: 0.0391 | J78: RYBALKAS | K78: Менеджер 2 | L78: не активный | N78: https://www.youtube.com/channel/UC3Wc772-8PBelvW1ivL8tcw | O78: =H78/F78 -> 0 | P78: =(H78/F78)*1000 -> 0
A79: Рыбалка по кайфу | B79: YouTube | C79: YouTube-база | D79: Рыбалка | E79: 67400 | F79: 91245 | G79: 0.0353 | I79: fargame2000@gmail.com; vk.com/idfargame | J79: RYBALKAP | K79: Менеджер 2 | L79: не наша ца | N79: https://www.youtube.com/channel/UCENnsGw3xk-1EvjBobTMoUQ | O79: =H79/F79 -> 0 | P79: =(H79/F79)*1000 -> 0
A80: Рыбалка на реках и озёрах | B80: YouTube | C80: YouTube-база | D80: Рыбалка | E80: 89800 | F80: 50680 | G80: 0.0288 | I80: vk.com/id357569604 | J80: RYBALKAN | K80: Менеджер 2 | L80: уже сотрудничают | N80: https://www.youtube.com/channel/UCNrT0fjlD-K1TZRPjpz32NA | O80: =H80/F80 -> 0 | P80: =(H80/F80)*1000 -> 0
A81: Сергей Веснин | B81: YouTube | C81: YouTube-база | D81: Рыбалка | E81: 66300 | F81: 58796 | G81: 0.057 | I81: https://knd.gov.ru/license?id=6737dcc0b5d2ec30cf746dcc&registryType=bloggersPermission | J81: SERGEIVE | K81: Менеджер 2 | L81: на хищников не наша ца | N81: https://www.youtube.com/channel/UCxNRrMeOWrwvW3ZUHHluC3w | O81: =H81/F81 -> 0 | P81: =(H81/F81)*1000 -> 0
A82: Гарик Рыболов. | B82: YouTube | C82: YouTube-база | D82: Рыбалка | E82: 62400 | F82: 40983 | G82: 0.0528 | I82: garikfihermen@yandex.ru | J82: GARIKRYB | K82: Менеджер 2 | N82: https://www.youtube.com/channel/UCHBZmzMpiuvo8sSu1Xtxiew | O82: =H82/F82 -> 0 | P82: =(H82/F82)*1000 -> 0
A83: NovichenkovFishing | B83: YouTube | C83: YouTube-база | D83: Рыбалка | E83: 32800 | F83: 31177 | G83: 0.0586 | I83: https://clck.ru/3QiDLY; https://clck.ru/3QiDNJ | J83: NOVICHEN | K83: Менеджер 2 | N83: https://www.youtube.com/channel/UCqwhN5t4D3tMD2QN0SzjMQw | O83: =H83/F83 -> 0 | P83: =(H83/F83)*1000 -> 0
A84: Клёвое место Ямал | B84: YouTube | C84: YouTube-база | D84: Рыбалка | E84: 60400 | F84: 67574 | G84: 0.0221 | J84: KLEVOEME | K84: Менеджер 2 | L84: не активный | N84: https://www.youtube.com/channel/UCwmT1rw7ZQFllFVnNlL4oBg | O84: =H84/F84 -> 0 | P84: =(H84/F84)*1000 -> 0
A85: Кержак. Рыбалка в тайге | B85: YouTube | C85: YouTube-база | D85: Рыбалка | E85: 58600 | F85: 101281 | G85: 0.0069 | I85: https://carptravel.mobz.link/kerzhak | J85: KERZHAKR | K85: Менеджер 2 | L85: не активный | N85: https://www.youtube.com/channel/UCsKbMwfWxBVcbOmDfkqYZEw | O85: =H85/F85 -> 0 | P85: =(H85/F85)*1000 -> 0
A86: Сибирская рыбалка | B86: YouTube | C86: YouTube-база | D86: Рыбалка | E86: 43100 | F86: 39109 | G86: 0.0668 | I86: vk.com/id324436513; vk.com/...rom; https://knd.gov.ru/license?id=673b1ed031a9292acd15c11a&registryType=bloggersPermission | J86: SIBIRSKA | K86: Менеджер 2 | L86: не активный | N86: https://www.youtube.com/channel/UCB6N3tv-AmmK2cWVOy3KNLg | O86: =H86/F86 -> 0 | P86: =(H86/F86)*1000 -> 0
A87: FishingSib.ru | B87: YouTube | C87: YouTube-база | D87: Рыбалка | E87: 40800 | F87: 87356 | G87: 0.0168 | J87: FISHINGS | K87: Менеджер 2 | N87: https://www.youtube.com/channel/UCVxs5hp57vZZW6_mA74V2Qw | O87: =H87/F87 -> 0 | P87: =(H87/F87)*1000 -> 0
A88: Рыбацкий Кайф | B88: YouTube | C88: YouTube-база | D88: Рыбалка | E88: 63800 | F88: 62964 | G88: 0.0326 | I88: vladka26a@gmail.com; https://knd.gov.ru/license? | J88: RYBACKII | K88: Менеджер 2 | L88: отправлено письмо | N88: https://www.youtube.com/channel/UCekGRaIjwZU8nu0FvSObUmA | O88: =H88/F88 -> 0 | P88: =(H88/F88)*1000 -> 0
A89: Рыбалка в Боровом | B89: YouTube | C89: YouTube-база | D89: Рыбалка | E89: 29100 | F89: 23547 | G89: 0.021 | I89: Maksutov-2005@bk.ru; @barkrf_bot201; https://chat.lera-trade.com/6cMvyZNLF2?utm_id=yt31; https://barknn.ru/@barkrf_bot201 | J89: RYBALKAV | K89: Менеджер 2 | N89: https://www.youtube.com/channel/UCrYeV85Ln_udR_g9AE3nG9g | O89: =H89/F89 -> 0 | P89: =(H89/F89)*1000 -> 0
A90: Андрей Брюховецкий | B90: YouTube | C90: YouTube-база | D90: Рыбалка | E90: 29400 | F90: 47864 | G90: 0.0088 | J90: ANDREIBR | K90: Менеджер 2 | N90: https://www.youtube.com/channel/UCecYT9x7r49dkOuzR-jrKEQ | O90: =H90/F90 -> 0 | P90: =(H90/F90)*1000 -> 0
A91: Евгений Середа | B91: YouTube | C91: YouTube-база | D91: Рыбалка | E91: 30000 | F91: 78691 | G91: 0.0242 | J91: EVGENIIS | K91: Менеджер 2 | N91: https://www.youtube.com/channel/UCra4W5pe9fTGjE7ChFadRRw | O91: =H91/F91 -> 0 | P91: =(H91/F91)*1000 -> 0
A92: Сматываем Удочки | B92: YouTube | C92: YouTube-база | D92: Рыбалка | E92: 39200 | F92: 16493 | G92: 0.0364 | I92: smatyvaemudochki@mail.ru; vk.com/kkisler; vk.com/smatyvaemudochki; vk.com/kiprinofishing; https://www.donationalerts.com/r/smatyvaemudochki; https://knd.gov.ru/license?id=674aa15946efdb335e0c976a&registryType=bloggersPermission | J92: SMATYVAE | K92: Менеджер 2 | N92: https://www.youtube.com/channel/UClcw3KW_zDl07o1GoDzB1aA | O92: =H92/F92 -> 0 | P92: =(H92/F92)*1000 -> 0
A93: Рыбалка В Сибири | B93: YouTube | C93: YouTube-база | D93: Рыбалка | E93: 32500 | F93: 41611 | G93: 0.0317 | I93: https://dzen.ru/id/625ead39a0b8661907934f73 | J93: RYBALKAV | K93: Менеджер 2 | N93: https://www.youtube.com/channel/UCRY8-G9MxuzOpGCANtY6RlQ | O93: =H93/F93 -> 0 | P93: =(H93/F93)*1000 -> 0
A94: Рыбалка с Антоном Мальцевым | B94: YouTube | C94: YouTube-база | D94: Рыбалка | E94: 26900 | F94: 86517 | G94: 0.0126 | J94: RYBALKAS | K94: Менеджер 2 | N94: https://www.youtube.com/channel/UC3deJoTQ0ZdrMHmvy0uVc_w | O94: =H94/F94 -> 0 | P94: =(H94/F94)*1000 -> 0
A95: РЫБАЛКА Илья Эверстов | B95: YouTube | C95: YouTube-база | D95: Рыбалка | E95: 18600 | F95: 233855 | G95: 0.0226 | J95: RYBALKAI | K95: Менеджер 2 | N95: https://www.youtube.com/channel/UC9uLFbxpbfsumFS-JRqgrRg | O95: =H95/F95 -> 0 | P95: =(H95/F95)*1000 -> 0
A96: Spin-feeder TV | B96: YouTube | C96: YouTube-база | D96: Рыбалка | E96: 17900 | F96: 17403 | G96: 0.0736 | I96: vk.com/spinfeeder | J96: SPINFEED | K96: Менеджер 2 | N96: https://www.youtube.com/channel/UCK_wzLu0QxxysoVLQrGXhog | O96: =H96/F96 -> 0 | P96: =(H96/F96)*1000 -> 0
A97: Александр Заядлый - Рыбалка | B97: YouTube | C97: YouTube-база | D97: Рыбалка | E97: 16800 | F97: 22612 | G97: 0.0342 | I97: bbeting@yandex.ru; @aeroladoga; vk.com/sashazayadlyy; https://finntrail.ru/zayadly; https://www.hunting-expo.ru/priroda-premia/stili_gizni/cart/76898 | J97: ALEKSAND | K97: Менеджер 2 | N97: https://www.youtube.com/channel/UCG8vVMKgthuE7_tf5DH6Gng | O97: =H97/F97 -> 0 | P97: =(H97/F97)*1000 -> 0
A98: рыбалка ньюс | B98: YouTube | C98: YouTube-база | D98: Рыбалка | E98: 16600 | F98: 23809 | G98: 0.0351 | I98: https://www.higashi.ru/catalog/udilishcha/spiningovye/seriya_fanat/udilishche_higashi_fanat_2_4m_5_20g; http://alii.pub/6fh65t | J98: RYBALKAN | K98: Менеджер 2 | N98: https://www.youtube.com/channel/UC8xHe5d46bUjwNSepFt0QSw | O98: =H98/F98 -> 0 | P98: =(H98/F98)*1000 -> 0
A99: Дача без забот | B99: Telegram | C99: Telega.in | D99: Сад-огород | E99: 14800 | G99: 0.00028 | H99: 1126 | I99: https://telega.in/channels/easy_dacha/card | J99: DACHABEZ | K99: Менеджер 2 | N99: https://t.me/easy_dacha
A100: Современная Дача | B100: Telegram | C100: Telega.in | D100: Сад-огород | E100: 14500 | G100: 0.00024 | H100: 699 | I100: https://telega.in/channels/+2RCOBqjrzA42YTAy/card | J100: SOVREMEN | K100: Менеджер 2 | N100: https://t.me/+2RCOBqjrzA42YTAy
A101: Японские Снасти - JPSNASTI | B101: YouTube | C101: YouTube-база | D101: Рыбалка | E101: 14500 | F101: 5497 | G101: 0.0224 | I101: https://www.jpsnasti.ru | J101: YAPONSKI | K101: Менеджер 2 | N101: https://www.youtube.com/channel/UCOM_Ir3zsiLVpcatY0T_Vhw | O101: =H101/F101 -> 0 | P101: =(H101/F101)*1000 -> 0
...

Sheet Медиаплан
A1: МЕДИАПЛАН — Триггер (прикормки для рыб)
A2: Синее — задаёт руководитель (бюджет, цель). Жёлтое — заполняет менеджер (охват, CTR, CR, чек, % выкупа). Серое — считается формулами.
A6: ▼ АВГУСТ 2026
A7: Бюджет на месяц, ₽ | B7: =3154950/2 -> 1577475 | D7: Целевой DRR | E7: 0.13
A8: Канал | B8: Бюджет, ₽ | C8: Прогноз CPV, ₽ | D8: Прогноз охвата | E8: CTR % | F8: Клики | G8: CR в заказ % | H8: Заказы | I8: CPO, ₽ | J8: Выкупы | K8: Стоимость выкупа, ₽ | L8: Выручка, ₽ | M8: DRR
A9: МАРКЕТПЛЕЙС (ВБ / Ozon) | G9: Ср. чек, ₽ | H9: 600 | J9: % выкупа | K9: 0.95 | M9: 0.18
A10: Telegram | B10: 200000 | C10: 0.57 | D10: =IF(OR(B10="",C10=""),"",ROUND(B10/C10,0)) -> 350877 | E10: 0.0082 | F10: =IF(OR(D10="",E10=""),"",ROUND(D10*E10,0)) -> 2877 | G10: 0.17 | H10: =IF(OR(F10="",G10=""),"",ROUND(F10*G10,0)) -> 489 | I10: =IF(N(H10)=0,"",ROUND(B10/H10,0)) -> 409 | J10: =IF(OR(N(H10)=0,$K$9=""),"",ROUND(H10*$K$9,0)) -> 465 | K10: =IF(N(J10)=0,"",ROUND(B10/J10,0)) -> 430 | L10: =IF(N(J10)=0,"",ROUND(J10*$H$9,0)) -> 279000 | M10: =IF(N(L10)=0,"",B10/L10) -> 0.71684588
A11: MAX | B11: 283000 | C11: 0.71 | D11: =IF(OR(B11="",C11=""),"",ROUND(B11/C11,0)) -> 398592 | E11: 0.021 | F11: =IF(OR(D11="",E11=""),"",ROUND(D11*E11,0)) -> 8370 | G11: 0.23 | H11: =IF(OR(F11="",G11=""),"",ROUND(F11*G11,0)) -> 1925 | I11: =IF(N(H11)=0,"",ROUND(B11/H11,0)) -> 147 | J11: =IF(OR(N(H11)=0,$K$9=""),"",ROUND(H11*$K$9,0)) -> 1829 | K11: =IF(N(J11)=0,"",ROUND(B11/J11,0)) -> 155 | L11: =IF(N(J11)=0,"",ROUND(J11*$H$9,0)) -> 1097400 | M11: =IF(N(L11)=0,"",B11/L11) -> 0.25788227
A12: VK | B12: 274000 | C12: 0.72 | D12: =IF(OR(B12="",C12=""),"",ROUND(B12/C12,0)) -> 380556 | E12: 0.012 | F12: =IF(OR(D12="",E12=""),"",ROUND(D12*E12,0)) -> 4567 | G12: 0.23 | H12: =IF(OR(F12="",G12=""),"",ROUND(F12*G12,0)) -> 1050 | I12: =IF(N(H12)=0,"",ROUND(B12/H12,0)) -> 261 | J12: =IF(OR(N(H12)=0,$K$9=""),"",ROUND(H12*$K$9,0)) -> 998 | K12: =IF(N(J12)=0,"",ROUND(B12/J12,0)) -> 275 | L12: =IF(N(J12)=0,"",ROUND(J12*$H$9,0)) -> 598800 | M12: =IF(N(L12)=0,"",B12/L12) -> 0.45758183
A13: YouTube | B13: 400000 | C13: 0.35 | D13: =IF(OR(B13="",C13=""),"",ROUND(B13/C13,0)) -> 1142857 | E13: 0.006 | F13: =IF(OR(D13="",E13=""),"",ROUND(D13*E13,0)) -> 6857 | G13: 0.23 | H13: =IF(OR(F13="",G13=""),"",ROUND(F13*G13,0)) -> 1577 | I13: =IF(N(H13)=0,"",ROUND(B13/H13,0)) -> 254 | J13: =IF(OR(N(H13)=0,$K$9=""),"",ROUND(H13*$K$9,0)) -> 1498 | K13: =IF(N(J13)=0,"",ROUND(B13/J13,0)) -> 267 | L13: =IF(N(J13)=0,"",ROUND(J13*$H$9,0)) -> 898800 | M13: =IF(N(L13)=0,"",B13/L13) -> 0.44503783
A14: TikTok | B14: 150000 | C14: 0.8 | D14: =IF(OR(B14="",C14=""),"",ROUND(B14/C14,0)) -> 187500 | E14: 0.01 | F14: =IF(OR(D14="",E14=""),"",ROUND(D14*E14,0)) -> 1875 | G14: 0.23 | H14: =IF(OR(F14="",G14=""),"",ROUND(F14*G14,0)) -> 431 | I14: =IF(N(H14)=0,"",ROUND(B14/H14,0)) -> 348 | J14: =IF(OR(N(H14)=0,$K$9=""),"",ROUND(H14*$K$9,0)) -> 409 | K14: =IF(N(J14)=0,"",ROUND(B14/J14,0)) -> 367 | L14: =IF(N(J14)=0,"",ROUND(J14*$H$9,0)) -> 245400 | M14: =IF(N(L14)=0,"",B14/L14) -> 0.61124694
A15: Rutube | D15: =IF(OR(B15="",C15=""),"",ROUND(B15/C15,0)) | F15: =IF(OR(D15="",E15=""),"",ROUND(D15*E15,0)) | H15: =IF(OR(F15="",G15=""),"",ROUND(F15*G15,0)) | I15: =IF(N(H15)=0,"",ROUND(B15/H15,0)) | J15: =IF(OR(N(H15)=0,$K$9=""),"",ROUND(H15*$K$9,0)) | K15: =IF(N(J15)=0,"",ROUND(B15/J15,0)) | L15: =IF(N(J15)=0,"",ROUND(J15*$H$9,0)) | M15: =IF(N(L15)=0,"",B15/L15)
A16: Instagram | D16: =IF(OR(B16="",C16=""),"",ROUND(B16/C16,0)) | F16: =IF(OR(D16="",E16=""),"",ROUND(D16*E16,0)) | H16: =IF(OR(F16="",G16=""),"",ROUND(F16*G16,0)) | I16: =IF(N(H16)=0,"",ROUND(B16/H16,0)) | J16: =IF(OR(N(H16)=0,$K$9=""),"",ROUND(H16*$K$9,0)) | K16: =IF(N(J16)=0,"",ROUND(B16/J16,0)) | L16: =IF(N(J16)=0,"",ROUND(J16*$H$9,0)) | M16: =IF(N(L16)=0,"",B16/L16)
A17: ИТОГО — МП | B17: =SUM(B10:B16) -> 1307000 | C17: =IF(N(D17)=0,"",ROUND(B17/D17,2)) -> 0.53 | D17: =SUM(D10:D16) -> 2460382 | F17: =SUM(F10:F16) -> 24546 | H17: =SUM(H10:H16) -> 5472 | I17: =IF(N(H17)=0,"",ROUND(B17/H17,0)) -> 239 | J17: =SUM(J10:J16) -> 5199 | K17: =IF(N(J17)=0,"",ROUND(B17/J17,0)) -> 251 | L17: =SUM(L10:L16) -> 3119400 | M17: =IF(N(L17)=0,"",B17/L17) -> 0.41899083
A18: САЙТ | G18: Ср. чек, ₽ | H18: 1180 | J18: % выкупа | K18: 0.95
A19: Telegram | B19: 40000 | C19: 0.57 | D19: =IF(OR(B19="",C19=""),"",ROUND(B19/C19,0)) -> 70175 | E19: 0.0082 | F19: =IF(OR(D19="",E19=""),"",ROUND(D19*E19,0)) -> 575 | G19: 0.08 | H19: =IF(OR(F19="",G19=""),"",ROUND(F19*G19,0)) -> 46 | I19: =IF(N(H19)=0,"",ROUND(B19/H19,0)) -> 870 | J19: =IF(OR(N(H19)=0,$K$18=""),"",ROUND(H19*$K$18,0)) -> 44 | K19: =IF(N(J19)=0,"",ROUND(B19/J19,0)) -> 909 | L19: =IF(N(J19)=0,"",ROUND(J19*$H$18,0)) -> 51920 | M19: =IF(N(L19)=0,"",B19/L19) -> 0.77041602
A20: MAX | B20: 50475 | C20: 0.71 | D20: =IF(OR(B20="",C20=""),"",ROUND(B20/C20,0)) -> 71092 | E20: 0.021 | F20: =IF(OR(D20="",E20=""),"",ROUND(D20*E20,0)) -> 1493 | G20: 0.11 | H20: =IF(OR(F20="",G20=""),"",ROUND(F20*G20,0)) -> 164 | I20: =IF(N(H20)=0,"",ROUND(B20/H20,0)) -> 308 | J20: =IF(OR(N(H20)=0,$K$18=""),"",ROUND(H20*$K$18,0)) -> 156 | K20: =IF(N(J20)=0,"",ROUND(B20/J20,0)) -> 324 | L20: =IF(N(J20)=0,"",ROUND(J20*$H$18,0)) -> 184080 | M20: =IF(N(L20)=0,"",B20/L20) -> 0.27420143
A21: VK | B21: 30000 | C21: 0.72 | D21: =IF(OR(B21="",C21=""),"",ROUND(B21/C21,0)) -> 41667 | E21: 0.012 | F21: =IF(OR(D21="",E21=""),"",ROUND(D21*E21,0)) -> 500 | G21: 0.11 | H21: =IF(OR(F21="",G21=""),"",ROUND(F21*G21,0)) -> 55 | I21: =IF(N(H21)=0,"",ROUND(B21/H21,0)) -> 545 | J21: =IF(OR(N(H21)=0,$K$18=""),"",ROUND(H21*$K$18,0)) -> 52 | K21: =IF(N(J21)=0,"",ROUND(B21/J21,0)) -> 577 | L21: =IF(N(J21)=0,"",ROUND(J21*$H$18,0)) -> 61360 | M21: =IF(N(L21)=0,"",B21/L21) -> 0.48891786
A22: YouTube | B22: 100000 | C22: 0.35 | D22: =IF(OR(B22="",C22=""),"",ROUND(B22/C22,0)) -> 285714 | E22: 0.006 | F22: =IF(OR(D22="",E22=""),"",ROUND(D22*E22,0)) -> 1714 | G22: 0.11 | H22: =IF(OR(F22="",G22=""),"",ROUND(F22*G22,0)) -> 189 | I22: =IF(N(H22)=0,"",ROUND(B22/H22,0)) -> 529 | J22: =IF(OR(N(H22)=0,$K$18=""),"",ROUND(H22*$K$18,0)) -> 180 | K22: =IF(N(J22)=0,"",ROUND(B22/J22,0)) -> 556 | L22: =IF(N(J22)=0,"",ROUND(J22*$H$18,0)) -> 212400 | M22: =IF(N(L22)=0,"",B22/L22) -> 0.47080979
A23: TikTok | B23: 50000 | C23: 0.8 | D23: =IF(OR(B23="",C23=""),"",ROUND(B23/C23,0)) -> 62500 | E23: 0.01 | F23: =IF(OR(D23="",E23=""),"",ROUND(D23*E23,0)) -> 625 | G23: 0.11 | H23: =IF(OR(F23="",G23=""),"",ROUND(F23*G23,0)) -> 69 | I23: =IF(N(H23)=0,"",ROUND(B23/H23,0)) -> 725 | J23: =IF(OR(N(H23)=0,$K$18=""),"",ROUND(H23*$K$18,0)) -> 66 | K23: =IF(N(J23)=0,"",ROUND(B23/J23,0)) -> 758 | L23: =IF(N(J23)=0,"",ROUND(J23*$H$18,0)) -> 77880 | M23: =IF(N(L23)=0,"",B23/L23) -> 0.64201335
A24: Rutube | D24: =IF(OR(B24="",C24=""),"",ROUND(B24/C24,0)) | F24: =IF(OR(D24="",E24=""),"",ROUND(D24*E24,0)) | H24: =IF(OR(F24="",G24=""),"",ROUND(F24*G24,0)) | I24: =IF(N(H24)=0,"",ROUND(B24/H24,0)) | J24: =IF(OR(N(H24)=0,$K$18=""),"",ROUND(H24*$K$18,0)) | K24: =IF(N(J24)=0,"",ROUND(B24/J24,0)) | L24: =IF(N(J24)=0,"",ROUND(J24*$H$18,0)) | M24: =IF(N(L24)=0,"",B24/L24)
A25: Instagram | D25: =IF(OR(B25="",C25=""),"",ROUND(B25/C25,0)) | F25: =IF(OR(D25="",E25=""),"",ROUND(D25*E25,0)) | H25: =IF(OR(F25="",G25=""),"",ROUND(F25*G25,0)) | I25: =IF(N(H25)=0,"",ROUND(B25/H25,0)) | J25: =IF(OR(N(H25)=0,$K$18=""),"",ROUND(H25*$K$18,0)) | K25: =IF(N(J25)=0,"",ROUND(B25/J25,0)) | L25: =IF(N(J25)=0,"",ROUND(J25*$H$18,0)) | M25: =IF(N(L25)=0,"",B25/L25)
A26: ИТОГО — Сайт | B26: =SUM(B19:B25) -> 270475 | C26: =IF(N(D26)=0,"",ROUND(B26/D26,2)) -> 0.51 | D26: =SUM(D19:D25) -> 531148 | F26: =SUM(F19:F25) -> 4907 | H26: =SUM(H19:H25) -> 523 | I26: =IF(N(H26)=0,"",ROUND(B26/H26,0)) -> 517 | J26: =SUM(J19:J25) -> 498 | K26: =IF(N(J26)=0,"",ROUND(B26/J26,0)) -> 543 | L26: =SUM(L19:L25) -> 587640 | M26: =IF(N(L26)=0,"",B26/L26) -> 0.4602733
A27: ИТОГО ЗА МЕСЯЦ (МП + Сайт) | B27: =B17+B26 -> 1577475 | C27: =IF(N(D27)=0,"",ROUND(B27/D27,2)) -> 0.53 | D27: =D17+D26 -> 2991530 | F27: =F17+F26 -> 29453 | H27: =H17+H26 -> 5995 | I27: =IF(N(H27)=0,"",ROUND(B27/H27,0)) -> 263 | J27: =J17+J26 -> 5697 | K27: =IF(N(J27)=0,"",ROUND(B27/J27,0)) -> 277 | L27: =L17+L26 -> 3707040 | M27: =IF(N(L27)=0,"",B27/L27) -> 0.42553493
A28: Вердикт по DRR | B28: =IF(OR(N(L27)=0,N($E$7)=0),"Заполни бюджет, CPV и параметры",IF(M27<=$E$7,"В ЦЕЛЬ: DRR "&ROUND(M27*100,1)&"% при цели "&ROUND($E$7*100,1)&"%","ВЫШЕ ЦЕЛИ: DRR "&ROUND(M27*100,1)&"% при цели "&ROUND($E$7*100,1)&"%")) -> ВЫШЕ ЦЕЛИ: DRR 42,6% при цели 13%
A30: ▼ Сентябрь 2026 | B30: AT
A31: Бюджет на месяц, ₽ | B31: 660000 | D31: Целевой DRR | E31: 0.13
A32: Канал | B32: Бюджет, ₽ | C32: Прогноз CPV, ₽ | D32: Прогноз охвата | E32: CTR % | F32: Клики | G32: CR в заказ % | H32: Заказы | I32: CPO, ₽ | J32: Выкупы | K32: Стоимость выкупа, ₽ | L32: Выручка, ₽ | M32: DRR
A33: МАРКЕТПЛЕЙС (ВБ / Ozon) | G33: Ср. чек, ₽ | H33: 748 | J33: % выкупа | K33: 0.95 | M33: 0.18
A34: Telegram | B34: 31000 | C34: 0.8 | D34: =IF(OR(B34="",C34=""),"",ROUND(B34/C34,0)) -> 38750 | E34: 0.0082 | F34: =IF(OR(D34="",E34=""),"",ROUND(D34*E34,0)) -> 318 | G34: 0.17 | H34: =IF(OR(F34="",G34=""),"",ROUND(F34*G34,0)) -> 54 | I34: =IF(N(H34)=0,"",ROUND(B34/H34,0)) -> 574 | J34: =IF(OR(N(H34)=0,$K$9=""),"",ROUND(H34*$K$9,0)) -> 51 | K34: =IF(N(J34)=0,"",ROUND(B34/J34,0)) -> 608 | L34: =IF(N(J34)=0,"",ROUND(J34*$H$9,0)) -> 30600 | M34: =IF(N(L34)=0,"",B34/L34) -> 1.0130719
A35: MAX | B35: 63000 | C35: 0.9 | D35: =IF(OR(B35="",C35=""),"",ROUND(B35/C35,0)) -> 70000 | E35: 0.021 | F35: =IF(OR(D35="",E35=""),"",ROUND(D35*E35,0)) -> 1470 | G35: 0.23 | H35: =IF(OR(F35="",G35=""),"",ROUND(F35*G35,0)) -> 338 | I35: =IF(N(H35)=0,"",ROUND(B35/H35,0)) -> 186 | J35: =IF(OR(N(H35)=0,$K$9=""),"",ROUND(H35*$K$9,0)) -> 321 | K35: =IF(N(J35)=0,"",ROUND(B35/J35,0)) -> 196 | L35: =IF(N(J35)=0,"",ROUND(J35*$H$9,0)) -> 192600 | M35: =IF(N(L35)=0,"",B35/L35) -> 0.3271028
A36: VK | B36: 119000 | C36: 0.72 | D36: =IF(OR(B36="",C36=""),"",ROUND(B36/C36,0)) -> 165278 | E36: 0.012 | F36: =IF(OR(D36="",E36=""),"",ROUND(D36*E36,0)) -> 1983 | G36: 0.23 | H36: =IF(OR(F36="",G36=""),"",ROUND(F36*G36,0)) -> 456 | I36: =IF(N(H36)=0,"",ROUND(B36/H36,0)) -> 261 | J36: =IF(OR(N(H36)=0,$K$9=""),"",ROUND(H36*$K$9,0)) -> 433 | K36: =IF(N(J36)=0,"",ROUND(B36/J36,0)) -> 275 | L36: =IF(N(J36)=0,"",ROUND(J36*$H$9,0)) -> 259800 | M36: =IF(N(L36)=0,"",B36/L36) -> 0.45804465
A37: YouTube | B37: 200000 | C37: 0.6 | D37: =IF(OR(B37="",C37=""),"",ROUND(B37/C37,0)) -> 333333 | E37: 0.006 | F37: =IF(OR(D37="",E37=""),"",ROUND(D37*E37,0)) -> 2000 | G37: 0.23 | H37: =IF(OR(F37="",G37=""),"",ROUND(F37*G37,0)) -> 460 | I37: =IF(N(H37)=0,"",ROUND(B37/H37,0)) -> 435 | J37: =IF(OR(N(H37)=0,$K$9=""),"",ROUND(H37*$K$9,0)) -> 437 | K37: =IF(N(J37)=0,"",ROUND(B37/J37,0)) -> 458 | L37: =IF(N(J37)=0,"",ROUND(J37*$H$9,0)) -> 262200 | M37: =IF(N(L37)=0,"",B37/L37) -> 0.76277651
A38: TikTok | B38: 217000 | C38: 0.8 | D38: =IF(OR(B38="",C38=""),"",ROUND(B38/C38,0)) -> 271250 | E38: 0.01 | F38: =IF(OR(D38="",E38=""),"",ROUND(D38*E38,0)) -> 2713 | G38: 0.23 | H38: =IF(OR(F38="",G38=""),"",ROUND(F38*G38,0)) -> 624 | I38: =IF(N(H38)=0,"",ROUND(B38/H38,0)) -> 348 | J38: =IF(OR(N(H38)=0,$K$9=""),"",ROUND(H38*$K$9,0)) -> 593 | K38: =IF(N(J38)=0,"",ROUND(B38/J38,0)) -> 366 | L38: =IF(N(J38)=0,"",ROUND(J38*$H$9,0)) -> 355800 | M38: =IF(N(L38)=0,"",B38/L38) -> 0.6098932
A39: Rutube | D39: =IF(OR(B39="",C39=""),"",ROUND(B39/C39,0)) | F39: =IF(OR(D39="",E39=""),"",ROUND(D39*E39,0)) | H39: =IF(OR(F39="",G39=""),"",ROUND(F39*G39,0)) | I39: =IF(N(H39)=0,"",ROUND(B39/H39,0)) | J39: =IF(OR(N(H39)=0,$K$9=""),"",ROUND(H39*$K$9,0)) | K39: =IF(N(J39)=0,"",ROUND(B39/J39,0)) | L39: =IF(N(J39)=0,"",ROUND(J39*$H$9,0)) | M39: =IF(N(L39)=0,"",B39/L39)
A40: Instagram | D40: =IF(OR(B40="",C40=""),"",ROUND(B40/C40,0)) | F40: =IF(OR(D40="",E40=""),"",ROUND(D40*E40,0)) | H40: =IF(OR(F40="",G40=""),"",ROUND(F40*G40,0)) | I40: =IF(N(H40)=0,"",ROUND(B40/H40,0)) | J40: =IF(OR(N(H40)=0,$K$9=""),"",ROUND(H40*$K$9,0)) | K40: =IF(N(J40)=0,"",ROUND(B40/J40,0)) | L40: =IF(N(J40)=0,"",ROUND(J40*$H$9,0)) | M40: =IF(N(L40)=0,"",B40/L40)
A41: ИТОГО — МП | B41: =SUM(B34:B40) -> 630000 | C41: =IF(N(D41)=0,"",ROUND(B41/D41,2)) -> 0.72 | D41: =SUM(D34:D40) -> 878611 | F41: =SUM(F34:F40) -> 8484 | H41: =SUM(H34:H40) -> 1932 | I41: =IF(N(H41)=0,"",ROUND(B41/H41,0)) -> 326 | J41: =SUM(J34:J40) -> 1835 | K41: =IF(N(J41)=0,"",ROUND(B41/J41,0)) -> 343 | L41: =SUM(L34:L40) -> 1101000 | M41: =IF(N(L41)=0,"",B41/L41) -> 0.57220708
A42: САЙТ | G42: Ср. чек, ₽ | H42: 1180 | J42: % выкупа | K42: 0.95
A43: Telegram | B43: 10000 | C43: 0.8 | D43: =IF(OR(B43="",C43=""),"",ROUND(B43/C43,0)) -> 12500 | E43: 0.0082 | F43: =IF(OR(D43="",E43=""),"",ROUND(D43*E43,0)) -> 103 | G43: 0.08 | H43: =IF(OR(F43="",G43=""),"",ROUND(F43*G43,0)) -> 8 | I43: =IF(N(H43)=0,"",ROUND(B43/H43,0)) -> 1250 | J43: =IF(OR(N(H43)=0,$K$18=""),"",ROUND(H43*$K$18,0)) -> 8 | K43: =IF(N(J43)=0,"",ROUND(B43/J43,0)) -> 1250 | L43: =IF(N(J43)=0,"",ROUND(J43*$H$18,0)) -> 9440 | M43: =IF(N(L43)=0,"",B43/L43) -> 1.059322
A44: MAX | B44: 20000 | C44: 0.9 | D44: =IF(OR(B44="",C44=""),"",ROUND(B44/C44,0)) -> 22222 | E44: 0.021 | F44: =IF(OR(D44="",E44=""),"",ROUND(D44*E44,0)) -> 467 | G44: 0.11 | H44: =IF(OR(F44="",G44=""),"",ROUND(F44*G44,0)) -> 51 | I44: =IF(N(H44)=0,"",ROUND(B44/H44,0)) -> 392 | J44: =IF(OR(N(H44)=0,$K$18=""),"",ROUND(H44*$K$18,0)) -> 48 | K44: =IF(N(J44)=0,"",ROUND(B44/J44,0)) -> 417 | L44: =IF(N(J44)=0,"",ROUND(J44*$H$18,0)) -> 56640 | M44: =IF(N(L44)=0,"",B44/L44) -> 0.35310734
A45: VK | B45: 0 | C45: 0.72 | D45: =IF(OR(B45="",C45=""),"",ROUND(B45/C45,0)) -> 0 | E45: 0.012 | F45: =IF(OR(D45="",E45=""),"",ROUND(D45*E45,0)) -> 0 | G45: 0.11 | H45: =IF(OR(F45="",G45=""),"",ROUND(F45*G45,0)) -> 0 | I45: =IF(N(H45)=0,"",ROUND(B45/H45,0)) | J45: =IF(OR(N(H45)=0,$K$18=""),"",ROUND(H45*$K$18,0)) | K45: =IF(N(J45)=0,"",ROUND(B45/J45,0)) | L45: =IF(N(J45)=0,"",ROUND(J45*$H$18,0)) | M45: =IF(N(L45)=0,"",B45/L45)
A46: YouTube | B46: 0 | C46: 0.6 | D46: =IF(OR(B46="",C46=""),"",ROUND(B46/C46,0)) -> 0 | E46: 0.006 | F46: =IF(OR(D46="",E46=""),"",ROUND(D46*E46,0)) -> 0 | G46: 0.11 | H46: =IF(OR(F46="",G46=""),"",ROUND(F46*G46,0)) -> 0 | I46: =IF(N(H46)=0,"",ROUND(B46/H46,0)) | J46: =IF(OR(N(H46)=0,$K$18=""),"",ROUND(H46*$K$18,0)) | K46: =IF(N(J46)=0,"",ROUND(B46/J46,0)) | L46: =IF(N(J46)=0,"",ROUND(J46*$H$18,0)) | M46: =IF(N(L46)=0,"",B46/L46)
A47: TikTok | B47: 0 | C47: 0.8 | D47: =IF(OR(B47="",C47=""),"",ROUND(B47/C47,0)) -> 0 | E47: 0.01 | F47: =IF(OR(D47="",E47=""),"",ROUND(D47*E47,0)) -> 0 | G47: 0.11 | H47: =IF(OR(F47="",G47=""),"",ROUND(F47*G47,0)) -> 0 | I47: =IF(N(H47)=0,"",ROUND(B47/H47,0)) | J47: =IF(OR(N(H47)=0,$K$18=""),"",ROUND(H47*$K$18,0)) | K47: =IF(N(J47)=0,"",ROUND(B47/J47,0)) | L47: =IF(N(J47)=0,"",ROUND(J47*$H$18,0)) | M47: =IF(N(L47)=0,"",B47/L47)
A48: Rutube | D48: =IF(OR(B48="",C48=""),"",ROUND(B48/C48,0)) | F48: =IF(OR(D48="",E48=""),"",ROUND(D48*E48,0)) | H48: =IF(OR(F48="",G48=""),"",ROUND(F48*G48,0)) | I48: =IF(N(H48)=0,"",ROUND(B48/H48,0)) | J48: =IF(OR(N(H48)=0,$K$18=""),"",ROUND(H48*$K$18,0)) | K48: =IF(N(J48)=0,"",ROUND(B48/J48,0)) | L48: =IF(N(J48)=0,"",ROUND(J48*$H$18,0)) | M48: =IF(N(L48)=0,"",B48/L48)
A49: Instagram | D49: =IF(OR(B49="",C49=""),"",ROUND(B49/C49,0)) | F49: =IF(OR(D49="",E49=""),"",ROUND(D49*E49,0)) | H49: =IF(OR(F49="",G49=""),"",ROUND(F49*G49,0)) | I49: =IF(N(H49)=0,"",ROUND(B49/H49,0)) | J49: =IF(OR(N(H49)=0,$K$18=""),"",ROUND(H49*$K$18,0)) | K49: =IF(N(J49)=0,"",ROUND(B49/J49,0)) | L49: =IF(N(J49)=0,"",ROUND(J49*$H$18,0)) | M49: =IF(N(L49)=0,"",B49/L49)
A50: ИТОГО — Сайт | B50: =SUM(B43:B49) -> 30000 | C50: =IF(N(D50)=0,"",ROUND(B50/D50,2)) -> 0.86 | D50: =SUM(D43:D49) -> 34722 | F50: =SUM(F43:F49) -> 570 | H50: =SUM(H43:H49) -> 59 | I50: =IF(N(H50)=0,"",ROUND(B50/H50,0)) -> 508 | J50: =SUM(J43:J49) -> 56 | K50: =IF(N(J50)=0,"",ROUND(B50/J50,0)) -> 536 | L50: =SUM(L43:L49) -> 66080 | M50: =IF(N(L50)=0,"",B50/L50) -> 0.45399516
A51: ИТОГО ЗА МЕСЯЦ (МП + Сайт) | B51: =B41+B50 -> 660000 | C51: =IF(N(D51)=0,"",ROUND(B51/D51,2)) -> 0.72 | D51: =D41+D50 -> 913333 | F51: =F41+F50 -> 9054 | H51: =H41+H50 -> 1991 | I51: =IF(N(H51)=0,"",ROUND(B51/H51,0)) -> 331 | J51: =J41+J50 -> 1891 | K51: =IF(N(J51)=0,"",ROUND(B51/J51,0)) -> 349 | L51: =L41+L50 -> 1167080 | M51: =IF(N(L51)=0,"",B51/L51) -> 0.56551393
A52: Вердикт по DRR | B52: =IF(OR(N(L51)=0,N($E$7)=0),"Заполни бюджет, CPV и параметры",IF(M51<=$E$7,"В ЦЕЛЬ: DRR "&ROUND(M51*100,1)&"% при цели "&ROUND($E$7*100,1)&"%","ВЫШЕ ЦЕЛИ: DRR "&ROUND(M51*100,1)&"% при цели "&ROUND($E$7*100,1)&"%")) -> ВЫШЕ ЦЕЛИ: DRR 56,6% при цели 13%
A54: ▼ Сентябрь 2026 | B54: ап
A55: Бюджет на месяц, ₽ | B55: 100000 | D55: Целевой DRR | E55: 0.13
A56: Канал | B56: Бюджет, ₽ | C56: Прогноз CPV, ₽ | D56: Прогноз охвата | E56: CTR % | F56: Клики | G56: CR в заказ % | H56: Заказы | I56: CPO, ₽ | J56: Выкупы | K56: Стоимость выкупа, ₽ | L56: Выручка, ₽ | M56: DRR
A57: МАРКЕТПЛЕЙС (ВБ / Ozon) | G57: Ср. чек, ₽ | H57: 748 | J57: % выкупа | K57: 0.95 | M57: 0.18
A58: Telegram | B58: 15000 | C58: 0.71 | D58: =IF(OR(B58="",C58=""),"",ROUND(B58/C58,0)) -> 21127 | E58: 0.0082 | F58: =IF(OR(D58="",E58=""),"",ROUND(D58*E58,0)) -> 173 | G58: 0.17 | H58: =IF(OR(F58="",G58=""),"",ROUND(F58*G58,0)) -> 29 | I58: =IF(N(H58)=0,"",ROUND(B58/H58,0)) -> 517 | J58: =IF(OR(N(H58)=0,$K$9=""),"",ROUND(H58*$K$9,0)) -> 28 | K58: =IF(N(J58)=0,"",ROUND(B58/J58,0)) -> 536 | L58: =IF(N(J58)=0,"",ROUND(J58*$H$9,0)) -> 16800 | M58: =IF(N(L58)=0,"",B58/L58) -> 0.89285714
A59: MAX | B59: 35000 | C59: 0.71 | D59: =IF(OR(B59="",C59=""),"",ROUND(B59/C59,0)) -> 49296 | E59: 0.021 | F59: =IF(OR(D59="",E59=""),"",ROUND(D59*E59,0)) -> 1035 | G59: 0.23 | H59: =IF(OR(F59="",G59=""),"",ROUND(F59*G59,0)) -> 238 | I59: =IF(N(H59)=0,"",ROUND(B59/H59,0)) -> 147 | J59: =IF(OR(N(H59)=0,$K$9=""),"",ROUND(H59*$K$9,0)) -> 226 | K59: =IF(N(J59)=0,"",ROUND(B59/J59,0)) -> 155 | L59: =IF(N(J59)=0,"",ROUND(J59*$H$9,0)) -> 135600 | M59: =IF(N(L59)=0,"",B59/L59) -> 0.25811209
A60: VK | B60: 50000 | C60: 0.72 | D60: =IF(OR(B60="",C60=""),"",ROUND(B60/C60,0)) -> 69444 | E60: 0.012 | F60: =IF(OR(D60="",E60=""),"",ROUND(D60*E60,0)) -> 833 | G60: 0.23 | H60: =IF(OR(F60="",G60=""),"",ROUND(F60*G60,0)) -> 192 | I60: =IF(N(H60)=0,"",ROUND(B60/H60,0)) -> 260 | J60: =IF(OR(N(H60)=0,$K$9=""),"",ROUND(H60*$K$9,0)) -> 182 | K60: =IF(N(J60)=0,"",ROUND(B60/J60,0)) -> 275 | L60: =IF(N(J60)=0,"",ROUND(J60*$H$9,0)) -> 109200 | M60: =IF(N(L60)=0,"",B60/L60) -> 0.45787546
A61: ИТОГО — МП | B61: =SUM(B58:B60) -> 100000 | C61: =IF(N(D61)=0,"",ROUND(B61/D61,2)) -> 0.71 | D61: =SUM(D58:D60) -> 139867 | F61: =SUM(F58:F60) -> 2041 | H61: =SUM(H58:H60) -> 459 | I61: =IF(N(H61)=0,"",ROUND(B61/H61,0)) -> 218 | J61: =SUM(J58:J60) -> 436 | K61: =IF(N(J61)=0,"",ROUND(B61/J61,0)) -> 229 | L61: =SUM(L58:L60) -> 261600 | M61: =IF(N(L61)=0,"",B61/L61) -> 0.382263
A62: ИТОГО ЗА МЕСЯЦ (МП + Сайт) | B62: =B61 -> 100000
A65: ▼ Октябрь 2026 | B65: AT
A66: Бюджет на месяц, ₽ | B66: 560000 | D66: Целевой DRR | E66: 0.13
A67: Канал | B67: Бюджет, ₽ | C67: Прогноз CPV, ₽ | D67: Прогноз охвата | E67: CTR % | F67: Клики | G67: CR в заказ % | H67: Заказы | I67: CPO, ₽ | J67: Выкупы | K67: Стоимость выкупа, ₽ | L67: Выручка, ₽ | M67: DRR
A68: МАРКЕТПЛЕЙС (ВБ / Ozon) | G68: Ср. чек, ₽ | H68: 748 | J68: % выкупа | K68: 0.95 | M68: 0.18
A69: Telegram | B69: 30000 | C69: 0.8 | D69: =IF(OR(B69="",C69=""),"",ROUND(B69/C69,0)) -> 37500 | E69: 0.0082 | F69: =IF(OR(D69="",E69=""),"",ROUND(D69*E69,0)) -> 308 | G69: 0.17 | H69: =IF(OR(F69="",G69=""),"",ROUND(F69*G69,0)) -> 52 | I69: =IF(N(H69)=0,"",ROUND(B69/H69,0)) -> 577 | J69: =IF(OR(N(H69)=0,$K$9=""),"",ROUND(H69*$K$9,0)) -> 49 | K69: =IF(N(J69)=0,"",ROUND(B69/J69,0)) -> 612 | L69: =IF(N(J69)=0,"",ROUND(J69*$H$9,0)) -> 29400 | M69: =IF(N(L69)=0,"",B69/L69) -> 1.0204082
A70: MAX | B70: 100000 | C70: 0.9 | D70: =IF(OR(B70="",C70=""),"",ROUND(B70/C70,0)) -> 111111 | E70: 0.021 | F70: =IF(OR(D70="",E70=""),"",ROUND(D70*E70,0)) -> 2333 | G70: 0.23 | H70: =IF(OR(F70="",G70=""),"",ROUND(F70*G70,0)) -> 537 | I70: =IF(N(H70)=0,"",ROUND(B70/H70,0)) -> 186 | J70: =IF(OR(N(H70)=0,$K$9=""),"",ROUND(H70*$K$9,0)) -> 510 | K70: =IF(N(J70)=0,"",ROUND(B70/J70,0)) -> 196 | L70: =IF(N(J70)=0,"",ROUND(J70*$H$9,0)) -> 306000 | M70: =IF(N(L70)=0,"",B70/L70) -> 0.32679739
A71: VK | B71: 50000 | C71: 0.72 | D71: =IF(OR(B71="",C71=""),"",ROUND(B71/C71,0)) -> 69444 | E71: 0.012 | F71: =IF(OR(D71="",E71=""),"",ROUND(D71*E71,0)) -> 833 | G71: 0.23 | H71: =IF(OR(F71="",G71=""),"",ROUND(F71*G71,0)) -> 192 | I71: =IF(N(H71)=0,"",ROUND(B71/H71,0)) -> 260 | J71: =IF(OR(N(H71)=0,$K$9=""),"",ROUND(H71*$K$9,0)) -> 182 | K71: =IF(N(J71)=0,"",ROUND(B71/J71,0)) -> 275 | L71: =IF(N(J71)=0,"",ROUND(J71*$H$9,0)) -> 109200 | M71: =IF(N(L71)=0,"",B71/L71) -> 0.45787546
A72: YouTube | B72: 100000 | C72: 0.6 | D72: =IF(OR(B72="",C72=""),"",ROUND(B72/C72,0)) -> 166667 | E72: 0.006 | F72: =IF(OR(D72="",E72=""),"",ROUND(D72*E72,0)) -> 1000 | G72: 0.23 | H72: =IF(OR(F72="",G72=""),"",ROUND(F72*G72,0)) -> 230 | I72: =IF(N(H72)=0,"",ROUND(B72/H72,0)) -> 435 | J72: =IF(OR(N(H72)=0,$K$9=""),"",ROUND(H72*$K$9,0)) -> 219 | K72: =IF(N(J72)=0,"",ROUND(B72/J72,0)) -> 457 | L72: =IF(N(J72)=0,"",ROUND(J72*$H$9,0)) -> 131400 | M72: =IF(N(L72)=0,"",B72/L72) -> 0.76103501
A73: TikTok | B73: 250000 | C73: 0.8 | D73: =IF(OR(B73="",C73=""),"",ROUND(B73/C73,0)) -> 312500 | E73: 0.01 | F73: =IF(OR(D73="",E73=""),"",ROUND(D73*E73,0)) -> 3125 | G73: 0.23 | H73: =IF(OR(F73="",G73=""),"",ROUND(F73*G73,0)) -> 719 | I73: =IF(N(H73)=0,"",ROUND(B73/H73,0)) -> 348 | J73: =IF(OR(N(H73)=0,$K$9=""),"",ROUND(H73*$K$9,0)) -> 683 | K73: =IF(N(J73)=0,"",ROUND(B73/J73,0)) -> 366 | L73: =IF(N(J73)=0,"",ROUND(J73*$H$9,0)) -> 409800 | M73: =IF(N(L73)=0,"",B73/L73) -> 0.61005368
A74: ИТОГО — МП | B74: =SUM(B69:B73) -> 530000 | C74: =IF(N(D74)=0,"",ROUND(B74/D74,2)) -> 0.76 | D74: =SUM(D69:D73) -> 697222 | F74: =SUM(F69:F73) -> 7599 | H74: =SUM(H69:H73) -> 1730 | I74: =IF(N(H74)=0,"",ROUND(B74/H74,0)) -> 306 | J74: =SUM(J69:J73) -> 1643 | K74: =IF(N(J74)=0,"",ROUND(B74/J74,0)) -> 323 | L74: =SUM(L69:L73) -> 985800 | M74: =IF(N(L74)=0,"",B74/L74) -> 0.53763441
A75: САЙТ | G75: Ср. чек, ₽ | H75: 1180 | J75: % выкупа | K75: 0.95
A76: Telegram | C76: 0.8 | D76: =IF(OR(B76="",C76=""),"",ROUND(B76/C76,0)) | E76: 0.0082 | F76: =IF(OR(D76="",E76=""),"",ROUND(D76*E76,0)) | G76: 0.08 | H76: =IF(OR(F76="",G76=""),"",ROUND(F76*G76,0)) | I76: =IF(N(H76)=0,"",ROUND(B76/H76,0)) | J76: =IF(OR(N(H76)=0,$K$18=""),"",ROUND(H76*$K$18,0)) | K76: =IF(N(J76)=0,"",ROUND(B76/J76,0)) | L76: =IF(N(J76)=0,"",ROUND(J76*$H$18,0)) | M76: =IF(N(L76)=0,"",B76/L76)
A77: MAX | B77: 30000 | C77: 0.9 | D77: =IF(OR(B77="",C77=""),"",ROUND(B77/C77,0)) -> 33333 | E77: 0.021 | F77: =IF(OR(D77="",E77=""),"",ROUND(D77*E77,0)) -> 700 | G77: 0.11 | H77: =IF(OR(F77="",G77=""),"",ROUND(F77*G77,0)) -> 77 | I77: =IF(N(H77)=0,"",ROUND(B77/H77,0)) -> 390 | J77: =IF(OR(N(H77)=0,$K$18=""),"",ROUND(H77*$K$18,0)) -> 73 | K77: =IF(N(J77)=0,"",ROUND(B77/J77,0)) -> 411 | L77: =IF(N(J77)=0,"",ROUND(J77*$H$18,0)) -> 86140 | M77: =IF(N(L77)=0,"",B77/L77) -> 0.34827026
A78: VK | C78: 0.72 | D78: =IF(OR(B78="",C78=""),"",ROUND(B78/C78,0)) | E78: 0.012 | F78: =IF(OR(D78="",E78=""),"",ROUND(D78*E78,0)) | G78: 0.11 | H78: =IF(OR(F78="",G78=""),"",ROUND(F78*G78,0)) | I78: =IF(N(H78)=0,"",ROUND(B78/H78,0)) | J78: =IF(OR(N(H78)=0,$K$18=""),"",ROUND(H78*$K$18,0)) | K78: =IF(N(J78)=0,"",ROUND(B78/J78,0)) | L78: =IF(N(J78)=0,"",ROUND(J78*$H$18,0)) | M78: =IF(N(L78)=0,"",B78/L78)
A79: YouTube | C79: 0.6 | D79: =IF(OR(B79="",C79=""),"",ROUND(B79/C79,0)) | E79: 0.006 | F79: =IF(OR(D79="",E79=""),"",ROUND(D79*E79,0)) | G79: 0.11 | H79: =IF(OR(F79="",G79=""),"",ROUND(F79*G79,0)) | I79: =IF(N(H79)=0,"",ROUND(B79/H79,0)) | J79: =IF(OR(N(H79)=0,$K$18=""),"",ROUND(H79*$K$18,0)) | K79: =IF(N(J79)=0,"",ROUND(B79/J79,0)) | L79: =IF(N(J79)=0,"",ROUND(J79*$H$18,0)) | M79: =IF(N(L79)=0,"",B79/L79)
A80: TikTok | C80: 0.8 | D80: =IF(OR(B80="",C80=""),"",ROUND(B80/C80,0)) | E80: 0.01 | F80: =IF(OR(D80="",E80=""),"",ROUND(D80*E80,0)) | G80: 0.11 | H80: =IF(OR(F80="",G80=""),"",ROUND(F80*G80,0)) | I80: =IF(N(H80)=0,"",ROUND(B80/H80,0)) | J80: =IF(OR(N(H80)=0,$K$18=""),"",ROUND(H80*$K$18,0)) | K80: =IF(N(J80)=0,"",ROUND(B80/J80,0)) | L80: =IF(N(J80)=0,"",ROUND(J80*$H$18,0)) | M80: =IF(N(L80)=0,"",B80/L80)
A81: ИТОГО — Сайт | B81: =SUM(B76:B80) -> 30000 | C81: =IF(N(D81)=0,"",ROUND(B81/D81,2)) -> 0.9 | D81: =SUM(D76:D80) -> 33333 | F81: =SUM(F76:F80) -> 700 | H81: =SUM(H76:H80) -> 77 | I81: =IF(N(H81)=0,"",ROUND(B81/H81,0)) -> 390 | J81: =SUM(J76:J80) -> 73 | K81: =IF(N(J81)=0,"",ROUND(B81/J81,0)) -> 411 | L81: =SUM(L76:L80) -> 86140 | M81: =IF(N(L81)=0,"",B81/L81) -> 0.34827026
A82: ИТОГО ЗА МЕСЯЦ (МП + Сайт) | B82: =B74+B81 -> 560000 | C82: =IF(N(D82)=0,"",ROUND(B82/D82,2)) -> 0.77 | D82: =D74+D81 -> 730555 | F82: =F74+F81 -> 8299 | H82: =H74+H81 -> 1807 | I82: =IF(N(H82)=0,"",ROUND(B82/H82,0)) -> 310 | J82: =J74+J81 -> 1716 | K82: =IF(N(J82)=0,"",ROUND(B82/J82,0)) -> 326 | L82: =L74+L81 -> 1071940 | M82: =IF(N(L82)=0,"",B82/L82) -> 0.5224173
A83: Вердикт по DRR | B83: =IF(OR(N(L82)=0,N($E$7)=0),"Заполни бюджет, CPV и параметры",IF(M82<=$E$7,"В ЦЕЛЬ: DRR "&ROUND(M82*100,1)&"% при цели "&ROUND($E$7*100,1)&"%","ВЫШЕ ЦЕЛИ: DRR "&ROUND(M82*100,1)&"% при цели "&ROUND($E$7*100,1)&"%")) -> ВЫШЕ ЦЕЛИ: DRR 52,2% при цели 13%
A86: ▼ Октябрь 2026 | B86: корм
A87: Бюджет на месяц, ₽ | B87: 210000 | D87: Целевой DRR | E87: 0.13
A88: Канал | B88: Бюджет, ₽ | C88: Прогноз CPV, ₽ | D88: Прогноз охвата | E88: CTR % | F88: Клики | G88: CR в заказ % | H88: Заказы | I88: CPO, ₽ | J88: Выкупы | K88: Стоимость выкупа, ₽ | L88: Выручка, ₽ | M88: DRR
A89: МАРКЕТПЛЕЙС (ВБ / Ozon) | G89: Ср. чек, ₽ | H89: 748 | J89: % выкупа | K89: 0.95 | M89: 0.18
A90: Telegram | C90: 0.8 | D90: =IF(OR(B90="",C90=""),"",ROUND(B90/C90,0)) | E90: 0.0082 | F90: =IF(OR(D90="",E90=""),"",ROUND(D90*E90,0)) | G90: 0.17 | H90: =IF(OR(F90="",G90=""),"",ROUND(F90*G90,0)) | I90: =IF(N(H90)=0,"",ROUND(B90/H90,0)) | J90: =IF(OR(N(H90)=0,$K$9=""),"",ROUND(H90*$K$9,0)) | K90: =IF(N(J90)=0,"",ROUND(B90/J90,0)) | L90: =IF(N(J90)=0,"",ROUND(J90*$H$9,0)) | M90: =IF(N(L90)=0,"",B90/L90)
A91: MAX | B91: 70000 | C91: 0.9 | D91: =IF(OR(B91="",C91=""),"",ROUND(B91/C91,0)) -> 77778 | E91: 0.021 | F91: =IF(OR(D91="",E91=""),"",ROUND(D91*E91,0)) -> 1633 | G91: 0.23 | H91: =IF(OR(F91="",G91=""),"",ROUND(F91*G91,0)) -> 376 | I91: =IF(N(H91)=0,"",ROUND(B91/H91,0)) -> 186 | J91: =IF(OR(N(H91)=0,$K$9=""),"",ROUND(H91*$K$9,0)) -> 357 | K91: =IF(N(J91)=0,"",ROUND(B91/J91,0)) -> 196 | L91: =IF(N(J91)=0,"",ROUND(J91*$H$9,0)) -> 214200 | M91: =IF(N(L91)=0,"",B91/L91) -> 0.32679739
A92: VK | C92: 0.72 | D92: =IF(OR(B92="",C92=""),"",ROUND(B92/C92,0)) | E92: 0.012 | F92: =IF(OR(D92="",E92=""),"",ROUND(D92*E92,0)) | G92: 0.23 | H92: =IF(OR(F92="",G92=""),"",ROUND(F92*G92,0)) | I92: =IF(N(H92)=0,"",ROUND(B92/H92,0)) | J92: =IF(OR(N(H92)=0,$K$9=""),"",ROUND(H92*$K$9,0)) | K92: =IF(N(J92)=0,"",ROUND(B92/J92,0)) | L92: =IF(N(J92)=0,"",ROUND(J92*$H$9,0)) | M92: =IF(N(L92)=0,"",B92/L92)
A93: YouTube | B93: 70000 | C93: 0.6 | D93: =IF(OR(B93="",C93=""),"",ROUND(B93/C93,0)) -> 116667 | E93: 0.006 | F93: =IF(OR(D93="",E93=""),"",ROUND(D93*E93,0)) -> 700 | G93: 0.23 | H93: =IF(OR(F93="",G93=""),"",ROUND(F93*G93,0)) -> 161 | I93: =IF(N(H93)=0,"",ROUND(B93/H93,0)) -> 435 | J93: =IF(OR(N(H93)=0,$K$9=""),"",ROUND(H93*$K$9,0)) -> 153 | K93: =IF(N(J93)=0,"",ROUND(B93/J93,0)) -> 458 | L93: =IF(N(J93)=0,"",ROUND(J93*$H$9,0)) -> 91800 | M93: =IF(N(L93)=0,"",B93/L93) -> 0.76252723
A94: TikTok | B94: 70000 | C94: 0.8 | D94: =IF(OR(B94="",C94=""),"",ROUND(B94/C94,0)) -> 87500 | E94: 0.01 | F94: =IF(OR(D94="",E94=""),"",ROUND(D94*E94,0)) -> 875 | G94: 0.23 | H94: =IF(OR(F94="",G94=""),"",ROUND(F94*G94,0)) -> 201 | I94: =IF(N(H94)=0,"",ROUND(B94/H94,0)) -> 348 | J94: =IF(OR(N(H94)=0,$K$9=""),"",ROUND(H94*$K$9,0)) -> 191 | K94: =IF(N(J94)=0,"",ROUND(B94/J94,0)) -> 366 | L94: =IF(N(J94)=0,"",ROUND(J94*$H$9,0)) -> 114600 | M94: =IF(N(L94)=0,"",B94/L94) -> 0.61082024
A95: ИТОГО — МП | B95: =SUM(B90:B94) -> 210000 | C95: =IF(N(D95)=0,"",ROUND(B95/D95,2)) -> 0.74 | D95: =SUM(D90:D94) -> 281945 | F95: =SUM(F90:F94) -> 3208 | H95: =SUM(H90:H94) -> 738 | I95: =IF(N(H95)=0,"",ROUND(B95/H95,0)) -> 285 | J95: =SUM(J90:J94) -> 701 | K95: =IF(N(J95)=0,"",ROUND(B95/J95,0)) -> 300 | L95: =SUM(L90:L94) -> 420600 | M95: =IF(N(L95)=0,"",B95/L95) -> 0.49928673
A96: САЙТ | G96: Ср. чек, ₽ | H96: 1180 | J96: % выкупа | K96: 0.95
A97: Telegram | C97: 0.8 | D97: =IF(OR(B97="",C97=""),"",ROUND(B97/C97,0)) | E97: 0.0082 | F97: =IF(OR(D97="",E97=""),"",ROUND(D97*E97,0)) | G97: 0.08 | H97: =IF(OR(F97="",G97=""),"",ROUND(F97*G97,0)) | I97: =IF(N(H97)=0,"",ROUND(B97/H97,0)) | J97: =IF(OR(N(H97)=0,$K$18=""),"",ROUND(H97*$K$18,0)) | K97: =IF(N(J97)=0,"",ROUND(B97/J97,0)) | L97: =IF(N(J97)=0,"",ROUND(J97*$H$18,0)) | M97: =IF(N(L97)=0,"",B97/L97)
A98: MAX | C98: 0.9 | D98: =IF(OR(B98="",C98=""),"",ROUND(B98/C98,0)) | E98: 0.021 | F98: =IF(OR(D98="",E98=""),"",ROUND(D98*E98,0)) | G98: 0.11 | H98: =IF(OR(F98="",G98=""),"",ROUND(F98*G98,0)) | I98: =IF(N(H98)=0,"",ROUND(B98/H98,0)) | J98: =IF(OR(N(H98)=0,$K$18=""),"",ROUND(H98*$K$18,0)) | K98: =IF(N(J98)=0,"",ROUND(B98/J98,0)) | L98: =IF(N(J98)=0,"",ROUND(J98*$H$18,0)) | M98: =IF(N(L98)=0,"",B98/L98)
A99: VK | C99: 0.72 | D99: =IF(OR(B99="",C99=""),"",ROUND(B99/C99,0)) | E99: 0.012 | F99: =IF(OR(D99="",E99=""),"",ROUND(D99*E99,0)) | G99: 0.11 | H99: =IF(OR(F99="",G99=""),"",ROUND(F99*G99,0)) | I99: =IF(N(H99)=0,"",ROUND(B99/H99,0)) | J99: =IF(OR(N(H99)=0,$K$18=""),"",ROUND(H99*$K$18,0)) | K99: =IF(N(J99)=0,"",ROUND(B99/J99,0)) | L99: =IF(N(J99)=0,"",ROUND(J99*$H$18,0)) | M99: =IF(N(L99)=0,"",B99/L99)
A100: YouTube | C100: 0.6 | D100: =IF(OR(B100="",C100=""),"",ROUND(B100/C100,0)) | E100: 0.006 | F100: =IF(OR(D100="",E100=""),"",ROUND(D100*E100,0)) | G100: 0.11 | H100: =IF(OR(F100="",G100=""),"",ROUND(F100*G100,0)) | I100: =IF(N(H100)=0,"",ROUND(B100/H100,0)) | J100: =IF(OR(N(H100)=0,$K$18=""),"",ROUND(H100*$K$18,0)) | K100: =IF(N(J100)=0,"",ROUND(B100/J100,0)) | L100: =IF(N(J100)=0,"",ROUND(J100*$H$18,0)) | M100: =IF(N(L100)=0,"",B100/L100)
A101: TikTok | C101: 0.8 | D101: =IF(OR(B101="",C101=""),"",ROUND(B101/C101,0)) | E101: 0.01 | F101: =IF(OR(D101="",E101=""),"",ROUND(D101*E101,0)) | G101: 0.11 | H101: =IF(OR(F101="",G101=""),"",ROUND(F101*G101,0)) | I101: =IF(N(H101)=0,"",ROUND(B101/H101,0)) | J101: =IF(OR(N(H101)=0,$K$18=""),"",ROUND(H101*$K$18,0)) | K101: =IF(N(J101)=0,"",ROUND(B101/J101,0)) | L101: =IF(N(J101)=0,"",ROUND(J101*$H$18,0)) | M101: =IF(N(L101)=0,"",B101/L101)
A102: ИТОГО — Сайт | B102: =SUM(B97:B101) -> 0 | C102: =IF(N(D102)=0,"",ROUND(B102/D102,2)) | D102: =SUM(D97:D101) -> 0 | F102: =SUM(F97:F101) -> 0 | H102: =SUM(H97:H101) -> 0 | I102: =IF(N(H102)=0,"",ROUND(B102/H102,0)) | J102: =SUM(J97:J101) -> 0 | K102: =IF(N(J102)=0,"",ROUND(B102/J102,0)) | L102: =SUM(L97:L101) -> 0 | M102: =IF(N(L102)=0,"",B102/L102)
A103: ИТОГО ЗА МЕСЯЦ (МП + Сайт) | B103: =B95+B102 -> 210000 | C103: =IF(N(D103)=0,"",ROUND(B103/D103,2)) -> 0.74 | D103: =D95+D102 -> 281945 | F103: =F95+F102 -> 3208 | H103: =H95+H102 -> 738 | I103: =IF(N(H103)=0,"",ROUND(B103/H103,0)) -> 285 | J103: =J95+J102 -> 701 | K103: =IF(N(J103)=0,"",ROUND(B103/J103,0)) -> 300 | L103: =L95+L102 -> 420600 | M103: =IF(N(L103)=0,"",B103/L103) -> 0.49928673
A104: Вердикт по DRR | B104: =IF(OR(N(L103)=0,N($E$7)=0),"Заполни бюджет, CPV и параметры",IF(M103<=$E$7,"В ЦЕЛЬ: DRR "&ROUND(M103*100,1)&"% при цели "&ROUND($E$7*100,1)&"%","ВЫШЕ ЦЕЛИ: DRR "&ROUND(M103*100,1)&"% при цели "&ROUND($E$7*100,1)&"%")) -> ВЫШЕ ЦЕЛИ: DRR 49,9% при цели 13%
A110: ▼ НОЯБРЬ 2026
A111: Бюджет на месяц, ₽ | C111: Целевой DRR
A112: Канал | B112: Бюджет, ₽
A113: МАРКЕТПЛЕЙС (ВБ / Ozon) | F113: Ср. чек, ₽ | I113: % выкупа
A114: Telegram | E114: =IF(OR(C114="",D114=""),"",ROUND(C114*D114,0)) | G114: =IF(OR(E114="",F114=""),"",ROUND(E114*F114,0)) | H114: =IF(N(G114)=0,"",ROUND(B114/G114,0)) | I114: =IF(OR(N(G114)=0,$J$113=""),"",ROUND(G114*$J$113,0)) | J114: =IF(N(I114)=0,"",ROUND(B114/I114,0)) | K114: =IF(N(I114)=0,"",ROUND(I114*$G$113,0)) | L114: =IF(N(K114)=0,"",B114/K114)
...

Sheet Август
A1: не
A2: Выбери блогера в колонке A — ссылка, подписчики, площадка, промокод, стоимость подтянутся. «🔗 открыть» ведёт на канал.
A3: Выкупы = Заказы × %выкупа. Выручка = Средний чек × Выкупы. CAC/CPO по факту.
A5: Блогер | B5: Ссылка на канал | C5: Подписчики | D5: Площадка | E5: Канал продаж | F5: № договора | G5: Сценарий рекламы | H5: Дата выхода | I5: Статус | J5: Стоимость размещения | K5: Налог | L5: Себестоимость продукции | M5: Итого к оплате | N5: Код маркировки (ERID) | O5: Ссылка с UTM | P5: Ссылка Мобзио | Q5: Промокод | R5: Подменный артикул | S5: Ссылка на размещение | T5: Право использования | U5: Охват | V5: CPV, ₽ | W5: Клики WB/ сайт | X5: Клики мобзио | Y5: Цена за клик, ₽ | Z5: Корзины | AA5: Заказы | AB5: Сумма заказов, ₽ | AC5: % выкупа | AD5: Выкупы | AE5: Средний чек, ₽ | AF5: Выручка от выкупов, ₽ | AG5: Стоимость выкупа, ₽ | AH5: CPO, ₽ | AI5: Продукт | AJ5: Комментарий
A6: НЕДЕЛЯ — 3–9 августа
A7: fishes43 | C7: 1900 | D7: MAX | E7: Сайт | F7: telega in | G7: t27 | H7: 46242 | I7: Вышло | J7: 769 | M7: =IF(N($J7)+N($K7)+N($L7)=0,"",N($J7)+N($K7)+N($L7)) -> 769 | O7: https://trigger-fish.ru/?utm_source=max&utm_medium=publik&utm_campaign=rybalkasakhalin&utm_content=t27&utm_term=0 | S7: https://max.ru/fishes43/AZ_f9UjBUjw | U7: 1062 | V7: =IF(N($U7)=0,"",$M7/$U7) -> 0.72410546 | W7: 22 | Y7: =IF(N($W7)=0,"",$M7/$W7) -> 34.954545 | Z7: 1 | AD7: 0 | AJ7: 3 дня
A8: Клёвое место | Рыбалка | B8: =IF($A8="","",IFERROR(HYPERLINK(VLOOKUP($A8,'Мои блогеры'!$A:$N,14,0),"🔗 открыть"),"")) -> 🔗 открыть | C8: 33000 | D8: MAX | E8: Сайт | F8: telega in | G8: t27 | H8: 46241 | I8: Вышло | J8: 10699 | L8: - | M8: =IF(N($J8)+N($K8)+N($L8)=0,"",N($J8)+N($K8)+N($L8)) -> 10699 | O8: https://trigger-fish.ru/?utm_source=max&utm_medium=publik&utm_campaign=klevoemesto&utm_content=t27&utm_term=0 | S8: https://max.ru/join/uCdz6lLBZaKQQ-TBrM1kCaXNxdhno0LlLSpv1_WO-yI | U8: 9852 | V8: =IF(N($U8)=0,"",$M8/$U8) -> 1.0859724 | W8: 262 | Y8: =IF(N($W8)=0,"",$M8/$W8) -> 40.835878 | Z8: 33 | AA8: 5 | AB8: 2950 | AD8: 2 | AE8: =AB8/AD8 -> 1475 | AF8: 1770 | AG8: =IF(N($AD8)=0,"",ROUND($M8/$AD8,0)) -> 5350 | AH8: =IF(N($AA8)=0,"",ROUND($M8/$AA8,0)) -> 2140 | AJ8: пост на месяц
A9: rybalka_severozapad | B9: =IF($A9="","",IFERROR(HYPERLINK(VLOOKUP($A9,'Мои блогеры'!$A:$N,14,0),"🔗 открыть"),"")) -> 🔗 открыть | C9: 5000 | D9: MAX | E9: Сайт | F9: telega in | G9: t27 | H9: 46241 | I9: Вышло | J9: 6933 | M9: =IF(N($J9)+N($K9)+N($L9)=0,"",N($J9)+N($K9)+N($L9)) -> 6933 | O9: https://trigger-fish.ru/?utm_source=max&utm_medium=publik&utm_campaign=rybalka_severozapad&utm_content=t27&utm_term=0 | S9: https://max.ru/rybalka_severozapad/AZ_anGIoWTQ | U9: 3067 | V9: =IF(N($U9)=0,"",$M9/$U9) -> 2.2605152 | W9: 70 | Y9: =IF(N($W9)=0,"",$M9/$W9) -> 99.042857 | Z9: 4 | AA9: 4 | AB9: 1180 | AD9: 1 | AE9: =AB9/AD9 -> 1180 | AF9: 1180 | AG9: =IF(N($AD9)=0,"",ROUND($M9/$AD9,0)) -> 6933 | AH9: =IF(N($AA9)=0,"",ROUND($M9/$AA9,0)) -> 1733 | AJ9: пост на месяц
A10: РЫБАЛКА В МОСКВЕ И ПОДМОСКОВЬЕ | B10: =IF($A10="","",IFERROR(HYPERLINK(VLOOKUP($A10,'Мои блогеры'!$A:$N,14,0),"🔗 открыть"),"")) -> 🔗 открыть | C10: =IFERROR(VLOOKUP($A10,'Мои блогеры'!$A:$N,5,0),"") -> 8699 | D10: Telegram | E10: Сайт | F10: telega in | G10: t27 | H10: 46243 | I10: Вышло | J10: =IFERROR(VLOOKUP($A10,'Мои блогеры'!$A:$N,8,0),"") -> 755 | M10: =IF(N($J10)+N($K10)+N($L10)=0,"",N($J10)+N($K10)+N($L10)) -> 755 | O10: https://trigger-fish.ru/?utm_source=max&utm_medium=publik&utm_campaign=rybalkavmoskve&utm_content=t27&utm_term=0 | S10: https://telegram.me/rubalkamoskva/42761 | U10: 1357 | V10: =IF(N($U10)=0,"",$M10/$U10) -> 0.55637436 | W10: 37 | Y10: =IF(N($W10)=0,"",$M10/$W10) -> 20.405405 | Z10: 10 | AA10: 4 | AB10: 2360 | AD10: 0 | AG10: =IF(N($AD10)=0,"",ROUND($M10/$AD10,0)) | AJ10: пост на месяц
A11: we_and_nature | B11: =IF($A11="","",IFERROR(HYPERLINK(VLOOKUP($A11,'Мои блогеры'!$A:$N,14,0),"🔗 открыть"),"")) -> 🔗 открыть | C11: =IFERROR(VLOOKUP($A11,'Мои блогеры'!$A:$N,5,0),"") -> 7000 | D11: MAX | E11: Сайт | F11: telega in | G11: t28 | H11: 46243 | I11: Вышло | J11: 3776 | M11: =IF(N($J11)+N($K11)+N($L11)=0,"",N($J11)+N($K11)+N($L11)) -> 3776 | O11: https://trigger-fish.ru/?utm_source=max&utm_medium=publik&utm_campaign=we_and_nature&utm_content=t28&utm_term=0 | S11: https://max.ru/we_and_nature/AZ_nQLlvTwc | U11: 3637 | V11: =IF(N($U11)=0,"",$M11/$U11) -> 1.0382183 | W11: 18 | Y11: =IF(N($W11)=0,"",$M11/$W11) -> 209.77778 | Z11: 1 | AD11: 0 | AG11: =IF(N($AD11)=0,"",ROUND($M11/$AD11,0)) | AJ11: пост на месяц
A12: Рыбалка | B12: =IF($A12="","",IFERROR(HYPERLINK(VLOOKUP($A12,'Мои блогеры'!$A:$N,14,0),"🔗 открыть"),"")) -> 🔗 открыть | C12: =IFERROR(VLOOKUP($A12,'Мои блогеры'!$A:$N,5,0),"") -> 25900 | D12: MAX | E12: Сайт | F12: telega in | G12: t28 | H12: 46242 | I12: Вышло | J12: 3216 | M12: =IF(N($J12)+N($K12)+N($L12)=0,"",N($J12)+N($K12)+N($L12)) -> 3216 | O12: https://trigger-fish.ru/?utm_source=max&utm_medium=publik&utm_campaign=rybalka&utm_content=t28&utm_term=0 | S12: https://max.ru/telefishing/AZ_gLNBzC3g | U12: 3380 | V12: =IF(N($U12)=0,"",$M12/$U12) -> 0.95147929 | W12: 91 | Y12: =IF(N($W12)=0,"",$M12/$W12) -> 35.340659 | Z12: 15 | AA12: 4 | AB12: 1180 | AD12: 1 | AE12: =AB12/AD12 -> 1180 | AF12: 1180 | AG12: =IF(N($AD12)=0,"",ROUND($M12/$AD12,0)) -> 3216 | AH12: =IF(N($AA12)=0,"",ROUND($M12/$AA12,0)) -> 804 | AJ12: на сутки
A13: Рыболовная сводка Спб | B13: =IF($A13="","",IFERROR(HYPERLINK(VLOOKUP($A13,'Мои блогеры'!$A:$N,14,0),"🔗 открыть"),"")) -> 🔗 открыть | C13: =IFERROR(VLOOKUP($A13,'Мои блогеры'!$A:$N,5,0),"") -> 35500 | D13: Telegram | E13: Сайт | F13: telega in | G13: t28 | H13: 46241 | I13: Вышло | J13: 6293 | M13: =IF(N($J13)+N($K13)+N($L13)=0,"",N($J13)+N($K13)+N($L13)) -> 6293 | O13: https://trigger-fish.ru/?utm_source=max&utm_medium=publik&utm_campaign=rybalovnayasvodkaspb&utm_content=t28&utm_term=0 | S13: https://max.ru/rybalka_severozapad/AZ_dYejXTGo | U13: 2650 | V13: =IF(N($U13)=0,"",$M13/$U13) -> 2.374717 | W13: 40 | Y13: =IF(N($W13)=0,"",$M13/$W13) -> 157.325 | Z13: 12 | AA13: 4 | AB13: 1180 | AD13: 0 | AG13: =IF(N($AD13)=0,"",ROUND($M13/$AD13,0)) | AJ13: пост на месяц
A14: rybalkasakhalin | C14: =IFERROR(VLOOKUP($A14,'Мои блогеры'!$A:$N,5,0),"") -> 12300 | D14: MAX | E14: Сайт | F14: telega in | G14: t28 | H14: 46241 | I14: Вышло | J14: =IFERROR(VLOOKUP($A14,'Мои блогеры'!$A:$N,8,0),"") -> 6933 | M14: =IF(N($J14)+N($K14)+N($L14)=0,"",N($J14)+N($K14)+N($L14)) -> 6933 | O14: https://trigger-fish.ru/?utm_source=max&utm_medium=publik&utm_campaign=rybalkasakhalin&utm_content=28 | S14: https://max.ru/rybalkasakhalin/AZ_mXo2jbBY | U14: 5090 | V14: =IF(N($U14)=0,"",$M14/$U14) -> 1.3620825 | W14: 39 | Y14: =IF(N($W14)=0,"",$M14/$W14) -> 177.76923 | Z14: 6 | AD14: 0 | AJ14: пост на месяц
A15: Итого:3-9 августа | I15: =COUNTIF(I7:I14,"Вышло")&" / "&COUNTA(A7:A14) -> 8 / 8 | J15: =SUM(J7:J14) -> 39374 | L15: =SUM(L8:L14) -> 0 | M15: =SUM(M7:M14) -> 39374 | N15: =SUM(N7:N14) -> 0 | O15: =SUM(O7:O14) -> 0 | P15: =SUM(P7:P14) -> 0 | Q15: =SUM(Q7:Q14) -> 0 | R15: =SUM(R7:R14) -> 0 | S15: =SUM(S7:S14) -> 0 | U15: =SUM(U7:U14) -> 30095 | V15: =SUM(V7:V14) -> 10.353464 | W15: =SUM(W7:W14) -> 579 | X15: =SUM(X7:X14) -> 0 | Y15: =SUM(Y7:Y14) -> 775.45135 | Z15: =SUM(Z7:Z14) -> 82 | AA15: =SUM(AA7:AA14) -> 21 | AB15: =SUM(AB7:AB14) -> 8850 | AD15: =SUM(AD7:AD14) -> 4 | AE15: =SUM(AE7:AE14) -> 3835 | AF15: =SUM(AF7:AF14) -> 4130 | AG15: =SUM(AG7:AG14) -> 15499 | AH15: =SUM(AH7:AH14) -> 4677
A16: НЕДЕЛЯ —10–17августа
A17: viktorlife24 | C17: =IFERROR(VLOOKUP($A17,'Мои блогеры'!$A:$N,5,0),"") -> 33000 | D17: TikTok | E17: WB | F17: 6 | G17: v1 | H17: 46248 | I17: Вышло | J17: =IFERROR(VLOOKUP($A17,'Мои блогеры'!$A:$N,8,0),"") -> 50000 | K17: 1800 | L17: 780 | M17: =IF(N($J17)+N($K17)+N($L17)=0,"",N($J17)+N($K17)+N($L17)) -> 52580 | N17: 2W5zFJrZboX | O17: https://wildberries.ru/catalog/0/search.aspx?search=WW888364 | P17: https://aminotriggerfish.mobz.market/7icq | R17: WW888364 | S17: https://vt.tiktok.com/ZSVewxP5s/ | T17: Да | U17: 243800 | V17: =IF(N($U17)=0,"",$M17/$U17) -> 0.21566858 | W17: 1063 | X17: 14 | Y17: =IF(N($W17)=0,"",$M17/$W17) -> 49.463782 | Z17: 126 | AA17: 17 | AB17: =743*AA17 -> 12631 | AD17: 17 | AE17: 743 | AF17: =AB17 -> 12631 | AG17: =IF(N($AD17)=0,"",ROUND($M17/$AD17,0)) -> 3093 | AH17: =IF(N($AA17)=0,"",ROUND($M17/$AA17,0)) -> 3093
A18: viktorlife24youtube | C18: =IFERROR(VLOOKUP($A18,'Мои блогеры'!$A:$N,5,0),"") -> 6000 | D18: YouTube | E18: WB | F18: 6 | G18: v1 | H18: 46248 | I18: Вышло | J18: =IFERROR(VLOOKUP($A18,'Мои блогеры'!$A:$N,8,0),"") -> 15000 | K18: 930 | L18: 0 | M18: =IF(N($J18)+N($K18)+N($L18)=0,"",N($J18)+N($K18)+N($L18)) -> 15930 | N18: 2W5zFJPtADF | O18: https://wildberries.ru/catalog/0/search.aspx?search=WW888378 | P18: https://aminotriggerfish.mobz.market/hs9mwe | R18: WW888378 | S18: https://youtube.com/shorts/rKxxYD_SDCc?si=B1QcWbyyjv0rHg-u | T18: Да | U18: 80000 | V18: =IF(N($U18)=0,"",$M18/$U18) -> 0.199125 | W18: 105 | X18: - | Y18: =IF(N($W18)=0,"",$M18/$W18) -> 151.71429 | Z18: 18 | AA18: 3 | AB18: =743*AA18 -> 2229 | AD18: 3 | AE18: 743 | AF18: =AB18 -> 2229 | AG18: =IF(N($AD18)=0,"",ROUND($M18/$AD18,0)) -> 5310 | AH18: =IF(N($AA18)=0,"",ROUND($M18/$AA18,0)) -> 5310
A19: fishercl | B19: =IF($A19="","",IFERROR(HYPERLINK(VLOOKUP($A19,'Мои блогеры'!$A:$N,14,0),"🔗 открыть"),"")) -> 🔗 открыть | C19: =IFERROR(VLOOKUP($A19,'Мои блогеры'!$A:$N,5,0),"") -> 22400 | D19: Telegram | E19: Сайт | F19: telega in | G19: t27 | H19: 46249 | I19: Вышло | J19: =IFERROR(VLOOKUP($A19,'Мои блогеры'!$A:$N,8,0),"") -> 1818 | M19: =IF(N($J19)+N($K19)+N($L19)=0,"",N($J19)+N($K19)+N($L19)) -> 1818 | O19: https://trigger-fish.ru/?utm_source=tg&utm_medium=publik&utm_campaign=fishercl&utm_content=t27 | S19: https://telegram.me/fishercl/5219 | U19: 3840 | V19: =IF(N($U19)=0,"",$M19/$U19) -> 0.4734375 | W19: 12 | Y19: =IF(N($W19)=0,"",$M19/$W19) -> 151.5 | Z19: 1 | AF19: =IF(OR(N($AD19)=0,$AE19=""),"",ROUND($AD19*$AE19,0)) | AG19: =IF(N($AD19)=0,"",ROUND($M19/$AD19,0)) | AH19: =IF(N($AA19)=0,"",ROUND($M19/$AA19,0)) | AJ19: 2 суток
A20: alexeyvfishing | B20: =IF($A20="","",IFERROR(HYPERLINK(VLOOKUP($A20,'Мои блогеры'!$A:$N,14,0),"🔗 открыть"),"")) -> 🔗 открыть | C20: =IFERROR(VLOOKUP($A20,'Мои блогеры'!$A:$N,5,0),"") -> 4000 | D20: MAX | E20: Сайт | F20: telega in | G20: t27 | H20: 46249 | I20: Вышло | J20: 349 | M20: =IF(N($J20)+N($K20)+N($L20)=0,"",N($J20)+N($K20)+N($L20)) -> 349 | O20: https://trigger-fish.ru/?utm_source=max&utm_medium=publik&utm_campaign=alexeyvfishing&utm_content=t27 | S20: https://max.ru/alexeyvfishing/AaAEOW_-O0w | U20: 652 | V20: =IF(N($U20)=0,"",$M20/$U20) -> 0.53527607 | W20: 16 | Y20: =IF(N($W20)=0,"",$M20/$W20) -> 21.8125 | Z20: 15 | AF20: =IF(OR(N($AD20)=0,$AE20=""),"",ROUND($AD20*$AE20,0)) | AG20: =IF(N($AD20)=0,"",ROUND($M20/$AD20,0)) | AH20: =IF(N($AA20)=0,"",ROUND($M20/$AA20,0))
A21: Рыбалка СПб и Карелия | B21: =IF($A21="","",IFERROR(HYPERLINK(VLOOKUP($A21,'Мои блогеры'!$A:$N,14,0),"🔗 открыть"),"")) -> 🔗 открыть | C21: =IFERROR(VLOOKUP($A21,'Мои блогеры'!$A:$N,5,0),"") -> 3300 | D21: MAX | E21: Сайт | F21: telega in | G21: t27 | H21: 46249 | I21: Вышло | J21: =IFERROR(VLOOKUP($A21,'Мои блогеры'!$A:$N,8,0),"") -> 560 | M21: =IF(N($J21)+N($K21)+N($L21)=0,"",N($J21)+N($K21)+N($L21)) -> 560 | O21: https://trigger-fish.ru/?utm_source=max&utm_medium=publik&utm_campaign=spbkorel&utm_content=t27 | S21: https://max.ru/fishingspb1/AaAEcE1jd0w | U21: 930 | V21: =IF(N($U21)=0,"",$M21/$U21) -> 0.60215054 | W21: 18 | Y21: =IF(N($W21)=0,"",$M21/$W21) -> 31.111111 | Z21: 15 | AA21: 2 | AB21: 1180 | AG21: =IF(N($AD21)=0,"",ROUND($M21/$AD21,0))
A22: rubalkarussia | B22: =IF($A22="","",IFERROR(HYPERLINK(VLOOKUP($A22,'Мои блогеры'!$A:$N,14,0),"🔗 открыть"),"")) -> 🔗 открыть | C22: =IFERROR(VLOOKUP($A22,'Мои блогеры'!$A:$N,5,0),"") -> 7800 | D22: MAX | E22: Сайт | F22: telega in | G22: t27 | H22: 46249 | I22: Вышло | J22: 2097 | M22: =IF(N($J22)+N($K22)+N($L22)=0,"",N($J22)+N($K22)+N($L22)) -> 2097 | O22: https://trigger-fish.ru/?utm_source=max&utm_medium=publik&utm_campaign=max.ru%2Frubalkarussia&utm_content=t27 | S22: https://max.ru/rubalkarussia/AaAGSbIzf8g | U22: 2329 | V22: =IF(N($U22)=0,"",$M22/$U22) -> 0.90038643 | W22: 41 | Y22: =IF(N($W22)=0,"",$M22/$W22) -> 51.146341 | Z22: 2 | AG22: =IF(N($AD22)=0,"",ROUND($M22/$AD22,0))
A23: fish_journal дневник | B23: =IF($A23="","",IFERROR(HYPERLINK(VLOOKUP($A23,'Мои блогеры'!$A:$N,14,0),"🔗 открыть"),"")) | C23: 5933 | D23: MAX | E23: Сайт | F23: telega in | G23: t27 | H23: 46249 | I23: Вышло | J23: 1258 | M23: =IF(N($J23)+N($K23)+N($L23)=0,"",N($J23)+N($K23)+N($L23)) -> 1258 | O23: https://trigger-fish.ru/?utm_source=max&utm_medium=publik&utm_campaign=fish_journal&utm_content=t27 | S23: https://max.ru/fish_journal/AaAEqvUQEUw | U23: 1493 | V23: =IF(N($U23)=0,"",$M23/$U23) -> 0.84259879 | W23: 74 | Y23: =IF(N($W23)=0,"",$M23/$W23) -> 17 | Z23: 16 | AA23: 4 | AB23: 2360 | AG23: =IF(N($AD23)=0,"",ROUND($M23/$AD23,0))
A24: Рыбалка в Нижнем Новгороде | B24: =IF($A24="","",IFERROR(HYPERLINK(VLOOKUP($A24,'Мои блогеры'!$A:$N,14,0),"🔗 открыть"),"")) -> 🔗 открыть | C24: =IFERROR(VLOOKUP($A24,'Мои блогеры'!$A:$N,5,0),"") -> 453 | D24: MAX | E24: Сайт | F24: telega in | G24: t27 | H24: 46249 | I24: Вышло | J24: =IFERROR(VLOOKUP($A24,'Мои блогеры'!$A:$N,8,0),"") -> 350 | M24: =IF(N($J24)+N($K24)+N($L24)=0,"",N($J24)+N($K24)+N($L24)) -> 350 | O24: https://trigger-fish.ru/?utm_source=max&utm_medium=publik&utm_campaign=channel_rybalka_52&utm_content=t27 | S24: https://max.ru/channel_Rybalka_52/AaAGlQguSww | U24: 505 | V24: =IF(N($U24)=0,"",$M24/$U24) -> 0.69306931 | W24: 35 | Y24: =IF(N($W24)=0,"",$M24/$W24) -> 10 | Z24: 1 | AG24: =IF(N($AD24)=0,"",ROUND($M24/$AD24,0))
A25: Рыбалка по-русски | B25: =IF($A25="","",IFERROR(HYPERLINK(VLOOKUP($A25,'Мои блогеры'!$A:$N,14,0),"🔗 открыть"),"")) -> 🔗 открыть | C25: =IFERROR(VLOOKUP($A25,'Мои блогеры'!$A:$N,5,0),"") -> 1200 | D25: MAX | E25: Сайт | F25: telega in | G25: t27 | H25: 46249 | I25: Вышло | J25: =IFERROR(VLOOKUP($A25,'Мои блогеры'!$A:$N,8,0),"") -> 532 | M25: =IF(N($J25)+N($K25)+N($L25)=0,"",N($J25)+N($K25)+N($L25)) -> 532 | O25: https://trigger-fish.ru/?utm_source=max&utm_medium=publik&utm_campaign=russian_fishing_pro&utm_content=t27 | S25: https://max.ru/russian_fishing_pro/AaAG5yAKQQw | U25: 892 | V25: =IF(N($U25)=0,"",$M25/$U25) -> 0.59641256 | W25: 10 | Y25: =IF(N($W25)=0,"",$M25/$W25) -> 53.2 | Z25: 1 | AG25: =IF(N($AD25)=0,"",ROUND($M25/$AD25,0)) | AH25: =IF(N($AA25)=0,"",ROUND($M25/$AA25,0))
A26: Рыбалка. Рыба. Рыбаки🎣 | B26: =IF($A26="","",IFERROR(HYPERLINK(VLOOKUP($A26,'Мои блогеры'!$A:$N,14,0),"🔗 открыть"),"")) -> 🔗 открыть | C26: =IFERROR(VLOOKUP($A26,'Мои блогеры'!$A:$N,5,0),"") -> 2800 | D26: MAX | E26: Сайт | F26: telega in | G26: t27 | H26: 46249 | I26: Вышло | J26: =IFERROR(VLOOKUP($A26,'Мои блогеры'!$A:$N,8,0),"") -> 979 | M26: =IF(N($J26)+N($K26)+N($L26)=0,"",N($J26)+N($K26)+N($L26)) -> 979 | O26: https://trigger-fish.ru/?utm_source=max&utm_medium=publik&utm_campaign=rybalka555&utm_content=t27 | S26: https://max.ru/rybalka555/AaADy5FHb0w | U26: 1429 | V26: =IF(N($U26)=0,"",$M26/$U26) -> 0.68509447 | W26: 36 | Y26: =IF(N($W26)=0,"",$M26/$W26) -> 27.194444 | Z26: 1 | AD26: =IF(OR(N($AA26)=0,$AC26=""),"",ROUND($AA26*$AC26,0)) | AF26: =IF(OR(N($AD26)=0,$AE26=""),"",ROUND($AD26*$AE26,0)) | AG26: =IF(N($AD26)=0,"",ROUND($M26/$AD26,0)) | AH26: =IF(N($AA26)=0,"",ROUND($M26/$AA26,0))
A27: Рыбалка на фидер в Санкт-Петербурге | C27: =IFERROR(VLOOKUP($A27,'Мои блогеры'!$A:$N,5,0),"") -> 2700 | D27: Telegram | E27: Сайт | F27: telega in | G27: t27 | H27: 46249 | I27: Вышло | J27: 293 | M27: =IF(N($J27)+N($K27)+N($L27)=0,"",N($J27)+N($K27)+N($L27)) -> 293 | O27: https://trigger-fish.ru/?utm_source=max&utm_medium=publik&utm_campaign=feeder_spb&utm_content=t27 | S27: https://telegram.me/feeder_spb/10105 | U27: 1329 | V27: =IF(N($U27)=0,"",$M27/$U27) -> 0.22046652 | W27: 11 | Y27: =IF(N($W27)=0,"",$M27/$W27) -> 26.636364 | Z27: 1 | AF27: =IF(OR(N($AD27)=0,$AE27=""),"",ROUND($AD27*$AE27,0)) | AG27: =IF(N($AD27)=0,"",ROUND($M27/$AD27,0)) | AH27: =IF(N($AA27)=0,"",ROUND($M27/$AA27,0))
A28: РЫБАКИ КУБАНЬ АДЫГЕЯ | ОТЧЕТЫ | C28: =IFERROR(VLOOKUP($A28,'Мои блогеры'!$A:$N,5,0),"") -> 3900 | D28: MAX | E28: Сайт | F28: telega in | G28: t27 | H28: 46249 | I28: Вышло | J28: =IFERROR(VLOOKUP($A28,'Мои блогеры'!$A:$N,8,0),"") -> 700 | M28: =IF(N($J28)+N($K28)+N($L28)=0,"",N($J28)+N($K28)+N($L28)) -> 700 | O28: https://trigger-fish.ru/?utm_source=max&utm_medium=publik&utm_campaign=fishing_kuban_adygea&utm_content=t27 | S28: https://max.ru/Fishing_Kuban_Adygea/AaAFS5vOGOw | U28: 1304 | V28: =IF(N($U28)=0,"",$M28/$U28) -> 0.53680982 | W28: 39 | Y28: =IF(N($W28)=0,"",$M28/$W28) -> 17.948718 | Z28: 1 | AF28: =IF(OR(N($AD28)=0,$AE28=""),"",ROUND($AD28*$AE28,0)) | AG28: =IF(N($AD28)=0,"",ROUND($M28/$AD28,0)) | AH28: =IF(N($AA28)=0,"",ROUND($M28/$AA28,0))
A29: Рыбалка на Волге | Самарская рыбалка | C29: =IFERROR(VLOOKUP($A29,'Мои блогеры'!$A:$N,5,0),"") -> 7200 | D29: Telegram | E29: Сайт | F29: telega in | G29: t27 | H29: 46249 | I29: Вышло | J29: =IFERROR(VLOOKUP($A29,'Мои блогеры'!$A:$N,8,0),"") -> 700 | M29: =IF(N($J29)+N($K29)+N($L29)=0,"",N($J29)+N($K29)+N($L29)) -> 700 | O29: https://trigger-fish.ru/?utm_source=telegram&utm_medium=publik&utm_campaign=samarafish&utm_content=t27 | S29: https://telegram.me/samarafish/19820 | U29: 1839 | V29: =IF(N($U29)=0,"",$M29/$U29) -> 0.38064165 | W29: 6 | Y29: =IF(N($W29)=0,"",$M29/$W29) -> 116.66667 | Z29: 3 | AF29: =IF(OR(N($AD29)=0,$AE29=""),"",ROUND($AD29*$AE29,0)) | AG29: =IF(N($AD29)=0,"",ROUND($M29/$AD29,0)) | AH29: =IF(N($AA29)=0,"",ROUND($M29/$AA29,0))
A30: РЫБАЛКА РОСТОВ И ОБЛАСТЬ🐟 | C30: =IFERROR(VLOOKUP($A30,'Мои блогеры'!$A:$N,5,0),"") -> 1600 | D30: MAX | E30: Сайт | F30: telega in | G30: t27 | H30: 46249 | I30: Вышло | J30: 699 | M30: =IF(N($J30)+N($K30)+N($L30)=0,"",N($J30)+N($K30)+N($L30)) -> 699 | O30: https://trigger-fish.ru/?utm_source=max&utm_medium=publik&utm_campaign=channel_rostov_fishing&utm_content=t27 | S30: https://max.ru/channel_Rostov_Fishing/AaAEOXtMP0w | U30: 979 | V30: =IF(N($U30)=0,"",$M30/$U30) -> 0.71399387 | W30: 71 | Y30: =IF(N($W30)=0,"",$M30/$W30) -> 9.8450704 | Z30: 2 | AF30: =IF(OR(N($AD30)=0,$AE30=""),"",ROUND($AD30*$AE30,0)) | AG30: =IF(N($AD30)=0,"",ROUND($M30/$AD30,0)) | AH30: =IF(N($AA30)=0,"",ROUND($M30/$AA30,0))
A31: Рыбалка | C31: =IFERROR(VLOOKUP($A31,'Мои блогеры'!$A:$N,5,0),"") -> 25900 | D31: MAX | E31: Сайт | F31: telega in | G31: t27 | H31: 46250 | I31: Вышло | J31: 3496 | M31: =IF(N($J31)+N($K31)+N($L31)=0,"",N($J31)+N($K31)+N($L31)) -> 3496 | O31: https://trigger-fish.ru/?utm_source=max&utm_medium=publik&utm_campaign=life_fishing&utm_content=t27 | S31: https://max.ru/life_fishing/AaAJXv4LLk0 | U31: 4593 | V31: =IF(N($U31)=0,"",$M31/$U31) -> 0.76115828 | W31: 72 | Y31: =IF(N($W31)=0,"",$M31/$W31) -> 48.555556 | Z31: 2 | AA31: 2 | AB31: 1180 | AG31: =IF(N($AD31)=0,"",ROUND($M31/$AD31,0)) | AH31: =IF(N($AA31)=0,"",ROUND($M31/$AA31,0)) -> 1748
A32: Итого 10-16 августа | I32: =SUM(I17:I31) -> 0 | J32: =SUM(J17:J31) -> 78831 | K32: =SUM(K17:K31) -> 2730 | L32: =SUM(L17:L31) -> 780 | M32: =SUM(M17:M31) -> 82341 | N32: =SUM(N17:N31) -> 0 | O32: =SUM(O17:O31) -> 0 | P32: =SUM(P17:P31) -> 0 | ... S32: =SUM(S17:S31) -> 0 | U32: =SUM(U17:U31) -> 345914 | V32: =SUM(V17:V31) -> 8.3562894 | W32: =SUM(W17:W31) -> 1609 | X32: =SUM(X17:X31) -> 14 | Y32: =SUM(Y17:Y31) -> 783.79484 | Z32: =SUM(Z17:Z31) -> 205 | AA32: =SUM(AA17:AA31) -> 28 | AB32: =SUM(AB17:AB31) -> 19580 | ... AH32: =SUM(AH17:AH31) -> 10151
A33: НЕДЕЛЯ — 17–23 августа
A34: https://vk.ru/fishinglifetv | B34: =IF($A34="","",IFERROR(HYPERLINK(VLOOKUP($A34,'Мои блогеры'!$A:$N,14,0),"🔗 открыть"),"")) -> 🔗 открыть | C34: =IFERROR(VLOOKUP($A34,'Мои блогеры'!$A:$N,5,0),"") -> 7800 | D34: =IFERROR(VLOOKUP($A34,'Мои блогеры'!$A:$N,2,0),"") -> VK | E34: Ozon | G34: свой сценарий | H34: 46256 | I34: Вышло | J34: =IFERROR(VLOOKUP($A34,'Мои блогеры'!$A:$N,8,0),"") -> 40000 | K34: 5000 | M34: =IF(N($J34)+N($K34)+N($L34)=0,"",N($J34)+N($K34)+N($L34)) -> 45000 | O34: https://ozon.onelink.me/SNMZ?af_dp=https://ozon.ru/product/aminotrigger-fish-aromatizator-dlya-rybalki-250-ml-5340361400/&af_web_dp=https://ozon.ru/product/aminotrigger-fish-aromatizator-dlya-rybalki-250-ml-5340361400/&is_retargeting=true&c=vendor_org_4202727_t28&pid=vk|video&af_keywords=fishinglifetv&hs=1&utm_source=vk&utm_medium=video&utm_campaign=vendor_org_4202727_t28&utm_term=fishinglifetv | P34: https://aminotriggerfish.mobz.market/b0g | S34: https://vk.ru/wall-226894765_643 | U34: 20300 | V34: =IF(N($U34)=0,"",$M34/$U34) -> 2.2167488 | W34: 116 | X34: - | Y34: =IF(N($W34)=0,"",$M34/$W34) -> 387.93103 | Z34: 18 | AD34: =IF(OR(N($AA34)=0,$AC34=""),"",ROUND($AA34*$AC34,0)) | AF34: =IF(OR(N($AD34)=0,$AE34=""),"",ROUND($AD34*$AE34,0)) | AG34: =IF(N($AD34)=0,"",ROUND($M34/$AD34,0)) | AH34: =IF(N($AA34)=0,"",ROUND($M34/$AA34,0)) | AJ34: тут будут еще доп посты
A35: pugleonid | B35: =IF($A35="","",IFERROR(HYPERLINK(VLOOKUP($A35,'Мои блогеры'!$A:$N,14,0),"🔗 открыть"),"")) -> 🔗 открыть | C35: =IFERROR(VLOOKUP($A35,'Мои блогеры'!$A:$N,5,0),"") -> 61000 | D35: =IFERROR(VLOOKUP($A35,'Мои блогеры'!$A:$N,2,0),"") -> VK | E35: Ozon | F35: 13 | G35: v1 | H35: 46253 | I35: Вышло | J35: =IFERROR(VLOOKUP($A35,'Мои блогеры'!$A:$N,8,0),"") -> 65000 | K35: =65000*0.09 -> 5850 | L35: 500 | M35: =IF(N($J35)+N($K35)+N($L35)=0,"",N($J35)+N($K35)+N($L35)) -> 71350 | O35: https://ozon.ru/product/aminotrigger-fish-aromatizator-dlya-rybalki-250-ml-5340361400/?hs=1&utm_campaign=vendor_org_4202727_pugleonid&utm_medium=video&utm_source=vk | P35: https://aminotriggerfish.mobz.market/s6i | S35: https://vk.ru/clip-221128641_456239567?c=1 | T35: Да | U35: 3900 | V35: =IF(N($U35)=0,"",$M35/$U35) -> 18.294872 | W35: 39 | X35: - | Y35: =IF(N($W35)=0,"",$M35/$W35) -> 1829.4872 | Z35: 24 | AD35: =IF(OR(N($AA35)=0,$AC35=""),"",ROUND($AA35*$AC35,0)) | AF35: =IF(OR(N($AD35)=0,$AE35=""),"",ROUND($AD35*$AE35,0)) | AG35: =IF(N($AD35)=0,"",ROUND($M35/$AD35,0)) | AH35: =IF(N($AA35)=0,"",ROUND($M35/$AA35,0)) | AJ35: дубль в други соц сети будет
A36: novo_fish | B36: =IF($A36="","",IFERROR(HYPERLINK(VLOOKUP($A36,'Мои блогеры'!$A:$N,14,0),"🔗 открыть"),"")) -> 🔗 открыть | C36: =IFERROR(VLOOKUP($A36,'Мои блогеры'!$A:$N,5,0),"") -> 7930 | D36: TikTok | E36: WB | G36: v1 | H36: 46257 | I36: Вышло | J36: =IFERROR(VLOOKUP($A36,'Мои блогеры'!$A:$N,8,0),"") -> 5000 | K36: 400 | L36: 822 | M36: =IF(N($J36)+N($K36)+N($L36)=0,"",N($J36)+N($K36)+N($L36)) -> 6222 | O36: https://wildberries.ru/catalog/0/search.aspx?search=WW947786 | R36: WW947786 | S36: https://www.tiktok.com/@novo_fish/video/7677190984953908513 | T36: Да | U36: 4489 | V36: =IF(N($U36)=0,"",$M36/$U36) -> 1.3860548 | W36: 17 | X36: - | Y36: =IF(N($W36)=0,"",$M36/$W36) -> 366 | Z36: 4 | AA36: 2 | AB36: =743*AA36 -> 1486 | AD36: 1 | AE36: =AB36/AD36 -> 1486 | AF36: =IF(OR(N($AD36)=0,$AE36=""),"",ROUND($AD36*$AE36,0)) -> 1486 | AG36: =IF(N($AD36)=0,"",ROUND($M36/$AD36,0)) -> 6222 | AH36: =IF(N($AA36)=0,"",ROUND($M36/$AA36,0)) -> 3111 | AJ36: только вышел
A37: Доступная рыбалка | B37: =IF($A37="","",IFERROR(HYPERLINK(VLOOKUP($A37,'Мои блогеры'!$A:$N,14,0),"🔗 открыть"),"")) -> 🔗 открыть | C37: =IFERROR(VLOOKUP($A37,'Мои блогеры'!$A:$N,5,0),"") -> 27100 | D37: =IFERROR(VLOOKUP($A37,'Мои блогеры'!$A:$N,2,0),"") -> VK | E37: Ozon | G37: t27 | H37: 46256 | I37: Вышло | J37: =IFERROR(VLOOKUP($A37,'Мои блогеры'!$A:$N,8,0),"") -> 13000 | K37: 780 | M37: =IF(N($J37)+N($K37)+N($L37)=0,"",N($J37)+N($K37)+N($L37)) -> 13780 | O37: https://ozon.onelink.me/SNMZ?af_dp=https://ozon.ru/product/aminotrigger-fish-aromatizator-dlya-rybalki-250-ml-5340361400/&af_web_dp=https://ozon.ru/product/aminotrigger-fish-aromatizator-dlya-rybalki-250-ml-5340361400/&is_retargeting=true&c=vendor_org_4202727_доступная рыбалка &pid=vk|blog&af_adset=т28 &hs=1&utm_source=vk&utm_medium=blog&utm_campaign=vendor_org_4202727_доступная+рыбалка &utm_content=т28 | S37: https://vk.ru/wall-136853349_64568 | U37: 24930 | V37: =IF(N($U37)=0,"",$M37/$U37) -> 0.55274769 | W37: 42 | Y37: =IF(N($W37)=0,"",$M37/$W37) -> 328.09524 | Z37: 8 | AD37: =IF(OR(N($AA37)=0,$AC37=""),"",ROUND($AA37*$AC37,0)) | AF37: =IF(OR(N($AD37)=0,$AE37=""),"",ROUND($AD37*$AE37,0)) | AG37: =IF(N($AD37)=0,"",ROUND($M37/$AD37,0)) | AH37: =IF(N($AA37)=0,"",ROUND($M37/$AA37,0)) | AJ37: сутки
A38: Рыбалка в кайф | C38: =IFERROR(VLOOKUP($A38,'Мои блогеры'!$A:$N,5,0),"") -> 761 | D38: MAX | E38: Сайт | F38: telega in | G38: t27 | H38: 46255 | I38: Вышло | J38: =IFERROR(VLOOKUP($A38,'Мои блогеры'!$A:$N,8,0),"") -> 348 | M38: =IF(N($J38)+N($K38)+N($L38)=0,"",N($J38)+N($K38)+N($L38)) -> 348 | O38: https://trigger-fish.ru/?utm_source=max&utm_medium=publik&utm_campaign=vkaifl_riabalka&utm_content=t27 | S38: https://max.ru/channel_riabalka/AaAiQ4ZBKcY | U38: 338 | V38: =IF(N($U38)=0,"",$M38/$U38) -> 1.0295858 | W38: 22 | Y38: =IF(N($W38)=0,"",$M38/$W38) -> 15.818182 | Z38: 3 | AJ38: сутки
A39: Рыбалка | Клёвое место | C39: =IFERROR(VLOOKUP($A39,'Мои блогеры'!$A:$N,5,0),"") -> 4200 | D39: MAX | E39: Сайт | F39: telega in | G39: t27 | H39: 46255 | I39: Вышло | J39: =IFERROR(VLOOKUP($A39,'Мои блогеры'!$A:$N,8,0),"") -> 980 | M39: =IF(N($J39)+N($K39)+N($L39)=0,"",N($J39)+N($K39)+N($L39)) -> 980 | O39: https://trigger-fish.ru/?utm_source=max&utm_medium=publik&utm_campaign=rybalka_7&utm_content=t27 | S39: https://max.ru/rybalka_7/AaAiQ3aoC8Y | U39: 1114 | V39: =IF(N($U39)=0,"",$M39/$U39) -> 0.87971275 | W39: 35 | Y39: =IF(N($W39)=0,"",$M39/$W39) -> 28 | Z39: 2 | AJ39: сутки
A40: блог рыбака | C40: =IFERROR(VLOOKUP($A40,'Мои блогеры'!$A:$N,5,0),"") -> 1600 | D40: MAX | E40: Сайт | F40: telega in | G40: t27 | H40: 46255 | I40: Вышло | J40: =IFERROR(VLOOKUP($A40,'Мои блогеры'!$A:$N,8,0),"") -> 392 | M40: =IF(N($J40)+N($K40)+N($L40)=0,"",N($J40)+N($K40)+N($L40)) -> 392 | O40: https://trigger-fish.ru/?utm_source=max&utm_medium=publik&utm_campaign=blogrybaka&utm_content=t27 | S40: https://max.ru/join/-B1pH9O5LwDun19v5QK_CES0a8YCZ940MUNS4gEcKOo | U40: 481 | V40: =IF(N($U40)=0,"",$M40/$U40) -> 0.81496881 | W40: 12 | Y40: =IF(N($W40)=0,"",$M40/$W40) -> 32.666667 | Z40: 1 | AJ40: сутки
A41: В САДКЕ - Рыбалка Хабаровский край и ДВ | C41: =IFERROR(VLOOKUP($A41,'Мои блогеры'!$A:$N,5,0),"") -> 1200 | D41: MAX | E41: Сайт | F41: telega in | G41: t27 | H41: 46255 | I41: Вышло | J41: =IFERROR(VLOOKUP($A41,'Мои блогеры'!$A:$N,8,0),"") -> 1258 | M41: =IF(N($J41)+N($K41)+N($L41)=0,"",N($J41)+N($K41)+N($L41)) -> 1258 | O41: https://trigger-fish.ru/?utm_source=max&utm_medium=publik&utm_campaign=channel_vsadke&utm_content=t27 | S41: https://max.ru/channel_VSADKE/AaAjWQZCNeY | U41: 769 | V41: =IF(N($U41)=0,"",$M41/$U41) -> 1.6358908 | W41: 15 | Y41: =IF(N($W41)=0,"",$M41/$W41) -> 83.866667 | Z41: 1 | AJ41: сутки
A42: трофейный | C42: =IFERROR(VLOOKUP($A42,'Мои блогеры'!$A:$N,5,0),"") -> 5300 | D42: MAX | E42: Сайт | F42: telega in | G42: t27 | H42: 46255 | I42: Вышло | J42: =IFERROR(VLOOKUP($A42,'Мои блогеры'!$A:$N,8,0),"") -> 980 | M42: =IF(N($J42)+N($K42)+N($L42)=0,"",N($J42)+N($K42)+N($L42)) -> 980 | O42: https://trigger-fish.ru/?utm_source=max&utm_medium=publik&utm_campaign=max.ru%2Ftrofeysaratov&utm_content=t27 | S42: https://max.ru/trofeysaratov/AaAjklWKX-Y | U42: 1024 | V42: =IF(N($U42)=0,"",$M42/$U42) -> 0.95703125 | W42: 6 | Y42: =IF(N($W42)=0,"",$M42/$W42) -> 163.33333 | Z42: 2 | AA42: 2 | AB42: 1180 | AD42: 1 | AE42: =AB42/AD42 -> 1180 | AF42: 1180 | AG42: =IF(N($AD42)=0,"",ROUND($M42/$AD42,0)) -> 980 | AH42: =IF(N($AA42)=0,"",ROUND($M42/$AA42,0)) -> 490 | AJ42: сутки
A43: Зая!чья лапка? | Товары за отзыв | WB и OZON | C43: =IFERROR(VLOOKUP($A43,'Мои блогеры'!$A:$N,5,0),"") -> 5100 | D43: MAX | E43: Сайт | F43: telega in | G43: t27 | H43: 46255 | I43: Вышло | J43: =IFERROR(VLOOKUP($A43,'Мои блогеры'!$A:$N,8,0),"") -> 293 | M43: =IF(N($J43)+N($K43)+N($L43)=0,"",N($J43)+N($K43)+N($L43)) -> 293 | O43: https://trigger-fish.ru/?utm_source=max&utm_medium=publik&utm_campaign=chilapka&utm_content=t27 | S43: https://max.ru/join/aCIbN1JRxCFy84v811-Q8Iadi1-loYRgzzUF2UQv0Ko | U43: 435 | V43: =IF(N($U43)=0,"",$M43/$U43) -> 0.67356322 | W43: 5 | Y43: =IF(N($W43)=0,"",$M43/$W43) -> 58.6 | Z43: 0 | AJ43: сутки
A44: домашние хитрости | C44: =IFERROR(VLOOKUP($A44,'Мои блогеры'!$A:$N,5,0),"") -> 2800 | D44: MAX | E44: Сайт | F44: telega in | G44: t27 | H44: 46255 | I44: Вышло | J44: =IFERROR(VLOOKUP($A44,'Мои блогеры'!$A:$N,8,0),"") -> 700 | M44: =IF(N($J44)+N($K44)+N($L44)=0,"",N($J44)+N($K44)+N($L44)) -> 700 | O44: https://trigger-fish.ru/?utm_source=max&utm_medium=publik&utm_campaign=domashniehitrosti&utm_content=t27 | S44: https://max.ru/join/-Ga5MmYNaN5TUj1yklwyICg_zp8zmmqzGhT9oJZq5BY | U44: 738 | V44: =IF(N($U44)=0,"",$M44/$U44) -> 0.94850949 | W44: 5 | Y44: =IF(N($W44)=0,"",$M44/$W44) -> 140 | Z44: 0 | AJ44: сутки
A45: Рыбалка в Сибири на Байкале | C45: =IFERROR(VLOOKUP($A45,'Мои блогеры'!$A:$N,5,0),"") -> 2900 | D45: MAX | E45: Сайт | F45: telega in | G45: t27 | H45: 46255 | I45: Вышло | J45: =IFERROR(VLOOKUP($A45,'Мои блогеры'!$A:$N,8,0),"") -> 4195 | M45: =IF(N($J45)+N($K45)+N($L45)=0,"",N($J45)+N($K45)+N($L45)) -> 4195 | O45: https://trigger-fish.ru/?utm_source=max&utm_medium=publik&utm_campaign=baikfish38rus&utm_content=t27 | S45: https://max.ru/fish38rus/AaAirVw6ecY | U45: 1267 | V45: =IF(N($U45)=0,"",$M45/$U45) -> 3.3109708 | W45: 28 | Y45: =IF(N($W45)=0,"",$M45/$W45) -> 149.82143 | Z45: 1 | AJ45: сутки
A46: Точки клева | C46: =IFERROR(VLOOKUP($A46,'Мои блогеры'!$A:$N,5,0),"") -> 9100 | D46: Telegram | E46: Сайт | F46: telega in | G46: t27 | H46: 46255 | I46: Вышло | J46: =IFERROR(VLOOKUP($A46,'Мои блогеры'!$A:$N,8,0),"") -> 307 | M46: =IF(N($J46)+N($K46)+N($L46)=0,"",N($J46)+N($K46)+N($L46)) -> 307 | O46: https://trigger-fish.ru/?utm_source=tg&utm_medium=publik&utm_campaign=tochkaklevarussian_fishrr4&utm_content=t27 | S46: https://telegram.me/Russian_FishRR4/48389 | U46: 1693 | V46: =IF(N($U46)=0,"",$M46/$U46) -> 0.18133491 | W46: 5 | Y46: =IF(N($W46)=0,"",$M46/$W46) -> 61.4 | Z46: 2 | AA46: 2 | AB46: 1180 | AJ46: сутки
A47: Подмосковные грибники и | C47: =IFERROR(VLOOKUP($A47,'Мои блогеры'!$A:$N,5,0),"") -> 3200 | D47: MAX | E47: Сайт | F47: telega in | G47: t27 | H47: 46255 | I47: Вышло | J47: =IFERROR(VLOOKUP($A47,'Мои блогеры'!$A:$N,8,0),"") -> 419 | M47: =IF(N($J47)+N($K47)+N($L47)=0,"",N($J47)+N($K47)+N($L47)) -> 419 | O47: https://trigger-fish.ru/?utm_source=tg&utm_medium=publik&utm_campaign=gribniki_i_ribalka_v_podmsk&utm_content=t27 | S47: https://telegram.me/gribniki_podmos/27434 | U47: 989 | V47: =IF(N($U47)=0,"",$M47/$U47) -> 0.42366026 | W47: 5 | Y47: =IF(N($W47)=0,"",$M47/$W47) -> 83.8 | Z47: 1 | AJ47: сутки
A48: Челнинские рыбаки | C48: =IFERROR(VLOOKUP($A48,'Мои блогеры'!$A:$N,5,0),"") -> 7900 | D48: Telegram | E48: Сайт | F48: telega in | G48: t27 | H48: 46255 | I48: Вышло | J48: =IFERROR(VLOOKUP($A48,'Мои блогеры'!$A:$N,8,0),"") -> 2800 | M48: =IF(N($J48)+N($K48)+N($L48)=0,"",N($J48)+N($K48)+N($L48)) -> 2800 | O48: https://trigger-fish.ru/?utm_source=tg&utm_medium=publik&utm_campaign=chelny_rybaki&utm_content=t27 | S48: https://telegram.me/chelny_rybaki/242830 | U48: 3200 | V48: =IF(N($U48)=0,"",$M48/$U48) -> 0.875 | W48: 5 | Y48: =IF(N($W48)=0,"",$M48/$W48) -> 560 | Z48: 4 | AJ48: сутки
A49: Тульские рыбаки | C49: =IFERROR(VLOOKUP($A49,'Мои блогеры'!$A:$N,5,0),"") -> 3000 | D49: Telegram | E49: Сайт | F49: telega in | G49: t27 | H49: 46255 | I49: Вышло | J49: =IFERROR(VLOOKUP($A49,'Мои блогеры'!$A:$N,8,0),"") -> 700 | M49: =IF(N($J49)+N($K49)+N($L49)=0,"",N($J49)+N($K49)+N($L49)) -> 700 | O49: https://trigger-fish.ru/?utm_source=tg&utm_medium=publik&utm_campaign=tulfishing_71&utm_content=t27 | S49: https://telegram.me/fishing_71/4145 | U49: 684 | V49: =IF(N($U49)=0,"",$M49/$U49) -> 1.0233918 | W49: 5 | Y49: =IF(N($W49)=0,"",$M49/$W49) -> 140 | Z49: 1 | AJ49: сутки
A50: Рыбалка Воронеж. Чат | C50: =IFERROR(VLOOKUP($A50,'Мои блогеры'!$A:$N,5,0),"") -> 1300 | D50: Telegram | E50: Сайт | F50: telega in | G50: t27 | H50: 46255 | I50: Вышло | J50: =IFERROR(VLOOKUP($A50,'Мои блогеры'!$A:$N,8,0),"") -> 2097 | M50: =IF(N($J50)+N($K50)+N($L50)=0,"",N($J50)+N($K50)+N($L50)) -> 2097 | O50: https://trigger-fish.ru/?utm_source=tg&utm_medium=publik&utm_campaign=rybalka_vrn&utm_content=t27 | S50: https://t.me/rybalka_vrn/156582 | U50: 1650 | V50: =IF(N($U50)=0,"",$M50/$U50) -> 1.2709091 | W50: 1 | Y50: =IF(N($W50)=0,"",$M50/$W50) -> 2097 | Z50: 2 | AA50: 2 | AB50: 1180 | AJ50: сутки
A51: Рыбалка в Башкортостане, Башкирии | Уфа | C51: =IFERROR(VLOOKUP($A51,'Мои блогеры'!$A:$N,5,0),"") -> 1100 | D51: MAX | E51: Сайт | F51: telega in | G51: t27 | H51: 46255 | I51: Вышло | J51: =IFERROR(VLOOKUP($A51,'Мои блогеры'!$A:$N,8,0),"") -> 490 | M51: =IF(N($J51)+N($K51)+N($L51)=0,"",N($J51)+N($K51)+N($L51)) -> 490 | O51: https://trigger-fish.ru/?utm_source=max&utm_medium=publik&utm_campaign=rybalka_bashkortostan&utm_content=t27 | S51: https://max.ru/Rybalka_Bashkortostan/AaAlNjdWCYY | U51: 673 | V51: =IF(N($U51)=0,"",$M51/$U51) -> 0.72808321 | W51: 15 | Y51: =IF(N($W51)=0,"",$M51/$W51) -> 32.666667 | Z51: 1 | AJ51: сутки
A52: ⚡РАСПРОДАЖА OZON WB 🛒 | Находки Озон | C52: =IFERROR(VLOOKUP($A52,'Мои блогеры'!$A:$N,5,0),"") -> 3600 | D52: MAX | E52: Сайт | F52: telega in | G52: t27 | H52: 46256 | I52: Вышло | J52: =IFERROR(VLOOKUP($A52,'Мои блогеры'!$A:$N,8,0),"") -> 700 | M52: =IF(N($J52)+N($K52)+N($L52)=0,"",N($J52)+N($K52)+N($L52)) -> 700 | O52: https://trigger-fish.ru/?utm_source=max&utm_medium=publik&utm_campaign=rasprodachaozon&utm_content=t27 | S52: https://max.ru/id575201032930_biz/AaApjzBmb0Y | U52: 782 | V52: =IF(N($U52)=0,"",$M52/$U52) -> 0.89514067 | W52: 7 | Y52: =IF(N($W52)=0,"",$M52/$W52) -> 100 | Z52: 0 | AJ52: сутки
A53: Сочи Online | C53: =IFERROR(VLOOKUP($A53,'Мои блогеры'!$A:$N,5,0),"") -> 2800 | D53: MAX | E53: Сайт | F53: telega in | G53: t27 | H53: 46257 | I53: Вышло | J53: =IFERROR(VLOOKUP($A53,'Мои блогеры'!$A:$N,8,0),"") -> 489 | M53: =IF(N($J53)+N($K53)+N($L53)=0,"",N($J53)+N($K53)+N($L53)) -> 489 | O53: https://trigger-fish.ru/?utm_source=max&utm_medium=publik&utm_campaign=proonlineee&utm_content=t27 | S53: https://max.ru/proonlineee/AaAta71JQQY | U53: 1022 | V53: =IF(N($U53)=0,"",$M53/$U53) -> 0.47847358 | W53: 3 | Y53: =IF(N($W53)=0,"",$M53/$W53) -> 163 | Z53: 1 | AJ53: сутки
A54: Итого: 17–23августа | I54: =COUNTIF(#REF!,"Вышло")&" / "&COUNTA(A34:A53) -> 0 / 20 | J54: =SUM(J34:J53) -> 140148 | K54: =SUM(K34:K53) -> 12030 | L54: =SUM(L34:L53) -> 1322 | M54: =SUM(M34:M53) -> 153500 | N54: =SUM(N34:N53) -> 0 | O54: =SUM(O34:O53) -> 0 | P54: =SUM(P34:P53) -> 0 | Q54: =SUM(Q34:Q53) -> 0 | ... S54: =SUM(S34:S53) -> 0 | U54: =SUM(U34:U53) -> 70478 | V54: =SUM(V34:V53) -> 38.576649 | W54: =SUM(W34:W53) -> 388 | X54: =SUM(X34:X53) -> 0 | Y54: =IF(N($W54)=0,"",$M54/$W54) -> 395.61856 | Z54: =SUM(Z34:Z53) -> 76 | AA54: =SUM(AA34:AA53) -> 8 | AB54: =SUM(AB34:AB53) -> 5026 | AC54: =SUM(AC34:AC53) -> 0 | AD54: =SUM(AD34:AD53) -> 2 | AE54: =SUM(AE34:AE53) -> 2666 | AF54: =SUM(AF34:AF53) -> 2666 | AG54: =SUM(AG34:AG53) -> 7202 | AH54: =SUM(AH34:AH53) -> 3601
A55: НЕДЕЛЯ — 24–29 августа
A56: https://www.youtube.com/@pikeordie | C56: =IFERROR(VLOOKUP($A56,'Мои блогеры'!$A:$N,5,0),"") -> 479000 | D56: =IFERROR(VLOOKUP($A56,'Мои блогеры'!$A:$N,2,0),"") -> YouTube | E56: Ozon | F56: 12 | H56: 46259 | I56: Вышло | J56: =IFERROR(VLOOKUP($A56,'Мои блогеры'!$A:$N,8,0),"") -> 13750 | K56: 1116 | M56: =IF(N($J56)+N($K56)+N($L56)=0,"",N($J56)+N($K56)+N($L56)) -> 14866 | O56: https://ozon.onelink.me/SNMZ/8de5za7t | S56: https://www.youtube.com/watch?v=954zrnc9vLA | T56: Да | U56: 14000 | V56: =IF(N($U56)=0,"",$M56/$U56) -> 1.0618571 | W56: 10 | X56: - | Y56: =IF(N($W56)=0,"",$M56/$W56) -> 1486.6 | Z56: 3 | AA56: 2 | AB56: 3400 | AD56: 2 | AE56: =AB56/AD56 -> 1700 | AF56: 3400 | AG56: =IF(N($AD56)=0,"",ROUND($M56/$AD56,0)) -> 7433 | AH56: =IF(N($AA56)=0,"",ROUND($M56/$AA56,0)) -> 7433 | AJ56: сутки
A57: Константин Андропов | B57: =IF($A57="","",IFERROR(HYPERLINK(VLOOKUP($A57,'Мои блогеры'!$A:$N,14,0),"🔗 открыть"),"")) -> 🔗 открыть | C57: =IFERROR(VLOOKUP($A57,'Мои блогеры'!$A:$N,5,0),"") -> 6400 | D57: =IFERROR(VLOOKUP($A57,'Мои блогеры'!$A:$N,2,0),"") -> Rutube | E57: Ozon | F57: 12 | H57: 46259 | I57: Вышло | J57: =IFERROR(VLOOKUP($A57,'Мои блогеры'!$A:$N,8,0),"") -> 7500 | K57: 1116 | M57: =IF(N($J57)+N($K57)+N($L57)=0,"",N($J57)+N($K57)+N($L57)) -> 8616 | O57: https://ozon.onelink.me/SNMZ/tstkfwui | S57: https://rutube.ru/video/87ce60088ef9c6bb5e353507f1301ad7/ | T57: Да | U57: 905 | V57: =IF(N($U57)=0,"",$M57/$U57) -> 9.520442 | W57: 2 | Y57: =IF(N($W57)=0,"",$M57/$W57) -> 4308 | Z57: 0 | AD57: =IF(OR(N($AA57)=0,$AC57=""),"",ROUND($AA57*$AC57,0)) | AG57: =IF(N($AD57)=0,"",ROUND($M57/$AD57,0)) | AH57: =IF(N($AA57)=0,"",ROUND($M57/$AA57,0)) | AI57: аминотригер | AJ57: сутки
A58: Константин Андропов ВК | B58: =IF($A58="","",IFERROR(HYPERLINK(VLOOKUP($A58,'Мои блогеры'!$A:$N,14,0),"🔗 открыть"),"")) -> 🔗 открыть | C58: =IFERROR(VLOOKUP($A58,'Мои блогеры'!$A:$N,5,0),"") -> 41300 | D58: =IFERROR(VLOOKUP($A58,'Мои блогеры'!$A:$N,2,0),"") -> VK | E58: Ozon | F58: 12 | H58: 46259 | I58: Вышло | J58: =IFERROR(VLOOKUP($A58,'Мои блогеры'!$A:$N,8,0),"") -> 13750 | K58: 1118 | M58: =IF(N($J58)+N($K58)+N($L58)=0,"",N($J58)+N($K58)+N($L58)) -> 14868 | O58: https://ozon.onelink.me/SNMZ/8l5jco46 | S58: https://vk.ru/im?z=video-110328564_456241951 | T58: Да | U58: 19000 | V58: =IF(N($U58)=0,"",$M58/$U58) -> 0.78252632 | W58: 5 | Y58: =IF(N($W58)=0,"",$M58/$W58) -> 2973.6 | Z58: 3 | AD58: =IF(OR(N($AA58)=0,$AC58=""),"",ROUND($AA58*$AC58,0)) | AG58: =IF(N($AD58)=0,"",ROUND($M58/$AD58,0)) | AH58: =IF(N($AA58)=0,"",ROUND($M58/$AA58,0)) | AI58: аминотригер | AJ58: сутки
A59: syilers26 | B59: =IF($A59="","",IFERROR(HYPERLINK(VLOOKUP($A59,'Мои блогеры'!$A:$N,14,0),"🔗 открыть"),"")) -> 🔗 открыть | C59: =IFERROR(VLOOKUP($A59,'Мои блогеры'!$A:$N,5,0),"") -> 103750 | D59: =IFERROR(VLOOKUP($A59,'Мои блогеры'!$A:$N,2,0),"") -> Telegram | E59: Ozon | H59: 46261 | I59: Вышло | J59: =IFERROR(VLOOKUP($A59,'Мои блогеры'!$A:$N,8,0),"") -> 30000 | K59: 2100 | L59: 725 | M59: =IF(N($J59)+N($K59)+N($L59)=0,"",N($J59)+N($K59)+N($L59)) -> 32825 | O59: https://ozon.onelink.me/SNMZ/5xw8wjxe | S59: https://t.me/syilers26/4200 | T59: Нет | U59: 12500 | V59: =IF(N($U59)=0,"",$M59/$U59) -> 2.626 | W59: 133 | Y59: =IF(N($W59)=0,"",$M59/$W59) -> 246.80451 | Z59: 42 | AA59: 4 | AB59: =3400+ 1920+ 1700 -> 7020 | AD59: 4 | AE59: =AB59/AD59 -> 1755 | AF59: 7020 | AG59: =IF(N($AD59)=0,"",ROUND($M59/$AD59,0)) -> 8206 | AH59: =IF(N($AA59)=0,"",ROUND($M59/$AA59,0)) -> 8206 | AI59: аминотригер
A60: syilers2019 | B60: =IF($A60="","",IFERROR(HYPERLINK(VLOOKUP($A60,'Мои блогеры'!$A:$N,14,0),"🔗 открыть"),"")) -> 🔗 открыть | C60: =IFERROR(VLOOKUP($A60,'Мои блогеры'!$A:$N,5,0),"") -> 16912 | D60: =IFERROR(VLOOKUP($A60,'Мои блогеры'!$A:$N,2,0),"") -> MAX | E60: Ozon | H60: 46261 | I60: Вышло | J60: =IFERROR(VLOOKUP($A60,'Мои блогеры'!$A:$N,8,0),"") -> 15000 | K60: 1050 | M60: =IF(N($J60)+N($K60)+N($L60)=0,"",N($J60)+N($K60)+N($L60)) -> 16050 | O60: https://ozon.onelink.me/SNMZ/fzc2s8oo | S60: https://max.ru/syilers2019/AaBC_lixIxo | T60: Нет | U60: 10000 | V60: =IF(N($U60)=0,"",$M60/$U60) -> 1.605 | W60: =286+32 -> 318 | Y60: =IF(N($W60)=0,"",$M60/$W60) -> 50.471698 | Z60: 100 | AA60: 21 | AB60: =24000+1900+2400+9600 -> 37900 | AD60: 21 | AE60: =AB60/AD60 -> 1804.7619 | AF60: =AB60 -> 37900 | AG60: =IF(N($AD60)=0,"",ROUND($M60/$AD60,0)) -> 764 | AH60: =IF(N($AA60)=0,"",ROUND($M60/$AA60,0)) -> 764 | AI60: аминотригер
A61: fishinglifetvrutub | B61: =IF($A61="","",IFERROR(HYPERLINK(VLOOKUP($A61,'Мои блогеры'!$A:$N,14,0),"🔗 открыть"),"")) -> 🔗 открыть | C61: =IFERROR(VLOOKUP($A61,'Мои блогеры'!$A:$N,5,0),"") -> 890 | D61: =IFERROR(VLOOKUP($A61,'Мои блогеры'!$A:$N,2,0),"") -> Rutube | E61: Ozon | H61: 46264 | I61: Вышло | J61: =IFERROR(VLOOKUP($A61,'Мои блогеры'!$A:$N,8,0),"") -> 0 | M61: 0 | O61: https://ozon.onelink.me/SNMZ/tc61op2m | S61: https://rutube.ru/video/9ead77f4a5d7ce5094851ac7e3fd4a5d/?r=a/ | T61: Да | U61: 164 | V61: =IF(N($U61)=0,"",$M61/$U61) -> 0 | W61: 0 | Y61: =IF(N($W61)=0,"",$M61/$W61) | Z61: 0 | AD61: =IF(OR(N($AA61)=0,$AC61=""),"",ROUND($AA61*$AC61,0)) | AE61: 0 | AF61: =IF(OR(N($AD61)=0,$AE61=""),"",ROUND($AD61*$AE61,0)) | AG61: =IF(N($AD61)=0,"",ROUND($M61/$AD61,0)) | AH61: =IF(N($AA61)=0,"",ROUND($M61/$AA61,0)) | AI61: аминотригер
A62: Fishing-Life TV | B62: =IF($A62="","",IFERROR(HYPERLINK(VLOOKUP($A62,'Мои блогеры'!$A:$N,14,0),"🔗 открыть"),"")) -> 🔗 открыть | C62: =IFERROR(VLOOKUP($A62,'Мои блогеры'!$A:$N,5,0),"") -> 182000 | D62: YouTube | E62: Ozon | F62: 4 | H62: 46262 | I62: Вышло | J62: =IFERROR(VLOOKUP($A62,'Мои блогеры'!$A:$N,8,0),"") -> 27500 | K62: =J62*0.06 -> 1650 | L62: 700 | M62: =IF(N($J62)+N($K62)+N($L62)=0,"",N($J62)+N($K62)+N($L62)) -> 29850 | O62: https://ozon.onelink.me/SNMZ/wxkr03el | S62: https://www.youtube.com/watch?v=IpPwpwE1GPc&t=100s | T62: Да | U62: 55000 | V62: =IF(N($U62)=0,"",$M62/$U62) -> 0.54272727 | W62: 218 | Y62: =IF(N($W62)=0,"",$M62/$W62) -> 136.92661 | Z62: 31 | AA62: 8 | AB62: 17800 | AD62: 8 | AE62: =AB62/AD62 -> 2225 | AF62: =IF(OR(N($AD62)=0,$AE62=""),"",ROUND($AD62*$AE62,0)) -> 17800 | AG62: =IF(N($AD62)=0,"",ROUND($M62/$AD62,0)) -> 3731 | AH62: =IF(N($AA62)=0,"",ROUND($M62/$AA62,0)) -> 3731 | AI62: аминотригер
A63: Fishing-Life TVvk | B63: =IF($A63="","",IFERROR(HYPERLINK(VLOOKUP($A63,'Мои блогеры'!$A:$N,14,0),"🔗 открыть"),"")) -> 🔗 открыть | C63: =IFERROR(VLOOKUP($A63,'Мои блогеры'!$A:$N,5,0),"") -> 7700 | D63: Vkontakte | E63: Ozon | F63: 4 | H63: 46264 | I63: Вышло | J63: =IFERROR(VLOOKUP($A63,'Мои блогеры'!$A:$N,8,0),"") -> 27500 | K63: =J63*0.06 -> 1650 | L63: 0 | M63: =IF(N($J63)+N($K63)+N($L63)=0,"",N($J63)+N($K63)+N($L63)) -> 29150 | O63: https://ozon.onelink.me/SNMZ/r298yc2n | S63: https://vkvideo.ru/video-226894765_456239497 | T63: Да | U63: 24900 | V63: =IF(N($U63)=0,"",$M63/$U63) -> 1.1706827 | W63: 112 | Y63: =IF(N($W63)=0,"",$M63/$W63) -> 260.26786 | Z63: 34 | AA63: 20 | AB63: 37200 | AD63: 20 | AE63: =AB63/AD63 -> 1860 | AF63: =IF(OR(N($AD63)=0,$AE63=""),"",ROUND($AD63*$AE63,0)) -> 37200 | AG63: =IF(N($AD63)=0,"",ROUND($M63/$AD63,0)) -> 1458 | AH63: =IF(N($AA63)=0,"",ROUND($M63/$AA63,0)) -> 1458 | AI63: аминотригер
A64: @batya_ilin | B64: =IF($A64="","",IFERROR(HYPERLINK(VLOOKUP($A64,'Мои блогеры'!$A:$N,14,0),"🔗 открыть"),"")) -> 🔗 открыть | C64: =IFERROR(VLOOKUP($A64,'Мои блогеры'!$A:$N,5,0),"") -> 29600 | D64: YouTube | E64: Ozon | H64: 46262 | I64: Вышло | J64: =IFERROR(VLOOKUP($A64,'Мои блогеры'!$A:$N,8,0),"") -> 38000 | K64: 2710 | L64: 715 | M64: =IF(N($J64)+N($K64)+N($L64)=0,"",N($J64)+N($K64)+N($L64)) -> 41425 | O64: - | P64: - | S64: https://www.youtube.com/shorts/mA8JJoOmi50 | T64: Да | U64: 336000 | V64: =IF(N($U64)=0,"",$M64/$U64) -> 0.12328869 | Y64: =IF(N($W64)=0,"",$M64/$W64) | AD64: =IF(OR(N($AA64)=0,$AC64=""),"",ROUND($AA64*$AC64,0)) | AF64: =IF(OR(N($AD64)=0,$AE64=""),"",ROUND($AD64*$AE64,0)) | AG64: =IF(N($AD64)=0,"",ROUND($M64/$AD64,0)) | AH64: =IF(N($AA64)=0,"",ROUND($M64/$AA64,0)) | AI64: аминотригер
A65: Спиннингисты Кубани и Адыгеи | B65: =IF($A65="","",IFERROR(HYPERLINK(VLOOKUP($A65,'Мои блогеры'!$A:$N,14,0),"🔗 открыть"),"")) -> 🔗 открыть | C65: =IFERROR(VLOOKUP($A65,'Мои блогеры'!$A:$N,5,0),"") -> 2500 | D65: =IFERROR(VLOOKUP($A65,'Мои блогеры'!$A:$N,2,0),"") -> Telegram | E65: Ozon | G65: t27 | H65: 46260 | I65: Вышло | J65: =IFERROR(VLOOKUP($A65,'Мои блогеры'!$A:$N,8,0),"") -> 699 | M65: =IF(N($J65)+N($K65)+N($L65)=0,"",N($J65)+N($K65)+N($L65)) -> 699 | O65: https://ozon.onelink.me/SNMZ/3lrtowoe | P65: https://aminotriggerfish.mobz.market/j3s | S65: https://t.me/Spinning_Kubani_Adygei/47228/312122 | U65: 1892 | V65: =IF(N($U65)=0,"",$M65/$U65) -> 0.36945032 | W65: 7 | X65: 4 | Y65: =IF(N($W65)=0,"",$M65/$W65) -> 99.857143 | Z65: 2 | AA65: 0 | AB65: 0 | AD65: 0 | AF65: =IF(OR(N($AD65)=0,$AE65=""),"",ROUND($AD65*$AE65,0)) | AG65: =IF(N($AD65)=0,"",ROUND($M65/$AD65,0)) | AH65: =IF(N($AA65)=0,"",ROUND($M65/$AA65,0)) | AI65: аминотригер
A66: Рыбалка | Рыбанутые | Охота | Туризм | C66: =IFERROR(VLOOKUP($A66,'Мои блогеры'!$A:$N,5,0),"") -> 71500 | D66: =IFERROR(VLOOKUP($A66,'Мои блогеры'!$A:$N,2,0),"") -> MAX | E66: Ozon | G66: t27 | H66: 46260 | I66: Вышло | J66: =IFERROR(VLOOKUP($A66,'Мои блогеры'!$A:$N,8,0),"") -> 11328 | M66: =IF(N($J66)+N($K66)+N($L66)=0,"",N($J66)+N($K66)+N($L66)) -> 11328 | O66: https://ozon.onelink.me/SNMZ/a0jumhdp | P66: https://aminotriggerfish.mobz.market/ciiuh | S66: https://max.ru/rybanutyye/AaA8rBz7BJg | U66: 11839 | V66: =IF(N($U66)=0,"",$M66/$U66) -> 0.95683757 | W66: 642 | X66: 563 | Y66: =IF(N($W66)=0,"",$M66/$W66) -> 17.64486 | Z66: 277 | AA66: 50 | AB66: 85000 | AD66: 50 | AE66: =AB66/AD66 -> 1700 | AF66: 85000 | AG66: =IF(N($AD66)=0,"",ROUND($M66/$AD66,0)) -> 227 | AH66: =IF(N($AA66)=0,"",ROUND($M66/$AA66,0)) -> 227 | AI66: аминотригер
A67: Рыбацкий канал | Рыбалка | B67: =IF($A67="","",IFERROR(HYPERLINK(VLOOKUP($A67,'Мои блогеры'!$A:$N,14,0),"🔗 открыть"),"")) -> 🔗 открыть | C67: =IFERROR(VLOOKUP($A67,'Мои блогеры'!$A:$N,5,0),"") -> 19200 | D67: =IFERROR(VLOOKUP($A67,'Мои блогеры'!$A:$N,2,0),"") -> MAX | E67: Ozon | G67: t27 | H67: 46260 | I67: Вышло | J67: =IFERROR(VLOOKUP($A67,'Мои блогеры'!$A:$N,8,0),"") -> 4195 | M67: =IF(N($J67)+N($K67)+N($L67)=0,"",N($J67)+N($K67)+N($L67)) -> 4195 | O67: https://ozon.onelink.me/SNMZ/wzijwzue | P67: https://aminotriggerfish.mobz.market/w5kp | S67: https://max.ru/ribalka_fishing24/AaA8rCnOepg | U67: 4830 | V67: =IF(N($U67)=0,"",$M67/$U67) -> 0.86853002 | W67: 241 | X67: 207 | Y67: =IF(N($W67)=0,"",$M67/$W67) -> 17.406639 | Z67: 81 | AA67: 20 | AB67: 40500 | AD67: 20 | AE67: =AB67/AD67 -> 2025 | AF67: =AB67 -> 40500 | AG67: =IF(N($AD67)=0,"",ROUND($M67/$AD67,0)) -> 210 | AH67: =IF(N($AA67)=0,"",ROUND($M67/$AA67,0)) -> 210 | AI67: аминотригер
A68: Рыбалка | B68: =IF($A68="","",IFERROR(HYPERLINK(VLOOKUP($A68,'Мои блогеры'!$A:$N,14,0),"🔗 открыть"),"")) -> 🔗 открыть | C68: =IFERROR(VLOOKUP($A68,'Мои блогеры'!$A:$N,5,0),"") -> 25900 | D68: =IFERROR(VLOOKUP($A68,'Мои блогеры'!$A:$N,2,0),"") -> MAX | E68: Ozon | G68: t27 | H68: 46260 | I68: Вышло | J68: 2237 | M68: =IF(N($J68)+N($K68)+N($L68)=0,"",N($J68)+N($K68)+N($L68)) -> 2237 | O68: https://ozon.onelink.me/SNMZ/35xi838x | P68: https://aminotriggerfish.mobz.market/6dyu | S68: https://max.ru/join/tv-zOLgP61IYsvZA5CGo-pJe1cAmeOwctc3pafS22ZEhttps://max.ru/ylov_ribaka | U68: 1735 | V68: =IF(N($U68)=0,"",$M68/$U68) -> 1.2893372 | W68: 83 | X68: 58 | Y68: =IF(N($W68)=0,"",$M68/$W68) -> 26.951807 | Z68: 60 | AA68: 2 | AB68: 3400 | AD68: 2 | AE68: =AB68/AD68 -> 1700 | AF68: 3400 | AG68: =IF(N($AD68)=0,"",ROUND($M68/$AD68,0)) -> 1119 | AH68: =IF(N($AA68)=0,"",ROUND($M68/$AA68,0)) -> 1119 | AI68: аминотригер
A69: Русская Рыбалка 4. Фарм. Троф. Мальцевидзе | B69: =IF($A69="","",IFERROR(HYPERLINK(VLOOKUP($A69,'Мои блогеры'!$A:$N,14,0),"🔗 открыть"),"")) -> 🔗 открыть | C69: =IFERROR(VLOOKUP($A69,'Мои блогеры'!$A:$N,5,0),"") -> 4000 | D69: =IFERROR(VLOOKUP($A69,'Мои блогеры'!$A:$N,2,0),"") -> MAX | E69: Ozon | G69: t27 | H69: 46260 | I69: Вышло | J69: 699 | M69: 699 | O69: https://ozon.onelink.me/SNMZ/373m7kvy | P69: https://aminotriggerfish.mobz.market/1kr | S69: https://max.ru/pp4farmtrof/AaA8PNzgPpg | U69: 445 | V69: =IF(N($U69)=0,"",$M69/$U69) -> 1.5707865 | W69: 14 | X69: 9 | Y69: =IF(N($W69)=0,"",$M69/$W69) -> 49.928571 | Z69: 2 | AA69: 1 | AB69: 1700 | AD69: 1 | AE69: =AB69/AD69 -> 1700 | AF69: 1700 | AG69: =IF(N($AD69)=0,"",ROUND($M69/$AD69,0)) -> 699 | AH69: =IF(N($AA69)=0,"",ROUND($M69/$AA69,0)) -> 699 | AI69: аминотригер
A70: РЫБАЛКА | B70: =IF($A70="","",IFERROR(HYPERLINK(VLOOKUP($A70,'Мои блогеры'!$A:$N,14,0),"🔗 открыть"),"")) -> 🔗 открыть | C70: =IFERROR(VLOOKUP($A70,'Мои блогеры'!$A:$N,5,0),"") -> 25200 | D70: =IFERROR(VLOOKUP($A70,'Мои блогеры'!$A:$N,2,0),"") -> MAX | E70: Ozon | G70: t27 | H70: 46260 | I70: Вышло | J70: =IFERROR(VLOOKUP($A70,'Мои блогеры'!$A:$N,8,0),"") -> 6293 | M70: =IF(N($J70)+N($K70)+N($L70)=0,"",N($J70)+N($K70)+N($L70)) -> 6293 | O70: https://ozon.onelink.me/SNMZ/ukn1iac9 | P70: https://aminotriggerfish.mobz.market/xej | S70: https://max.ru/ylov_ribaka/AaA-YGB_KDg | U70: 4973 | V70: =IF(N($U70)=0,"",$M70/$U70) -> 1.2654333 | W70: 256 | X70: 219 | Y70: =IF(N($W70)=0,"",$M70/$W70) -> 24.582031 | Z70: 113 | AA70: 19 | AB70: 32300 | AD70: 19 | AE70: =AB70/AD70 -> 1700 | AF70: 32300 | AG70: =IF(N($AD70)=0,"",ROUND($M70/$AD70,0)) -> 331 | AH70: =IF(N($AA70)=0,"",ROUND($M70/$AA70,0)) -> 331 | AI70: аминотригер
A71: bibliya_sada | C71: =IFERROR(VLOOKUP($A71,'Мои блогеры'!$A:$N,5,0),"") -> 66200 | D71: =IFERROR(VLOOKUP($A71,'Мои блогеры'!$A:$N,2,0),"") -> MAX | E71: WB | H71: 46262 | I71: Вышло | J71: =IFERROR(VLOOKUP($A71,'Мои блогеры'!$A:$N,8,0),"") -> 10560 | M71: =IF(N($J71)+N($K71)+N($L71)=0,"",N($J71)+N($K71)+N($L71)) -> 10560 | O71: https://wildberries.ru/catalog/0/search.aspx?search=WW979669 | P71: https://aminotriggerfish.mobz.market/86db1v | R71: WW979669 | S71: https://max.ru/bibliya_sada/AaBIOSqPbnk | U71: 7954 | V71: =IF(N($U71)=0,"",$M71/$U71) -> 1.3276339 | W71: 193 | X71: 166 | Y71: =IF(N($W71)=0,"",$M71/$W71) -> 54.715026 | Z71: 14 | AA71: 1 | AB71: 3729 | AD71: 1 | AE71: =AB71/AD71 -> 3729 | AF71: =AB71 -> 3729 | AG71: =IF(N($AD71)=0,"",ROUND($M71/$AD71,0)) -> 10560 | AI71: аппликатор
A72: супер отпуск | C72: =IFERROR(VLOOKUP($A72,'Мои блогеры'!$A:$N,5,0),"") -> 50200 | D72: =IFERROR(VLOOKUP($A72,'Мои блогеры'!$A:$N,2,0),"") -> Telegram | E72: WB | H72: 46262 | I72: Вышло | J72: =IFERROR(VLOOKUP($A72,'Мои блогеры'!$A:$N,8,0),"") -> 11889 | M72: =IF(N($J72)+N($K72)+N($L72)=0,"",N($J72)+N($K72)+N($L72)) -> 11889 | O72: https://wildberries.ru/catalog/0/search.aspx?search=WW979700 | P72: https://aminotriggerfish.mobz.market/w0rbq | R72: WW979700 | S72: https://t.me/superotpusknadache/17431 | U72: 3116 | V72: =IF(N($U72)=0,"",$M72/$U72) -> 3.8154685 | W72: 81 | X72: 69 | Y72: =IF(N($W72)=0,"",$M72/$W72) -> 146.77778 | Z72: 14 | AA72: 2 | AB72: =3729+3729 -> 7458 | AD72: 2 | AE72: =AB72/AD72 -> 3729 | AF72: =AB72 -> 7458 | AG72: =IF(N($AD72)=0,"",ROUND($M72/$AD72,0)) -> 5945 | AI72: аппликатор
A73: Жизнь между городом и дачей | C73: =IFERROR(VLOOKUP($A73,'Мои блогеры'!$A:$N,5,0),"") -> 25400 | D73: =IFERROR(VLOOKUP($A73,'Мои блогеры'!$A:$N,2,0),"") -> MAX | E73: WB | H73: 46264 | I73: Вышло | J73: =IFERROR(VLOOKUP($A73,'Мои блогеры'!$A:$N,8,0),"") -> 11189 | M73: =IF(N($J73)+N($K73)+N($L73)=0,"",N($J73)+N($K73)+N($L73)) -> 11189 | O73: https://wildberries.ru/catalog/0/search.aspx?search=WW979686 | P73: https://aminotriggerfish.mobz.market/4l3ji | R73: WW979686 | S73: https://max.ru/ch_60a62c32e184214713fa6055/AaBNSNJPawo | U73: 7113 | V73: =IF(N($U73)=0,"",$M73/$U73) -> 1.5730353 | W73: 83 | X73: 75 | Y73: =IF(N($W73)=0,"",$M73/$W73) -> 134.80723 | Z73: 12 | AA73: 0 | AG73: =IF(N($AD73)=0,"",ROUND($M73/$AD73,0)) | AI73: аппликатор
A74: На даче пригодиться | C74: =IFERROR(VLOOKUP($A74,'Мои блогеры'!$A:$N,5,0),"") -> 13300 | D74: =IFERROR(VLOOKUP($A74,'Мои блогеры'!$A:$N,2,0),"") -> MAX | E74: WB | H74: 46263 | I74: Вышло | J74: =IFERROR(VLOOKUP($A74,'Мои блогеры'!$A:$N,8,0),"") -> 3217 | M74: =IF(N($J74)+N($K74)+N($L74)=0,"",N($J74)+N($K74)+N($L74)) -> 3217 | O74: https://wildberries.ru/catalog/0/search.aspx?search=WW979690 | P74: https://aminotriggerfish.mobz.market/okk3 | R74: WW979690 | S74: https://max.ru/Nadacheprigoditca/AaBMV_FWX50 | U74: 2212 | V74: =IF(N($U74)=0,"",$M74/$U74) -> 1.45434 | W74: 74 | X74: 65 | Y74: =IF(N($W74)=0,"",$M74/$W74) -> 43.472973 | Z74: 8 | AA74: 0 | AG74: =IF(N($AD74)=0,"",ROUND($M74/$AD74,0)) | AI74: аппликатор
A75: деревня сосотояние души | C75: =IFERROR(VLOOKUP($A75,'Мои блогеры'!$A:$N,5,0),"") -> 3300 | D75: =IFERROR(VLOOKUP($A75,'Мои блогеры'!$A:$N,2,0),"") -> MAX | E75: WB | H75: 46263 | I75: Вышло | J75: =IFERROR(VLOOKUP($A75,'Мои блогеры'!$A:$N,8,0),"") -> 3497 | M75: =IF(N($J75)+N($K75)+N($L75)=0,"",N($J75)+N($K75)+N($L75)) -> 3497 | O75: https://wildberries.ru/catalog/0/search.aspx?search=WW979704 | P75: https://aminotriggerfish.mobz.market/7q1 | R75: WW979704 | S75: https://max.ru/ch_60a62c32e184214713fa6055/AaBNSNJPawo | U75: 1487 | V75: =IF(N($U75)=0,"",$M75/$U75) -> 2.3517149 | W75: 22 | X75: 19 | Y75: =IF(N($W75)=0,"",$M75/$W75) -> 158.95455 | Z75: 24 | AA75: 0 | AG75: =IF(N($AD75)=0,"",ROUND($M75/$AD75,0)) | AI75: аппликатор
A76: Итого: 24–29 августа | I76: =COUNTIF(I56:I75,"Вышло")&" / "&COUNTA(A56:A75) -> 20 / 20 | J76: =SUM(J56:J75) -> 238803 | K76: =SUM(K56:K75) -> 12510 | L76: =SUM(L56:L75) -> 2140 | M76: =SUM(M56:M75) -> 253453 | N76: =SUM(N56:N75) -> 0 | O76: =SUM(O56:O75) -> 0 | P76: =SUM(P56:P75) -> 0 | Q76: =SUM(Q56:Q75) -> 0 | ... S76: =SUM(S56:S75) -> 0 | U76: =SUM(U56:U75) -> 520065 | V76: =SUM(V56:V75) -> 34.275092 | W76: =SUM(W56:W75) -> 2494 | X76: =SUM(X56:X75) -> 1454 | Y76: =SUM(Y56:Y75) -> 10237.769 | Z76: =SUM(Z56:Z75) -> 820 | AA76: =SUM(AA56:AA75) -> 150 | AB76: =SUM(AB56:AB75) -> 277407 | ... AF76: =SUM(AF56:AF75) -> 277407 | AG76: =IF(N(AD76)=0,"—",ROUND(M76/AD76,0)) -> 1690 | AH76: =IF(N(AA76)=0,"—",ROUND(M76/AA76,0)) -> 1690
A77: НЕДЕЛЯ — 30–31 августа
A78: https://vk.com/feallkin_dom | C78: =IFERROR(VLOOKUP($A78,'Мои блогеры'!$A:$N,5,0),"") -> 63600 | D78: =IFERROR(VLOOKUP($A78,'Мои блогеры'!$A:$N,2,0),"") -> VK | E78: WB | F78: 19 | H78: 46264 | I78: Вышло | J78: =IFERROR(VLOOKUP($A78,'Мои блогеры'!$A:$N,8,0),"") -> 16000 | K78: 1760 | L78: 3598 | M78: =IF(N($J78)+N($K78)+N($L78)=0,"",N($J78)+N($K78)+N($L78)) -> 21358 | O78: https://wildberries.ru/catalog/0/search.aspx?search=WW996788 | R78: WW996788 | S78: https://vk.ru/story-211208898_456241852 | T78: Нет | U78: 28403 | V78: =IF(N($U78)=0,"",$M78/$U78) -> 0.75196282 | W78: 122 | Y78: =IF(N($W78)=0,"",$M78/$W78) -> 175.06557 | Z78: 52 | AI78: аппликатор | AJ78: только вышла
A79: https://max.ru/feallkin_dom | C79: =IFERROR(VLOOKUP($A79,'Мои блогеры'!$A:$N,5,0),"") -> 3890 | D79: =IFERROR(VLOOKUP($A79,'Мои блогеры'!$A:$N,2,0),"") -> MAX | E79: WB | F79: 19 | H79: 46264 | I79: Вышло | J79: =IFERROR(VLOOKUP($A79,'Мои блогеры'!$A:$N,8,0),"") -> 6000 | M79: =IF(N($J79)+N($K79)+N($L79)=0,"",N($J79)+N($K79)+N($L79)) -> 6000 | O79: https://wildberries.ru/catalog/0/search.aspx?search=WW996801 | R79: WW996801 | S79: https://max.ru/feallkin_dom/AaBTOlA3JnI | T79: Нет | U79: 3800 | V79: =IF(N($U79)=0,"",$M79/$U79) -> 1.5789474 | W79: 36 | Y79: =IF(N($W79)=0,"",$M79/$W79) -> 166.66667 | Z79: 12 | AI79: аппликатор
A80: @pug_leonid | C80: =IFERROR(VLOOKUP($A80,'Мои блогеры'!$A:$N,5,0),"") -> 2000000 | D80: =IFERROR(VLOOKUP($A80,'Мои блогеры'!$A:$N,2,0),"") -> TikTok | E80: Ozon | H80: 46265 | I80: Вышло | J80: 0 | M80: 0 | O80: https://ozon.onelink.me/SNMZ/7kc6t0p4 | S80: https://t.me/Leonid_music/2828 | U80: 4500 | V80: =IF(N($U80)=0,"",$M80/$U80) -> 0 | W80: 8 | Y80: =IF(N($W80)=0,"",$M80/$W80) -> 0 | Z80: 1 | AA80: 1 | AB80: 1900 | AD80: 1 | AF80: 1900 | AI80: аминотригер | AJ80: доп
A81: Leonid_music | C81: =IFERROR(VLOOKUP($A81,'Мои блогеры'!$A:$N,5,0),"") -> 19000 | D81: =IFERROR(VLOOKUP($A81,'Мои блогеры'!$A:$N,2,0),"") -> Telegram | E81: Ozon | H81: 46265 | I81: Вышло | J81: 0 | M81: 0 | O81: - | S81: https://vt.tiktok.com/ZSV3VRjhs/ | U81: 37100 | V81: =IF(N($U81)=0,"",$M81/$U81) -> 0 | Y81: =IF(N($W81)=0,"",$M81/$W81) | AI81: аминотригер | AJ81: доп
V82: =IF(N($U82)=0,"",$M82/$U82) | Y82: =IF(N($W82)=0,"",$M82/$W82)
B83: =IF($A83="","",IFERROR(HYPERLINK(VLOOKUP($A83,'Мои блогеры'!$A:$N,14,0),"🔗 открыть"),"")) | C83: =IFERROR(VLOOKUP($A83,'Мои блогеры'!$A:$N,5,0),"") | D83: =IFERROR(VLOOKUP($A83,'Мои блогеры'!$A:$N,2,0),"") | J83: =IFERROR(VLOOKUP($A83,'Мои блогеры'!$A:$N,8,0),"") | M83: =IF(N($J83)+N($K83)+N($L83)=0,"",N($J83)+N($K83)+N($L83)) | Q83: =IFERROR(VLOOKUP($A83,'Мои блогеры'!$A:$N,10,0)&"-TRG","") | V83: =IF(N($U83)=0,"",$M83/$U83) | Y83: =IF(N($W83)=0,"",$M83/$W83) | AD83: =IF(OR(N($AA83)=0,$AC83=""),"",ROUND($AA83*$AC83,0)) | AF83: =IF(OR(N($AD83)=0,$AE83=""),"",ROUND($AD83*$AE83,0)) | AG83: =IF(N($AD83)=0,"",ROUND($M83/$AD83,0)) | AH83: =IF(N($AA83)=0,"",ROUND($M83/$AA83,0))
B84: =IF($A84="","",IFERROR(HYPERLINK(VLOOKUP($A84,'Мои блогеры'!$A:$N,14,0),"🔗 открыть"),"")) | C84: =IFERROR(VLOOKUP($A84,'Мои блогеры'!$A:$N,5,0),"") | D84: =IFERROR(VLOOKUP($A84,'Мои блогеры'!$A:$N,2,0),"") | J84: =IFERROR(VLOOKUP($A84,'Мои блогеры'!$A:$N,8,0),"") | M84: =IF(N($J84)+N($K84)+N($L84)=0,"",N($J84)+N($K84)+N($L84)) | Q84: =IFERROR(VLOOKUP($A84,'Мои блогеры'!$A:$N,10,0)&"-TRG","") | V84: =IF(N($U84)=0,"",$M84/$U84) | Y84: =IF(N($W84)=0,"",$M84/$W84) | AD84: =IF(OR(N($AA84)=0,$AC84=""),"",ROUND($AA84*$AC84,0)) | AF84: =IF(OR(N($AD84)=0,$AE84=""),"",ROUND($AD84*$AE84,0)) | AG84: =IF(N($AD84)=0,"",ROUND($M84/$AD84,0)) | AH84: =IF(N($AA84)=0,"",ROUND($M84/$AA84,0))
A85: Итого: 29–31 июля | I85: =COUNTIF(I78:I84,"Вышло")&" / "&COUNTA(A79:A84) -> 4 / 3 | J85: =SUM(J79:J84) -> 6000 | L85: =SUM(L79:L84) -> 0 | M85: =SUM(M78:M84) -> 27358 | U85: =SUM(U78:U84) -> 73803 | W85: =SUM(W78:W84) -> 166 | X85: =SUM(X78:X84) -> 0 | Z85: =SUM(Z78:Z84) -> 65 | AA85: =SUM(AA78:AA84) -> 1 | AB85: =SUM(AB78:AB84) -> 1900 | AD85: =SUM(AD78:AD84) -> 1 | AF85: =SUM(AF78:AF84) -> 1900 | AG85: =SUM(AG78:AG84) -> 0 | AH85: =SUM(AH78:AH84) -> 0
A86: ИТОГО ЗА МЕСЯЦ | J86: =J15+J32+J54+J76+J85 -> 503156 | L86: =L15+L32+L54+L76+L85 -> 4242 | M86: =M15+M32+M54+M76+M85 -> 556026 | U86: =U15+U32+U54+U76+U85 -> 1040355 | V86: =IF(N($U86)=0,"",$M86/$U86) -> 0.53445795 | W86: =W15+W32+W54+W76+W85 -> 5236 | X86: =X15+X32+X54+X76+X85 -> 1468 | Y86: =IF(N($W86)=0,"",$M86/$W86) -> 106.1929 | Z86: =Z15+Z32+Z54+Z76+Z85 -> 1248 | AA86: =AA15+AA32+AA54+AA76+AA85 -> 208 | AB86: =AB15+AB32+AB54+AB76+AB85 -> 312763 | AD86: =AD15+AD32+AD54+AD76+AD85 -> 177 | AF86: =AF15+AF32+AF54+AF76+AF85 -> 300963

Sheet Сентябрь
A1: не
A2: Выбери блогера в колонке A — ссылка, подписчики, площадка, промокод, стоимость подтянутся. «🔗 открыть» ведёт на канал.
A3: Выкупы = Заказы × %выкупа. Выручка = Средний чек × Выкупы. CAC/CPO по факту.
A5: Блогер | B5: Ссылка на канал | C5: Подписчики | D5: Площадка | E5: Канал продаж | F5: № договора | G5: Сценарий рекламы | H5: Дата выхода | I5: Статус | J5: Стоимость размещения | K5: Налог | L5: Себестоимость продукции | M5: Итого к оплате | N5: Код маркировки (ERID) | O5: Ссылка с UTM | P5: Ссылка Мобзио | Q5: Промокод | R5: Подменный артикул | S5: Ссылка на размещение | T5: Право использования | U5: Охват факт | V5: CPV, ₽ | W5: Клики WB/ сайт | X5: Клики мобзио | Y5: Цена за клик, ₽ | Z5: Корзины | AA5: Заказы | AB5: Сумма заказов, ₽ | AC5: % выкупа | AD5: Выкупы | AE5: Средний чек, ₽ | AF5: Выручка от выкупов, ₽ | AG5: Стоимость выкупа, ₽ | AH5: CPO, ₽ | AI5: Продукт | AJ5: РЕГ | AK5: CPA | AL5: Комментарий
A6: НЕДЕЛЯ —1–7 сентября
A7: https://www.tiktok.com/@batya_ilin | B7: =IF($A7="","",IFERROR(HYPERLINK(VLOOKUP($A7,'Мои блогеры'!$A:$N,14,0),"🔗 открыть"),"")) -> 🔗 открыть | C7: =IFERROR(VLOOKUP($A7,'Мои блогеры'!$A:$N,5,0),"") -> 84300 | D7: =IFERROR(VLOOKUP($A7,'Мои блогеры'!$A:$N,2,0),"") -> TikTok | E7: Ozon | F7: 22 | G7: v1 | H7: 46266 | I7: Вышло | J7: =IFERROR(VLOOKUP($A7,'Мои блогеры'!$A:$N,8,0),"") -> 30000 | K7: 1500 | M7: =IF(N($J7)+N($K7)+N($L7)=0,"",N($J7)+N($K7)+N($L7)) -> 31500 | N7: 2W5zFJ8vuds | O7: - | Q7: BATYA10 | R7: - | S7: https://vt.tiktok.com/ZSVKS2TKF/ | T7: Да | U7: 585100 | V7: =IF(N($U7)=0,"",$M7/$U7) -> 0.053836951 | W7: - | Y7: =IF(N($W7)=0,"",$M7/$W7) | AA7: 2 | AB7: 2160 | AD7: 2 | AE7: =AB7/AD7 -> 1080 | AF7: =IF(OR(N($AD7)=0,$AE7=""),"",ROUND($AD7*$AE7,0)) -> 2160 | AG7: =IF(N($AD7)=0,"",ROUND($M7/$AD7,0)) -> 15750 | AH7: =IF(N($AA7)=0,"",ROUND($M7/$AA7,0)) -> 15750 | AI7: Aminotrigger-Fish
A8: https://vk.ru/batya_ilin | B8: =IF($A8="","",IFERROR(HYPERLINK(VLOOKUP($A8,'Мои блогеры'!$A:$N,14,0),"🔗 открыть"),"")) -> 🔗 открыть | C8: =IFERROR(VLOOKUP($A8,'Мои блогеры'!$A:$N,5,0),"") -> 60500 | D8: =IFERROR(VLOOKUP($A8,'Мои блогеры'!$A:$N,2,0),"") -> VK | E8: Ozon | F8: 22 | G8: v1 | H8: 46270 | I8: Вышло | J8: =IFERROR(VLOOKUP($A8,'Мои блогеры'!$A:$N,8,0),"") -> 20000 | K8: 1500 | M8: =IF(N($J8)+N($K8)+N($L8)=0,"",N($J8)+N($K8)+N($L8)) -> 21500 | N8: 2W5zFJd6fzR | O8: https://ozon.onelink.me/SNMZ/ik1u4ho0 | R8: - | S8: https://vk.ru/clip-235277864_456239553?c=1 | T8: Да | U8: 148800 | V8: =IF(N($U8)=0,"",$M8/$U8) -> 0.14448925 | W8: 318 | X8: 201 | Y8: =IF(N($W8)=0,"",$M8/$W8) -> 67.610063 | Z8: 101 | AA8: 6 | AB8: 11800 | AD8: 6 | AE8: =AB8/AD8 -> 1966.6667 | AF8: =IF(OR(N($AD8)=0,$AE8=""),"",ROUND($AD8*$AE8,0)) -> 11800 | AG8: =IF(N($AD8)=0,"",ROUND($M8/$AD8,0)) -> 3583 | AH8: =IF(N($AA8)=0,"",ROUND($M8/$AA8,0)) -> 3583 | AI8: Aminotrigger-Fish
A9: https://max.ru/batya_ilin | B9: =IF($A9="","",IFERROR(HYPERLINK(VLOOKUP($A9,'Мои блогеры'!$A:$N,14,0),"🔗 открыть"),"")) -> 🔗 открыть | C9: =IFERROR(VLOOKUP($A9,'Мои блогеры'!$A:$N,5,0),"") -> 2600 | D9: =IFERROR(VLOOKUP($A9,'Мои блогеры'!$A:$N,2,0),"") -> MAX | E9: Ozon | F9: 22 | G9: v1 | H9: 46266 | I9: Вышло | J9: =IFERROR(VLOOKUP($A9,'Мои блогеры'!$A:$N,8,0),"") -> 0 | M9: 0 | N9: 2W5zFJkWcQ9 | O9: https://ozon.onelink.me/SNMZ/5enzywu9 | R9: - | S9: https://max.ru/batya_ilin/AaBdXlvIQR8 | T9: Да | U9: 1823 | V9: =IF(N($U9)=0,"",$M9/$U9) -> 0 | W9: 34 | X9: 34 | Y9: =IF(N($W9)=0,"",$M9/$W9) -> 0 | Z9: 8 | AA9: 2 | AB9: 3800 | AD9: 2 | AE9: =AB9/AD9 -> 1900 | AF9: =IF(OR(N($AD9)=0,$AE9=""),"",ROUND($AD9*$AE9,0)) -> 3800 | AG9: =IF(N($AD9)=0,"",ROUND($M9/$AD9,0)) -> 0 | AH9: =IF(N($AA9)=0,"",ROUND($M9/$AA9,0)) -> 0 | AI9: Aminotrigger-Fish
A10: https://vk.ru/fishinglifetv | B10: =IF($A10="","",IFERROR(HYPERLINK(VLOOKUP($A10,'Мои блогеры'!$A:$N,14,0),"🔗 открыть"),"")) -> 🔗 открыть | C10: =IFERROR(VLOOKUP($A10,'Мои блогеры'!$A:$N,5,0),"") -> 7800 | D10: =IFERROR(VLOOKUP($A10,'Мои блогеры'!$A:$N,2,0),"") -> VK | E10: Ozon | G10: t30 | H10: 46268 | I10: Вышло | J10: доп размещение | M10: 0 | O10: https://ozon.onelink.me/SNMZ/fmla4pxl | R10: - | S10: https://vk.ru/wall-226894765_699 | T10: Да | U10: 1002 | V10: =IF(N($U10)=0,"",$M10/$U10) -> 0 | W10: 51 | X10: - | Y10: =IF(N($W10)=0,"",$M10/$W10) -> 0 | Z10: 21 | AA10: 9 | AB10: =1900+13300+1900 -> 17100 | AD10: 9 | AE10: =AB10/AD10 -> 1900 | AF10: =IF(OR(N($AD10)=0,$AE10=""),"",ROUND($AD10*$AE10,0)) -> 17100 | AG10: =IF(N($AD10)=0,"",ROUND($M10/$AD10,0)) -> 0 | AH10: =IF(N($AA10)=0,"",ROUND($M10/$AA10,0)) -> 0 | AI10: Aminotrigger-Fish
A11: Итого: 1–7 сентябрь | I11: =COUNTIF(I7:I10,"Вышло")&" / "&COUNTA(A7:A10) -> 4 / 4 | J11: =SUM(J7:J10) -> 50000 | K11: =SUM(K7:K10) -> 3000 | L11: =SUM(L7:L10) -> 0 | M11: =SUM(M7:M10) -> 53000 | N11: =SUM(N7:N10) -> 0 | O11: =SUM(O7:O10) -> 0 | P11: =SUM(P7:P10) -> 0 | Q11: =SUM(Q7:Q10) -> 0 | ... U11: =SUM(U7:U10) -> 736725 | V11: =IF(N($U11)=0,"",$M11/$U11) -> 0.071940005 | W11: =SUM(W7:W10) -> 403 | X11: =SUM(X7:X10) -> 235 | Y11: =IF(N($W11)=0,"",$M11/$W11) -> 131.51365 | Z11: =SUM(Z7:Z10) -> 130 | AA11: =SUM(AA7:AA10) -> 19 | AB11: =SUM(AB7:AB10) -> 34860 | AC11: =SUM(AC7:AC10) -> 0 | AD11: =SUM(AD7:AD10) -> 19 | AE11: =SUM(AE7:AE10) -> 6846.6667 | AF11: =SUM(AF7:AF10) -> 34860 | AG11: =AF11/AD11 -> 1834.7368 | AH11: =IF(N($AA11)=0,"",ROUND($M11/$AA11,0)) -> 2789
A12: НЕДЕЛЯ —8–14 сентября
A13: ОРЗ ТВ - Охотники и Рыболовы ЗАПОЛЯРЬЯ | B13: =IF($A13="","",IFERROR(HYPERLINK(VLOOKUP($A13,'Мои блогеры'!$A:$N,14,0),"🔗 открыть"),"")) -> 🔗 открыть | C13: =IFERROR(VLOOKUP($A13,'Мои блогеры'!$A:$N,5,0),"") -> 171000 | D13: =IFERROR(VLOOKUP($A13,'Мои блогеры'!$A:$N,2,0),"") -> YouTube | E13: Ozon | F13: 10 | G13: своя подача общая | H13: 46273 | I13: Вышло | J13: =IFERROR(VLOOKUP($A13,'Мои блогеры'!$A:$N,8,0),"") -> 35000 | K13: 1000 | L13: 750 | M13: =IF(N($J13)+N($K13)+N($L13)=0,"",N($J13)+N($K13)+N($L13)) -> 36750 | O13: https://ozon.ru/product/aminotrigger-fish-aromatizator-dlya-rybalki-250-ml-5340361400?hs=1&utm_campaign=vendor_org_4202727_youohotnikinao&utm_content=video&utm_medium=blog&utm_source=youtube&utm_term=youohotnikinao | P13: https://aminotriggerfish.mobz.market/nsd | S13: https://www.youtube.com/watch?v=nSfzw0ZV1RM | T13: Нет | U13: 17000 | V13: =IF(N($U13)=0,"",$M13/$U13) -> 2.1617647 | W13: 27 | X13: 27 | Y13: =IF(N($W13)=0,"",$M13/$W13) -> 1361.1111 | Z13: 12 | AA13: 6 | AB13: 11400 | AD13: 6 | AE13: =AB13/AD13 -> 1900 | AF13: =IF(OR(N($AD13)=0,$AE13=""),"",ROUND($AD13*$AE13,0)) -> 11400 | AG13: =IF(N($AD13)=0,"",ROUND($M13/$AD13,0)) -> 6125 | AH13: =IF(N($AA13)=0,"",ROUND($M13/$AA13,0)) -> 6125 | AI13: Aminotrigger-Fish | AL13: полная интеграция дольше набирает охват
A14: https://vk.ru/ohotnikinao | C14: =IFERROR(VLOOKUP($A14,'Мои блогеры'!$A:$N,5,0),"") -> 7500 | D14: =IFERROR(VLOOKUP($A14,'Мои блогеры'!$A:$N,2,0),"") -> VK | E14: Ozon | F14: 10 | G14: своя подача общая | H14: 46273 | I14: Вышло | J14: =IFERROR(VLOOKUP($A14,'Мои блогеры'!$A:$N,8,0),"") -> 0 | M14: 0 | O14: https://ozon.ru/product/aminotrigger-fish-aromatizator-dlya-rybalki-250-ml-5340361400?hs=1&utm_campaign=vendor_org_4202727_ohotnikinao&utm_content=video&utm_medium=blog&utm_source=vk&utm_term=ohotnikinao | P14: https://aminotriggerfish.mobz.market/89g?detail_erid=5340361400 | S14: https://vk.ru/ohotnikinao?z=video-7653648_456239864 | T14: Нет | U14: 5200 | V14: =IF(N($U14)=0,"",$M14/$U14) -> 0 | W14: 11 | X14: 11 | Y14: =IF(N($W14)=0,"",$M14/$W14) -> 0 | Z14: 1 | AA14: 1 | AB14: 2100 | AD14: 1 | AE14: =AB14/AD14 -> 2100 | AF14: =IF(OR(N($AD14)=0,$AE14=""),"",ROUND($AD14*$AE14,0)) -> 2100 | AG14: =IF(N($AD14)=0,"",ROUND($M14/$AD14,0)) -> 0 | AH14: =IF(N($AA14)=0,"",ROUND($M14/$AA14,0)) -> 0 | AI14: Aminotrigger-Fish
A15: https://vk.ru/syilers | B15: =IF($A15="","",IFERROR(HYPERLINK(VLOOKUP($A15,'Мои блогеры'!$A:$N,14,0),"🔗 открыть"),"")) -> 🔗 открыть | C15: 72000 | D15: =IFERROR(VLOOKUP($A15,'Мои блогеры'!$A:$N,2,0),"") -> VK | E15: Ozon | F15: доп выход | G15: своя подача общая | H15: 46273 | I15: Вышло | J15: доп размещение | M15: 0 | O15: https://ozon.ru/product/aminotrigger-fish-aromatizator-dlya-rybalki-250-ml-5340361400/?hs=1&utm_campaign=vendor_org_4202727_vkrusyilers&utm_content=stories&utm_medium=video&utm_source=vk&utm_term=syilers | P15: https://aminotriggerfish.mobz.market/470li | S15: https://vk.ru/story-212140642_456241030 | T15: Нет | U15: 28930 | V15: =IF(N($U15)=0,"",$M15/$U15) -> 0 | W15: 68 | X15: 68 | Y15: =IF(N($W15)=0,"",$M15/$W15) -> 0 | Z15: 1 | AA15: 1 | AB15: 2400 | AD15: 1 | AE15: =AB15/AD15 -> 2400 | AF15: =IF(OR(N($AD15)=0,$AE15=""),"",ROUND($AD15*$AE15,0)) -> 2400 | AG15: =IF(N($AD15)=0,"",ROUND($M15/$AD15,0)) -> 0 | AH15: =IF(N($AA15)=0,"",ROUND($M15/$AA15,0)) -> 0 | AI15: Aminotrigger-Fish
A16: https://vk.ru/dimon_dloger | C16: =IFERROR(VLOOKUP($A16,'Мои блогеры'!$A:$N,5,0),"") -> 18700 | D16: =IFERROR(VLOOKUP($A16,'Мои блогеры'!$A:$N,2,0),"") -> VK | E16: Ozon | F16: консоль | G16: v4 | H16: 46276 | I16: Вышло | J16: =IFERROR(VLOOKUP($A16,'Мои блогеры'!$A:$N,8,0),"") -> 27000 | K16: 2150 | L16: 800 | M16: =IF(N($J16)+N($K16)+N($L16)=0,"",N($J16)+N($K16)+N($L16)) -> 29950 | O16: https://ozon.onelink.me/SNMZ/24nhzhe9 | S16: https://vk.ru/clip-232644511_456239777?c=1 | T16: Да | U16: 307900 | V16: =IF(N($U16)=0,"",$M16/$U16) -> 0.097271842 | W16: =545+58 -> 603 | X16: =545+58 -> 603 | Y16: =IF(N($W16)=0,"",$M16/$W16) -> 49.668325 | Z16: =25+267 -> 292 | AA16: 61 | AB16: =55700+12000+2600 -> 70300 | AD16: 61 | AE16: =AB16/AD16 -> 1152.459 | AF16: =IF(OR(N($AD16)=0,$AE16=""),"",ROUND($AD16*$AE16,0)) -> 70300 | AG16: =IF(N($AD16)=0,"",ROUND($M16/$AD16,0)) -> 491 | AH16: =IF(N($AA16)=0,"",ROUND($M16/$AA16,0)) -> 491 | AI16: Aminotrigger-Fish
A17: https://www.tiktok.com/@bloger_dimon | C17: =IFERROR(VLOOKUP($A17,'Мои блогеры'!$A:$N,5,0),"") -> 40700 | D17: =IFERROR(VLOOKUP($A17,'Мои блогеры'!$A:$N,2,0),"") -> TikTok | E17: Ozon | F17: консоль | G17: v4 | H17: 46276 | I17: Вышло | J17: =IFERROR(VLOOKUP($A17,'Мои блогеры'!$A:$N,8,0),"") -> 30000 | K17: 2150 | M17: =IF(N($J17)+N($K17)+N($L17)=0,"",N($J17)+N($K17)+N($L17)) -> 32150 | O17: промокод | Q17: Dimon5 | S17: https://vt.tiktok.com/ZSqfQ5b88 | T17: Да | U17: 111900 | V17: =IF(N($U17)=0,"",$M17/$U17) -> 0.2873101 | W17: - | X17: - | Y17: - | Z17: - | AA17: - | AB17: - | AG17: =IF(N($AD17)=0,"",ROUND($M17/$AD17,0)) | AH17: =IF(N($AA17)=0,"",ROUND($M17/$AA17,0)) | AI17: Aminotrigger-Fish
A18: https://max.ru/channel_Dimon_Bloger | B18: =IF($A18="","",IFERROR(HYPERLINK(VLOOKUP($A18,'Мои блогеры'!$A:$N,14,0),"🔗 открыть"),"")) -> 🔗 открыть | C18: =IFERROR(VLOOKUP($A18,'Мои блогеры'!$A:$N,5,0),"") -> 7220 | D18: =IFERROR(VLOOKUP($A18,'Мои блогеры'!$A:$N,2,0),"") -> MAX | E18: Ozon | F18: консоль | G18: v4 | H18: 46276 | I18: Вышло | J18: =IFERROR(VLOOKUP($A18,'Мои блогеры'!$A:$N,8,0),"") -> 3000 | M18: =IF(N($J18)+N($K18)+N($L18)=0,"",N($J18)+N($K18)+N($L18)) -> 3000 | O18: https://ozon.onelink.me/SNMZ/ly3le08a | S18: https://max.ru/channel_Dimon_Bloger | T18: Да | U18: 3789 | V18: =IF(N($U18)=0,"",$M18/$U18) -> 0.79176564 | W18: 109 | X18: 109 | Y18: =IF(N($W18)=0,"",$M18/$W18) -> 27.522936 | Z18: 25 | AA18: 4 | AB18: 5900 | AD18: 4 | AE18: =AB18/AD18 -> 1475 | AF18: =IF(OR(N($AD18)=0,$AE18=""),"",ROUND($AD18*$AE18,0)) -> 5900 | AG18: =IF(N($AD18)=0,"",ROUND($M18/$AD18,0)) -> 750 | AH18: =IF(N($AA18)=0,"",ROUND($M18/$AA18,0)) -> 750 | AI18: Aminotrigger-Fish
A19: Простая Рыбалка🐟 | C19: =IFERROR(VLOOKUP($A19,'Мои блогеры'!$A:$N,5,0),"") -> 152000 | D19: =IFERROR(VLOOKUP($A19,'Мои блогеры'!$A:$N,2,0),"") -> Telegram | E19: Ozon | F19: телега ин | G19: t30 | H19: 46275 | I19: Вышло | J19: =IFERROR(VLOOKUP($A19,'Мои блогеры'!$A:$N,8,0),"") -> 20979 | M19: =IF(N($J19)+N($K19)+N($L19)=0,"",N($J19)+N($K19)+N($L19)) -> 20979 | O19: https://ozon.onelink.me/SNMZ/qwnnkdli | P19: https://aminotriggerfish.mobz.market/t4mjo1 | S19: https://t.me/ribalka_prostaya/31130 | U19: 24302 | V19: =IF(N($U19)=0,"",$M19/$U19) -> 0.86326228 | W19: 59 | X19: 39 | Y19: =IF(N($W19)=0,"",$M19/$W19) -> 355.57627 | Z19: 12 | AA19: 2 | AB19: 3800 | AD19: 2 | AE19: =AB19/AD19 -> 1900 | AF19: =IF(OR(N($AD19)=0,$AE19=""),"",ROUND($AD19*$AE19,0)) -> 3800 | AG19: =IF(N($AD19)=0,"",ROUND($M19/$AD19,0)) -> 10490 | AH19: =IF(N($AA19)=0,"",ROUND($M19/$AA19,0)) -> 10490 | AI19: Aminotrigger-Fish
A20: rybalka_severozapad | C20: =IFERROR(VLOOKUP($A20,'Мои блогеры'!$A:$N,5,0),"") -> 5000 | D20: =IFERROR(VLOOKUP($A20,'Мои блогеры'!$A:$N,2,0),"") -> MAX | E20: Ozon | F20: телега ин | G20: t30 | H20: 46275 | I20: Вышло | J20: 1510 | M20: =IF(N($J20)+N($K20)+N($L20)=0,"",N($J20)+N($K20)+N($L20)) -> 1510 | O20: https://ozon.onelink.me/SNMZ/1qd8qzmz | P20: https://aminotriggerfish.mobz.market/mekc5 | S20: https://max.ru/rybalka_severozapad/AaCMlZAhLfQ | U20: 1814 | V20: =IF(N($U20)=0,"",$M20/$U20) -> 0.83241455 | W20: 50 | X20: 37 | Y20: =IF(N($W20)=0,"",$M20/$W20) -> 30.2 | Z20: 11 | AA20: 7 | AB20: 7600 | AD20: 7 | AE20: =AB20/AD20 -> 1085.7143 | AF20: =IF(OR(N($AD20)=0,$AE20=""),"",ROUND($AD20*$AE20,0)) -> 7600 | AG20: =IF(N($AD20)=0,"",ROUND($M20/$AD20,0)) -> 216 | AH20: =IF(N($AA20)=0,"",ROUND($M20/$AA20,0)) -> 216 | AI20: Aminotrigger-Fish
A21: Рыбалка | Рыбанутые | Охота | Туризм | C21: =IFERROR(VLOOKUP($A21,'Мои блогеры'!$A:$N,5,0),"") -> 71500 | D21: =IFERROR(VLOOKUP($A21,'Мои блогеры'!$A:$N,2,0),"") -> MAX | E21: Ozon | F21: телега ин | G21: t30 | H21: 46276 | I21: Вышло | J21: =IFERROR(VLOOKUP($A21,'Мои блогеры'!$A:$N,8,0),"") -> 11328 | M21: =IF(N($J21)+N($K21)+N($L21)=0,"",N($J21)+N($K21)+N($L21)) -> 11328 | O21: https://ozon.onelink.me/SNMZ/dii0wx5b | P21: https://aminotriggerfish.mobz.market/0jyfax | S21: https://max.ru/rybanutyye/AaCQVylgLM4 | U21: 19700 | V21: =IF(N($U21)=0,"",$M21/$U21) -> 0.57502538 | W21: 307 | X21: 298 | Y21: =IF(N($W21)=0,"",$M21/$W21) -> 36.899023 | Z21: 89 | AA21: 20 | AB21: =30400+4800 -> 35200 | AD21: 20 | AE21: =AB21/AD21 -> 1760 | AF21: =IF(OR(N($AD21)=0,$AE21=""),"",ROUND($AD21*$AE21,0)) -> 35200 | AG21: =IF(N($AD21)=0,"",ROUND($M21/$AD21,0)) -> 566 | AH21: =IF(N($AA21)=0,"",ROUND($M21/$AA21,0)) -> 566 | AI21: Aminotrigger-Fish
A22: Рыбалка Воронеж. Чат | C22: =IFERROR(VLOOKUP($A22,'Мои блогеры'!$A:$N,5,0),"") -> 1300 | D22: =IFERROR(VLOOKUP($A22,'Мои блогеры'!$A:$N,2,0),"") -> Telegram | E22: Ozon | F22: телега ин | G22: t30 | H22: 46276 | I22: Вышло | J22: =IFERROR(VLOOKUP($A22,'Мои блогеры'!$A:$N,8,0),"") -> 2097 | M22: =IF(N($J22)+N($K22)+N($L22)=0,"",N($J22)+N($K22)+N($L22)) -> 2097 | O22: https://ozon.onelink.me/SNMZ/rcu58t0c | P22: https://aminotriggerfish.mobz.market/voyt | S22: https://t.me/rybalka_vrn/156708 | U22: 2302 | V22: =IF(N($U22)=0,"",$M22/$U22) -> 0.910947 | W22: 28 | X22: 28 | Y22: =IF(N($W22)=0,"",$M22/$W22) -> 74.892857 | Z22: 1 | AA22: 0 | AB22: 0 | AD22: 0 | AG22: =IF(N($AD22)=0,"",ROUND($M22/$AD22,0)) | AH22: =IF(N($AA22)=0,"",ROUND($M22/$AA22,0)) | AI22: Aminotrigger-Fish
A23: Рыбалка | C23: =IFERROR(VLOOKUP($A23,'Мои блогеры'!$A:$N,5,0),"") -> 25900 | D23: =IFERROR(VLOOKUP($A23,'Мои блогеры'!$A:$N,2,0),"") -> MAX | E23: Ozon | F23: телега ин | G23: t30 | H23: 46278 | I23: Вышло | J23: 3496 | M23: =IF(N($J23)+N($K23)+N($L23)=0,"",N($J23)+N($K23)+N($L23)) -> 3496 | O23: https://ozon.onelink.me/SNMZ/qn6e0e54 | P23: https://aminotriggerfish.mobz.market/zkczqy | S23: https://max.ru/life_fishing/AaCZkNqHdb0 | U23: 4906 | V23: =IF(N($U23)=0,"",$M23/$U23) -> 0.71259682 | W23: 150 | X23: 143 | Y23: =IF(N($W23)=0,"",$M23/$W23) -> 23.306667 | Z23: 38 | AA23: 16 | AB23: =30500+2400 -> 32900 | AD23: 16 | AE23: =AB23/AD23 -> 2056.25 | AF23: =IF(OR(N($AD23)=0,$AE23=""),"",ROUND($AD23*$AE23,0)) -> 32900 | AG23: =IF(N($AD23)=0,"",ROUND($M23/$AD23,0)) -> 219 | AH23: =IF(N($AA23)=0,"",ROUND($M23/$AA23,0)) -> 219 | AI23: Aminotrigger-Fish
A24: https://vk.ru/fishinglifetv | B24: =IF($A24="","",IFERROR(HYPERLINK(VLOOKUP($A24,'Мои блогеры'!$A:$N,14,0),"🔗 открыть"),"")) -> 🔗 открыть | C24: =IFERROR(VLOOKUP($A24,'Мои блогеры'!$A:$N,5,0),"") -> 7800 | D24: =IFERROR(VLOOKUP($A24,'Мои блогеры'!$A:$N,2,0),"") -> VK | E24: Ozon | F24: консоль | G24: v4 | H24: 46276 | I24: Вышло | J24: 22000 | M24: =IF(N($J24)+N($K24)+N($L24)=0,"",N($J24)+N($K24)+N($L24)) -> 22000 | O24: https://ozon.onelink.me/SNMZ/fmla4pxl | R24: - | S24: https://vk.ru/wall-226894765_699?w=story-226894765_456239037%2Fowner_feed-226894765 | T24: Да | U24: 23983 | V24: =IF(N($U24)=0,"",$M24/$U24) -> 0.91731643 | W24: 263 | X24: 263 | Y24: =IF(N($W24)=0,"",$M24/$W24) -> 83.65019 | Z24: 141 | AA24: 11 | AB24: 20100 | AD24: 11 | AE24: =AB24/AD24 -> 1827.2727 | AF24: =IF(OR(N($AD24)=0,$AE24=""),"",ROUND($AD24*$AE24,0)) -> 20100 | AG24: =IF(N($AD24)=0,"",ROUND($M24/$AD24,0)) -> 2000 | AH24: =IF(N($AA24)=0,"",ROUND($M24/$AA24,0)) -> 2000 | AI24: Aminotrigger-Fish
A25: https://www.youtube.com/@slavkaivanov5497 | B25: =IF($A25="","",IFERROR(HYPERLINK(VLOOKUP($A25,'Мои блогеры'!$A:$N,14,0),"🔗 открыть"),"")) -> 🔗 открыть | C25: =IFERROR(VLOOKUP($A25,'Мои блогеры'!$A:$N,5,0),"") -> 305000 | D25: =IFERROR(VLOOKUP($A25,'Мои блогеры'!$A:$N,2,0),"") -> YouTube | E25: Ozon | F25: консоль | G25: v4 | H25: 46277 | I25: Вышло | J25: =IFERROR(VLOOKUP($A25,'Мои блогеры'!$A:$N,8,0),"") -> 26824 | K25: 1824 | L25: 800 | M25: =IF(N($J25)+N($K25)+N($L25)=0,"",N($J25)+N($K25)+N($L25)) -> 29448 | O25: - | Q25: Ivanov | S25: https://youtube.com/shorts/yRe3U-VjnO0?si=9P_G8F7NPaKb2Zo7 | T25: Да | U25: 279000 | V25: =IF(N($U25)=0,"",$M25/$U25) -> 0.10554839 | W25: 4 | X25: 4 | Y25: =IF(N($W25)=0,"",$M25/$W25) -> 7362 | Z25: 2 | AA25: 6 | AB25: 3538 | AD25: 6 | AE25: =AB25/AD25 -> 589.66667 | AF25: =IF(OR(N($AD25)=0,$AE25=""),"",ROUND($AD25*$AE25,0)) -> 3538 | AG25: =IF(N($AD25)=0,"",ROUND($M25/$AD25,0)) -> 4908 | AH25: =IF(N($AA25)=0,"",ROUND($M25/$AA25,0)) -> 4908 | AI25: Aminotrigger-Fish | AL25: продажи по промо
A26: https://t.me/SlavkaIvanovTv | B26: =IF($A26="","",IFERROR(HYPERLINK(VLOOKUP($A26,'Мои блогеры'!$A:$N,14,0),"🔗 открыть"),"")) -> 🔗 открыть | C26: =IFERROR(VLOOKUP($A26,'Мои блогеры'!$A:$N,5,0),"") -> 4900 | D26: =IFERROR(VLOOKUP($A26,'Мои блогеры'!$A:$N,2,0),"") -> Telegram | E26: Ozon | F26: консоль | G26: v4 | H26: 46277 | I26: Вышло | J26: 0 | M26: 0 | O26: https://ozon.onelink.me/SNMZ/bjw197k8 | Q26: - | S26: https://t.me/SlavkaIvanovTv/1127 | T26: Да | U26: 609 | V26: =IF(N($U26)=0,"",$M26/$U26) -> 0 | W26: 23 | X26: 23 | Y26: =IF(N($W26)=0,"",$M26/$W26) -> 0 | Z26: 2 | AB26: 0 | AD26: 0 | AG26: =IF(N($AD26)=0,"",ROUND($M26/$AD26,0)) | AH26: =IF(N($AA26)=0,"",ROUND($M26/$AA26,0)) | AI26: Aminotrigger-Fish
A27: www.tiktok.com/@vyacheslav19916 | C27: =IFERROR(VLOOKUP($A27,'Мои блогеры'!$A:$N,5,0),"") -> 178000 | D27: =IFERROR(VLOOKUP($A27,'Мои блогеры'!$A:$N,2,0),"") -> TikTok | E27: Ozon | F27: консоль | G27: v4 | H27: 46277 | I27: Вышло | J27: =IFERROR(VLOOKUP($A27,'Мои блогеры'!$A:$N,8,0),"") -> 37200 | K27: 912 | M27: =IF(N($J27)+N($K27)+N($L27)=0,"",N($J27)+N($K27)+N($L27)) -> 38112 | O27: - | Q27: Ivanov5 | S27: https://vt.tiktok.com/ZSqHX9VUe/ | T27: Да | U27: 313000 | V27: =IF(N($U27)=0,"",$M27/$U27) -> 0.12176358 | X27: - | Y27: =IF(N($W27)=0,"",$M27/$W27) | AA27: 4 | AB27: 2418 | AD27: 4 | AE27: =AB27/AD27 -> 604.5 | AF27: =IF(OR(N($AD27)=0,$AE27=""),"",ROUND($AD27*$AE27,0)) -> 2418 | AG27: =IF(N($AD27)=0,"",ROUND($M27/$AD27,0)) -> 9528 | AH27: =IF(N($AA27)=0,"",ROUND($M27/$AA27,0)) -> 9528 | AI27: Aminotrigger-Fish | AL27: продажи по промо
A28: Иванов МАХ | C28: =IFERROR(VLOOKUP($A28,'Мои блогеры'!$A:$N,5,0),"") -> 3600 | D28: =IFERROR(VLOOKUP($A28,'Мои блогеры'!$A:$N,2,0),"") -> MAX | E28: Ozon | F28: консоль | G28: v4 | H28: 46277 | I28: Вышло | J28: 0 | M28: 0 | O28: https://ozon.onelink.me/SNMZ/nm4y995d | Q28: - | S28: https://max.ru/join/BdpFb_OnAKVK9ZwJMX7JSGH7jZmsUHACR6T_8yOR5BI | T28: Да | U28: 503 | V28: =IF(N($U28)=0,"",$M28/$U28) -> 0 | X28: - | Y28: =IF(N($W28)=0,"",$M28/$W28) | Z28: 1 | AA28: 0 | AB28: 0 | AG28: =IF(N($AD28)=0,"",ROUND($M28/$AD28,0)) | AH28: =IF(N($AA28)=0,"",ROUND($M28/$AA28,0)) | AI28: Aminotrigger-Fish
A29: https://vk.com/clips/vyacheslav246 | C29: =IFERROR(VLOOKUP($A29,'Мои блогеры'!$A:$N,5,0),"") -> 9700 | D29: =IFERROR(VLOOKUP($A29,'Мои блогеры'!$A:$N,2,0),"") -> VK | E29: Ozon | F29: консоль | G29: v4 | H29: 46277 | I29: Вышло | J29: =IFERROR(VLOOKUP($A29,'Мои блогеры'!$A:$N,8,0),"") -> 19000 | K29: 912 | M29: =IF(N($J29)+N($K29)+N($L29)=0,"",N($J29)+N($K29)+N($L29)) -> 19912 | O29: https://ozon.onelink.me/SNMZ/ucvmp6cd | Q29: - | S29: vk.com/clip-228281080_456239149?c=1 | T29: Да | U29: 213000 | V29: =IF(N($U29)=0,"",$M29/$U29) -> 0.093483568 | W29: 368 | X29: 368 | Y29: =IF(N($W29)=0,"",$M29/$W29) -> 54.108696 | Z29: 201 | AA29: 16 | AB29: =34500+2400+2600 -> 39500 | AD29: 16 | AE29: =AB29/AD29 -> 2468.75 | AF29: =IF(OR(N($AD29)=0,$AE29=""),"",ROUND($AD29*$AE29,0)) -> 39500 | AG29: =IF(N($AD29)=0,"",ROUND($M29/$AD29,0)) -> 1245 | AH29: =IF(N($AA29)=0,"",ROUND($M29/$AA29,0)) -> 1245 | AI29: Aminotrigger-Fish
A30: Сад и огород и дача | C30: =IFERROR(VLOOKUP($A30,'Мои блогеры'!$A:$N,5,0),"") -> 58400 | D30: =IFERROR(VLOOKUP($A30,'Мои блогеры'!$A:$N,2,0),"") -> MAX | E30: WB | F30: телега ин | H30: 46276 | I30: Вышло | J30: =IFERROR(VLOOKUP($A30,'Мои блогеры'!$A:$N,8,0),"") -> 19580 | M30: =IF(N($J30)+N($K30)+N($L30)=0,"",N($J30)+N($K30)+N($L30)) -> 19580 | O30: https://wildberries.ru/catalog/0/search.aspx?search=WW1072329 | P30: https://aminotriggerfish.mobz.market/730vqb | S30: https://max.ru/join/__OvnQb3bzZzI5byvALgfigzQA1gwIo0ZNxBfYXDAyg | U30: 24890 | V30: =IF(N($U30)=0,"",$M30/$U30) -> 0.78666131 | W30: 75 | X30: 70 | Y30: =IF(N($W30)=0,"",$M30/$W30) -> 261.06667 | Z30: 1 | AI30: Аппликатор Ермакова
A31: Дачные секреты | Дача и Огород | C31: =IFERROR(VLOOKUP($A31,'Мои блогеры'!$A:$N,5,0),"") -> 29300 | D31: =IFERROR(VLOOKUP($A31,'Мои блогеры'!$A:$N,2,0),"") -> MAX | E31: WB | F31: телега ин | H31: 46277 | I31: Вышло | J31: =IFERROR(VLOOKUP($A31,'Мои блогеры'!$A:$N,8,0),"") -> 2097 | M31: =IF(N($J31)+N($K31)+N($L31)=0,"",N($J31)+N($K31)+N($L31)) -> 2097 | O31: https://wildberries.ru/catalog/0/search.aspx?search=WW1072350 | P31: https://aminotriggerfish.mobz.market/d57v | S31: https://max.ru/prosto_dacha/AaCVgcZ8GDY | U31: 3097 | V31: =IF(N($U31)=0,"",$M31/$U31) -> 0.67710688 | W31: 20 | X31: 14 | Y31: =IF(N($W31)=0,"",$M31/$W31) -> 104.85 | Z31: 2 | AI31: Аппликатор Ермакова
A32: Дача | Сад и Огород | C32: =IFERROR(VLOOKUP($A32,'Мои блогеры'!$A:$N,5,0),"") -> 30100 | D32: =IFERROR(VLOOKUP($A32,'Мои блогеры'!$A:$N,2,0),"") -> MAX | E32: WB | F32: телега ин | H32: 46276 | I32: Вышло | J32: =IFERROR(VLOOKUP($A32,'Мои блогеры'!$A:$N,8,0),"") -> 4195 | M32: =IF(N($J32)+N($K32)+N($L32)=0,"",N($J32)+N($K32)+N($L32)) -> 4195 | O32: https://wildberries.ru/catalog/0/search.aspx?search=WW1072383 | P32: https://aminotriggerfish.mobz.market/t125dp | S32: https://max.ru/join/L5jEV8WiwQ0PnORs9PzpP4qBAZttshkSFmnpokCbgPs | U32: 11390 | V32: =IF(N($U32)=0,"",$M32/$U32) -> 0.36830553 | W32: 20 | X32: 17 | Y32: =IF(N($W32)=0,"",$M32/$W32) -> 209.75 | Z32: 1 | AI32: Аппликатор Ермакова
A33: Дачные советы. Сад и огород | C33: =IFERROR(VLOOKUP($A33,'Мои блогеры'!$A:$N,5,0),"") -> 10400 | D33: =IFERROR(VLOOKUP($A33,'Мои блогеры'!$A:$N,2,0),"") -> Telegram | E33: WB | F33: телега ин | H33: 46278 | I33: Вышло | J33: 8391 | M33: 8391 | O33: https://wildberries.ru/catalog/0/search.aspx?search=WW1072388 | P33: https://aminotriggerfish.mobz.market/kykkxs | S33: https://max.ru/dachniesoveti/AaCZkfVVLoY | U33: 8963 | V33: =IF(N($U33)=0,"",$M33/$U33) -> 0.93618208 | W33: 29 | X33: 27 | Y33: =IF(N($W33)=0,"",$M33/$W33) -> 289.34483 | Z33: 3 | AI33: Аппликатор Ермакова
A34: ДАЧА ДЛЯ ДУШИ ✅ I СОВЕТЫ САДОВОДАМ И | C34: =IFERROR(VLOOKUP($A34,'Мои блогеры'!$A:$N,5,0),"") -> 4200 | D34: =IFERROR(VLOOKUP($A34,'Мои блогеры'!$A:$N,2,0),"") -> MAX | E34: WB | F34: телега ин | H34: 46276 | I34: Вышло | J34: =IFERROR(VLOOKUP($A34,'Мои блогеры'!$A:$N,8,0),"") -> 907 | M34: =IF(N($J34)+N($K34)+N($L34)=0,"",N($J34)+N($K34)+N($L34)) -> 907 | O34: https://wildberries.ru/catalog/0/search.aspx?search=WW1072400 | P34: https://aminotriggerfish.mobz.market/wy33q9 | S34: https://max.ru/public223173343 | U34: 1078 | V34: =IF(N($U34)=0,"",$M34/$U34) -> 0.84137291 | W34: 15 | X34: 13 | Y34: =IF(N($W34)=0,"",$M34/$W34) -> 60.466667 | Z34: 2 | AA34: 0 | AI34: Аппликатор Ермакова
A35: Моя Дача. Сад и огород | C35: =IFERROR(VLOOKUP($A35,'Мои блогеры'!$A:$N,5,0),"") -> 286000 | D35: =IFERROR(VLOOKUP($A35,'Мои блогеры'!$A:$N,2,0),"") -> Telegram | E35: WB | F35: телега ин | H35: 46276 | I35: Вышло | J35: =IFERROR(VLOOKUP($A35,'Мои блогеры'!$A:$N,8,0),"") -> 2097 | M35: =IF(N($J35)+N($K35)+N($L35)=0,"",N($J35)+N($K35)+N($L35)) -> 2097 | O35: https://wildberries.ru/catalog/0/search.aspx?search=WW1072412 | P35: https://aminotriggerfish.mobz.market/38lllx | S35: https://telegram.me/dacha_my | U35: 4905 | V35: =IF(N($U35)=0,"",$M35/$U35) -> 0.42752294 | W35: 31 | X35: 25 | Y35: =IF(N($W35)=0,"",$M35/$W35) -> 67.645161 | Z35: 1 | AA35: 0 | AI35: Аппликатор Ермакова
A36: Итого: 8-14 сентября | I36: =COUNTIF(I13:I35,"Вышло")&" / "&COUNTA(A13:A35) -> 23 / 23 | J36: =SUM(J13:J35) -> 276701 | K36: =SUM(K13:K35) -> 8948 | L36: =SUM(L13:L35) -> 2350 | M36: =SUM(M13:M35) -> 287999 | U36: =SUM(U13:U35) -> 1412161 | V36: =IF(N($U36)=0,"",$M36/$U36) -> 0.20394204 | W36: =SUM(W13:W35) -> 2260 | X36: =SUM(X13:X35) -> 2187 | Y36: =IF(N($W36)=0,"",$M36/$W36) -> 127.43319 | Z36: =SUM(Z13:Z35) -> 839 | AA36: =SUM(AA13:AA35) -> 155 | AB36: =SUM(AB13:AB35) -> 237156 | AD36: =SUM(AD13:AD35) -> 155 | AE36: =SUM(AE13:AE35) -> 21319.613 | AF36: =SUM(AF13:AF35) -> 237156 | AG36: =AF36/AD36 -> 1530.0387 | AH36: =IF(N($AA36)=0,"",ROUND($M36/$AA36,0)) -> 1858
A37: НЕДЕЛЯ —15-21 сентября
A38: http://tiktok.com/@budni_zubareva | B38: =IF($A38="","",IFERROR(HYPERLINK(VLOOKUP($A38,'Мои блогеры'!$A:$N,14,0),"🔗 открыть"),"")) -> 🔗 открыть | C38: =IFERROR(VLOOKUP($A38,'Мои блогеры'!$A:$N,5,0),"") -> 11700 | D38: =IFERROR(VLOOKUP($A38,'Мои блогеры'!$A:$N,2,0),"") -> TikTok | E38: Ozon | F38: консоль | G38: v1 | H38: 46282 | I38: Вышло | J38: =IFERROR(VLOOKUP($A38,'Мои блогеры'!$A:$N,8,0),"") -> 7000 | K38: 553 | L38: 800 | M38: =IF(N($J38)+N($K38)+N($L38)=0,"",N($J38)+N($K38)+N($L38)) -> 8353 | Q38: zuborev5 | S38: https://vt.tiktok.com/ZSqpcwWMU/ | T38: Да | U38: 56500 | V38: =IF(N($U38)=0,"",$M38/$U38) -> 0.14784071 | W38: - | X38: - | Y38: - | Z38: - | AG38: =IF(N($AD38)=0,"",ROUND($M38/$AD38,0)) | AH38: =IF(N($AA38)=0,"",ROUND($M38/$AA38,0)) | AI38: Aminotrigger-Fish
A39: https://vk.ru/budni_zubareva | B39: =IF($A39="","",IFERROR(HYPERLINK(VLOOKUP($A39,'Мои блогеры'!$A:$N,14,0),"🔗 открыть"),"")) -> 🔗 открыть | C39: =IFERROR(VLOOKUP($A39,'Мои блогеры'!$A:$N,5,0),"") -> 3700 | D39: =IFERROR(VLOOKUP($A39,'Мои блогеры'!$A:$N,2,0),"") -> VK | E39: Ozon | F39: консоль | G39: v1 | H39: 46282 | I39: Вышло | J39: =IFERROR(VLOOKUP($A39,'Мои блогеры'!$A:$N,8,0),"") -> 3000 | K39: 553 | M39: =IF(N($J39)+N($K39)+N($L39)=0,"",N($J39)+N($K39)+N($L39)) -> 3553 | S39: https://vk.ru/clip-236832541_456239267?c=1 | T39: Да | U39: 7600 | V39: =IF(N($U39)=0,"",$M39/$U39) -> 0.4675 | W39: 6 | Y39: =IF(N($W39)=0,"",$M39/$W39) -> 592.16667 | Z39: 1 | AA39: 1 | AB39: 2400 | AD39: 1 | AE39: =AB39/AD39 -> 2400 | AF39: =IF(OR(N($AD39)=0,$AE39=""),"",ROUND($AD39*$AE39,0)) -> 2400 | AG39: =IF(N($AD39)=0,"",ROUND($M39/$AD39,0)) -> 3553 | AH39: =IF(N($AA39)=0,"",ROUND($M39/$AA39,0)) -> 3553 | AI39: Aminotrigger-Fish
A40: https://youtube.com/@budni_zubareva | B40: =IF($A40="","",IFERROR(HYPERLINK(VLOOKUP($A40,'Мои блогеры'!$A:$N,14,0),"🔗 открыть"),"")) -> 🔗 открыть | C40: =IFERROR(VLOOKUP($A40,'Мои блогеры'!$A:$N,5,0),"") -> 3000 | D40: =IFERROR(VLOOKUP($A40,'Мои блогеры'!$A:$N,2,0),"") -> YouTube | E40: Ozon | F40: консоль | G40: v1 | H40: 46282 | I40: Вышло | J40: =IFERROR(VLOOKUP($A40,'Мои блогеры'!$A:$N,8,0),"") -> 5000 | M40: =IF(N($J40)+N($K40)+N($L40)=0,"",N($J40)+N($K40)+N($L40)) -> 5000 | Q40: zuborev | S40: https://youtube.com/shorts/kUBgu_gtu9M?si=s8s8zRp5driIQUHc | T40: Да | U40: 27000 | V40: =IF(N($U40)=0,"",$M40/$U40) -> 0.18518519 | W40: - | X40: - | Y40: - | Z40: - | AG40: =IF(N($AD40)=0,"",ROUND($M40/$AD40,0)) | AH40: =IF(N($AA40)=0,"",ROUND($M40/$AA40,0)) | AI40: Aminotrigger-Fish
A41: https://www.tiktok.com/@semenov.alexander | B41: =IF($A41="","",IFERROR(HYPERLINK(VLOOKUP($A41,'Мои блогеры'!$A:$N,14,0),"🔗 открыть"),"")) -> 🔗 открыть | C41: =IFERROR(VLOOKUP($A41,'Мои блогеры'!$A:$N,5,0),"") -> 106800 | D41: =IFERROR(VLOOKUP($A41,'Мои блогеры'!$A:$N,2,0),"") -> TikTok | E41: Ozon | F41: консоль | G41: v5 | H41: 46280 | I41: Вышло | J41: =IFERROR(VLOOKUP($A41,'Мои блогеры'!$A:$N,8,0),"") -> 50000 | K41: 2300 | L41: 800 | M41: =IF(N($J41)+N($K41)+N($L41)=0,"",N($J41)+N($K41)+N($L41)) -> 53100 | O41: - | Q41: semenov10 | S41: https://www.tiktok.com/@semenov.alexander/video/7685735317101415688 | T41: Да | U41: 260400 | V41: =IF(N($U41)=0,"",$M41/$U41) -> 0.20391705 | W41: - | X41: - | Y41: - | AG41: =IF(N($AD41)=0,"",ROUND($M41/$AD41,0)) | AH41: =IF(N($AA41)=0,"",ROUND($M41/$AA41,0)) | AI41: Aminotrigger-Fish
A42: https://youtube.com/@official.semenov | B42: =IF($A42="","",IFERROR(HYPERLINK(VLOOKUP($A42,'Мои блогеры'!$A:$N,14,0),"🔗 открыть"),"")) -> 🔗 открыть | C42: =IFERROR(VLOOKUP($A42,'Мои блогеры'!$A:$N,5,0),"") -> 9500 | D42: =IFERROR(VLOOKUP($A42,'Мои блогеры'!$A:$N,2,0),"") -> YouTube | E42: Ozon | F42: консоль | G42: v5 | H42: 46280 | I42: Вышло | J42: =IFERROR(VLOOKUP($A42,'Мои блогеры'!$A:$N,8,0),"") -> 15000 | K42: 2300 | M42: =IF(N($J42)+N($K42)+N($L42)=0,"",N($J42)+N($K42)+N($L42)) -> 17300 | O42: - | Q42: semenov11 | S42: https://www.youtube.com/shorts/LK9adofQvpw | T42: Да | U42: 97000 | V42: =IF(N($U42)=0,"",$M42/$U42) -> 0.17835052 | W42: - | X42: - | Y42: - | AG42: =IF(N($AD42)=0,"",ROUND($M42/$AD42,0)) | AH42: =IF(N($AA42)=0,"",ROUND($M42/$AA42,0)) | AI42: Aminotrigger-Fish
A43: namechtala | C43: =IFERROR(VLOOKUP($A43,'Мои блогеры'!$A:$N,5,0),"") -> 137000 | D43: =IFERROR(VLOOKUP($A43,'Мои блогеры'!$A:$N,2,0),"") -> VK | E43: WB | F43: консоль | H43: 46283 | I43: Вышло | J43: =IFERROR(VLOOKUP($A43,'Мои блогеры'!$A:$N,8,0),"") -> 25000 | K43: 2870 | L43: 3700 | M43: =IF(N($J43)+N($K43)+N($L43)=0,"",N($J43)+N($K43)+N($L43)) -> 31570 | O43: https://wildberries.ru/catalog/0/search.aspx?search=WW1111630 | R43: WW1111630 | S43: https://vk.ru/story-211242042_456248667 | T43: Нет | U43: 38290 | V43: =IF(N($U43)=0,"",$M43/$U43) -> 0.82449726 | W43: 409 | X43: 339 | Y43: =IF(N($W43)=0,"",$M43/$W43) -> 77.188264 | Z43: 97 | AA43: 0 | AG43: =IF(N($AD43)=0,"",ROUND($M43/$AD43,0)) | AH43: =IF(N($AA43)=0,"",ROUND($M43/$AA43,0)) | AI43: Аппликатор Ермакова | AL43: сторис
A44: Сиимоновы | C44: =IFERROR(VLOOKUP($A44,'Мои блогеры'!$A:$N,5,0),"") -> 10890 | D44: =IFERROR(VLOOKUP($A44,'Мои блогеры'!$A:$N,2,0),"") -> Telegram | E44: Ozon | F44: консоль | G44: t31 | H44: 46284 | I44: Вышло | J44: =IFERROR(VLOOKUP($A44,'Мои блогеры'!$A:$N,8,0),"") -> 5000 | K44: 500 | M44: =IF(N($J44)+N($K44)+N($L44)=0,"",N($J44)+N($K44)+N($L44)) -> 5500 | O44: https://ozon.onelink.me/SNMZ/kkfg4xvb | S44: https://t.me/simoniata/15098 | T44: Да | U44: 1500 | V44: =IF(N($U44)=0,"",$M44/$U44) -> 3.6666667 | W44: 7 | X44: 7 | Y44: =IF(N($W44)=0,"",$M44/$W44) -> 785.71429 | Z44: 3 | AA44: 1 | AB44: 2400 | AD44: 1 | AE44: =AB44/AD44 -> 2400 | AF44: =IF(OR(N($AD44)=0,$AE44=""),"",ROUND($AD44*$AE44,0)) -> 2400 | AG44: =IF(N($AD44)=0,"",ROUND($M44/$AD44,0)) -> 5500 | AH44: =IF(N($AA44)=0,"",ROUND($M44/$AA44,0)) -> 5500 | AI44: Aminotrigger-Fish | AL44: месяц
A45: simoniatamax | C45: =IFERROR(VLOOKUP($A45,'Мои блогеры'!$A:$N,5,0),"") -> 5900 | D45: =IFERROR(VLOOKUP($A45,'Мои блогеры'!$A:$N,2,0),"") -> MAX | E45: Ozon | F45: консоль | G45: t31 | H45: 46284 | I45: Вышло | J45: =IFERROR(VLOOKUP($A45,'Мои блогеры'!$A:$N,8,0),"") -> 10000 | K45: 500 | M45: =IF(N($J45)+N($K45)+N($L45)=0,"",N($J45)+N($K45)+N($L45)) -> 10500 | O45: https://ozon.onelink.me/SNMZ/vu1a681t | S45: https://max.ru/simoniata/AaC4n18id-w | T45: Да | U45: 3544 | V45: =IF(N($U45)=0,"",$M45/$U45) -> 2.962754 | W45: 38 | X45: 38 | Y45: =IF(N($W45)=0,"",$M45/$W45) -> 276.31579 | Z45: 14 | AA45: 1 | AB45: 1529 | AD45: 1 | AE45: =AB45/AD45 -> 1529 | AF45: =IF(OR(N($AD45)=0,$AE45=""),"",ROUND($AD45*$AE45,0)) -> 1529 | AG45: =IF(N($AD45)=0,"",ROUND($M45/$AD45,0)) -> 10500 | AH45: =IF(N($AA45)=0,"",ROUND($M45/$AA45,0)) -> 10500 | AI45: Aminotrigger-Fish | AL45: месяц
A46: relaxcomedy | C46: =IFERROR(VLOOKUP($A46,'Мои блогеры'!$A:$N,5,0),"") -> 52000 | D46: =IFERROR(VLOOKUP($A46,'Мои блогеры'!$A:$N,2,0),"") -> VK | E46: Ozon | F46: консоль | G46: t31 | H46: 46281 | I46: Вышло | J46: =IFERROR(VLOOKUP($A46,'Мои блогеры'!$A:$N,8,0),"") -> 20000 | K46: 2000 | M46: =IF(N($J46)+N($K46)+N($L46)=0,"",N($J46)+N($K46)+N($L46)) -> 22000 | O46: https://ozon.onelink.me/SNMZ/imk1epi4 | S46: https://vk.ru/wall-211691270_11342 | T46: Да | U46: 75000 | V46: =IF(N($U46)=0,"",$M46/$U46) -> 0.29333333 | W46: 159 | X46: 159 | Y46: =IF(N($W46)=0,"",$M46/$W46) -> 138.36478 | Z46: 23 | AA46: 11 | AB46: 33000 | AD46: 11 | AE46: =AB46/AD46 -> 3000 | AF46: =IF(OR(N($AD46)=0,$AE46=""),"",ROUND($AD46*$AE46,0)) -> 33000 | AG46: =IF(N($AD46)=0,"",ROUND($M46/$AD46,0)) -> 2000 | AH46: =IF(N($AA46)=0,"",ROUND($M46/$AA46,0)) -> 2000 | AI46: Aminotrigger-Fish | AL46: 4 суток
A47: dadvision | C47: =IFERROR(VLOOKUP($A47,'Мои блогеры'!$A:$N,5,0),"") -> 9700 | D47: =IFERROR(VLOOKUP($A47,'Мои блогеры'!$A:$N,2,0),"") -> VK | E47: Ozon | F47: консоль | G47: t31 | H47: 46281 | I47: Вышло | J47: =IFERROR(VLOOKUP($A47,'Мои блогеры'!$A:$N,8,0),"") -> 15000 | M47: =IF(N($J47)+N($K47)+N($L47)=0,"",N($J47)+N($K47)+N($L47)) -> 15000 | O47: https://ozon.onelink.me/SNMZ/pgo7yb0t | S47: https://vk.ru/wall-236887004_658 | T47: Да | U47: 43900 | V47: =IF(N($U47)=0,"",$M47/$U47) -> 0.34168565 | W47: 13 | X47: 13 | Y47: =IF(N($W47)=0,"",$M47/$W47) -> 1153.8462 | Z47: 8 | AA47: 7 | AB47: 21300 | AD47: 7 | AE47: =AB47/AD47 -> 3042.8571 | AF47: =IF(OR(N($AD47)=0,$AE47=""),"",ROUND($AD47*$AE47,0)) -> 21300 | AG47: =IF(N($AD47)=0,"",ROUND($M47/$AD47,0)) -> 2143 | AH47: =IF(N($AA47)=0,"",ROUND($M47/$AA47,0)) -> 2143 | AI47: Aminotrigger-Fish | AL47: месяц
A48: greenpapan_blog | C48: =IFERROR(VLOOKUP($A48,'Мои блогеры'!$A:$N,5,0),"") -> 10200 | D48: =IFERROR(VLOOKUP($A48,'Мои блогеры'!$A:$N,2,0),"") -> VK | E48: Ozon | F48: консоль | G48: t31 | H48: 46283 | I48: Вышло | J48: 15000 | K48: =J48*0.09 -> 1350 | M48: =IF(N($J48)+N($K48)+N($L48)=0,"",N($J48)+N($K48)+N($L48)) -> 16350 | O48: https://ozon.onelink.me/SNMZ/0cvk5ooe | S48: https://vk.ru/wall-51070170_9362 | T48: Да | U48: 56000 | V48: =IF(N($U48)=0,"",$M48/$U48) -> 0.29196429 | W48: 59 | X48: 59 | Y48: =IF(N($W48)=0,"",$M48/$W48) -> 277.11864 | Z48: 49 | AA48: 13 | AB48: =28800 -> 28800 | AD48: 13 | AE48: =AB48/AD48 -> 2215.3846 | AF48: =IF(OR(N($AD48)=0,$AE48=""),"",ROUND($AD48*$AE48,0)) -> 28800 | AG48: =IF(N($AD48)=0,"",ROUND($M48/$AD48,0)) -> 1258 | AH48: =IF(N($AA48)=0,"",ROUND($M48/$AA48,0)) -> 1258 | AI48: Aminotrigger-Fish | AL48: неделя
A49: DostupnayaRybalka | C49: =IFERROR(VLOOKUP($A49,'Мои блогеры'!$A:$N,5,0),"") -> 1900 | D49: =IFERROR(VLOOKUP($A49,'Мои блогеры'!$A:$N,2,0),"") -> Telegram | E49: Ozon | F49: консоль | G49: t31 | H49: 46283 | I49: Вышло | J49: =IFERROR(VLOOKUP($A49,'Мои блогеры'!$A:$N,8,0),"") -> 4000 | M49: =IF(N($J49)+N($K49)+N($L49)=0,"",N($J49)+N($K49)+N($L49)) -> 4000 | O49: https://ozon.ru/product/aktivator-kleva-attraktant-prikormka-rybolovnaya-karp-leshch-250-ml-5340361400?hs=1&utm_campaign=vendor_org_4202727_DostupnayaRybalka&utm_content=t31&utm_medium=blog&utm_source=telegram | S49: https://vk.ru/aliexfisher?z=photo-136853349_457276135%2Falbum-136853349_0%2Frev | T49: Да | U49: 4309 | V49: =IF(N($U49)=0,"",$M49/$U49) -> 0.92828963 | W49: 43 | X49: 43 | Y49: =IF(N($W49)=0,"",$M49/$W49) -> 93.023256 | Z49: 9 | AA49: 0 | AB49: 0 | AD49: 0 | AG49: =IF(N($AD49)=0,"",ROUND($M49/$AD49,0)) | AH49: =IF(N($AA49)=0,"",ROUND($M49/$AA49,0)) | AI49: Aminotrigger-Fish | AL49: сутк
A50: aliexfisher | C50: =IFERROR(VLOOKUP($A50,'Мои блогеры'!$A:$N,5,0),"") -> 28000 | D50: =IFERROR(VLOOKUP($A50,'Мои блогеры'!$A:$N,2,0),"") -> VK | E50: Ozon | F50: консоль | G50: t31 | H50: 46283 | I50: Вышло | J50: =IFERROR(VLOOKUP($A50,'Мои блогеры'!$A:$N,8,0),"") -> 26000 | M50: =IF(N($J50)+N($K50)+N($L50)=0,"",N($J50)+N($K50)+N($L50)) -> 26000 | O50: https://ozon.ru/product/aktivator-kleva-attraktant-prikormka-rybolovnaya-karp-leshch-250-ml-5340361400?hs=1&utm_campaign=vendor_org_4202727_vkaliexfisher&utm_content=t31&utm_medium=blog&utm_source=vk | S50: https://t.me/DostupnayaRybalka/7990 | T50: Да | U50: 24379 | V50: =IF(N($U50)=0,"",$M50/$U50) -> 1.0664917 | W50: 302 | X50: 302 | Y50: =IF(N($W50)=0,"",$M50/$W50) -> 86.092715 | Z50: 17 | AA50: 6 | AB50: =9600+7000 -> 16600 | AD50: 6 | AE50: =AB50/AD50 -> 2766.6667 | AF50: =IF(OR(N($AD50)=0,$AE50=""),"",ROUND($AD50*$AE50,0)) -> 16600 | AG50: =IF(N($AD50)=0,"",ROUND($M50/$AD50,0)) -> 4333 | AH50: =IF(N($AA50)=0,"",ROUND($M50/$AA50,0)) -> 4333 | AI50: Aminotrigger-Fish | AL50: сутк
A51: Клёвое место | Рыбалка | C51: =IFERROR(VLOOKUP($A51,'Мои блогеры'!$A:$N,5,0),"") -> 33000 | D51: =IFERROR(VLOOKUP($A51,'Мои блогеры'!$A:$N,2,0),"") -> MAX | E51: Ozon | F51: телегаин | G51: t31 | H51: 46282 | I51: Вышло | J51: 4755 | M51: =IF(N($J51)+N($K51)+N($L51)=0,"",N($J51)+N($K51)+N($L51)) -> 4755 | O51: https://ozon.onelink.me/SNMZ/gigc33eh | P51: https://aminotriggerfish.mobz.market/4sr | S51: https://max.ru/join/uCdz6lLBZaKQQ-TBrM1kCaXNxdhno0LlLSpv1_WO-yI | T51: Да | U51: 6790 | V51: =IF(N($U51)=0,"",$M51/$U51) -> 0.70029455 | W51: 189 | X51: 168 | Y51: =IF(N($W51)=0,"",$M51/$W51) -> 25.15873 | Z51: 33 | AA51: 8 | AB51: 21000 | AD51: 8 | AE51: =AB51/AD51 -> 2625 | AF51: =IF(OR(N($AD51)=0,$AE51=""),"",ROUND($AD51*$AE51,0)) -> 21000 | AG51: =IF(N($AD51)=0,"",ROUND($M51/$AD51,0)) -> 594 | AH51: =IF(N($AA51)=0,"",ROUND($M51/$AA51,0)) -> 594 | AI51: Aminotrigger-Fish | AL51: 2 сут
A52: rubalkarussia | C52: 8100 | D52: =IFERROR(VLOOKUP($A52,'Мои блогеры'!$A:$N,2,0),"") -> MAX | E52: Ozon | F52: телегаин | G52: t31 | H52: 46282 | I52: Вышло | J52: 1888 | M52: =IF(N($J52)+N($K52)+N($L52)=0,"",N($J52)+N($K52)+N($L52)) -> 1888 | O52: https://ozon.onelink.me/SNMZ/an60ulki | P52: https://aminotriggerfish.mobz.market/30s | S52: https://max.ru/rubalkarussia/AaCunOlNUfQ | T52: Да | U52: 2543 | V52: =IF(N($U52)=0,"",$M52/$U52) -> 0.7424302 | W52: 58 | X52: 47 | Y52: =IF(N($W52)=0,"",$M52/$W52) -> 32.551724 | Z52: 3 | AA52: 0 | AI52: Aminotrigger-Fish | AL52: сутк
A53: Рыболовная сводка Спб | C53: =IFERROR(VLOOKUP($A53,'Мои блогеры'!$A:$N,5,0),"") -> 35500 | D53: =IFERROR(VLOOKUP($A53,'Мои блогеры'!$A:$N,2,0),"") -> Telegram | E53: Ozon | F53: телегаин | G53: t31 | H53: 46283 | I53: Вышло | J53: 3356 | M53: =IF(N($J53)+N($K53)+N($L53)=0,"",N($J53)+N($K53)+N($L53)) -> 3356 | O53: https://ozon.onelink.me/SNMZ/1ctcef22 | P53: https://aminotriggerfish.mobz.market/z8n8q | S53: https://t.me/rybalka_spb_lenoblasti/26621 | T53: Да | U53: 4192 | V53: =IF(N($U53)=0,"",$M53/$U53) -> 0.80057252 | W53: 26 | X53: 24 | Y53: =IF(N($W53)=0,"",$M53/$W53) -> 129.07692 | Z53: 1 | AA53: 0 | AG53: =IF(N($AD53)=0,"",ROUND($M53/$AD53,0)) | AH53: =IF(N($AA53)=0,"",ROUND($M53/$AA53,0)) | AI53: Aminotrigger-Fish | AL53: сутк
A54: Рыбалка в спб чат | C54: =IFERROR(VLOOKUP($A54,'Мои блогеры'!$A:$N,5,0),"") -> 11300 | D54: =IFERROR(VLOOKUP($A54,'Мои блогеры'!$A:$N,2,0),"") -> Telegram | E54: Ozon | F54: телегаин | G54: t31 | H54: 46282 | I54: Вышло | J54: =IFERROR(VLOOKUP($A54,'Мои блогеры'!$A:$N,8,0),"") -> 1398 | M54: =IFERROR(VLOOKUP($A54,'Мои блогеры'!$A:$N,8,0),"") -> 1398 | O54: https://ozon.onelink.me/SNMZ/nrwpzvr9 | P54: https://aminotriggerfish.mobz.market/ckpw | S54: https://t.me/dumbfishspb/501064 | T54: Да | U54: 2682 | V54: =IF(N($U54)=0,"",$M54/$U54) -> 0.5212528 | W54: 21 | X54: 21 | Y54: =IF(N($W54)=0,"",$M54/$W54) -> 66.571429 | Z54: 1 | AA54: 0 | AG54: =IF(N($AD54)=0,"",ROUND($M54/$AD54,0)) | AH54: =IF(N($AA54)=0,"",ROUND($M54/$AA54,0)) | AI54: Aminotrigger-Fish | AL54: сутк
A55: Рыбалка Казань чат | B55: =IF($A55="","",IFERROR(HYPERLINK(VLOOKUP($A55,'Мои блогеры'!$A:$N,14,0),"🔗 открыть"),"")) -> 🔗 открыть | C55: =IFERROR(VLOOKUP($A55,'Мои блогеры'!$A:$N,5,0),"") -> 3400 | D55: =IFERROR(VLOOKUP($A55,'Мои блогеры'!$A:$N,2,0),"") -> Telegram | E55: Ozon | F55: телегаин | G55: t31 | H55: 46282 | I55: Вышло | J55: =IFERROR(VLOOKUP($A55,'Мои блогеры'!$A:$N,8,0),"") -> 839 | M55: =IF(N($J55)+N($K55)+N($L55)=0,"",N($J55)+N($K55)+N($L55)) -> 839 | O55: https://ozon.onelink.me/SNMZ/cq9b529c | P55: https://aminotriggerfish.mobz.market/ego | S55: https://telegram.me/kazanfisher/116977 | T55: Да | U55: 1928 | V55: =IF(N($U55)=0,"",$M55/$U55) -> 0.43516598 | W55: 33 | X55: 33 | Y55: =IF(N($W55)=0,"",$M55/$W55) -> 25.424242 | Z55: 2 | AA55: 1 | AB55: 1529 | AD55: 1 | AE55: =AB55/AD55 -> 1529 | AF55: =IF(OR(N($AD55)=0,$AE55=""),"",ROUND($AD55*$AE55,0)) -> 1529 | AG55: =IF(N($AD55)=0,"",ROUND($M55/$AD55,0)) -> 839 | AH55: =IF(N($AA55)=0,"",ROUND($M55/$AA55,0)) -> 839 | AI55: Aminotrigger-Fish | AL55: сутк
A56: ТОЧКИ КЛЁВА РУССКАЯ РЫБАЛКА 4 | B56: =IF($A56="","",IFERROR(HYPERLINK(VLOOKUP($A56,'Мои блогеры'!$A:$N,14,0),"🔗 открыть"),"")) -> 🔗 открыть | C56: =IFERROR(VLOOKUP($A56,'Мои блогеры'!$A:$N,5,0),"") -> 6933 | D56: =IFERROR(VLOOKUP($A56,'Мои блогеры'!$A:$N,2,0),"") -> MAX | E56: Ozon | F56: телегаин | G56: опрос | H56: 46283 | I56: Вышло | J56: =IFERROR(VLOOKUP($A56,'Мои блогеры'!$A:$N,8,0),"") -> 314 | M56: =IF(N($J56)+N($K56)+N($L56)=0,"",N($J56)+N($K56)+N($L56)) -> 314 | S56: https://max.ru/rf4map/AaC1rfbIIKI | T56: Да | U56: 973 | V56: =IF(N($U56)=0,"",$M56/$U56) -> 0.32271326 | W56: 50 | AG56: =IF(N($AD56)=0,"",ROUND($M56/$AD56,0)) | AH56: =IF(N($AA56)=0,"",ROUND($M56/$AA56,0)) | AI56: опрос подарок | AL56: сутк
A57: Рыбалка СПб и Карелия | B57: =IF($A57="","",IFERROR(HYPERLINK(VLOOKUP($A57,'Мои блогеры'!$A:$N,14,0),"🔗 открыть"),"")) -> 🔗 открыть | C57: =IFERROR(VLOOKUP($A57,'Мои блогеры'!$A:$N,5,0),"") -> 3300 | D57: =IFERROR(VLOOKUP($A57,'Мои блогеры'!$A:$N,2,0),"") -> MAX | E57: Ozon | F57: телегаин | G57: опрос | H57: 46283 | I57: Вышло | J57: 503 | M57: =IF(N($J57)+N($K57)+N($L57)=0,"",N($J57)+N($K57)+N($L57)) -> 503 | S57: https://max.ru/fishingspb1/AaCziRtzWqI | T57: Да | U57: 696 | V57: =IF(N($U57)=0,"",$M57/$U57) -> 0.72270115 | W57: 16 | AG57: =IF(N($AD57)=0,"",ROUND($M57/$AD57,0)) | AH57: =IF(N($AA57)=0,"",ROUND($M57/$AA57,0)) | AI57: опрос подарок | AL57: сутк
A58: Рыбалка | B58: =IF($A58="","",IFERROR(HYPERLINK(VLOOKUP($A58,'Мои блогеры'!$A:$N,14,0),"🔗 открыть"),"")) -> 🔗 открыть | C58: 10240 | D58: =IFERROR(VLOOKUP($A58,'Мои блогеры'!$A:$N,2,0),"") -> MAX | E58: Ozon | F58: телегаин | G58: опрос | H58: 46283 | I58: Вышло | J58: 1188 | M58: =IF(N($J58)+N($K58)+N($L58)=0,"",N($J58)+N($K58)+N($L58)) -> 1188 | S58: https://max.ru/ylov_ribaka/AaC0LX28KqI | T58: Да | U58: 1439 | V58: =IF(N($U58)=0,"",$M58/$U58) -> 0.82557331 | W58: 32 | AG58: =IF(N($AD58)=0,"",ROUND($M58/$AD58,0)) | AH58: =IF(N($AA58)=0,"",ROUND($M58/$AA58,0)) | AI58: опрос подарок | AL58: сутк
A59: Рыбалка фидер спб | B59: =IF($A59="","",IFERROR(HYPERLINK(VLOOKUP($A59,'Мои блогеры'!$A:$N,14,0),"🔗 открыть"),"")) -> 🔗 открыть | C59: =IFERROR(VLOOKUP($A59,'Мои блогеры'!$A:$N,5,0),"") -> 2204 | D59: =IFERROR(VLOOKUP($A59,'Мои блогеры'!$A:$N,2,0),"") -> MAX | E59: Ozon | F59: телегаин | G59: опрос | H59: 46283 | I59: Вышло | J59: =IFERROR(VLOOKUP($A59,'Мои блогеры'!$A:$N,8,0),"") -> 587 | M59: =IF(N($J59)+N($K59)+N($L59)=0,"",N($J59)+N($K59)+N($L59)) -> 587 | S59: https://max.ru/feederspb/AaCy41ZNJiA | T59: Да | U59: 570 | V59: =IF(N($U59)=0,"",$M59/$U59) -> 1.0298246 | W59: 6 | AG59: =IF(N($AD59)=0,"",ROUND($M59/$AD59,0)) | AH59: =IF(N($AA59)=0,"",ROUND($M59/$AA59,0)) | AI59: опрос подарок | AL59: сутк
A60: РЫБАЛКА В МОСКВЕ И ПОДМОСКОВЬЕ | B60: =IF($A60="","",IFERROR(HYPERLINK(VLOOKUP($A60,'Мои блогеры'!$A:$N,14,0),"🔗 открыть"),"")) -> 🔗 открыть | C60: =IFERROR(VLOOKUP($A60,'Мои блогеры'!$A:$N,5,0),"") -> 8699 | D60: =IFERROR(VLOOKUP($A60,'Мои блогеры'!$A:$N,2,0),"") -> Telegram | E60: Ozon | F60: телегаин | G60: опрос | H60: 46283 | I60: Вышло | J60: 419 | M60: =IF(N($J60)+N($K60)+N($L60)=0,"",N($J60)+N($K60)+N($L60)) -> 419 | S60: https://t.me/rubalkamoskva/43973 | T60: Да | U60: 810 | V60: =IF(N($U60)=0,"",$M60/$U60) -> 0.51728395 | W60: 10 | AG60: =IF(N($AD60)=0,"",ROUND($M60/$AD60,0)) | AH60: =IF(N($AA60)=0,"",ROUND($M60/$AA60,0)) | AI60: опрос подарок | AL60: сутк
A61: avto_dvizg | B61: =IF($A61="","",IFERROR(HYPERLINK(VLOOKUP($A61,'Мои блогеры'!$A:$N,14,0),"🔗 открыть"),"")) -> 🔗 открыть | C61: =IFERROR(VLOOKUP($A61,'Мои блогеры'!$A:$N,5,0),"") -> 32100 | D61: =IFERROR(VLOOKUP($A61,'Мои блогеры'!$A:$N,2,0),"") -> VK | E61: Ozon | F61: консоль | G61: t31 | H61: 46283 | I61: Вышло | J61: =IFERROR(VLOOKUP($A61,'Мои блогеры'!$A:$N,8,0),"") -> 15000 | K61: =J61*0.09 -> 1350 | M61: =IF(N($J61)+N($K61)+N($L61)=0,"",N($J61)+N($K61)+N($L61)) -> 16350 | O61: https://ozon.onelink.me/SNMZ/0klzbi87 | S61: https://vk.ru/wall-165180619_132415 | T61: Да | U61: 17900 | V61: =IF(N($U61)=0,"",$M61/$U61) -> 0.91340782 | W61: 194 | X61: 186 | Y61: =IF(N($W61)=0,"",$M61/$W61) -> 84.278351 | Z61: 140 | AA61: 5 | AB61: =9600+2400 -> 12000 | AD61: 5 | AE61: =AB61/AD61 -> 2400 | AF61: =IF(OR(N($AD61)=0,$AE61=""),"",ROUND($AD61*$AE61,0)) -> 12000 | AG61: =IF(N($AD61)=0,"",ROUND($M61/$AD61,0)) -> 3270 | AH61: =IF(N($AA61)=0,"",ROUND($M61/$AA61,0)) -> 3270 | AI61: Aminotrigger-Fish | AL61: 30 дней
A62: https://vk.ru/batya_ilin | C62: =IFERROR(VLOOKUP($A62,'Мои блогеры'!$A:$N,5,0),"") -> 60500 | D62: =IFERROR(VLOOKUP($A62,'Мои блогеры'!$A:$N,2,0),"") -> VK | E62: Ozon | F62: консоль | G62: t31 | H62: 46284 | I62: Вышло | J62: 15000 | K62: 1350 | M62: =IF(N($J62)+N($K62)+N($L62)=0,"",N($J62)+N($K62)+N($L62)) -> 16350 | O62: https://ozon.onelink.me/SNMZ/kvl1wzir | S62: https://vk.ru/wall-235277864_27244 | T62: Да | U62: 21200 | V62: =IF(N($U62)=0,"",$M62/$U62) -> 0.77122642 | W62: 29 | X62: 29 | Y62: =IF(N($W62)=0,"",$M62/$W62) -> 563.7931 | Z62: 12 | AA62: 8 | AB62: =7200+1900+4800 -> 13900 | AD62: 8 | AE62: =AB62/AD62 -> 1737.5 | AF62: =IF(OR(N($AD62)=0,$AE62=""),"",ROUND($AD62*$AE62,0)) -> 13900 | AG62: =IF(N($AD62)=0,"",ROUND($M62/$AD62,0)) -> 2044 | AH62: =IF(N($AA62)=0,"",ROUND($M62/$AA62,0)) -> 2044 | AI62: Aminotrigger-Fish | AL62: 30 дней
A63: https://max.ru/batya_ilin | C63: =IFERROR(VLOOKUP($A63,'Мои блогеры'!$A:$N,5,0),"") -> 2600 | D63: =IFERROR(VLOOKUP($A63,'Мои блогеры'!$A:$N,2,0),"") -> MAX | E63: Ozon | F63: консоль | G63: t31 | H63: 46284 | I63: Вышло | J63: =IFERROR(VLOOKUP($A63,'Мои блогеры'!$A:$N,8,0),"") -> 0 | M63: 0 | O63: https://ozon.onelink.me/SNMZ/z93ytn17 | S63: https://max.ru/batya_ilin/AaC30kbQID0 | T63: Да | U63: 1000 | V63: =IF(N($U63)=0,"",$M63/$U63) -> 0 | W63: 19 | X63: 19 | Y63: =IF(N($W63)=0,"",$M63/$W63) -> 0 | Z63: 13 | AG63: =IF(N($AD63)=0,"",ROUND($M63/$AD63,0)) | AH63: =IF(N($AA63)=0,"",ROUND($M63/$AA63,0)) | AI63: Aminotrigger-Fish | AL63: 30 дней
A64: Рыбалка с Иванычем | C64: =IFERROR(VLOOKUP($A64,'Мои блогеры'!$A:$N,5,0),"") -> 9000 | D64: =IFERROR(VLOOKUP($A64,'Мои блогеры'!$A:$N,2,0),"") -> MAX | E64: Ozon | F64: телегаин | G64: t31 | H64: 46285 | I64: Вышло | J64: =IFERROR(VLOOKUP($A64,'Мои блогеры'!$A:$N,8,0),"") -> 2937 | M64: =IFERROR(VLOOKUP($A64,'Мои блогеры'!$A:$N,8,0),"") -> 2937 | O64: https://ozon.ru/product/aminotrigger-fish-aromatizator-dlya-rybalki-250-ml-5340361400/?hs=1&utm_campaign=vendor_org_4202727_ivanich&utm_content=t31&utm_medium=blog&utm_source=max | S64: https://max.ru/join/kvs60m93OU3-oc3VRfehLDVbvVymDAR0Q-Rcs0e3qDY | T64: Да | U64: 3436 | V64: =IF(N($U64)=0,"",$M64/$U64) -> 0.85477299 | W64: 118 | X64: 118 | Y64: =IF(N($W64)=0,"",$M64/$W64) -> 24.889831 | Z64: 67 | AA64: 1 | AB64: 2400 | AD64: 1 | AE64: =AB64/AD64 -> 2400 | AF64: =IF(OR(N($AD64)=0,$AE64=""),"",ROUND($AD64*$AE64,0)) -> 2400 | AG64: =IF(N($AD64)=0,"",ROUND($M64/$AD64,0)) -> 2937 | AH64: =IF(N($AA64)=0,"",ROUND($M64/$AA64,0)) -> 2937 | AI64: Aminotrigger-Fish | AL64: сутк
A65: Русская рыбалка крейзи | C65: =IFERROR(VLOOKUP($A65,'Мои блогеры'!$A:$N,5,0),"") -> 11565 | D65: =IFERROR(VLOOKUP($A65,'Мои блогеры'!$A:$N,2,0),"") -> Telegram | E65: Ozon | F65: телегаин | G65: t31 | H65: 46285 | I65: Вышло | J65: =IFERROR(VLOOKUP($A65,'Мои блогеры'!$A:$N,8,0),"") -> 352 | M65: =IFERROR(VLOOKUP($A65,'Мои блогеры'!$A:$N,8,0),"") -> 352 | O65: https://ozon.ru/product/aminotrigger-fish-aromatizator-dlya-rybalki-250-ml-5340361400?hs=1&utm_campaign=vendor_org_4202727_ruskayacrazy&utm_content=t32&utm_medium=blog&utm_source=max | S65: https://telegram.me/rf4crazyft/80192 | T65: Да | U65: 690 | V65: =IF(N($U65)=0,"",$M65/$U65) -> 0.51014493 | W65: 3 | X65: 3 | Y65: =IF(N($W65)=0,"",$M65/$W65) -> 117.33333 | Z65: 3 | AA65: 1 | AB65: 2400 | AD65: 1 | AE65: =AB65/AD65 -> 2400 | AF65: =IF(OR(N($AD65)=0,$AE65=""),"",ROUND($AD65*$AE65,0)) -> 2400 | AG65: =IF(N($AD65)=0,"",ROUND($M65/$AD65,0)) -> 352 | AH65: =IF(N($AA65)=0,"",ROUND($M65/$AA65,0)) -> 352 | AI65: Aminotrigger-Fish | AL65: сутк
A66: макавозы | C66: =IFERROR(VLOOKUP($A66,'Мои блогеры'!$A:$N,5,0),"") -> 38200 | D66: =IFERROR(VLOOKUP($A66,'Мои блогеры'!$A:$N,2,0),"") -> VK | E66: Ozon | F66: консоль | G66: t31 | H66: 46285 | I66: Вышло | J66: =IFERROR(VLOOKUP($A66,'Мои блогеры'!$A:$N,8,0),"") -> 15000 | K66: 1350 | M66: =IF(N($J66)+N($K66)+N($L66)=0,"",N($J66)+N($K66)+N($L66)) -> 16350 | O66: https://ozon.ru/product/aktivator-kleva-attraktant-prikormka-rybolovnaya-karp-leshch-250-ml-5340361400?hs=1&utm_campaign=vendor_org_4202727_club211182784&utm_content=t31 &utm_medium=blog&utm_source=vk | S66: https://vk.ru/club211182784?w=story-211182784_456240270%2Fowner_feed-211182784 | T66: Да | U66: 18290 | V66: =IF(N($U66)=0,"",$M66/$U66) -> 0.89393111 | W66: 534 | X66: 534 | Y66: =IF(N($W66)=0,"",$M66/$W66) -> 30.617978 | Z66: 32 | AA66: 1 | AB66: 2600 | AD66: 1 | AE66: =AB66/AD66 -> 2600 | AF66: =IF(OR(N($AD66)=0,$AE66=""),"",ROUND($AD66*$AE66,0)) -> 2600 | AG66: =IF(N($AD66)=0,"",ROUND($M66/$AD66,0)) -> 16350 | AH66: =IF(N($AA66)=0,"",ROUND($M66/$AA66,0)) -> 16350 | AI66: Aminotrigger-Fish | AL66: сутк
A67: https://t.me/makovozovy | C67: =IFERROR(VLOOKUP($A67,'Мои блогеры'!$A:$N,5,0),"") -> 32890 | D67: =IFERROR(VLOOKUP($A67,'Мои блогеры'!$A:$N,2,0),"") -> Telegram | E67: Ozon | F67: консоль | G67: t31 | H67: 46285 | I67: Вышло | J67: =IFERROR(VLOOKUP($A67,'Мои блогеры'!$A:$N,8,0),"") -> 15000 | K67: 1350 | M67: =IF(N($J67)+N($K67)+N($L67)=0,"",N($J67)+N($K67)+N($L67)) -> 16350 | O67: https://ozon.ru/product/aktivator-kleva-attraktant-prikormka-rybolovnaya-karp-leshch-250-ml-5340361400?hs=1&utm_campaign=vendor_org_4202727_makovozovy&utm_content=t31&utm_medium=blog&utm_source=telegram | S67: https://t.me/makovozovy/68707 | T67: Да | U67: 21090 | V67: =IF(N($U67)=0,"",$M67/$U67) -> 0.77524893 | W67: 69 | X67: 69 | Y67: =IF(N($W67)=0,"",$M67/$W67) -> 236.95652 | Z67: 11 | AA67: 1 | AB67: 2600 | AD67: 1 | AE67: =AB67/AD67 -> 2600 | AF67: =IF(OR(N($AD67)=0,$AE67=""),"",ROUND($AD67*$AE67,0)) -> 2600 | AG67: =IF(N($AD67)=0,"",ROUND($M67/$AD67,0)) -> 16350 | AH67: =IF(N($AA67)=0,"",ROUND($M67/$AA67,0)) -> 16350 | AI67: Aminotrigger-Fish | AL67: сутк
A68: Итого: 15-21 сентября | I68: =COUNTIF(I38:I67,"Вышло")&" / "&COUNTA(A38:A67) -> 30 / 30 | J68: =SUM(J38:J67) -> 278536 | K68: =SUM(K38:K67) -> 18326 | L68: =SUM(L38:L67) -> 5300 | M68: =SUM(M38:M67) -> 302162 | U68: =SUM(U38:U67) -> 801651 | V68: =IF(N($U68)=0,"",$M68/$U68) -> 0.37692462 | W68: =SUM(W38:W67) -> 2443 | X68: =SUM(X38:X67) -> 2211 | Y68: =IF(N($W68)=0,"",$M68/$W68) -> 123.68481 | Z68: =SUM(Z38:Z67) -> 539 | AA68: =SUM(AA38:AA67) -> 66 | AB68: =SUM(AB38:AB67) -> 164458 | AD68: =SUM(AD38:AD67) -> 66 | AE68: =SUM(AE38:AE67) -> 35645.408 | AF68: =SUM(AF38:AF67) -> 164458 | AG68: =AF68/AD68 -> 2491.7879 | AH68: =IF(N($AA68)=0,"",ROUND($M68/$AA68,0)) -> 4578 | AI68: =SUM(AI38:AI67) -> 0
A69: НЕДЕЛЯ —22-28 сентября
A70: Северная рыбалка /Nord fishing | C70: =IFERROR(VLOOKUP($A70,'Мои блогеры'!$A:$N,5,0),"") -> 119000 | D70: YouTube | E70: Ozon | F70: договор | G70: v1 | H70: 46292 | I70: Вышло | J70: =IFERROR(VLOOKUP($A70,'Мои блогеры'!$A:$N,8,0),"") -> 78335 | K70: 5106.85 | L70: 492 | M70: =IF(N($J70)+N($K70)+N($L70)=0,"",N($J70)+N($K70)+N($L70)) -> 83933.85 | O70: https://ozon.onelink.me/SNMZ/cifnxffc | S70: https://youtu.be/rkx_oIUERaM?t=291 | T70: Нет | U70: 63000 | V70: =IF(N($U70)=0,"",$M70/$U70) -> 1.3322833 | W70: 144 | X70: 144 | Y70: =IF(N($W70)=0,"",$M70/$W70) -> 582.87396 | Z70: 41 | AA70: 39 | AB70: 105180 | AD70: 39 | AE70: =AB70/AD70 -> 2696.9231 | AF70: =IF(OR(N($AD70)=0,$AE70=""),"",ROUND($AD70*$AE70,0)) -> 105180 | AG70: =IF(N($AD70)=0,"",ROUND($M70/$AD70,0)) -> 2152 | AH70: =IF(N($AA70)=0,"",ROUND($M70/$AA70,0)) -> 2152 | AI70: Aminotrigger-Fish | AL70: только вышел сутки не прошли
A71: stas_blogs | B71: =IF($A71="","",IFERROR(HYPERLINK(VLOOKUP($A71,'Мои блогеры'!$A:$N,14,0),"🔗 открыть"),"")) -> 🔗 открыть | C71: =IFERROR(VLOOKUP($A71,'Мои блогеры'!$A:$N,5,0),"") -> 15100 | D71: =IFERROR(VLOOKUP($A71,'Мои блогеры'!$A:$N,2,0),"") -> Telegram | E71: Ozon | F71: консоль | G71: t31 | H71: 46287 | I71: Вышло | J71: 14000 | K71: =J71*0.07 -> 980 | M71: =IF(N($J71)+N($K71)+N($L71)=0,"",N($J71)+N($K71)+N($L71)) -> 14980 | O71: https://ozon.onelink.me/SNMZ/z2e2wcmr | S71: https://t.me/stas_blogs/175 | U71: 14700 | V71: =IF(N($U71)=0,"",$M71/$U71) -> 1.0190476 | W71: 219 | X71: - | Y71: =IF(N($W71)=0,"",$M71/$W71) -> 68.401826 | Z71: 4 | AA71: 1 | AB71: 2400 | AD71: 1 | AE71: =AB71/AD71 -> 2400 | AF71: =IF(OR(N($AD71)=0,$AE71=""),"",ROUND($AD71*$AE71,0)) -> 2400 | AG71: =IF(N($AD71)=0,"",ROUND($M71/$AD71,0)) -> 14980 | AH71: =IF(N($AA71)=0,"",ROUND($M71/$AA71,0)) -> 14980 | AI71: Aminotrigger-Fish | AL71: 10 дней
A72: A_lfa_live | C72: =IFERROR(VLOOKUP($A72,'Мои блогеры'!$A:$N,5,0),"") -> 22564 | D72: =IFERROR(VLOOKUP($A72,'Мои блогеры'!$A:$N,2,0),"") -> Telegram | E72: Ozon | F72: консоль | G72: t31 | H72: 46287 | I72: Вышло | J72: =IFERROR(VLOOKUP($A72,'Мои блогеры'!$A:$N,8,0),"") -> 17120 | M72: =IF(N($J72)+N($K72)+N($L72)=0,"",N($J72)+N($K72)+N($L72)) -> 17120 | O72: https://ozon.ru/product/aktivator-kleva-attraktant-prikormka-rybolovnaya-karp-leshch-250-ml-5340361400/?hs=1&utm_campaign=vendor_org_4202727_A_lfa_live&utm_content=t31&utm_medium=blog&utm_source=telegram | P72: https://aminotriggerfish.mobz.market/lscy | S72: https://t.me/A_lfa_live/2609 | U72: 20120 | V72: =IF(N($U72)=0,"",$M72/$U72) -> 0.85089463 | W72: 126 | X72: 126 | Y72: =IF(N($W72)=0,"",$M72/$W72) -> 135.87302 | Z72: 26 | AA72: 4 | AB72: 5200 | AD72: 4 | AE72: =AB72/AD72 -> 1300 | AF72: =IF(OR(N($AD72)=0,$AE72=""),"",ROUND($AD72*$AE72,0)) -> 5200 | AG72: =IF(N($AD72)=0,"",ROUND($M72/$AD72,0)) -> 4280 | AH72: =IF(N($AA72)=0,"",ROUND($M72/$AA72,0)) -> 4280 | AI72: Aminotrigger-Fish | AL72: сутк
A73: big_zozh | B73: =IF($A73="","",IFERROR(HYPERLINK(VLOOKUP($A73,'Мои блогеры'!$A:$N,14,0),"🔗 открыть"),"")) -> 🔗 открыть | C73: =IFERROR(VLOOKUP($A73,'Мои блогеры'!$A:$N,5,0),"") -> 27700 | D73: =IFERROR(VLOOKUP($A73,'Мои блогеры'!$A:$N,2,0),"") -> VK | E73: Ozon | F73: консоль | G73: t31 | H73: 46287 | I73: Вышло | J73: 20000 | K73: 1400 | M73: =IF(N($J73)+N($K73)+N($L73)=0,"",N($J73)+N($K73)+N($L73)) -> 21400 | O73: https://ozon.ru/product/aktivator-kleva-attraktant-prikormka-rybolovnaya-karp-leshch-250-ml-5340361400/?hs=1&utm_campaign=vendor_org_4202727_vk.rubig_zozh&utm_content=t31&utm_medium=blog&utm_source=vk | P73: https://aminotriggerfish.mobz.market/zu4pvf | S73: https://vk.ru/wall-184497761_301 | U73: 38290 | V73: =IF(N($U73)=0,"",$M73/$U73) -> 0.55889266 | W73: 118 | X73: 118 | Y73: =IF(N($W73)=0,"",$M73/$W73) -> 181.35593 | Z73: 21 | AA73: 3 | AB73: 8300 | AD73: 3 | AE73: =AB73/AD73 -> 2766.6667 | AF73: =IF(OR(N($AD73)=0,$AE73=""),"",ROUND($AD73*$AE73,0)) -> 8300 | AG73: =IF(N($AD73)=0,"",ROUND($M73/$AD73,0)) -> 7133 | AH73: =IF(N($AA73)=0,"",ROUND($M73/$AA73,0)) -> 7133 | AI73: Aminotrigger-Fish | AL73: сутк
A74: papavkyrse | B74: =IF($A74="","",IFERROR(HYPERLINK(VLOOKUP($A74,'Мои блогеры'!$A:$N,14,0),"🔗 открыть"),"")) -> 🔗 открыть | C74: =IFERROR(VLOOKUP($A74,'Мои блогеры'!$A:$N,5,0),"") -> 18082 | D74: =IFERROR(VLOOKUP($A74,'Мои блогеры'!$A:$N,2,0),"") -> Telegram | E74: Ozon | F74: консоль | G74: t31 | H74: 46288 | I74: Вышло | J74: =IFERROR(VLOOKUP($A74,'Мои блогеры'!$A:$N,8,0),"") -> 16500 | M74: =IF(N($J74)+N($K74)+N($L74)=0,"",N($J74)+N($K74)+N($L74)) -> 16500 | O74: https://ozon.ru/product/aktivator-kleva-attraktant-prikormka-rybolovnaya-karp-leshch-250-ml-5340361400/?hs=1&utm_campaign=vendor_org_4202727_papavkyrse&utm_content=t31&utm_medium=blog&utm_source=vk | P74: https://aminotriggerfish.mobz.market/5x5 | S74: https://t.me/papavkyrse/2507 | U74: 18300 | V74: =IF(N($U74)=0,"",$M74/$U74) -> 0.90163934 | W74: 39 | X74: 36 | Y74: =IF(N($W74)=0,"",$M74/$W74) -> 423.07692 | Z74: 3 | AA74: 1 | AB74: 2600 | AD74: 1 | AE74: 2600 | AF74: =IF(OR(N($AD74)=0,$AE74=""),"",ROUND($AD74*$AE74,0)) -> 2600 | AG74: =IF(N($AD74)=0,"",ROUND($M74/$AD74,0)) -> 16500 | AH74: =IF(N($AA74)=0,"",ROUND($M74/$AA74,0)) -> 16500 | AI74: Aminotrigger-Fish | AL74: сутк
A75: Мужская гильдия | B75: =IF($A75="","",IFERROR(HYPERLINK(VLOOKUP($A75,'Мои блогеры'!$A:$N,14,0),"🔗 открыть"),"")) -> 🔗 открыть | C75: =IFERROR(VLOOKUP($A75,'Мои блогеры'!$A:$N,5,0),"") -> 34057 | D75: =IFERROR(VLOOKUP($A75,'Мои блогеры'!$A:$N,2,0),"") -> Telegram | E75: Ozon | F75: консоль | G75: t31 | H75: 46291 | I75: Вышло | J75: =IFERROR(VLOOKUP($A75,'Мои блогеры'!$A:$N,8,0),"") -> 15000 | K75: =J75*0.1 -> 1500 | M75: =IF(N($J75)+N($K75)+N($L75)=0,"",N($J75)+N($K75)+N($L75)) -> 16500 | O75: https://ozon.ru/product/aktivator-kleva-attraktant-prikormka-rybolovnaya-karp-leshch-250-ml-5340361400/?hs=1&utm_campaign=vendor_org_4202727_mushckaygildiy&utm_content=t31&utm_medium=blog&utm_source=telegram | P75: https://aminotriggerfish.mobz.market/j5kc | S75: https://t.me/Mans_Clan/2441 | U75: 31400 | V75: =IF(N($U75)=0,"",$M75/$U75) -> 0.52547771 | W75: 20 | X75: 20 | Y75: =IF(N($W75)=0,"",$M75/$W75) -> 825 | Z75: 4 | AA75: 2 | AB75: 2400 | AD75: 2 | AE75: =AB75/AD75 -> 1200 | AF75: =IF(OR(N($AD75)=0,$AE75=""),"",ROUND($AD75*$AE75,0)) -> 2400 | AG75: =IF(N($AD75)=0,"",ROUND($M75/$AD75,0)) -> 8250 | AH75: =IF(N($AA75)=0,"",ROUND($M75/$AA75,0)) -> 8250 | AI75: Aminotrigger-Fish | AL75: 3 сутк
A76: Русская рыбалка нев | C76: =IFERROR(VLOOKUP($A76,'Мои блогеры'!$A:$N,5,0),"") -> 3300 | D76: =IFERROR(VLOOKUP($A76,'Мои блогеры'!$A:$N,2,0),"") -> MAX | E76: Ozon | F76: телега ин | G76: t31 | H76: 46288 | I76: Вышло | J76: =IFERROR(VLOOKUP($A76,'Мои блогеры'!$A:$N,8,0),"") -> 594 | M76: =IF(N($J76)+N($K76)+N($L76)=0,"",N($J76)+N($K76)+N($L76)) -> 594 | O76: https://ozon.ru/product/aminotrigger-fish-aromatizator-dlya-rybalki-250-ml-5340361400/?hs=1&utm_campaign=vendor_org_4202727_max.ruchannel_rus_fishin&utm_content=t31&utm_medium=blog&utm_source=max | P76: https://aminotriggerfish.mobz.market/ytee | S76: https://max.ru/channel_rus_fishin/AaDMhyZVaXg | U76: 993 | V76: =IF(N($U76)=0,"",$M76/$U76) -> 0.59818731 | W76: 28 | X76: 28 | Y76: =IF(N($W76)=0,"",$M76/$W76) -> 21.214286 | Z76: 7 | AA76: 0 | AB76: 0 | AF76: =IF(OR(N($AD76)=0,$AE76=""),"",ROUND($AD76*$AE76,0)) | AG76: =IF(N($AD76)=0,"",ROUND($M76/$AD76,0)) | AH76: =IF(N($AA76)=0,"",ROUND($M76/$AA76,0)) | AI76: Aminotrigger-Fish | AL76: сутк
A77: Охота рыбалка отдых | C77: =IFERROR(VLOOKUP($A77,'Мои блогеры'!$A:$N,5,0),"") -> 9500 | D77: =IFERROR(VLOOKUP($A77,'Мои блогеры'!$A:$N,2,0),"") -> MAX | E77: Ozon | F77: телега ин | G77: t31 | H77: 46288 | I77: Вышло | J77: =IFERROR(VLOOKUP($A77,'Мои блогеры'!$A:$N,8,0),"") -> 1118 | M77: =IF(N($J77)+N($K77)+N($L77)=0,"",N($J77)+N($K77)+N($L77)) -> 1118 | O77: https://ozon.ru/product/aminotrigger-fish-aromatizator-dlya-rybalki-250-ml-5340361400/?hs=1&utm_campaign=vendor_org_4202727_ohotarybalka&utm_content=t31&utm_medium=blog&utm_source=max | P77: https://aminotriggerfish.mobz.market/9bd | S77: https://max.ru/join/-MJhyPPkgreSIoYuLu0lh-AJuR-cShsiv9NjhUZbTuM | U77: 1864 | V77: =IF(N($U77)=0,"",$M77/$U77) -> 0.59978541 | W77: 77 | X77: 77 | Y77: =IF(N($W77)=0,"",$M77/$W77) -> 14.519481 | Z77: 25 | AA77: 3 | AB77: 7200 | AD77: 3 | AE77: =AB77/AD77 -> 2400 | AF77: =IF(OR(N($AD77)=0,$AE77=""),"",ROUND($AD77*$AE77,0)) -> 7200 | AG77: =IF(N($AD77)=0,"",ROUND($M77/$AD77,0)) -> 373 | AH77: =IF(N($AA77)=0,"",ROUND($M77/$AA77,0)) -> 373 | AI77: Aminotrigger-Fish | AL77: сутк
A78: Рыбалка в ростова ВРР | C78: =IFERROR(VLOOKUP($A78,'Мои блогеры'!$A:$N,5,0),"") -> 3100 | D78: =IFERROR(VLOOKUP($A78,'Мои блогеры'!$A:$N,2,0),"") -> MAX | E78: Ozon | F78: телега ин | G78: t31 | H78: 46286 | I78: Вышло | J78: =IFERROR(VLOOKUP($A78,'Мои блогеры'!$A:$N,8,0),"") -> 1888 | M78: =IF(N($J78)+N($K78)+N($L78)=0,"",N($J78)+N($K78)+N($L78)) -> 1888 | O78: https://ozon.ru/product/aminotrigger-fish-aromatizator-dlya-rybalki-250-ml-5340361400/?hs=1&utm_campaign=vendor_org_4202727_rybalkavrostove&utm_content=t31&utm_medium=blog&utm_source=max | P78: https://aminotriggerfish.mobz.market/d83kuh | S78: https://max.ru/rybalkavrostove/AaDIueixF3g | U78: 1989 | V78: =IF(N($U78)=0,"",$M78/$U78) -> 0.94922071 | W78: 53 | X78: 53 | Y78: =IF(N($W78)=0,"",$M78/$W78) -> 35.622642 | Z78: 12 | AA78: 4 | AB78: 12000 | AD78: 4 | AE78: =AB78/AD78 -> 3000 | AF78: =IF(OR(N($AD78)=0,$AE78=""),"",ROUND($AD78*$AE78,0)) -> 12000 | AG78: =IF(N($AD78)=0,"",ROUND($M78/$AD78,0)) -> 472 | AH78: =IF(N($AA78)=0,"",ROUND($M78/$AA78,0)) -> 472 | AI78: Aminotrigger-Fish | AL78: сутк
A79: УДачная рыбалка | C79: =IFERROR(VLOOKUP($A79,'Мои блогеры'!$A:$N,5,0),"") -> 7600 | D79: =IFERROR(VLOOKUP($A79,'Мои блогеры'!$A:$N,2,0),"") -> MAX | E79: Ozon | F79: телега ин | G79: t31 | H79: 46286 | I79: Вышло | J79: =IFERROR(VLOOKUP($A79,'Мои блогеры'!$A:$N,8,0),"") -> 2797 | M79: =IF(N($J79)+N($K79)+N($L79)=0,"",N($J79)+N($K79)+N($L79)) -> 2797 | O79: https://ozon.ru/product/aminotrigger-fish-aromatizator-dlya-rybalki-250-ml-5340361400/?hs=1&utm_campaign=vendor_org_4202727_rybalkaudachnaya&utm_content=t31&utm_medium=blog&utm_source=max | P79: https://aminotriggerfish.mobz.market/3rcc | S79: https://max.ru/rybalkaudachnaya/AaDIhVdSUJs | U79: 4134 | V79: =IF(N($U79)=0,"",$M79/$U79) -> 0.67658442 | W79: 45 | X79: 42 | Y79: =IF(N($W79)=0,"",$M79/$W79) -> 62.155556 | Z79: 10 | AA79: 4 | AB79: 4800 | AD79: 4 | AE79: =AB79/AD79 -> 1200 | AF79: =IF(OR(N($AD79)=0,$AE79=""),"",ROUND($AD79*$AE79,0)) -> 4800 | AG79: =IF(N($AD79)=0,"",ROUND($M79/$AD79,0)) -> 699 | AH79: =IF(N($AA79)=0,"",ROUND($M79/$AA79,0)) -> 699 | AI79: Aminotrigger-Fish | AL79: сутк
A80: Рыбалка снасти обзоры | C80: =IFERROR(VLOOKUP($A80,'Мои блогеры'!$A:$N,5,0),"") -> 586 | D80: =IFERROR(VLOOKUP($A80,'Мои блогеры'!$A:$N,2,0),"") -> MAX | E80: Ozon | F80: телега ин | G80: t31 | H80: 46286 | I80: Вышло | J80: =IFERROR(VLOOKUP($A80,'Мои блогеры'!$A:$N,8,0),"") -> 293 | M80: =IF(N($J80)+N($K80)+N($L80)=0,"",N($J80)+N($K80)+N($L80)) -> 293 | O80: https://ozon.ru/product/aminotrigger-fish-aromatizator-dlya-rybalki-250-ml-5340361400/?hs=1&utm_campaign=vendor_org_4202727_aliekemp&utm_content=t31&utm_medium=blog&utm_source=max | P80: https://aminotriggerfish.mobz.market/f0lo7 | S80: https://max.ru/aliekemp/AaDIf94PF3g | U80: 498 | V80: =IF(N($U80)=0,"",$M80/$U80) -> 0.58835341 | W80: 13 | X80: 13 | Y80: =IF(N($W80)=0,"",$M80/$W80) -> 22.538462 | Z80: 1 | AA80: 0 | AB80: 0 | AF80: =IF(OR(N($AD80)=0,$AE80=""),"",ROUND($AD80*$AE80,0)) | AG80: =IF(N($AD80)=0,"",ROUND($M80/$AD80,0)) | AH80: =IF(N($AA80)=0,"",ROUND($M80/$AA80,0)) | AI80: Aminotrigger-Fish | AL80: сутк
A81: с полем охота и рыбалка | C81: =IFERROR(VLOOKUP($A81,'Мои блогеры'!$A:$N,5,0),"") -> 2800 | D81: =IFERROR(VLOOKUP($A81,'Мои блогеры'!$A:$N,2,0),"") -> MAX | E81: Ozon | F81: телега ин | G81: t31 | H81: 46288 | I81: Вышло | J81: =IFERROR(VLOOKUP($A81,'Мои блогеры'!$A:$N,8,0),"") -> 377 | M81: =IF(N($J81)+N($K81)+N($L81)=0,"",N($J81)+N($K81)+N($L81)) -> 377 | O81: https://ozon.ru/product/aminotrigger-fish-aromatizator-dlya-rybalki-250-ml-5340361400/?hs=1&utm_campaign=vendor_org_4202727_spolem&utm_content=t31&utm_medium=blog&utm_source=max | P81: https://aminotriggerfish.mobz.market/j3iq9n | S81: https://max.ru/join/TAz62IvarhreupeVWAwOLTP6R8EY_0-2O7jKs9CK0tM | U81: 1034 | V81: =IF(N($U81)=0,"",$M81/$U81) -> 0.36460348 | W81: 24 | X81: 24 | Y81: =IF(N($W81)=0,"",$M81/$W81) -> 15.708333 | Z81: 2 | AA81: 1 | AB81: 2400 | AD81: 1 | AE81: =AB81/AD81 -> 2400 | AF81: =IF(OR(N($AD81)=0,$AE81=""),"",ROUND($AD81*$AE81,0)) -> 2400 | AG81: =IF(N($AD81)=0,"",ROUND($M81/$AD81,0)) -> 377 | AH81: =IF(N($AA81)=0,"",ROUND($M81/$AA81,0)) -> 377 | AI81: Aminotrigger-Fish | AL81: сутк
A82: Рыбалка 25 - Рыбалка Приморский край и ДВ | B82: =IF($A82="","",IFERROR(HYPERLINK(VLOOKUP($A82,'Мои блогеры'!$A:$N,14,0),"🔗 открыть"),"")) -> 🔗 открыть | C82: =IFERROR(VLOOKUP($A82,'Мои блогеры'!$A:$N,5,0),"") -> 1800 | D82: =IFERROR(VLOOKUP($A82,'Мои блогеры'!$A:$N,2,0),"") -> MAX | E82: Ozon | F82: телега ин | G82: t31 | H82: 46288 | I82: Вышло | J82: =IFERROR(VLOOKUP($A82,'Мои блогеры'!$A:$N,8,0),"") -> 1069 | M82: =IF(N($J82)+N($K82)+N($L82)=0,"",N($J82)+N($K82)+N($L82)) -> 1069 | O82: https://ozon.ru/product/aminotrigger-fish-aromatizator-dlya-rybalki-250-ml-5340361400/?hs=1&utm_campaign=vendor_org_4202727_channel_Ribalka25&utm_content=t31&utm_medium=blog&utm_source=max | P82: https://aminotriggerfish.mobz.market/asy7sl | S82: https://max.ru/channel_Ribalka25/AaDLWRbjdXg | U82: 1296 | V82: =IF(N($U82)=0,"",$M82/$U82) -> 0.82484568 | W82: 23 | X82: 23 | Y82: =IF(N($W82)=0,"",$M82/$W82) -> 46.478261 | Z82: 4 | AA82: 2 | AB82: 7000 | AD82: 2 | AE82: =AB82/AD82 -> 3500 | AF82: =IF(OR(N($AD82)=0,$AE82=""),"",ROUND($AD82*$AE82,0)) -> 7000 | AG82: =IF(N($AD82)=0,"",ROUND($M82/$AD82,0)) -> 535 | AH82: =IF(N($AA82)=0,"",ROUND($M82/$AA82,0)) -> 535 | AI82: Aminotrigger-Fish | AL82: сутк
A83: Водитель рф | C83: =IFERROR(VLOOKUP($A83,'Мои блогеры'!$A:$N,5,0),"") -> 25500 | D83: =IFERROR(VLOOKUP($A83,'Мои блогеры'!$A:$N,2,0),"") -> MAX | E83: Ozon | F83: телега ин | G83: t32 | H83: 46289 | I83: Вышло | J83: =IFERROR(VLOOKUP($A83,'Мои блогеры'!$A:$N,8,0),"") -> 4195 | M83: =IF(N($J83)+N($K83)+N($L83)=0,"",N($J83)+N($K83)+N($L83)) -> 4195 | O83: https://ozon.ru/product/aktivator-kleva-attraktant-prikormka-rybolovnaya-karp-leshch-250-ml-5340361400/?hs=1&utm_campaign=vendor_org_4202727_voditelrf&utm_content=t32&utm_medium=blog&utm_source=max | P83: https://aminotriggerfish.mobz.market/lyn2u | S83: https://max.ru/id560405164432_biz/AaDSqjWlakU | U83: 5339 | V83: =IF(N($U83)=0,"",$M83/$U83) -> 0.78572766 | W83: 60 | X83: 53 | Y83: =IF(N($W83)=0,"",$M83/$W83) -> 69.916667 | Z83: 6 | AA83: 2 | AB83: =2600+2600 -> 5200 | AD83: 2 | AE83: =AB83/AD83 -> 2600 | AF83: =IF(OR(N($AD83)=0,$AE83=""),"",ROUND($AD83*$AE83,0)) -> 5200 | AG83: =IF(N($AD83)=0,"",ROUND($M83/$AD83,0)) -> 2098 | AH83: =IF(N($AA83)=0,"",ROUND($M83/$AA83,0)) -> 2098 | AI83: Aminotrigger-Fish | AL83: сутк
A84: Рыбалка | Рыбанутые | Охота | Туризм | C84: =IFERROR(VLOOKUP($A84,'Мои блогеры'!$A:$N,5,0),"") -> 71500 | D84: =IFERROR(VLOOKUP($A84,'Мои блогеры'!$A:$N,2,0),"") -> MAX | E84: Ozon | F84: телега ин | G84: t32 | H84: 46289 | I84: Вышло | J84: =IFERROR(VLOOKUP($A84,'Мои блогеры'!$A:$N,8,0),"") -> 11328 | M84: =IF(N($J84)+N($K84)+N($L84)=0,"",N($J84)+N($K84)+N($L84)) -> 11328 | O84: https://ozon.ru/product/aktivator-kleva-attraktant-prikormka-rybolovnaya-karp-leshch-250-ml-5340361400/?hs=1&utm_campaign=vendor_org_4202727_rybanutyye&utm_content=t32&utm_medium=blog&utm_source=max | P84: https://aminotriggerfish.mobz.market/rezl | S84: https://max.ru/rybanutyye/AaDSAr2CekU | U84: 13928 | V84: =IF(N($U84)=0,"",$M84/$U84) -> 0.81332567 | W84: 594 | X84: 594 | Y84: =IF(N($W84)=0,"",$M84/$W84) -> 19.070707 | Z84: 112 | AA84: 17 | AB84: 41000 | AD84: 17 | AE84: =AB84/AD84 -> 2411.7647 | AF84: =IF(OR(N($AD84)=0,$AE84=""),"",ROUND($AD84*$AE84,0)) -> 41000 | AG84: =IF(N($AD84)=0,"",ROUND($M84/$AD84,0)) -> 666 | AH84: =IF(N($AA84)=0,"",ROUND($M84/$AA84,0)) -> 666 | AI84: Aminotrigger-Fish | AL84: сутк
A85: Мы родились в сибири | C85: =IFERROR(VLOOKUP($A85,'Мои блогеры'!$A:$N,5,0),"") -> 6800 | D85: =IFERROR(VLOOKUP($A85,'Мои блогеры'!$A:$N,2,0),"") -> MAX | E85: Ozon | F85: телега ин | G85: t32 | H85: 46290 | I85: Вышло | J85: =IFERROR(VLOOKUP($A85,'Мои блогеры'!$A:$N,8,0),"") -> 1538 | M85: =IF(N($J85)+N($K85)+N($L85)=0,"",N($J85)+N($K85)+N($L85)) -> 1538 | O85: https://ozon.ru/product/aktivator-kleva-attraktant-prikormka-rybolovnaya-karp-leshch-250-ml-5340361400/?hs=1&utm_campaign=vendor_org_4202727_myrodilisvsibiri&utm_content=t32&utm_medium=blog&utm_source=max | P85: https://aminotriggerfish.mobz.market/htj | S85: https://max.ru/ch_602408dd140d5e56b2f80f26/AaDY9JY8QkU | U85: 3789 | V85: =IF(N($U85)=0,"",$M85/$U85) -> 0.40591185 | W85: 18 | X85: 18 | Y85: =IF(N($W85)=0,"",$M85/$W85) -> 85.444444 | Z85: 7 | AA85: 0 | AB85: 0 | AF85: =IF(OR(N($AD85)=0,$AE85=""),"",ROUND($AD85*$AE85,0)) | AG85: =IF(N($AD85)=0,"",ROUND($M85/$AD85,0)) | AH85: =IF(N($AA85)=0,"",ROUND($M85/$AA85,0)) | AI85: Aminotrigger-Fish | AL85: сутк
A86: дальнобойщики | C86: =IFERROR(VLOOKUP($A86,'Мои блогеры'!$A:$N,5,0),"") -> 8900 | D86: =IFERROR(VLOOKUP($A86,'Мои блогеры'!$A:$N,2,0),"") -> MAX | E86: Ozon | F86: телега ин | G86: t32 | H86: 46289 | I86: Вышло | J86: =IFERROR(VLOOKUP($A86,'Мои блогеры'!$A:$N,8,0),"") -> 1398 | M86: =IF(N($J86)+N($K86)+N($L86)=0,"",N($J86)+N($K86)+N($L86)) -> 1398 | O86: https://ozon.ru/product/aktivator-kleva-attraktant-prikormka-rybolovnaya-karp-leshch-250-ml-5340361400/?hs=1&utm_campaign=vendor_org_4202727_dolnoboishiki&utm_content=t32&utm_medium=blog&utm_source=max | P86: https://aminotriggerfish.mobz.market/0i3e | S86: https://max.ru/vk_dalnoboy/AaDQJaOWOkU | U86: 3448 | V86: =IF(N($U86)=0,"",$M86/$U86) -> 0.40545244 | W86: 27 | X86: 27 | Y86: =IF(N($W86)=0,"",$M86/$W86) -> 51.777778 | Z86: 3 | AA86: 1 | AB86: 2400 | AD86: 1 | AE86: =AB86/AD86 -> 2400 | AF86: =IF(OR(N($AD86)=0,$AE86=""),"",ROUND($AD86*$AE86,0)) -> 2400 | AG86: =IF(N($AD86)=0,"",ROUND($M86/$AD86,0)) -> 1398 | AH86: =IF(N($AA86)=0,"",ROUND($M86/$AA86,0)) -> 1398 | AI86: Aminotrigger-Fish | AL86: сутк
A87: в курской деревне | C87: =IFERROR(VLOOKUP($A87,'Мои блогеры'!$A:$N,5,0),"") -> 12800 | D87: =IFERROR(VLOOKUP($A87,'Мои блогеры'!$A:$N,2,0),"") -> MAX | E87: Ozon | F87: телега ин | G87: t32 | H87: 46288 | I87: Вышло | J87: =IFERROR(VLOOKUP($A87,'Мои блогеры'!$A:$N,8,0),"") -> 5594 | M87: =IF(N($J87)+N($K87)+N($L87)=0,"",N($J87)+N($K87)+N($L87)) -> 5594 | O87: https://ozon.ru/product/aktivator-kleva-attraktant-prikormka-rybolovnaya-karp-leshch-250-ml-5340361400/?hs=1&utm_campaign=vendor_org_4202727_vkurskoyderevne&utm_content=t32&utm_medium=blog&utm_source=max | P87: https://aminotriggerfish.mobz.market/hxbim | S87: https://max.ru/ch_600bd9ea0424210ae70922c8/AaDPbRtuePg | U87: 6733 | V87: =IF(N($U87)=0,"",$M87/$U87) -> 0.83083321 | W87: 38 | X87: 38 | Y87: =IF(N($W87)=0,"",$M87/$W87) -> 147.21053 | Z87: 15 | AA87: 1 | AB87: 2400 | AD87: 1 | AE87: =AB87/AD87 -> 2400 | AF87: =IF(OR(N($AD87)=0,$AE87=""),"",ROUND($AD87*$AE87,0)) -> 2400 | AG87: =IF(N($AD87)=0,"",ROUND($M87/$AD87,0)) -> 5594 | AH87: =IF(N($AA87)=0,"",ROUND($M87/$AA87,0)) -> 5594 | AI87: Aminotrigger-Fish | AL87: сутк
A88: СВО сводки | C88: =IFERROR(VLOOKUP($A88,'Мои блогеры'!$A:$N,5,0),"") -> 39200 | D88: =IFERROR(VLOOKUP($A88,'Мои блогеры'!$A:$N,2,0),"") -> MAX | E88: Ozon | F88: телега ин | G88: t32 | H88: 46289 | I88: Вышло | J88: =IFERROR(VLOOKUP($A88,'Мои блогеры'!$A:$N,8,0),"") -> 5734 | M88: =IF(N($J88)+N($K88)+N($L88)=0,"",N($J88)+N($K88)+N($L88)) -> 5734 | O88: https://ozon.ru/product/aktivator-kleva-attraktant-prikormka-rybolovnaya-karp-leshch-250-ml-5340361400/?hs=1&utm_campaign=vendor_org_4202727_svodkisvo&utm_content=t32&utm_medium=blog&utm_source=max | P88: https://aminotriggerfish.mobz.market/ufxk3u | S88: https://max.ru/bestnogotochki/AaDS3xkUGEU | U88: 6645 | V88: =IF(N($U88)=0,"",$M88/$U88) -> 0.86290444 | W88: 67 | X88: 67 | Y88: =IF(N($W88)=0,"",$M88/$W88) -> 85.58209 | Z88: 17 | AA88: 1 | AB88: 2600 | AD88: 1 | AE88: =AB88/AD88 -> 2600 | AF88: =IF(OR(N($AD88)=0,$AE88=""),"",ROUND($AD88*$AE88,0)) -> 2600 | AG88: =IF(N($AD88)=0,"",ROUND($M88/$AD88,0)) -> 5734 | AH88: =IF(N($AA88)=0,"",ROUND($M88/$AA88,0)) -> 5734 | AI88: Aminotrigger-Fish | AL88: сутк
A89: Клёвое место | Рыбалка | C89: =IFERROR(VLOOKUP($A89,'Мои блогеры'!$A:$N,5,0),"") -> 33000 | D89: =IFERROR(VLOOKUP($A89,'Мои блогеры'!$A:$N,2,0),"") -> MAX | E89: Ozon | F89: телега ин | G89: t32 | H89: 46289 | I89: Вышло | J89: 3566 | M89: =IF(N($J89)+N($K89)+N($L89)=0,"",N($J89)+N($K89)+N($L89)) -> 3566 | O89: https://ozon.ru/product/aktivator-kleva-attraktant-prikormka-rybolovnaya-karp-leshch-250-ml-5340361400/?hs=1&utm_campaign=vendor_org_4202727_klevoemesto&utm_content=t32&utm_medium=blog&utm_source=max | P89: https://aminotriggerfish.mobz.market/nuip | S89: https://max.ru/join/uCdz6lLBZaKQQ-TBrM1kCaXNxdhno0LlLSpv1_WO-yI | U89: 5016 | V89: =IF(N($U89)=0,"",$M89/$U89) -> 0.71092504 | W89: 248 | X89: 248 | Y89: =IF(N($W89)=0,"",$M89/$W89) -> 14.379032 | Z89: 49 | AA89: 3 | AB89: 7400 | AD89: 3 | AE89: =AB89/AD89 -> 2466.6667 | AF89: =IF(OR(N($AD89)=0,$AE89=""),"",ROUND($AD89*$AE89,0)) -> 7400 | AG89: =IF(N($AD89)=0,"",ROUND($M89/$AD89,0)) -> 1189 | AH89: =IF(N($AA89)=0,"",ROUND($M89/$AA89,0)) -> 1189 | AI89: Aminotrigger-Fish | AL89: сутк
A90: Рыбацкий канал | Рыбалка | C90: =IFERROR(VLOOKUP($A90,'Мои блогеры'!$A:$N,5,0),"") -> 19200 | D90: =IFERROR(VLOOKUP($A90,'Мои блогеры'!$A:$N,2,0),"") -> MAX | E90: Ozon | F90: телега ин | G90: t32 | H90: 46289 | I90: Вышло | J90: 3776 | M90: =IF(N($J90)+N($K90)+N($L90)=0,"",N($J90)+N($K90)+N($L90)) -> 3776 | O90: https://ozon.ru/product/aktivator-kleva-attraktant-prikormka-rybolovnaya-karp-leshch-250-ml-5340361400/?hs=1&utm_campaign=vendor_org_4202727_rybatskiykanal&utm_content=t32&utm_medium=blog&utm_source=max | P90: https://aminotriggerfish.mobz.market/edkpeg | S90: https://max.ru/ribalka_fishing24/AaDSAsPnUkU | U90: 4707 | V90: =IF(N($U90)=0,"",$M90/$U90) -> 0.80220948 | W90: 193 | X90: 193 | Y90: =IF(N($W90)=0,"",$M90/$W90) -> 19.564767 | Z90: 36 | AA90: 4 | AB90: 9600 | AD90: 4 | AE90: =AB90/AD90 -> 2400 | AF90: =IF(OR(N($AD90)=0,$AE90=""),"",ROUND($AD90*$AE90,0)) -> 9600 | AG90: =IF(N($AD90)=0,"",ROUND($M90/$AD90,0)) -> 944 | AH90: =IF(N($AA90)=0,"",ROUND($M90/$AA90,0)) -> 944 | AI90: Aminotrigger-Fish | AL90: сутк
A91: rubalkarussia | C91: =IFERROR(VLOOKUP($A91,'Мои блогеры'!$A:$N,5,0),"") -> 7800 | D91: =IFERROR(VLOOKUP($A91,'Мои блогеры'!$A:$N,2,0),"") -> MAX | E91: Ozon | F91: телега ин | G91: t32 | H91: 46289 | I91: Вышло | J91: 1258 | M91: =IF(N($J91)+N($K91)+N($L91)=0,"",N($J91)+N($K91)+N($L91)) -> 1258 | O91: https://ozon.ru/product/aktivator-kleva-attraktant-prikormka-rybolovnaya-karp-leshch-250-ml-5340361400/?hs=1&utm_campaign=vendor_org_4202727_rybalkarussii&utm_content=t32&utm_medium=blog&utm_source=max | P91: https://aminotriggerfish.mobz.market/491 | S91: https://max.ru/rubalkarussia/AaDScAuhBEU | U91: 1278 | V91: =IF(N($U91)=0,"",$M91/$U91) -> 0.98435055 | W91: 64 | X91: 64 | Y91: =IF(N($W91)=0,"",$M91/$W91) -> 19.65625 | Z91: 12 | AA91: 1 | AB91: 2400 | AD91: 1 | AE91: =AB91/AD91 -> 2400 | AF91: =IF(OR(N($AD91)=0,$AE91=""),"",ROUND($AD91*$AE91,0)) -> 2400 | AG91: =IF(N($AD91)=0,"",ROUND($M91/$AD91,0)) -> 1258 | AH91: =IF(N($AA91)=0,"",ROUND($M91/$AA91,0)) -> 1258 | AI91: Aminotrigger-Fish | AL91: сутк
A92: сводки сво | C92: =IFERROR(VLOOKUP($A92,'Мои блогеры'!$A:$N,5,0),"") -> 13700 | D92: =IFERROR(VLOOKUP($A92,'Мои блогеры'!$A:$N,2,0),"") -> MAX | E92: Ozon | F92: телега ин | G92: t32 | H92: 46290 | I92: Вышло | J92: =IFERROR(VLOOKUP($A92,'Мои блогеры'!$A:$N,8,0),"") -> 1328 | M92: =IF(N($J92)+N($K92)+N($L92)=0,"",N($J92)+N($K92)+N($L92)) -> 1328 | O92: https://ozon.ru/product/aktivator-kleva-attraktant-prikormka-rybolovnaya-karp-leshch-250-ml-5340361400/?hs=1&utm_campaign=vendor_org_4202727_svodkisvo&utm_content=t32&utm_medium=blog&utm_source=max | P92: https://aminotriggerfish.mobz.market/jc8ot | S92: https://max.ru/bestnogotochki | U92: 3854 | V92: =IF(N($U92)=0,"",$M92/$U92) -> 0.34457706 | W92: 45 | X92: 44 | Y92: =IF(N($W92)=0,"",$M92/$W92) -> 29.511111 | Z92: 17 | AA92: 2 | AB92: =2600+2600 -> 5200 | AD92: 2 | AE92: =AB92/AD92 -> 2600 | AF92: =IF(OR(N($AD92)=0,$AE92=""),"",ROUND($AD92*$AE92,0)) -> 5200 | AG92: =IF(N($AD92)=0,"",ROUND($M92/$AD92,0)) -> 664 | AH92: =IF(N($AA92)=0,"",ROUND($M92/$AA92,0)) -> 664 | AI92: Aminotrigger-Fish | AL92: сутк
A93: Мужские хитрости | C93: =IFERROR(VLOOKUP($A93,'Мои блогеры'!$A:$N,5,0),"") -> 6000 | D93: =IFERROR(VLOOKUP($A93,'Мои блогеры'!$A:$N,2,0),"") -> MAX | E93: Ozon | F93: телега ин | G93: t32 | H93: 46289 | I93: Вышло | J93: =IFERROR(VLOOKUP($A93,'Мои блогеры'!$A:$N,8,0),"") -> 2237 | M93: =IF(N($J93)+N($K93)+N($L93)=0,"",N($J93)+N($K93)+N($L93)) -> 2237 | O93: https://ozon.ru/product/aktivator-kleva-attraktant-prikormka-rybolovnaya-karp-leshch-250-ml-5340361400/?hs=1&utm_campaign=vendor_org_4202727_mychskaygildiy&utm_content=t32&utm_medium=blog&utm_source=max | P93: https://aminotriggerfish.mobz.market/k16rxq | S93: https://max.ru/men_115/AaDSAsDkYkU | U93: 3400 | V93: =IF(N($U93)=0,"",$M93/$U93) -> 0.65794118 | W93: 36 | X93: 36 | Y93: =IF(N($W93)=0,"",$M93/$W93) -> 62.138889 | Z93: 6 | AA93: 0 | AB93: 0 | AF93: =IF(OR(N($AD93)=0,$AE93=""),"",ROUND($AD93*$AE93,0)) | AG93: =IF(N($AD93)=0,"",ROUND($M93/$AD93,0)) | AH93: =IF(N($AA93)=0,"",ROUND($M93/$AA93,0)) | AI93: Aminotrigger-Fish | AL93: сутк
A94: Автоновости авто | C94: =IFERROR(VLOOKUP($A94,'Мои блогеры'!$A:$N,5,0),"") -> 7200 | D94: =IFERROR(VLOOKUP($A94,'Мои блогеры'!$A:$N,2,0),"") -> MAX | E94: Ozon | F94: телега ин | G94: t32 | H94: 46289 | I94: Вышло | J94: =IFERROR(VLOOKUP($A94,'Мои блогеры'!$A:$N,8,0),"") -> 1118 | M94: =IF(N($J94)+N($K94)+N($L94)=0,"",N($J94)+N($K94)+N($L94)) -> 1118 | O94: https://ozon.ru/product/aktivator-kleva-attraktant-prikormka-rybolovnaya-karp-leshch-250-ml-5340361400/?hs=1&utm_campaign=vendor_org_4202727_avtomobiln+avto&utm_content=t32&utm_medium=blog&utm_source=max | P94: https://aminotriggerfish.mobz.market/t21 | S94: https://max.ru/murom_navashino/AaDRzJfrNEU | U94: 2325 | V94: =IF(N($U94)=0,"",$M94/$U94) -> 0.48086022 | W94: 17 | X94: 17 | Y94: =IF(N($W94)=0,"",$M94/$W94) -> 65.764706 | Z94: 10 | AA94: 1 | AB94: 2400 | AD94: 1 | AE94: =AB94/AD94 -> 2400 | AF94: =IF(OR(N($AD94)=0,$AE94=""),"",ROUND($AD94*$AE94,0)) -> 2400 | AG94: =IF(N($AD94)=0,"",ROUND($M94/$AD94,0)) -> 1118 | AH94: =IF(N($AA94)=0,"",ROUND($M94/$AA94,0)) -> 1118 | AI94: Aminotrigger-Fish | AL94: сутк
